Workbook

Sheet Guida_v3
A1: LexShield | Modello finanziario v3.1
A2: Versione v3.1, 7 ottobre 2026: 13 correzioni sulla v3 del 6 ottobre, elencate in Fonti_Modifiche dalla riga 26. Originali non modificati.
A4: Argomento | B4: Istruzioni
A5: Scopo | B5: Modello gestionale mensile 2027–2031 per due società. La v3 corregge dipendenze, capacità, liquidità e controlli; non valida contratti, mercato o qualifiche giuridiche.
A6: Partenza | B6: Aprire Cruscotto. Scegliere scenario in Ipotesi!C5. Tutti i nove scenari sono ricalcolati dalle stesse ipotesi.
A7: Input da confermare | B7: Compilare le celle gialle di Parametri_v3, verificare Finanziamenti e Piano_SS. Le due quote consulenziali sono intenzionalmente vuote.
A8: Colori | B8: Blu: input; nero: formule; verde: collegamenti diretti. I valori V2_Riferimento sono snapshot storici, non motore.
A9: Crescita SaaS | B9: Clienti nuovi limitati da obiettivo, budget/CAC ritardato, funnel e capacità sviluppatori/supporto. Churn mensile derivato dal tasso annuo. Pricing annuo applicato a tutti i clienti: ipotesi di rinnovo semplificata.
A10: Ricavi servizi | B10: Giornate vendute limitate da capacità. Preparazione formazione esplicita, R&S sottratta dalla capacità tecnica. Nessun contributo gratuito dei soci presunto.
A11: Finanziamenti | B11: Default include fonti pianificate non confermate. Parametri_v3!C6=1 esclude le fonti esterne con status 0; gli apporti iniziali restano input separati. Scenari 6–9 stressano indisponibilità delle fonti.
A12: Cassa e patrimonio | B12: Saldo negativo = deficit non finanziato. I periodi successivi sono condizionati a nuova copertura. Scadenza fido proposta a dicembre 2031, modificabile in Parametri_v3!C63.
A13: IVA e imposte | B13: IVA a 22% e quote imponibili sono ipotesi da validare. Incassi/pagamenti lordi, compensazione IVA e imposte gestionali con acconti storici; nessuna dichiarazione fiscale prodotta. IRAP e rettifiche fiscali restano semplificate.
A14: TFR | B14: Quota del costo all-in già presente, non costo aggiuntivo. Accumulo del fondo e liquidazioni separati: parametrizzazione da sostituire con dati paghe.
A15: Smart&Start | B15: Budget 500 mila allocato a cinque categorie, spese pagate stimate, tetti e date. Contributo escluso sul circolante; quota non rimborsabile proiettata ai SAL nel CE gestionale, da validare contabilmente.
... A23: Novità v3.1 | B23: Leve per scenario su CAC (Ipotesi riga 27), FTE fatturabili e costi fissi (righe 125-126); dividendi bloccati dopo deficit; R&S al netto del supporto clienti; flag fondo perduto (Parametri_v3!C64); scadenza fido 12/2032; organico startup 2029-2031 ridotto.

Sheet Cruscotto
A1: Decisioni e liquidità | scenario selezionato
A2: Non confondere assenza di errori di formula con sostenibilità economica.
A4: Indicatore | B4: Valore (€ ove applicabile) | C4: Lettura
A5: Scenario selezionato | B5: =INDEX(Ipotesi!$C$6:$K$6,1,Ipotesi!$C$5) -> Base | C5: Modificare Ipotesi!C5 da 1 a 9.
A6: Regime finanziamenti | B6: =IF(Parametri_v3!C6=1,"SOLO ESTERNI CONFERMATI","FONTI ESTERNE IPOTIZZATE") -> FONTI ESTERNE IPOTIZZATE | C6: Le erogazioni non sono garanzie di disponibilità.
A7: Ricavi gruppo 2031 | B7: =Gruppo!G9 -> 3651225.3 | C7: Derivati da capacità, budget acquisizione e churn.
A8: EBITDA gruppo 2031 | B8: =Gruppo!G10 -> 446595.61 | C8: Esclusi contributi SS.
A9: Minimo mensile cassa startup | B9: =MIN(Startup!C19:G19) -> -73138.76 | C9: Include utilizzo fido massimo disponibile nello scenario.
A10: Minimo mensile cassa Advisory | B10: =MIN(Advisory!C19:G19) -> -16783.08 | C10: Non compensare automaticamente con cassa startup.
A11: Picco capitale aggiuntivo startup | B11: =MAX(Startup!C20:G20) -> 98138.76 | C11: Incluso buffer proposto; fabbisogno NON finanziato.
A12: Picco capitale aggiuntivo Advisory | B12: =MAX(Advisory!C20:G20) -> 26783.08 | C12: Separato; non sommare i picchi come simultanei senza controllare i mesi.
A13: Patrimonio startup 2031 | B13: =Startup!G37 -> 88867.762 | C13: Pro forma condizionato, con perdite e riserve.
A14: Clienti SaaS 2031 | B14: =Gruppo!G14 -> 228.89967 | C14: Valori attesi, anche frazionari.
A15: Rapporto R&S 2031 | B15: =Requisiti!G9 -> 0.17394745 | C15: Denominatore corretto gestionale; ammissibilità non attestata.
A16: Esito finanziario | B16: =IF(OR(MIN(Startup!C19:G19)<0,MIN(Advisory!C19:G19)<0),"DEFICIT: PIANO NON FINANZIATO","CASSA NON NEGATIVA NELLO SCENARIO") -> DEFICIT: PIANO NON FINANZIATO | C16: L'esito non valida mercato, status o concessioni.
A17: Esito tecnico | B17: =IF(MAX(Controlli!B5:B9)<0.01,"QUADRATURE OK","VERIFICARE QUADRATURE") -> QUADRATURE OK | C17: Controllo contabile automatico, non certificazione.
A18: Primo mese con deficit di cassa | B18: =IFERROR(INDEX(Tesoreria!A5:A64,MATCH(1,Tesoreria!M5:M64,0)),"NESSUNO") -> 46447 | C18: Prima cassa negativa in una delle società; vedere Tesoreria.
A19: Picco gap simultaneo di gruppo | B19: =MAX(Tesoreria!L5:L64) -> 104317.9 | C19: Somma dei fabbisogni nello stesso mese, con buffer separati.
A20: Anno | B20: Ricavi gruppo | C20: EBITDA gruppo | D20: Cassa startup | E20: Cassa Advisory
A21: 2027 | B21: =Gruppo!C9 -> 288276.32 | C21: =Gruppo!C10 -> -171028.84 | D21: =Gruppo!C24 -> 25000 | E21: =Gruppo!C25 -> 26513.727
A22: 2028 | B22: =Gruppo!D9 -> 732688.61 | C22: =Gruppo!D10 -> -263199.15 | D22: =Gruppo!D24 -> 40136.79 | E22: =Gruppo!D25 -> 15038.563
A23: 2029 | B23: =Gruppo!E9 -> 1533406.2 | C23: =Gruppo!E10 -> -350161.38 | D23: =Gruppo!E24 -> 448452.52 | E23: =Gruppo!E25 -> 99567.655
A24: 2030 | B24: =Gruppo!F9 -> 2580413.9 | C24: =Gruppo!F10 -> 52824.185 | D24: =Gruppo!F24 -> 28722.381 | E24: =Gruppo!F25 -> 218002.56
A25: 2031 | B25: =Gruppo!G9 -> 3651225.3 | C25: =Gruppo!G10 -> 446595.61 | D25: =Gruppo!G24 -> 25000 | E25: =Gruppo!G25 -> 341896.8
A27: Minimo cassa startup escluso rimborso finale fido | B27: =MIN(INDEX(Motore_Startup!$BH$5:$BH$544,(Ipotesi!$C$5-1)*60+1):INDEX(Motore_Startup!$BH$5:$BH$544,(Ipotesi!$C$5-1)*60+60))+INDEX(Motore_Startup!$BF$5:$BF$544,(Ipotesi!$C$5-1)*60+60) -> -73138.76 | C27: Utile se la scadenza fido (Parametri_v3!C63) cade nel 2031.

Sheet Gruppo
A1: Gruppo | aggregato gestionale delle due società
A2: Ricavi e partite reciproche eliminati; non è un bilancio consolidato civilistico.
A4: Indicatore | B4: Unità | C4: 2027 | D4: 2028 | E4: 2029 | F4: 2030 | G4: 2031
A5: Ricavi tecnici esterni | B5: € | C5: =SUM(INDEX(Motore_Operativo!$AQ$5:$AQ$544,(Ipotesi!$C$5-1)*60+0*12+1):INDEX(Motore_Operativo!$AQ$5:$AQ$544,((Ipotesi!$C$5-1)*60+0*12+1)+11)) -> 90000 | D5: =SUM(INDEX(Motore_Operativo!$AQ$5:$AQ$544,(Ipotesi!$C$5-1)*60+1*12+1):INDEX(Motore_Operativo!$AQ$5:$AQ$544,((Ipotesi!$C$5-1)*60+1*12+1)+11)) -> 256500 | E5: =SUM(INDEX(Motore_Operativo!$AQ$5:$AQ$544,(Ipotesi!$C$5-1)*60+2*12+1):INDEX(Motore_Operativo!$AQ$5:$AQ$544,((Ipotesi!$C$5-1)*60+2*12+1)+11)) -> 500000 | F5: =SUM(INDEX(Motore_Operativo!$AQ$5:$AQ$544,(Ipotesi!$C$5-1)*60+3*12+1):INDEX(Motore_Operativo!$AQ$5:$AQ$544,((Ipotesi!$C$5-1)*60+3*12+1)+11)) -> 777000 | G5: =SUM(INDEX(Motore_Operativo!$AQ$5:$AQ$544,(Ipotesi!$C$5-1)*60+4*12+1):INDEX(Motore_Operativo!$AQ$5:$AQ$544,((Ipotesi!$C$5-1)*60+4*12+1)+11)) -> 1078000
A6: Ricavi SaaS | B6: € | C6: =SUM(INDEX(Motore_Operativo!$BF$5:$BF$544,(Ipotesi!$C$5-1)*60+0*12+1):INDEX(Motore_Operativo!$BF$5:$BF$544,((Ipotesi!$C$5-1)*60+0*12+1)+11)) -> 3750 | D6: =SUM(INDEX(Motore_Operativo!$BF$5:$BF$544,(Ipotesi!$C$5-1)*60+1*12+1):INDEX(Motore_Operativo!$BF$5:$BF$544,((Ipotesi!$C$5-1)*60+1*12+1)+11)) -> 68413.96 | E6: =SUM(INDEX(Motore_Operativo!$BF$5:$BF$544,(Ipotesi!$C$5-1)*60+2*12+1):INDEX(Motore_Operativo!$BF$5:$BF$544,((Ipotesi!$C$5-1)*60+2*12+1)+11)) -> 307406.25 | F6: =SUM(INDEX(Motore_Operativo!$BF$5:$BF$544,(Ipotesi!$C$5-1)*60+3*12+1):INDEX(Motore_Operativo!$BF$5:$BF$544,((Ipotesi!$C$5-1)*60+3*12+1)+11)) -> 720513.92 | G6: =SUM(INDEX(Motore_Operativo!$BF$5:$BF$544,(Ipotesi!$C$5-1)*60+4*12+1):INDEX(Motore_Operativo!$BF$5:$BF$544,((Ipotesi!$C$5-1)*60+4*12+1)+11)) -> 1181725.3
A7: Ricavi consulenza | B7: € | C7: =SUM(INDEX(Motore_Operativo!$AK$5:$AK$544,(Ipotesi!$C$5-1)*60+0*12+1):INDEX(Motore_Operativo!$AK$5:$AK$544,((Ipotesi!$C$5-1)*60+0*12+1)+11)) -> 145894.74 | D7: =SUM(INDEX(Motore_Operativo!$AK$5:$AK$544,(Ipotesi!$C$5-1)*60+1*12+1):INDEX(Motore_Operativo!$AK$5:$AK$544,((Ipotesi!$C$5-1)*60+1*12+1)+11)) -> 312338.03 | E7: =SUM(INDEX(Motore_Operativo!$AK$5:$AK$544,(Ipotesi!$C$5-1)*60+2*12+1):INDEX(Motore_Operativo!$AK$5:$AK$544,((Ipotesi!$C$5-1)*60+2*12+1)+11)) -> 561000 | F7: =SUM(INDEX(Motore_Operativo!$AK$5:$AK$544,(Ipotesi!$C$5-1)*60+3*12+1):INDEX(Motore_Operativo!$AK$5:$AK$544,((Ipotesi!$C$5-1)*60+3*12+1)+11)) -> 837900 | G7: =SUM(INDEX(Motore_Operativo!$AK$5:$AK$544,(Ipotesi!$C$5-1)*60+4*12+1):INDEX(Motore_Operativo!$AK$5:$AK$544,((Ipotesi!$C$5-1)*60+4*12+1)+11)) -> 1092500
A8: Ricavi formazione | B8: € | C8: =SUM(INDEX(Motore_Operativo!$AL$5:$AL$544,(Ipotesi!$C$5-1)*60+0*12+1):INDEX(Motore_Operativo!$AL$5:$AL$544,((Ipotesi!$C$5-1)*60+0*12+1)+11)) -> 48631.579 | D8: =SUM(INDEX(Motore_Operativo!$AL$5:$AL$544,(Ipotesi!$C$5-1)*60+1*12+1):INDEX(Motore_Operativo!$AL$5:$AL$544,((Ipotesi!$C$5-1)*60+1*12+1)+11)) -> 95436.62 | E8: =SUM(INDEX(Motore_Operativo!$AL$5:$AL$544,(Ipotesi!$C$5-1)*60+2*12+1):INDEX(Motore_Operativo!$AL$5:$AL$544,((Ipotesi!$C$5-1)*60+2*12+1)+11)) -> 165000 | F8: =SUM(INDEX(Motore_Operativo!$AL$5:$AL$544,(Ipotesi!$C$5-1)*60+3*12+1):INDEX(Motore_Operativo!$AL$5:$AL$544,((Ipotesi!$C$5-1)*60+3*12+1)+11)) -> 245000 | G8: =SUM(INDEX(Motore_Operativo!$AL$5:$AL$544,(Ipotesi!$C$5-1)*60+4*12+1):INDEX(Motore_Operativo!$AL$5:$AL$544,((Ipotesi!$C$5-1)*60+4*12+1)+11)) -> 299000
A9: Ricavi esterni di gruppo | B9: € | C9: =SUM(C5:C8) -> 288276.32 | D9: =SUM(D5:D8) -> 732688.61 | E9: =SUM(E5:E8) -> 1533406.2 | F9: =SUM(F5:F8) -> 2580413.9 | G9: =SUM(G5:G8) -> 3651225.3
A10: EBITDA di gruppo senza contributi | B10: € | C10: =Startup!C9+Advisory!C9 -> -171028.84 | D10: =Startup!D9+Advisory!D9 -> -263199.15 | E10: =Startup!E9+Advisory!E9 -> -350161.38 | F10: =Startup!F9+Advisory!F9 -> 52824.185 | G10: =Startup!G9+Advisory!G9 -> 446595.61
A11: Margine EBITDA | B11: % | C11: =IF(C9=0,0,C10/C9) -> -0.59328093 | D11: =IF(D9=0,0,D10/D9) -> -0.35922375 | E11: =IF(E9=0,0,E10/E9) -> -0.22835526 | F11: =IF(F9=0,0,F10/F9) -> 0.020471206 | G11: =IF(G9=0,0,G10/G9) -> 0.1223139
A12: Utile netto aggregato | B12: € | C12: =Startup!C16+Advisory!C16 -> -176453.47 | D12: =Startup!D16+Advisory!D16 -> -246208.03 | E12: =Startup!E16+Advisory!E16 -> -386461.1 | F12: =Startup!F16+Advisory!F16 -> -72172.842 | G12: =Startup!G16+Advisory!G16 -> 278317.87
A14: Clienti SaaS finali | B14: clienti | C14: =INDEX(Motore_Operativo!$BD$5:$BD$544,((Ipotesi!$C$5-1)*60+0*12+1)+11) -> 5 | D14: =INDEX(Motore_Operativo!$BD$5:$BD$544,((Ipotesi!$C$5-1)*60+1*12+1)+11) -> 32.63937 | E14: =INDEX(Motore_Operativo!$BD$5:$BD$544,((Ipotesi!$C$5-1)*60+2*12+1)+11) -> 88.253797 | F14: =INDEX(Motore_Operativo!$BD$5:$BD$544,((Ipotesi!$C$5-1)*60+3*12+1)+11) -> 154.906 | G14: =INDEX(Motore_Operativo!$BD$5:$BD$544,((Ipotesi!$C$5-1)*60+4*12+1)+11) -> 228.89967
A15: ARR SaaS | B15: € | C15: =INDEX(Motore_Operativo!$BG$5:$BG$544,((Ipotesi!$C$5-1)*60+0*12+1)+11) -> 10000 | D15: =INDEX(Motore_Operativo!$BG$5:$BG$544,((Ipotesi!$C$5-1)*60+1*12+1)+11) -> 130557.48 | E15: =INDEX(Motore_Operativo!$BG$5:$BG$544,((Ipotesi!$C$5-1)*60+2*12+1)+11) -> 485395.88 | F15: =INDEX(Motore_Operativo!$BG$5:$BG$544,((Ipotesi!$C$5-1)*60+3*12+1)+11) -> 929436.02 | G15: =INDEX(Motore_Operativo!$BG$5:$BG$544,((Ipotesi!$C$5-1)*60+4*12+1)+11) -> 1419177.9
A16: Nuovi clienti nell'anno | B16: clienti | C16: =SUM(INDEX(Motore_Operativo!$BC$5:$BC$544,(Ipotesi!$C$5-1)*60+0*12+1):INDEX(Motore_Operativo!$BC$5:$BC$544,((Ipotesi!$C$5-1)*60+0*12+1)+11)) -> 5 | D16: =SUM(INDEX(Motore_Operativo!$BC$5:$BC$544,(Ipotesi!$C$5-1)*60+1*12+1):INDEX(Motore_Operativo!$BC$5:$BC$544,((Ipotesi!$C$5-1)*60+1*12+1)+11)) -> 29.312708 | E16: =SUM(INDEX(Motore_Operativo!$BC$5:$BC$544,(Ipotesi!$C$5-1)*60+2*12+1):INDEX(Motore_Operativo!$BC$5:$BC$544,((Ipotesi!$C$5-1)*60+2*12+1)+11)) -> 61.234385 | F16: =SUM(INDEX(Motore_Operativo!$BC$5:$BC$544,(Ipotesi!$C$5-1)*60+3*12+1):INDEX(Motore_Operativo!$BC$5:$BC$544,((Ipotesi!$C$5-1)*60+3*12+1)+11)) -> 78.957788 | G16: =SUM(INDEX(Motore_Operativo!$BC$5:$BC$544,(Ipotesi!$C$5-1)*60+4*12+1):INDEX(Motore_Operativo!$BC$5:$BC$544,((Ipotesi!$C$5-1)*60+4*12+1)+11)) -> 93.664154
A17: Clienti persi nell'anno | B17: clienti | C17: =SUM(INDEX(Motore_Operativo!$AW$5:$AW$544,(Ipotesi!$C$5-1)*60+0*12+1):INDEX(Motore_Operativo!$AW$5:$AW$544,((Ipotesi!$C$5-1)*60+0*12+1)+11)) -> 0 | D17: =SUM(INDEX(Motore_Operativo!$AW$5:$AW$544,(Ipotesi!$C$5-1)*60+1*12+1):INDEX(Motore_Operativo!$AW$5:$AW$544,((Ipotesi!$C$5-1)*60+1*12+1)+11)) -> 1.6733384 | E17: =SUM(INDEX(Motore_Operativo!$AW$5:$AW$544,(Ipotesi!$C$5-1)*60+2*12+1):INDEX(Motore_Operativo!$AW$5:$AW$544,((Ipotesi!$C$5-1)*60+2*12+1)+11)) -> 5.6199583 | F17: =SUM(INDEX(Motore_Operativo!$AW$5:$AW$544,(Ipotesi!$C$5-1)*60+3*12+1):INDEX(Motore_Operativo!$AW$5:$AW$544,((Ipotesi!$C$5-1)*60+3*12+1)+11)) -> 12.305581 | G17: =SUM(INDEX(Motore_Operativo!$AW$5:$AW$544,(Ipotesi!$C$5-1)*60+4*12+1):INDEX(Motore_Operativo!$AW$5:$AW$544,((Ipotesi!$C$5-1)*60+4*12+1)+11)) -> 19.67049
A18: Budget acquisizione SaaS | B18: € | C18: =SUM(INDEX(Motore_Operativo!$AT$5:$AT$544,(Ipotesi!$C$5-1)*60+0*12+1):INDEX(Motore_Operativo!$AT$5:$AT$544,((Ipotesi!$C$5-1)*60+0*12+1)+11)) -> 40750 | D18: =SUM(INDEX(Motore_Operativo!$AT$5:$AT$544,(Ipotesi!$C$5-1)*60+1*12+1):INDEX(Motore_Operativo!$AT$5:$AT$544,((Ipotesi!$C$5-1)*60+1*12+1)+11)) -> 103667.5 | E18: =SUM(INDEX(Motore_Operativo!$AT$5:$AT$544,(Ipotesi!$C$5-1)*60+2*12+1):INDEX(Motore_Operativo!$AT$5:$AT$544,((Ipotesi!$C$5-1)*60+2*12+1)+11)) -> 373673.4 | F18: =SUM(INDEX(Motore_Operativo!$AT$5:$AT$544,(Ipotesi!$C$5-1)*60+3*12+1):INDEX(Motore_Operativo!$AT$5:$AT$544,((Ipotesi!$C$5-1)*60+3*12+1)+11)) -> 507104.5 | G18: =SUM(INDEX(Motore_Operativo!$AT$5:$AT$544,(Ipotesi!$C$5-1)*60+4*12+1):INDEX(Motore_Operativo!$AT$5:$AT$544,((Ipotesi!$C$5-1)*60+4*12+1)+11)) -> 642721.17
A19: CAC corrente (budget anno / nuovi anno; ciclo da considerare) | B19: € | C19: =IF(C16=0,0,C18/C16) -> 8150 | D19: =IF(D16=0,0,D18/D16) -> 3536.606 | E19: =IF(E16=0,0,E18/E16) -> 6102.3459 | F19: =IF(F16=0,0,F18/F16) -> 6422.4761 | G19: =IF(G16=0,0,G18/G16) -> 6861.9759
A20: Margine lordo SaaS da costi | B20: % | C20: =IF(C6=0,0,1-SUM(INDEX(Motore_Operativo!$CL$5:$CL$544,(Ipotesi!$C$5-1)*60+0*12+1):INDEX(Motore_Operativo!$CL$5:$CL$544,((Ipotesi!$C$5-1)*60+0*12+1)+11))/C6) -> -4.88 | D20: =IF(D6=0,0,1-SUM(INDEX(Motore_Operativo!$CL$5:$CL$544,(Ipotesi!$C$5-1)*60+1*12+1):INDEX(Motore_Operativo!$CL$5:$CL$544,((Ipotesi!$C$5-1)*60+1*12+1)+11))/D6) -> 0.39587452 | E20: =IF(E6=0,0,1-SUM(INDEX(Motore_Operativo!$CL$5:$CL$544,(Ipotesi!$C$5-1)*60+2*12+1):INDEX(Motore_Operativo!$CL$5:$CL$544,((Ipotesi!$C$5-1)*60+2*12+1)+11))/E6) -> 0.68484343 | F20: =IF(F6=0,0,1-SUM(INDEX(Motore_Operativo!$CL$5:$CL$544,(Ipotesi!$C$5-1)*60+3*12+1):INDEX(Motore_Operativo!$CL$5:$CL$544,((Ipotesi!$C$5-1)*60+3*12+1)+11))/F6) -> 0.79681144 | G20: =IF(G6=0,0,1-SUM(INDEX(Motore_Operativo!$CL$5:$CL$544,(Ipotesi!$C$5-1)*60+4*12+1):INDEX(Motore_Operativo!$CL$5:$CL$544,((Ipotesi!$C$5-1)*60+4*12+1)+11))/G6) -> 0.83015999
A21: Obiettivo margine lordo SaaS | B21: % | C21: =Ipotesi!$C$36 -> 0.8 | D21: =Ipotesi!$C$36 -> 0.8 | E21: =Ipotesi!$C$36 -> 0.8 | F21: =Ipotesi!$C$36 -> 0.8 | G21: =Ipotesi!$C$36 -> 0.8
A23: Organico medio gruppo (FTE) | B23: FTE | C23: =AVERAGE(INDEX(Motore_Operativo!$M$5:$M$544,(Ipotesi!$C$5-1)*60+0*12+1):INDEX(Motore_Operativo!$M$5:$M$544,((Ipotesi!$C$5-1)*60+0*12+1)+11))+AVERAGE(INDEX(Motore_Operativo!$N$5:$N$544,(Ipotesi!$C$5-1)*60+0*12+1):INDEX(Motore_Operativo!$N$5:$N$544,((Ipotesi!$C$5-1)*60+0*12+1)+11))+AVERAGE(INDEX(Motore_Operativo!$O$5:$O$544,(Ipotesi!$C$5-1)*60+0*12+1):INDEX(Motore_Operativo!$O$5:$O$544,((Ipotesi!$C$5-1)*60+0*12+1)+11))+AVERAGE(INDEX(Motore_Operativo!$P$5:$P$544,(Ipotesi!$C$5-1)*60+0*12+1):INDEX(Motore_Operativo!$P$5:$P$544,((Ipotesi!$C$5-1)*60+0*12+1)+11))+AVERAGE(INDEX(Motore_Operativo!$Q$5:$Q$544,(Ipotesi!$C$5-1)*60+0*12+1):INDEX(Motore_Operativo!$Q$5:$Q$544,((Ipotesi!$C$5-1)*60+0*12+1)+11))+AVERAGE(INDEX(Motore_Operativo!$R$5:$R$544,(Ipotesi!$C$5-1)*60+0*12+1):INDEX(Motore_Operativo!$R$5:$R$544,((Ipotesi!$C$5-1)*60+0*12+1)+11))+AVERAGE(INDEX(Motore_Operativo!$S$5:$S$544,(Ipotesi!$C$5-1)*60+0*12+1):INDEX(Motore_Operativo!$S$5:$S$544,((Ipotesi!$C$5-1)*60+0*12+1)+11))+AVERAGE(INDEX(Motore_Operativo!$T$5:$T$544,(Ipotesi!$C$5-1)*60+0*12+1):INDEX(Motore_Operativo!$T$5:$T$544,((Ipotesi!$C$5-1)*60+0*12+1)+11))+AVERAGE(INDEX(Motore_Operativo!$U$5:$U$544,(Ipotesi!$C$5-1)*60+0*12+1):INDEX(Motore_Operativo!$U$5:$U$544,((Ipotesi!$C$5-1)*60+0*12+1)+11)) -> 5.75 | D23: =AVERAGE(INDEX(Motore_Operativo!$M$5:$M$544,(Ipotesi!$C$5-1)*60+1*12+1):INDEX(Motore_Operativo!$M$5:$M$544,((Ipotesi!$C$5-1)*60+1*12+1)+11))+AVERAGE(INDEX(Motore_Operativo!$N$5:$N$544,(Ipotesi!$C$5-1)*60+1*12+1):INDEX(Motore_Operativo!$N$5:$N$544,((Ipotesi!$C$5-1)*60+1*12+1)+11))+AVERAGE(INDEX(Motore_Operativo!$O$5:$O$544,(Ipotesi!$C$5-1)*60+1*12+1):INDEX(Motore_Operativo!$O$5:$O$544,((Ipotesi!$C$5-1)*60+1*12+1)+11))+AVERAGE(INDEX(Motore_Operativo!$P$5:$P$544,(Ipotesi!$C$5-1)*60+1*12+1):INDEX(Motore_Operativo!$P$5:$P$544,((Ipotesi!$C$5-1)*60+1*12+1)+11))+AVERAGE(INDEX(Motore_Operativo!$Q$5:$Q$544,(Ipotesi!$C$5-1)*60+1*12+1):INDEX(Motore_Operativo!$Q$5:$Q$544,((Ipotesi!$C$5-1)*60+1*12+1)+11))+AVERAGE(INDEX(Motore_Operativo!$R$5:$R$544,(Ipotesi!$C$5-1)*60+1*12+1):INDEX(Motore_Operativo!$R$5:$R$544,((Ipotesi!$C$5-1)*60+1*12+1)+11))+AVERAGE(INDEX(Motore_Operativo!$S$5:$S$544,(Ipotesi!$C$5-1)*60+1*12+1):INDEX(Motore_Operativo!$S$5:$S$544,((Ipotesi!$C$5-1)*60+1*12+1)+11))+AVERAGE(INDEX(Motore_Operativo!$T$5:$T$544,(Ipotesi!$C$5-1)*60+1*12+1):INDEX(Motore_Operativo!$T$5:$T$544,((Ipotesi!$C$5-1)*60+1*12+1)+11))+AVERAGE(INDEX(Motore_Operativo!$U$5:$U$544,(Ipotesi!$C$5-1)*60+1*12+1):INDEX(Motore_Operativo!$U$5:$U$544,((Ipotesi!$C$5-1)*60+1*12+1)+11)) -> 13 | E23: =AVERAGE(INDEX(Motore_Operativo!$M$5:$M$544,(Ipotesi!$C$5-1)*60+2*12+1):INDEX(Motore_Operativo!$M$5:$M$544,((Ipotesi!$C$5-1)*60+2*12+1)+11))+AVERAGE(INDEX(Motore_Operativo!$N$5:$N$544,(Ipotesi!$C$5-1)*60+2*12+1):INDEX(Motore_Operativo!$N$5:$N$544,((Ipotesi!$C$5-1)*60+2*12+1)+11))+AVERAGE(INDEX(Motore_Operativo!$O$5:$O$544,(Ipotesi!$C$5-1)*60+2*12+1):INDEX(Motore_Operativo!$O$5:$O$544,((Ipotesi!$C$5-1)*60+2*12+1)+11))+AVERAGE(INDEX(Motore_Operativo!$P$5:$P$544,(Ipotesi!$C$5-1)*60+2*12+1):INDEX(Motore_Operativo!$P$5:$P$544,((Ipotesi!$C$5-1)*60+2*12+1)+11))+AVERAGE(INDEX(Motore_Operativo!$Q$5:$Q$544,(Ipotesi!$C$5-1)*60+2*12+1):INDEX(Motore_Operativo!$Q$5:$Q$544,((Ipotesi!$C$5-1)*60+2*12+1)+11))+AVERAGE(INDEX(Motore_Operativo!$R$5:$R$544,(Ipotesi!$C$5-1)*60+2*12+1):INDEX(Motore_Operativo!$R$5:$R$544,((Ipotesi!$C$5-1)*60+2*12+1)+11))+AVERAGE(INDEX(Motore_Operativo!$S$5:$S$544,(Ipotesi!$C$5-1)*60+2*12+1):INDEX(Motore_Operativo!$S$5:$S$544,((Ipotesi!$C$5-1)*60+2*12+1)+11))+AVERAGE(INDEX(Motore_Operativo!$T$5:$T$544,(Ipotesi!$C$5-1)*60+2*12+1):INDEX(Motore_Operativo!$T$5:$T$544,((Ipotesi!$C$5-1)*60+2*12+1)+11))+AVERAGE(INDEX(Motore_Operativo!$U$5:$U$544,(Ipotesi!$C$5-1)*60+2*12+1):INDEX(Motore_Operativo!$U$5:$U$544,((Ipotesi!$C$5-1)*60+2*12+1)+11)) -> 23 | F23: =AVERAGE(INDEX(Motore_Operativo!$M$5:$M$544,(Ipotesi!$C$5-1)*60+3*12+1):INDEX(Motore_Operativo!$M$5:$M$544,((Ipotesi!$C$5-1)*60+3*12+1)+11))+AVERAGE(INDEX(Motore_Operativo!$N$5:$N$544,(Ipotesi!$C$5-1)*60+3*12+1):INDEX(Motore_Operativo!$N$5:$N$544,((Ipotesi!$C$5-1)*60+3*12+1)+11))+AVERAGE(INDEX(Motore_Operativo!$O$5:$O$544,(Ipotesi!$C$5-1)*60+3*12+1):INDEX(Motore_Operativo!$O$5:$O$544,((Ipotesi!$C$5-1)*60+3*12+1)+11))+AVERAGE(INDEX(Motore_Operativo!$P$5:$P$544,(Ipotesi!$C$5-1)*60+3*12+1):INDEX(Motore_Operativo!$P$5:$P$544,((Ipotesi!$C$5-1)*60+3*12+1)+11))+AVERAGE(INDEX(Motore_Operativo!$Q$5:$Q$544,(Ipotesi!$C$5-1)*60+3*12+1):INDEX(Motore_Operativo!$Q$5:$Q$544,((Ipotesi!$C$5-1)*60+3*12+1)+11))+AVERAGE(INDEX(Motore_Operativo!$R$5:$R$544,(Ipotesi!$C$5-1)*60+3*12+1):INDEX(Motore_Operativo!$R$5:$R$544,((Ipotesi!$C$5-1)*60+3*12+1)+11))+AVERAGE(INDEX(Motore_Operativo!$S$5:$S$544,(Ipotesi!$C$5-1)*60+3*12+1):INDEX(Motore_Operativo!$S$5:$S$544,((Ipotesi!$C$5-1)*60+3*12+1)+11))+AVERAGE(INDEX(Motore_Operativo!$T$5:$T$544,(Ipotesi!$C$5-1)*60+3*12+1):INDEX(Motore_Operativo!$T$5:$T$544,((Ipotesi!$C$5-1)*60+3*12+1)+11))+AVERAGE(INDEX(Motore_Operativo!$U$5:$U$544,(Ipotesi!$C$5-1)*60+3*12+1):INDEX(Motore_Operativo!$U$5:$U$544,((Ipotesi!$C$5-1)*60+3*12+1)+11)) -> 29.5 | G23: =AVERAGE(INDEX(Motore_Operativo!$M$5:$M$544,(Ipotesi!$C$5-1)*60+4*12+1):INDEX(Motore_Operativo!$M$5:$M$544,((Ipotesi!$C$5-1)*60+4*12+1)+11))+AVERAGE(INDEX(Motore_Operativo!$N$5:$N$544,(Ipotesi!$C$5-1)*60+4*12+1):INDEX(Motore_Operativo!$N$5:$N$544,((Ipotesi!$C$5-1)*60+4*12+1)+11))+AVERAGE(INDEX(Motore_Operativo!$O$5:$O$544,(Ipotesi!$C$5-1)*60+4*12+1):INDEX(Motore_Operativo!$O$5:$O$544,((Ipotesi!$C$5-1)*60+4*12+1)+11))+AVERAGE(INDEX(Motore_Operativo!$P$5:$P$544,(Ipotesi!$C$5-1)*60+4*12+1):INDEX(Motore_Operativo!$P$5:$P$544,((Ipotesi!$C$5-1)*60+4*12+1)+11))+AVERAGE(INDEX(Motore_Operativo!$Q$5:$Q$544,(Ipotesi!$C$5-1)*60+4*12+1):INDEX(Motore_Operativo!$Q$5:$Q$544,((Ipotesi!$C$5-1)*60+4*12+1)+11))+AVERAGE(INDEX(Motore_Operativo!$R$5:$R$544,(Ipotesi!$C$5-1)*60+4*12+1):INDEX(Motore_Operativo!$R$5:$R$544,((Ipotesi!$C$5-1)*60+4*12+1)+11))+AVERAGE(INDEX(Motore_Operativo!$S$5:$S$544,(Ipotesi!$C$5-1)*60+4*12+1):INDEX(Motore_Operativo!$S$5:$S$544,((Ipotesi!$C$5-1)*60+4*12+1)+11))+AVERAGE(INDEX(Motore_Operativo!$T$5:$T$544,(Ipotesi!$C$5-1)*60+4*12+1):INDEX(Motore_Operativo!$T$5:$T$544,((Ipotesi!$C$5-1)*60+4*12+1)+11))+AVERAGE(INDEX(Motore_Operativo!$U$5:$U$544,(Ipotesi!$C$5-1)*60+4*12+1):INDEX(Motore_Operativo!$U$5:$U$544,((Ipotesi!$C$5-1)*60+4*12+1)+11)) -> 36.5
A24: Cassa S a fine anno | B24: € | C24: =Startup!C18 -> 25000 | D24: =Startup!D18 -> 40136.79 | E24: =Startup!E18 -> 448452.52 | F24: =Startup!F18 -> 28722.381 | G24: =Startup!G18 -> 25000
A25: Cassa A a fine anno | B25: € | C25: =Advisory!C18 -> 26513.727 | D25: =Advisory!D18 -> 15038.563 | E25: =Advisory!E18 -> 99567.655 | F25: =Advisory!F18 -> 218002.56 | G25: =Advisory!G18 -> 341896.8
A26: Cassa totale a fine anno | B26: € | C26: =C24+C25 -> 51513.727 | D26: =D24+D25 -> 55175.353 | E26: =E24+E25 -> 548020.18 | F26: =F24+F25 -> 246724.94 | G26: =G24+G25 -> 366896.8
A27: Cassa minima startup | B27: € | C27: =Startup!C19 -> 25000 | D27: =Startup!D19 -> -73138.76 | E27: =Startup!E19 -> -73078.563 | F27: =Startup!F19 -> 28722.381 | G27: =Startup!G19 -> 25000
A28: Cassa minima Advisory | B28: € | C28: =Advisory!C19 -> -10462.852 | D28: =Advisory!D19 -> -9688.9021 | E28: =Advisory!E19 -> -16783.08 | F28: =Advisory!F19 -> 73892.896 | G28: =Advisory!G19 -> 169280.37
A29: Fabbisogno massimo startup con buffer | B29: € | C29: =Startup!C20 -> 0 | D29: =Startup!D20 -> 98138.76 | E29: =Startup!E20 -> 98078.563 | F29: =Startup!F20 -> 0 | G29: =Startup!G20 -> 0
A30: Fabbisogno massimo Advisory con buffer | B30: € | C30: =Advisory!C20 -> 20462.852 | D30: =Advisory!D20 -> 19688.902 | E30: =Advisory!E20 -> 26783.08 | F30: =Advisory!F20 -> 0 | G30: =Advisory!G20 -> 0
A32: Patrimonio netto aggregato | B32: € | C32: =Startup!C37+Advisory!C37 -> -26453.47 | D32: =Startup!D37+Advisory!D37 -> 27338.496 | E32: =Startup!E37+Advisory!E37 -> 540877.4 | F32: =Startup!F37+Advisory!F37 -> 444095.67 | G32: =Startup!G37+Advisory!G37 -> 674360.92
A33: Debito finanziario totale | B33: € | C33: =Startup!C21+Startup!C24 -> 122180.44 | D33: =Startup!D21+Startup!D24 -> 176155.05 | E33: =Startup!E21+Startup!E24 -> 265393 | F33: =Startup!F21+Startup!F24 -> 238853.7 | G33: =Startup!G21+Startup!G24 -> 324193.4
A34: Dividendi netti trattenuti dai soci | B34: € | C34: =Advisory!C27*(1-Ipotesi!$C$95)*(1-Ipotesi!$C$96) -> 0 | D34: =Advisory!D27*(1-Ipotesi!$C$95)*(1-Ipotesi!$C$96) -> 0 | E34: =Advisory!E27*(1-Ipotesi!$C$95)*(1-Ipotesi!$C$96) -> 0 | F34: =Advisory!F27*(1-Ipotesi!$C$95)*(1-Ipotesi!$C$96) -> 8926.7541 | G34: =Advisory!G27*(1-Ipotesi!$C$95)*(1-Ipotesi!$C$96) -> 17430.848
A35: Imposta dividendi pagata dai soci | B35: € | C35: =Advisory!C27*Ipotesi!$C$95 -> 0 | D35: =Advisory!D27*Ipotesi!$C$95 -> 0 | E35: =Advisory!E27*Ipotesi!$C$95 -> 0 | F35: =Advisory!F27*Ipotesi!$C$95 -> 15682.136 | G35: =Advisory!G27*Ipotesi!$C$95 -> 30621.761
A36: Scarto saldi IC | B36: € | C36: =Startup!C31-Advisory!C31 -> 0 | D36: =Startup!D31-Advisory!D31 -> 0 | E36: =Startup!E31-Advisory!E31 -> 0 | F36: =Startup!F31-Advisory!F31 -> 0 | G36: =Startup!G31-Advisory!G31 -> 0
A37: Ricavi SaaS obiettivo V2 (solo confronto) | B37: € | C37: =V2_Riferimento!C6 -> 5000 | D37: =V2_Riferimento!D6 -> 80000 | E37: =V2_Riferimento!E6 -> 453750 | F37: =V2_Riferimento!F6 -> 1320000 | G37: =V2_Riferimento!G6 -> 2697000

Sheet Startup
A1: Startup | riepilogo annuale selezionato
A2: Conto economico gestionale, posizione patrimoniale e picco del fabbisogno mensile.
A4: Indicatore | B4: Unità | C4: 2027 | D4: 2028 | E4: 2029 | F4: 2030 | G4: 2031
A5: Ricavi esterni | B5: € | C5: =SUM(INDEX(Motore_Startup!$F$5:$F$544,(Ipotesi!$C$5-1)*60+0*12+1):INDEX(Motore_Startup!$F$5:$F$544,((Ipotesi!$C$5-1)*60+0*12+1)+11)) -> 93750 | D5: =SUM(INDEX(Motore_Startup!$F$5:$F$544,(Ipotesi!$C$5-1)*60+1*12+1):INDEX(Motore_Startup!$F$5:$F$544,((Ipotesi!$C$5-1)*60+1*12+1)+11)) -> 324913.96 | E5: =SUM(INDEX(Motore_Startup!$F$5:$F$544,(Ipotesi!$C$5-1)*60+2*12+1):INDEX(Motore_Startup!$F$5:$F$544,((Ipotesi!$C$5-1)*60+2*12+1)+11)) -> 807406.25 | F5: =SUM(INDEX(Motore_Startup!$F$5:$F$544,(Ipotesi!$C$5-1)*60+3*12+1):INDEX(Motore_Startup!$F$5:$F$544,((Ipotesi!$C$5-1)*60+3*12+1)+11)) -> 1497513.9 | G5: =SUM(INDEX(Motore_Startup!$F$5:$F$544,(Ipotesi!$C$5-1)*60+4*12+1):INDEX(Motore_Startup!$F$5:$F$544,((Ipotesi!$C$5-1)*60+4*12+1)+11)) -> 2259725.3
A6: Canone infragruppo (ricavo S / costo A) | B6: € | C6: =SUM(INDEX(Motore_Startup!$G$5:$G$544,(Ipotesi!$C$5-1)*60+0*12+1):INDEX(Motore_Startup!$G$5:$G$544,((Ipotesi!$C$5-1)*60+0*12+1)+11)) -> 19452.632 | D6: =SUM(INDEX(Motore_Startup!$G$5:$G$544,(Ipotesi!$C$5-1)*60+1*12+1):INDEX(Motore_Startup!$G$5:$G$544,((Ipotesi!$C$5-1)*60+1*12+1)+11)) -> 40777.465 | E6: =SUM(INDEX(Motore_Startup!$G$5:$G$544,(Ipotesi!$C$5-1)*60+2*12+1):INDEX(Motore_Startup!$G$5:$G$544,((Ipotesi!$C$5-1)*60+2*12+1)+11)) -> 72600 | F6: =SUM(INDEX(Motore_Startup!$G$5:$G$544,(Ipotesi!$C$5-1)*60+3*12+1):INDEX(Motore_Startup!$G$5:$G$544,((Ipotesi!$C$5-1)*60+3*12+1)+11)) -> 108290 | G6: =SUM(INDEX(Motore_Startup!$G$5:$G$544,(Ipotesi!$C$5-1)*60+4*12+1):INDEX(Motore_Startup!$G$5:$G$544,((Ipotesi!$C$5-1)*60+4*12+1)+11)) -> 139150
A7: Ricavi conto economico | B7: € | C7: =SUM(INDEX(Motore_Startup!$H$5:$H$544,(Ipotesi!$C$5-1)*60+0*12+1):INDEX(Motore_Startup!$H$5:$H$544,((Ipotesi!$C$5-1)*60+0*12+1)+11)) -> 113202.63 | D7: =SUM(INDEX(Motore_Startup!$H$5:$H$544,(Ipotesi!$C$5-1)*60+1*12+1):INDEX(Motore_Startup!$H$5:$H$544,((Ipotesi!$C$5-1)*60+1*12+1)+11)) -> 365691.43 | E7: =SUM(INDEX(Motore_Startup!$H$5:$H$544,(Ipotesi!$C$5-1)*60+2*12+1):INDEX(Motore_Startup!$H$5:$H$544,((Ipotesi!$C$5-1)*60+2*12+1)+11)) -> 880006.25 | F7: =SUM(INDEX(Motore_Startup!$H$5:$H$544,(Ipotesi!$C$5-1)*60+3*12+1):INDEX(Motore_Startup!$H$5:$H$544,((Ipotesi!$C$5-1)*60+3*12+1)+11)) -> 1605803.9 | G7: =SUM(INDEX(Motore_Startup!$H$5:$H$544,(Ipotesi!$C$5-1)*60+4*12+1):INDEX(Motore_Startup!$H$5:$H$544,((Ipotesi!$C$5-1)*60+4*12+1)+11)) -> 2398875.3
A8: Costi operativi | B8: € | C8: =SUM(INDEX(Motore_Startup!$I$5:$I$544,(Ipotesi!$C$5-1)*60+0*12+1):INDEX(Motore_Startup!$I$5:$I$544,((Ipotesi!$C$5-1)*60+0*12+1)+11)) -> 333383.58 | D8: =SUM(INDEX(Motore_Startup!$I$5:$I$544,(Ipotesi!$C$5-1)*60+1*12+1):INDEX(Motore_Startup!$I$5:$I$544,((Ipotesi!$C$5-1)*60+1*12+1)+11)) -> 690041.28 | E8: =SUM(INDEX(Motore_Startup!$I$5:$I$544,(Ipotesi!$C$5-1)*60+2*12+1):INDEX(Motore_Startup!$I$5:$I$544,((Ipotesi!$C$5-1)*60+2*12+1)+11)) -> 1401048.9 | F8: =SUM(INDEX(Motore_Startup!$I$5:$I$544,(Ipotesi!$C$5-1)*60+3*12+1):INDEX(Motore_Startup!$I$5:$I$544,((Ipotesi!$C$5-1)*60+3*12+1)+11)) -> 1884917.7 | G8: =SUM(INDEX(Motore_Startup!$I$5:$I$544,(Ipotesi!$C$5-1)*60+4*12+1):INDEX(Motore_Startup!$I$5:$I$544,((Ipotesi!$C$5-1)*60+4*12+1)+11)) -> 2388274
A9: EBITDA senza contributi | B9: € | C9: =SUM(INDEX(Motore_Startup!$J$5:$J$544,(Ipotesi!$C$5-1)*60+0*12+1):INDEX(Motore_Startup!$J$5:$J$544,((Ipotesi!$C$5-1)*60+0*12+1)+11)) -> -220180.95 | D9: =SUM(INDEX(Motore_Startup!$J$5:$J$544,(Ipotesi!$C$5-1)*60+1*12+1):INDEX(Motore_Startup!$J$5:$J$544,((Ipotesi!$C$5-1)*60+1*12+1)+11)) -> -324349.85 | E9: =SUM(INDEX(Motore_Startup!$J$5:$J$544,(Ipotesi!$C$5-1)*60+2*12+1):INDEX(Motore_Startup!$J$5:$J$544,((Ipotesi!$C$5-1)*60+2*12+1)+11)) -> -521042.63 | F9: =SUM(INDEX(Motore_Startup!$J$5:$J$544,(Ipotesi!$C$5-1)*60+3*12+1):INDEX(Motore_Startup!$J$5:$J$544,((Ipotesi!$C$5-1)*60+3*12+1)+11)) -> -279113.73 | G9: =SUM(INDEX(Motore_Startup!$J$5:$J$544,(Ipotesi!$C$5-1)*60+4*12+1):INDEX(Motore_Startup!$J$5:$J$544,((Ipotesi!$C$5-1)*60+4*12+1)+11)) -> 10601.279
A10: Ammortamenti | B10: € | C10: =SUM(INDEX(Motore_Startup!$L$5:$L$544,(Ipotesi!$C$5-1)*60+0*12+1):INDEX(Motore_Startup!$L$5:$L$544,((Ipotesi!$C$5-1)*60+0*12+1)+11)) -> 3611.1111 | D10: =SUM(INDEX(Motore_Startup!$L$5:$L$544,(Ipotesi!$C$5-1)*60+1*12+1):INDEX(Motore_Startup!$L$5:$L$544,((Ipotesi!$C$5-1)*60+1*12+1)+11)) -> 11180.556 | E10: =SUM(INDEX(Motore_Startup!$L$5:$L$544,(Ipotesi!$C$5-1)*60+2*12+1):INDEX(Motore_Startup!$L$5:$L$544,((Ipotesi!$C$5-1)*60+2*12+1)+11)) -> 20416.667 | F10: =SUM(INDEX(Motore_Startup!$L$5:$L$544,(Ipotesi!$C$5-1)*60+3*12+1):INDEX(Motore_Startup!$L$5:$L$544,((Ipotesi!$C$5-1)*60+3*12+1)+11)) -> 28611.111 | G10: =SUM(INDEX(Motore_Startup!$L$5:$L$544,(Ipotesi!$C$5-1)*60+4*12+1):INDEX(Motore_Startup!$L$5:$L$544,((Ipotesi!$C$5-1)*60+4*12+1)+11)) -> 36180.556
A11: EBIT | B11: € | C11: =SUM(INDEX(Motore_Startup!$M$5:$M$544,(Ipotesi!$C$5-1)*60+0*12+1):INDEX(Motore_Startup!$M$5:$M$544,((Ipotesi!$C$5-1)*60+0*12+1)+11)) -> -223792.06 | D11: =SUM(INDEX(Motore_Startup!$M$5:$M$544,(Ipotesi!$C$5-1)*60+1*12+1):INDEX(Motore_Startup!$M$5:$M$544,((Ipotesi!$C$5-1)*60+1*12+1)+11)) -> -335530.41 | E11: =SUM(INDEX(Motore_Startup!$M$5:$M$544,(Ipotesi!$C$5-1)*60+2*12+1):INDEX(Motore_Startup!$M$5:$M$544,((Ipotesi!$C$5-1)*60+2*12+1)+11)) -> -541459.29 | F11: =SUM(INDEX(Motore_Startup!$M$5:$M$544,(Ipotesi!$C$5-1)*60+3*12+1):INDEX(Motore_Startup!$M$5:$M$544,((Ipotesi!$C$5-1)*60+3*12+1)+11)) -> -307724.85 | G11: =SUM(INDEX(Motore_Startup!$M$5:$M$544,(Ipotesi!$C$5-1)*60+4*12+1):INDEX(Motore_Startup!$M$5:$M$544,((Ipotesi!$C$5-1)*60+4*12+1)+11)) -> -25579.277
A12: Contributo SS gestionale | B12: € | C12: =SUM(INDEX(Motore_Startup!$N$5:$N$544,(Ipotesi!$C$5-1)*60+0*12+1):INDEX(Motore_Startup!$N$5:$N$544,((Ipotesi!$C$5-1)*60+0*12+1)+11)) -> 14322.667 | D12: =SUM(INDEX(Motore_Startup!$N$5:$N$544,(Ipotesi!$C$5-1)*60+1*12+1):INDEX(Motore_Startup!$N$5:$N$544,((Ipotesi!$C$5-1)*60+1*12+1)+11)) -> 52143.783 | E12: =SUM(INDEX(Motore_Startup!$N$5:$N$544,(Ipotesi!$C$5-1)*60+2*12+1):INDEX(Motore_Startup!$N$5:$N$544,((Ipotesi!$C$5-1)*60+2*12+1)+11)) -> 36987.692 | F12: =SUM(INDEX(Motore_Startup!$N$5:$N$544,(Ipotesi!$C$5-1)*60+3*12+1):INDEX(Motore_Startup!$N$5:$N$544,((Ipotesi!$C$5-1)*60+3*12+1)+11)) -> 0 | G12: =SUM(INDEX(Motore_Startup!$N$5:$N$544,(Ipotesi!$C$5-1)*60+4*12+1):INDEX(Motore_Startup!$N$5:$N$544,((Ipotesi!$C$5-1)*60+4*12+1)+11)) -> 0
A13: Interessi e commissioni | B13: € | C13: =SUM(INDEX(Motore_Startup!$O$5:$O$544,(Ipotesi!$C$5-1)*60+0*12+1):INDEX(Motore_Startup!$O$5:$O$544,((Ipotesi!$C$5-1)*60+0*12+1)+11)) -> 2032.2039 | D13: =SUM(INDEX(Motore_Startup!$O$5:$O$544,(Ipotesi!$C$5-1)*60+1*12+1):INDEX(Motore_Startup!$O$5:$O$544,((Ipotesi!$C$5-1)*60+1*12+1)+11)) -> 5539.1636 | E13: =SUM(INDEX(Motore_Startup!$O$5:$O$544,(Ipotesi!$C$5-1)*60+2*12+1):INDEX(Motore_Startup!$O$5:$O$544,((Ipotesi!$C$5-1)*60+2*12+1)+11)) -> 2621.31 | F13: =SUM(INDEX(Motore_Startup!$O$5:$O$544,(Ipotesi!$C$5-1)*60+3*12+1):INDEX(Motore_Startup!$O$5:$O$544,((Ipotesi!$C$5-1)*60+3*12+1)+11)) -> 0 | G13: =SUM(INDEX(Motore_Startup!$O$5:$O$544,(Ipotesi!$C$5-1)*60+4*12+1):INDEX(Motore_Startup!$O$5:$O$544,((Ipotesi!$C$5-1)*60+4*12+1)+11)) -> 5738.2277
A14: Risultato ante imposte | B14: € | C14: =SUM(INDEX(Motore_Startup!$P$5:$P$544,(Ipotesi!$C$5-1)*60+0*12+1):INDEX(Motore_Startup!$P$5:$P$544,((Ipotesi!$C$5-1)*60+0*12+1)+11)) -> -211501.6 | D14: =SUM(INDEX(Motore_Startup!$P$5:$P$544,(Ipotesi!$C$5-1)*60+1*12+1):INDEX(Motore_Startup!$P$5:$P$544,((Ipotesi!$C$5-1)*60+1*12+1)+11)) -> -288925.79 | E14: =SUM(INDEX(Motore_Startup!$P$5:$P$544,(Ipotesi!$C$5-1)*60+2*12+1):INDEX(Motore_Startup!$P$5:$P$544,((Ipotesi!$C$5-1)*60+2*12+1)+11)) -> -507092.91 | F14: =SUM(INDEX(Motore_Startup!$P$5:$P$544,(Ipotesi!$C$5-1)*60+3*12+1):INDEX(Motore_Startup!$P$5:$P$544,((Ipotesi!$C$5-1)*60+3*12+1)+11)) -> -307724.85 | G14: =SUM(INDEX(Motore_Startup!$P$5:$P$544,(Ipotesi!$C$5-1)*60+4*12+1):INDEX(Motore_Startup!$P$5:$P$544,((Ipotesi!$C$5-1)*60+4*12+1)+11)) -> -31317.505
A15: Imposte CE | B15: € | C15: =SUM(INDEX(Motore_Startup!$X$5:$X$544,(Ipotesi!$C$5-1)*60+0*12+1):INDEX(Motore_Startup!$X$5:$X$544,((Ipotesi!$C$5-1)*60+0*12+1)+11)) -> 0 | D15: =SUM(INDEX(Motore_Startup!$X$5:$X$544,(Ipotesi!$C$5-1)*60+1*12+1):INDEX(Motore_Startup!$X$5:$X$544,((Ipotesi!$C$5-1)*60+1*12+1)+11)) -> 0 | E15: =SUM(INDEX(Motore_Startup!$X$5:$X$544,(Ipotesi!$C$5-1)*60+2*12+1):INDEX(Motore_Startup!$X$5:$X$544,((Ipotesi!$C$5-1)*60+2*12+1)+11)) -> 0 | F15: =SUM(INDEX(Motore_Startup!$X$5:$X$544,(Ipotesi!$C$5-1)*60+3*12+1):INDEX(Motore_Startup!$X$5:$X$544,((Ipotesi!$C$5-1)*60+3*12+1)+11)) -> 0 | G15: =SUM(INDEX(Motore_Startup!$X$5:$X$544,(Ipotesi!$C$5-1)*60+4*12+1):INDEX(Motore_Startup!$X$5:$X$544,((Ipotesi!$C$5-1)*60+4*12+1)+11)) -> 0
A16: Utile netto | B16: € | C16: =SUM(INDEX(Motore_Startup!$Y$5:$Y$544,(Ipotesi!$C$5-1)*60+0*12+1):INDEX(Motore_Startup!$Y$5:$Y$544,((Ipotesi!$C$5-1)*60+0*12+1)+11)) -> -211501.6 | D16: =SUM(INDEX(Motore_Startup!$Y$5:$Y$544,(Ipotesi!$C$5-1)*60+1*12+1):INDEX(Motore_Startup!$Y$5:$Y$544,((Ipotesi!$C$5-1)*60+1*12+1)+11)) -> -288925.79 | E16: =SUM(INDEX(Motore_Startup!$Y$5:$Y$544,(Ipotesi!$C$5-1)*60+2*12+1):INDEX(Motore_Startup!$Y$5:$Y$544,((Ipotesi!$C$5-1)*60+2*12+1)+11)) -> -507092.91 | F16: =SUM(INDEX(Motore_Startup!$Y$5:$Y$544,(Ipotesi!$C$5-1)*60+3*12+1):INDEX(Motore_Startup!$Y$5:$Y$544,((Ipotesi!$C$5-1)*60+3*12+1)+11)) -> -307724.85 | G16: =SUM(INDEX(Motore_Startup!$Y$5:$Y$544,(Ipotesi!$C$5-1)*60+4*12+1):INDEX(Motore_Startup!$Y$5:$Y$544,((Ipotesi!$C$5-1)*60+4*12+1)+11)) -> -31317.505
A18: Cassa teorica a fine anno / deficit | B18: € | C18: =INDEX(Motore_Startup!$BH$5:$BH$544,((Ipotesi!$C$5-1)*60+0*12+1)+11) -> 25000 | D18: =INDEX(Motore_Startup!$BH$5:$BH$544,((Ipotesi!$C$5-1)*60+1*12+1)+11) -> 40136.79 | E18: =INDEX(Motore_Startup!$BH$5:$BH$544,((Ipotesi!$C$5-1)*60+2*12+1)+11) -> 448452.52 | F18: =INDEX(Motore_Startup!$BH$5:$BH$544,((Ipotesi!$C$5-1)*60+3*12+1)+11) -> 28722.381 | G18: =INDEX(Motore_Startup!$BH$5:$BH$544,((Ipotesi!$C$5-1)*60+4*12+1)+11) -> 25000
A19: Minimo mensile di cassa nell'anno | B19: € | C19: =MIN(INDEX(Motore_Startup!$BH$5:$BH$544,(Ipotesi!$C$5-1)*60+0*12+1):INDEX(Motore_Startup!$BH$5:$BH$544,((Ipotesi!$C$5-1)*60+0*12+1)+11)) -> 25000 | D19: =MIN(INDEX(Motore_Startup!$BH$5:$BH$544,(Ipotesi!$C$5-1)*60+1*12+1):INDEX(Motore_Startup!$BH$5:$BH$544,((Ipotesi!$C$5-1)*60+1*12+1)+11)) -> -73138.76 | E19: =MIN(INDEX(Motore_Startup!$BH$5:$BH$544,(Ipotesi!$C$5-1)*60+2*12+1):INDEX(Motore_Startup!$BH$5:$BH$544,((Ipotesi!$C$5-1)*60+2*12+1)+11)) -> -73078.563 | F19: =MIN(INDEX(Motore_Startup!$BH$5:$BH$544,(Ipotesi!$C$5-1)*60+3*12+1):INDEX(Motore_Startup!$BH$5:$BH$544,((Ipotesi!$C$5-1)*60+3*12+1)+11)) -> 28722.381 | G19: =MIN(INDEX(Motore_Startup!$BH$5:$BH$544,(Ipotesi!$C$5-1)*60+4*12+1):INDEX(Motore_Startup!$BH$5:$BH$544,((Ipotesi!$C$5-1)*60+4*12+1)+11)) -> 25000
A20: Massimo fabbisogno per buffer nell'anno | B20: € | C20: =MAX(INDEX(Motore_Startup!$BI$5:$BI$544,(Ipotesi!$C$5-1)*60+0*12+1):INDEX(Motore_Startup!$BI$5:$BI$544,((Ipotesi!$C$5-1)*60+0*12+1)+11)) -> 0 | D20: =MAX(INDEX(Motore_Startup!$BI$5:$BI$544,(Ipotesi!$C$5-1)*60+1*12+1):INDEX(Motore_Startup!$BI$5:$BI$544,((Ipotesi!$C$5-1)*60+1*12+1)+11)) -> 98138.76 | E20: =MAX(INDEX(Motore_Startup!$BI$5:$BI$544,(Ipotesi!$C$5-1)*60+2*12+1):INDEX(Motore_Startup!$BI$5:$BI$544,((Ipotesi!$C$5-1)*60+2*12+1)+11)) -> 98078.563 | F20: =MAX(INDEX(Motore_Startup!$BI$5:$BI$544,(Ipotesi!$C$5-1)*60+3*12+1):INDEX(Motore_Startup!$BI$5:$BI$544,((Ipotesi!$C$5-1)*60+3*12+1)+11)) -> 0 | G20: =MAX(INDEX(Motore_Startup!$BI$5:$BI$544,(Ipotesi!$C$5-1)*60+4*12+1):INDEX(Motore_Startup!$BI$5:$BI$544,((Ipotesi!$C$5-1)*60+4*12+1)+11)) -> 0
A21: Fido utilizzato a fine anno | B21: € | C21: =INDEX(Motore_Startup!$BG$5:$BG$544,((Ipotesi!$C$5-1)*60+0*12+1)+11) -> 83960.882 | D21: =INDEX(Motore_Startup!$BG$5:$BG$544,((Ipotesi!$C$5-1)*60+1*12+1)+11) -> 0 | E21: =INDEX(Motore_Startup!$BG$5:$BG$544,((Ipotesi!$C$5-1)*60+2*12+1)+11) -> 0 | F21: =INDEX(Motore_Startup!$BG$5:$BG$544,((Ipotesi!$C$5-1)*60+3*12+1)+11) -> 0 | G21: =INDEX(Motore_Startup!$BG$5:$BG$544,((Ipotesi!$C$5-1)*60+4*12+1)+11) -> 111879
A22: SS erogato nell'anno | B22: € | C22: =SUM(INDEX(Motore_Startup!$BA$5:$BA$544,(Ipotesi!$C$5-1)*60+0*12+1):INDEX(Motore_Startup!$BA$5:$BA$544,((Ipotesi!$C$5-1)*60+0*12+1)+11)) -> 52542.222 | D22: =SUM(INDEX(Motore_Startup!$BA$5:$BA$544,(Ipotesi!$C$5-1)*60+1*12+1):INDEX(Motore_Startup!$BA$5:$BA$544,((Ipotesi!$C$5-1)*60+1*12+1)+11)) -> 190079.28 | E22: =SUM(INDEX(Motore_Startup!$BA$5:$BA$544,(Ipotesi!$C$5-1)*60+2*12+1):INDEX(Motore_Startup!$BA$5:$BA$544,((Ipotesi!$C$5-1)*60+2*12+1)+11)) -> 126225.64 | F22: =SUM(INDEX(Motore_Startup!$BA$5:$BA$544,(Ipotesi!$C$5-1)*60+3*12+1):INDEX(Motore_Startup!$BA$5:$BA$544,((Ipotesi!$C$5-1)*60+3*12+1)+11)) -> 0 | G22: =SUM(INDEX(Motore_Startup!$BA$5:$BA$544,(Ipotesi!$C$5-1)*60+4*12+1):INDEX(Motore_Startup!$BA$5:$BA$544,((Ipotesi!$C$5-1)*60+4*12+1)+11)) -> 0
A23: SS rimborsato nell'anno | B23: € | C23: =SUM(INDEX(Motore_Startup!$BB$5:$BB$544,(Ipotesi!$C$5-1)*60+0*12+1):INDEX(Motore_Startup!$BB$5:$BB$544,((Ipotesi!$C$5-1)*60+0*12+1)+11)) -> 0 | D23: =SUM(INDEX(Motore_Startup!$BB$5:$BB$544,(Ipotesi!$C$5-1)*60+1*12+1):INDEX(Motore_Startup!$BB$5:$BB$544,((Ipotesi!$C$5-1)*60+1*12+1)+11)) -> 0 | E23: =SUM(INDEX(Motore_Startup!$BB$5:$BB$544,(Ipotesi!$C$5-1)*60+2*12+1):INDEX(Motore_Startup!$BB$5:$BB$544,((Ipotesi!$C$5-1)*60+2*12+1)+11)) -> 0 | F23: =SUM(INDEX(Motore_Startup!$BB$5:$BB$544,(Ipotesi!$C$5-1)*60+3*12+1):INDEX(Motore_Startup!$BB$5:$BB$544,((Ipotesi!$C$5-1)*60+3*12+1)+11)) -> 26539.3 | G23: =SUM(INDEX(Motore_Startup!$BB$5:$BB$544,(Ipotesi!$C$5-1)*60+4*12+1):INDEX(Motore_Startup!$BB$5:$BB$544,((Ipotesi!$C$5-1)*60+4*12+1)+11)) -> 26539.3
A24: Debito SS residuo | B24: € | C24: =INDEX(Motore_Startup!$BC$5:$BC$544,((Ipotesi!$C$5-1)*60+0*12+1)+11) -> 38219.556 | D24: =INDEX(Motore_Startup!$BC$5:$BC$544,((Ipotesi!$C$5-1)*60+1*12+1)+11) -> 176155.05 | E24: =INDEX(Motore_Startup!$BC$5:$BC$544,((Ipotesi!$C$5-1)*60+2*12+1)+11) -> 265393 | F24: =INDEX(Motore_Startup!$BC$5:$BC$544,((Ipotesi!$C$5-1)*60+3*12+1)+11) -> 238853.7 | G24: =INDEX(Motore_Startup!$BC$5:$BC$544,((Ipotesi!$C$5-1)*60+4*12+1)+11) -> 212314.4
A25: Apporti iniziali | B25: € | C25: =SUM(INDEX(Motore_Startup!$AW$5:$AW$544,(Ipotesi!$C$5-1)*60+0*12+1):INDEX(Motore_Startup!$AW$5:$AW$544,((Ipotesi!$C$5-1)*60+0*12+1)+11)) -> 130000 | D25: =SUM(INDEX(Motore_Startup!$AW$5:$AW$544,(Ipotesi!$C$5-1)*60+1*12+1):INDEX(Motore_Startup!$AW$5:$AW$544,((Ipotesi!$C$5-1)*60+1*12+1)+11)) -> 0 | E25: =SUM(INDEX(Motore_Startup!$AW$5:$AW$544,(Ipotesi!$C$5-1)*60+2*12+1):INDEX(Motore_Startup!$AW$5:$AW$544,((Ipotesi!$C$5-1)*60+2*12+1)+11)) -> 0 | F25: =SUM(INDEX(Motore_Startup!$AW$5:$AW$544,(Ipotesi!$C$5-1)*60+3*12+1):INDEX(Motore_Startup!$AW$5:$AW$544,((Ipotesi!$C$5-1)*60+3*12+1)+11)) -> 0 | G25: =SUM(INDEX(Motore_Startup!$AW$5:$AW$544,(Ipotesi!$C$5-1)*60+4*12+1):INDEX(Motore_Startup!$AW$5:$AW$544,((Ipotesi!$C$5-1)*60+4*12+1)+11)) -> 0
A26: Round incassati | B26: € | C26: =SUM(INDEX(Motore_Startup!$AX$5:$AX$544,(Ipotesi!$C$5-1)*60+0*12+1):INDEX(Motore_Startup!$AX$5:$AX$544,((Ipotesi!$C$5-1)*60+0*12+1)+11)) -> 0 | D26: =SUM(INDEX(Motore_Startup!$AX$5:$AX$544,(Ipotesi!$C$5-1)*60+1*12+1):INDEX(Motore_Startup!$AX$5:$AX$544,((Ipotesi!$C$5-1)*60+1*12+1)+11)) -> 300000 | E26: =SUM(INDEX(Motore_Startup!$AX$5:$AX$544,(Ipotesi!$C$5-1)*60+2*12+1):INDEX(Motore_Startup!$AX$5:$AX$544,((Ipotesi!$C$5-1)*60+2*12+1)+11)) -> 900000 | F26: =SUM(INDEX(Motore_Startup!$AX$5:$AX$544,(Ipotesi!$C$5-1)*60+3*12+1):INDEX(Motore_Startup!$AX$5:$AX$544,((Ipotesi!$C$5-1)*60+3*12+1)+11)) -> 0 | G26: =SUM(INDEX(Motore_Startup!$AX$5:$AX$544,(Ipotesi!$C$5-1)*60+4*12+1):INDEX(Motore_Startup!$AX$5:$AX$544,((Ipotesi!$C$5-1)*60+4*12+1)+11)) -> 0
A27: Dividendi lordi distribuiti | B27: € | C27: =SUM(INDEX(Motore_Startup!$AY$5:$AY$544,(Ipotesi!$C$5-1)*60+0*12+1):INDEX(Motore_Startup!$AY$5:$AY$544,((Ipotesi!$C$5-1)*60+0*12+1)+11)) -> 0 | D27: =SUM(INDEX(Motore_Startup!$AY$5:$AY$544,(Ipotesi!$C$5-1)*60+1*12+1):INDEX(Motore_Startup!$AY$5:$AY$544,((Ipotesi!$C$5-1)*60+1*12+1)+11)) -> 0 | E27: =SUM(INDEX(Motore_Startup!$AY$5:$AY$544,(Ipotesi!$C$5-1)*60+2*12+1):INDEX(Motore_Startup!$AY$5:$AY$544,((Ipotesi!$C$5-1)*60+2*12+1)+11)) -> 0 | F27: =SUM(INDEX(Motore_Startup!$AY$5:$AY$544,(Ipotesi!$C$5-1)*60+3*12+1):INDEX(Motore_Startup!$AY$5:$AY$544,((Ipotesi!$C$5-1)*60+3*12+1)+11)) -> 0 | G27: =SUM(INDEX(Motore_Startup!$AY$5:$AY$544,(Ipotesi!$C$5-1)*60+4*12+1):INDEX(Motore_Startup!$AY$5:$AY$544,((Ipotesi!$C$5-1)*60+4*12+1)+11)) -> 0
A28: Dividendi reinvestiti dai soci | B28: € | C28: =SUM(INDEX(Motore_Startup!$AZ$5:$AZ$544,(Ipotesi!$C$5-1)*60+0*12+1):INDEX(Motore_Startup!$AZ$5:$AZ$544,((Ipotesi!$C$5-1)*60+0*12+1)+11)) -> 0 | D28: =SUM(INDEX(Motore_Startup!$AZ$5:$AZ$544,(Ipotesi!$C$5-1)*60+1*12+1):INDEX(Motore_Startup!$AZ$5:$AZ$544,((Ipotesi!$C$5-1)*60+1*12+1)+11)) -> 0 | E28: =SUM(INDEX(Motore_Startup!$AZ$5:$AZ$544,(Ipotesi!$C$5-1)*60+2*12+1):INDEX(Motore_Startup!$AZ$5:$AZ$544,((Ipotesi!$C$5-1)*60+2*12+1)+11)) -> 0 | F28: =SUM(INDEX(Motore_Startup!$AZ$5:$AZ$544,(Ipotesi!$C$5-1)*60+3*12+1):INDEX(Motore_Startup!$AZ$5:$AZ$544,((Ipotesi!$C$5-1)*60+3*12+1)+11)) -> 35707.016 | G28: =SUM(INDEX(Motore_Startup!$AZ$5:$AZ$544,(Ipotesi!$C$5-1)*60+4*12+1):INDEX(Motore_Startup!$AZ$5:$AZ$544,((Ipotesi!$C$5-1)*60+4*12+1)+11)) -> 69723.393
A30: Crediti esterni IVA inclusa | B30: € | C30: =INDEX(Motore_Startup!$AD$5:$AD$544,((Ipotesi!$C$5-1)*60+0*12+1)+11) -> 29991.667 | D30: =INDEX(Motore_Startup!$AD$5:$AD$544,((Ipotesi!$C$5-1)*60+1*12+1)+11) -> 113239.53 | E30: =INDEX(Motore_Startup!$AD$5:$AD$544,((Ipotesi!$C$5-1)*60+2*12+1)+11) -> 286627 | F30: =INDEX(Motore_Startup!$AD$5:$AD$544,((Ipotesi!$C$5-1)*60+3*12+1)+11) -> 504631.67 | G30: =INDEX(Motore_Startup!$AD$5:$AD$544,((Ipotesi!$C$5-1)*60+4*12+1)+11) -> 743698.48
A31: Saldo infragruppo | B31: € | C31: =INDEX(Motore_Startup!$AG$5:$AG$544,((Ipotesi!$C$5-1)*60+0*12+1)+11) -> 1977.6842 | D31: =INDEX(Motore_Startup!$AG$5:$AG$544,((Ipotesi!$C$5-1)*60+1*12+1)+11) -> 4145.7089 | E31: =INDEX(Motore_Startup!$AG$5:$AG$544,((Ipotesi!$C$5-1)*60+2*12+1)+11) -> 7381 | F31: =INDEX(Motore_Startup!$AG$5:$AG$544,((Ipotesi!$C$5-1)*60+3*12+1)+11) -> 11009.483 | G31: =INDEX(Motore_Startup!$AG$5:$AG$544,((Ipotesi!$C$5-1)*60+4*12+1)+11) -> 14146.917
A32: Debiti fornitori esterni | B32: € | C32: =INDEX(Motore_Startup!$AJ$5:$AJ$544,((Ipotesi!$C$5-1)*60+0*12+1)+11) -> 23562.548 | D32: =INDEX(Motore_Startup!$AJ$5:$AJ$544,((Ipotesi!$C$5-1)*60+1*12+1)+11) -> 43547.568 | E32: =INDEX(Motore_Startup!$AJ$5:$AJ$544,((Ipotesi!$C$5-1)*60+2*12+1)+11) -> 104937.84 | F32: =INDEX(Motore_Startup!$AJ$5:$AJ$544,((Ipotesi!$C$5-1)*60+3*12+1)+11) -> 148703.05 | G32: =INDEX(Motore_Startup!$AJ$5:$AJ$544,((Ipotesi!$C$5-1)*60+4*12+1)+11) -> 194334.47
A33: Saldo IVA (debito + / credito -) | B33: € | C33: =INDEX(Motore_Startup!$AM$5:$AM$544,((Ipotesi!$C$5-1)*60+0*12+1)+11) -> -1633.1503 | D33: =INDEX(Motore_Startup!$AM$5:$AM$544,((Ipotesi!$C$5-1)*60+1*12+1)+11) -> 3847.6305 | E33: =INDEX(Motore_Startup!$AM$5:$AM$544,((Ipotesi!$C$5-1)*60+2*12+1)+11) -> 10269.946 | F33: =INDEX(Motore_Startup!$AM$5:$AM$544,((Ipotesi!$C$5-1)*60+3*12+1)+11) -> 20469.921 | G33: =INDEX(Motore_Startup!$AM$5:$AM$544,((Ipotesi!$C$5-1)*60+4*12+1)+11) -> 31707.815
A34: Saldo imposte (debito + / credito -) | B34: € | C34: =INDEX(Motore_Startup!$AR$5:$AR$544,((Ipotesi!$C$5-1)*60+0*12+1)+11) -> 0 | D34: =INDEX(Motore_Startup!$AR$5:$AR$544,((Ipotesi!$C$5-1)*60+1*12+1)+11) -> 0 | E34: =INDEX(Motore_Startup!$AR$5:$AR$544,((Ipotesi!$C$5-1)*60+2*12+1)+11) -> 0 | F34: =INDEX(Motore_Startup!$AR$5:$AR$544,((Ipotesi!$C$5-1)*60+3*12+1)+11) -> 0 | G34: =INDEX(Motore_Startup!$AR$5:$AR$544,((Ipotesi!$C$5-1)*60+4*12+1)+11) -> 0
A35: Fondo TFR | B35: € | C35: =INDEX(Motore_Startup!$AV$5:$AV$544,((Ipotesi!$C$5-1)*60+0*12+1)+11) -> 10750 | D35: =INDEX(Motore_Startup!$AV$5:$AV$544,((Ipotesi!$C$5-1)*60+1*12+1)+11) -> 34607.5 | E35: =INDEX(Motore_Startup!$AV$5:$AV$544,((Ipotesi!$C$5-1)*60+2*12+1)+11) -> 79171.7 | F35: =INDEX(Motore_Startup!$AV$5:$AV$544,((Ipotesi!$C$5-1)*60+3*12+1)+11) -> 137055.55 | G35: =INDEX(Motore_Startup!$AV$5:$AV$544,((Ipotesi!$C$5-1)*60+4*12+1)+11) -> 208741.95
A36: Immobilizzazioni nette | B36: € | C36: =INDEX(Motore_Startup!$BL$5:$BL$544,((Ipotesi!$C$5-1)*60+0*12+1)+11) -> 16388.889 | D36: =INDEX(Motore_Startup!$BL$5:$BL$544,((Ipotesi!$C$5-1)*60+1*12+1)+11) -> 30208.333 | E36: =INDEX(Motore_Startup!$BL$5:$BL$544,((Ipotesi!$C$5-1)*60+2*12+1)+11) -> 39791.667 | F36: =INDEX(Motore_Startup!$BL$5:$BL$544,((Ipotesi!$C$5-1)*60+3*12+1)+11) -> 51180.556 | G36: =INDEX(Motore_Startup!$BL$5:$BL$544,((Ipotesi!$C$5-1)*60+4*12+1)+11) -> 65000
A37: Patrimonio netto | B37: € | C37: =INDEX(Motore_Startup!$BQ$5:$BQ$544,((Ipotesi!$C$5-1)*60+0*12+1)+11) -> -81501.596 | D37: =INDEX(Motore_Startup!$BQ$5:$BQ$544,((Ipotesi!$C$5-1)*60+1*12+1)+11) -> -70427.385 | E37: =INDEX(Motore_Startup!$BQ$5:$BQ$544,((Ipotesi!$C$5-1)*60+2*12+1)+11) -> 322479.7 | F37: =INDEX(Motore_Startup!$BQ$5:$BQ$544,((Ipotesi!$C$5-1)*60+3*12+1)+11) -> 50461.874 | G37: =INDEX(Motore_Startup!$BQ$5:$BQ$544,((Ipotesi!$C$5-1)*60+4*12+1)+11) -> 88867.762
A38: Totale attività teoriche | B38: € | C38: =INDEX(Motore_Startup!$BR$5:$BR$544,((Ipotesi!$C$5-1)*60+0*12+1)+11) -> 74991.39 | D38: =INDEX(Motore_Startup!$BR$5:$BR$544,((Ipotesi!$C$5-1)*60+1*12+1)+11) -> 187730.36 | E38: =INDEX(Motore_Startup!$BR$5:$BR$544,((Ipotesi!$C$5-1)*60+2*12+1)+11) -> 782252.19 | F38: =INDEX(Motore_Startup!$BR$5:$BR$544,((Ipotesi!$C$5-1)*60+3*12+1)+11) -> 595544.09 | G38: =INDEX(Motore_Startup!$BR$5:$BR$544,((Ipotesi!$C$5-1)*60+4*12+1)+11) -> 847845.4
A39: Passività e patrimonio netto | B39: € | C39: =INDEX(Motore_Startup!$BS$5:$BS$544,((Ipotesi!$C$5-1)*60+0*12+1)+11) -> 74991.39 | D39: =INDEX(Motore_Startup!$BS$5:$BS$544,((Ipotesi!$C$5-1)*60+1*12+1)+11) -> 187730.36 | E39: =INDEX(Motore_Startup!$BS$5:$BS$544,((Ipotesi!$C$5-1)*60+2*12+1)+11) -> 782252.19 | F39: =INDEX(Motore_Startup!$BS$5:$BS$544,((Ipotesi!$C$5-1)*60+3*12+1)+11) -> 595544.09 | G39: =INDEX(Motore_Startup!$BS$5:$BS$544,((Ipotesi!$C$5-1)*60+4*12+1)+11) -> 847845.4
A40: Quadratura SP fine anno | B40: € | C40: =INDEX(Motore_Startup!$BT$5:$BT$544,((Ipotesi!$C$5-1)*60+0*12+1)+11) -> 0 | D40: =INDEX(Motore_Startup!$BT$5:$BT$544,((Ipotesi!$C$5-1)*60+1*12+1)+11) -> 0 | E40: =INDEX(Motore_Startup!$BT$5:$BT$544,((Ipotesi!$C$5-1)*60+2*12+1)+11) -> 0 | F40: =INDEX(Motore_Startup!$BT$5:$BT$544,((Ipotesi!$C$5-1)*60+3*12+1)+11) -> 0 | G40: =INDEX(Motore_Startup!$BT$5:$BT$544,((Ipotesi!$C$5-1)*60+4*12+1)+11) -> 0
A42: Investimenti pagati ex IVA | B42: € | C42: =SUM(INDEX(Motore_Startup!$K$5:$K$544,(Ipotesi!$C$5-1)*60+0*12+1):INDEX(Motore_Startup!$K$5:$K$544,((Ipotesi!$C$5-1)*60+0*12+1)+11)) -> 20000 | D42: =SUM(INDEX(Motore_Startup!$K$5:$K$544,(Ipotesi!$C$5-1)*60+1*12+1):INDEX(Motore_Startup!$K$5:$K$544,((Ipotesi!$C$5-1)*60+1*12+1)+11)) -> 25000 | E42: =SUM(INDEX(Motore_Startup!$K$5:$K$544,(Ipotesi!$C$5-1)*60+2*12+1):INDEX(Motore_Startup!$K$5:$K$544,((Ipotesi!$C$5-1)*60+2*12+1)+11)) -> 30000 | F42: =SUM(INDEX(Motore_Startup!$K$5:$K$544,(Ipotesi!$C$5-1)*60+3*12+1):INDEX(Motore_Startup!$K$5:$K$544,((Ipotesi!$C$5-1)*60+3*12+1)+11)) -> 40000 | G42: =SUM(INDEX(Motore_Startup!$K$5:$K$544,(Ipotesi!$C$5-1)*60+4*12+1):INDEX(Motore_Startup!$K$5:$K$544,((Ipotesi!$C$5-1)*60+4*12+1)+11)) -> 50000
A43: Imposte effettivamente pagate | B43: € | C43: =SUM(INDEX(Motore_Startup!$AQ$5:$AQ$544,(Ipotesi!$C$5-1)*60+0*12+1):INDEX(Motore_Startup!$AQ$5:$AQ$544,((Ipotesi!$C$5-1)*60+0*12+1)+11)) -> 0 | D43: =SUM(INDEX(Motore_Startup!$AQ$5:$AQ$544,(Ipotesi!$C$5-1)*60+1*12+1):INDEX(Motore_Startup!$AQ$5:$AQ$544,((Ipotesi!$C$5-1)*60+1*12+1)+11)) -> 0 | E43: =SUM(INDEX(Motore_Startup!$AQ$5:$AQ$544,(Ipotesi!$C$5-1)*60+2*12+1):INDEX(Motore_Startup!$AQ$5:$AQ$544,((Ipotesi!$C$5-1)*60+2*12+1)+11)) -> 0 | F43: =SUM(INDEX(Motore_Startup!$AQ$5:$AQ$544,(Ipotesi!$C$5-1)*60+3*12+1):INDEX(Motore_Startup!$AQ$5:$AQ$544,((Ipotesi!$C$5-1)*60+3*12+1)+11)) -> 0 | G43: =SUM(INDEX(Motore_Startup!$AQ$5:$AQ$544,(Ipotesi!$C$5-1)*60+4*12+1):INDEX(Motore_Startup!$AQ$5:$AQ$544,((Ipotesi!$C$5-1)*60+4*12+1)+11)) -> 0
A44: IVA versata | B44: € | C44: =SUM(INDEX(Motore_Startup!$AL$5:$AL$544,(Ipotesi!$C$5-1)*60+0*12+1):INDEX(Motore_Startup!$AL$5:$AL$544,((Ipotesi!$C$5-1)*60+0*12+1)+11)) -> 0 | D44: =SUM(INDEX(Motore_Startup!$AL$5:$AL$544,(Ipotesi!$C$5-1)*60+1*12+1):INDEX(Motore_Startup!$AL$5:$AL$544,((Ipotesi!$C$5-1)*60+1*12+1)+11)) -> 29660.664 | E44: =SUM(INDEX(Motore_Startup!$AL$5:$AL$544,(Ipotesi!$C$5-1)*60+2*12+1):INDEX(Motore_Startup!$AL$5:$AL$544,((Ipotesi!$C$5-1)*60+2*12+1)+11)) -> 85253.028 | F44: =SUM(INDEX(Motore_Startup!$AL$5:$AL$544,(Ipotesi!$C$5-1)*60+3*12+1):INDEX(Motore_Startup!$AL$5:$AL$544,((Ipotesi!$C$5-1)*60+3*12+1)+11)) -> 198282.89 | G44: =SUM(INDEX(Motore_Startup!$AL$5:$AL$544,(Ipotesi!$C$5-1)*60+4*12+1):INDEX(Motore_Startup!$AL$5:$AL$544,((Ipotesi!$C$5-1)*60+4*12+1)+11)) -> 327014.55
A45: Contributo SS gestionale dell'anno | B45: € | C45: =SUM(INDEX(Motore_Startup!$N$5:$N$544,(Ipotesi!$C$5-1)*60+0*12+1):INDEX(Motore_Startup!$N$5:$N$544,((Ipotesi!$C$5-1)*60+0*12+1)+11)) -> 14322.667 | D45: =SUM(INDEX(Motore_Startup!$N$5:$N$544,(Ipotesi!$C$5-1)*60+1*12+1):INDEX(Motore_Startup!$N$5:$N$544,((Ipotesi!$C$5-1)*60+1*12+1)+11)) -> 52143.783 | E45: =SUM(INDEX(Motore_Startup!$N$5:$N$544,(Ipotesi!$C$5-1)*60+2*12+1):INDEX(Motore_Startup!$N$5:$N$544,((Ipotesi!$C$5-1)*60+2*12+1)+11)) -> 36987.692 | F45: =SUM(INDEX(Motore_Startup!$N$5:$N$544,(Ipotesi!$C$5-1)*60+3*12+1):INDEX(Motore_Startup!$N$5:$N$544,((Ipotesi!$C$5-1)*60+3*12+1)+11)) -> 0 | G45: =SUM(INDEX(Motore_Startup!$N$5:$N$544,(Ipotesi!$C$5-1)*60+4*12+1):INDEX(Motore_Startup!$N$5:$N$544,((Ipotesi!$C$5-1)*60+4*12+1)+11)) -> 0

Sheet Advisory
A1: Advisory | riepilogo annuale selezionato
A2: Patrimonio e cassa autonomi: non sono liberamente trasferibili tra le società.
A4: Indicatore | B4: Unità | C4: 2027 | D4: 2028 | E4: 2029 | F4: 2030 | G4: 2031
A5: Ricavi esterni | B5: € | C5: =SUM(INDEX(Motore_Advisory!$F$5:$F$544,(Ipotesi!$C$5-1)*60+0*12+1):INDEX(Motore_Advisory!$F$5:$F$544,((Ipotesi!$C$5-1)*60+0*12+1)+11)) -> 194526.32 | D5: =SUM(INDEX(Motore_Advisory!$F$5:$F$544,(Ipotesi!$C$5-1)*60+1*12+1):INDEX(Motore_Advisory!$F$5:$F$544,((Ipotesi!$C$5-1)*60+1*12+1)+11)) -> 407774.65 | E5: =SUM(INDEX(Motore_Advisory!$F$5:$F$544,(Ipotesi!$C$5-1)*60+2*12+1):INDEX(Motore_Advisory!$F$5:$F$544,((Ipotesi!$C$5-1)*60+2*12+1)+11)) -> 726000 | F5: =SUM(INDEX(Motore_Advisory!$F$5:$F$544,(Ipotesi!$C$5-1)*60+3*12+1):INDEX(Motore_Advisory!$F$5:$F$544,((Ipotesi!$C$5-1)*60+3*12+1)+11)) -> 1082900 | G5: =SUM(INDEX(Motore_Advisory!$F$5:$F$544,(Ipotesi!$C$5-1)*60+4*12+1):INDEX(Motore_Advisory!$F$5:$F$544,((Ipotesi!$C$5-1)*60+4*12+1)+11)) -> 1391500
A6: Canone infragruppo (ricavo S / costo A) | B6: € | C6: =SUM(INDEX(Motore_Advisory!$G$5:$G$544,(Ipotesi!$C$5-1)*60+0*12+1):INDEX(Motore_Advisory!$G$5:$G$544,((Ipotesi!$C$5-1)*60+0*12+1)+11)) -> 19452.632 | D6: =SUM(INDEX(Motore_Advisory!$G$5:$G$544,(Ipotesi!$C$5-1)*60+1*12+1):INDEX(Motore_Advisory!$G$5:$G$544,((Ipotesi!$C$5-1)*60+1*12+1)+11)) -> 40777.465 | E6: =SUM(INDEX(Motore_Advisory!$G$5:$G$544,(Ipotesi!$C$5-1)*60+2*12+1):INDEX(Motore_Advisory!$G$5:$G$544,((Ipotesi!$C$5-1)*60+2*12+1)+11)) -> 72600 | F6: =SUM(INDEX(Motore_Advisory!$G$5:$G$544,(Ipotesi!$C$5-1)*60+3*12+1):INDEX(Motore_Advisory!$G$5:$G$544,((Ipotesi!$C$5-1)*60+3*12+1)+11)) -> 108290 | G6: =SUM(INDEX(Motore_Advisory!$G$5:$G$544,(Ipotesi!$C$5-1)*60+4*12+1):INDEX(Motore_Advisory!$G$5:$G$544,((Ipotesi!$C$5-1)*60+4*12+1)+11)) -> 139150
A7: Ricavi conto economico | B7: € | C7: =SUM(INDEX(Motore_Advisory!$H$5:$H$544,(Ipotesi!$C$5-1)*60+0*12+1):INDEX(Motore_Advisory!$H$5:$H$544,((Ipotesi!$C$5-1)*60+0*12+1)+11)) -> 194526.32 | D7: =SUM(INDEX(Motore_Advisory!$H$5:$H$544,(Ipotesi!$C$5-1)*60+1*12+1):INDEX(Motore_Advisory!$H$5:$H$544,((Ipotesi!$C$5-1)*60+1*12+1)+11)) -> 407774.65 | E7: =SUM(INDEX(Motore_Advisory!$H$5:$H$544,(Ipotesi!$C$5-1)*60+2*12+1):INDEX(Motore_Advisory!$H$5:$H$544,((Ipotesi!$C$5-1)*60+2*12+1)+11)) -> 726000 | F7: =SUM(INDEX(Motore_Advisory!$H$5:$H$544,(Ipotesi!$C$5-1)*60+3*12+1):INDEX(Motore_Advisory!$H$5:$H$544,((Ipotesi!$C$5-1)*60+3*12+1)+11)) -> 1082900 | G7: =SUM(INDEX(Motore_Advisory!$H$5:$H$544,(Ipotesi!$C$5-1)*60+4*12+1):INDEX(Motore_Advisory!$H$5:$H$544,((Ipotesi!$C$5-1)*60+4*12+1)+11)) -> 1391500
A8: Costi operativi | B8: € | C8: =SUM(INDEX(Motore_Advisory!$I$5:$I$544,(Ipotesi!$C$5-1)*60+0*12+1):INDEX(Motore_Advisory!$I$5:$I$544,((Ipotesi!$C$5-1)*60+0*12+1)+11)) -> 145374.21 | D8: =SUM(INDEX(Motore_Advisory!$I$5:$I$544,(Ipotesi!$C$5-1)*60+1*12+1):INDEX(Motore_Advisory!$I$5:$I$544,((Ipotesi!$C$5-1)*60+1*12+1)+11)) -> 346623.94 | E8: =SUM(INDEX(Motore_Advisory!$I$5:$I$544,(Ipotesi!$C$5-1)*60+2*12+1):INDEX(Motore_Advisory!$I$5:$I$544,((Ipotesi!$C$5-1)*60+2*12+1)+11)) -> 555118.75 | F8: =SUM(INDEX(Motore_Advisory!$I$5:$I$544,(Ipotesi!$C$5-1)*60+3*12+1):INDEX(Motore_Advisory!$I$5:$I$544,((Ipotesi!$C$5-1)*60+3*12+1)+11)) -> 750962.08 | G8: =SUM(INDEX(Motore_Advisory!$I$5:$I$544,(Ipotesi!$C$5-1)*60+4*12+1):INDEX(Motore_Advisory!$I$5:$I$544,((Ipotesi!$C$5-1)*60+4*12+1)+11)) -> 955505.67
A9: EBITDA senza contributi | B9: € | C9: =SUM(INDEX(Motore_Advisory!$J$5:$J$544,(Ipotesi!$C$5-1)*60+0*12+1):INDEX(Motore_Advisory!$J$5:$J$544,((Ipotesi!$C$5-1)*60+0*12+1)+11)) -> 49152.105 | D9: =SUM(INDEX(Motore_Advisory!$J$5:$J$544,(Ipotesi!$C$5-1)*60+1*12+1):INDEX(Motore_Advisory!$J$5:$J$544,((Ipotesi!$C$5-1)*60+1*12+1)+11)) -> 61150.704 | E9: =SUM(INDEX(Motore_Advisory!$J$5:$J$544,(Ipotesi!$C$5-1)*60+2*12+1):INDEX(Motore_Advisory!$J$5:$J$544,((Ipotesi!$C$5-1)*60+2*12+1)+11)) -> 170881.25 | F9: =SUM(INDEX(Motore_Advisory!$J$5:$J$544,(Ipotesi!$C$5-1)*60+3*12+1):INDEX(Motore_Advisory!$J$5:$J$544,((Ipotesi!$C$5-1)*60+3*12+1)+11)) -> 331937.92 | G9: =SUM(INDEX(Motore_Advisory!$J$5:$J$544,(Ipotesi!$C$5-1)*60+4*12+1):INDEX(Motore_Advisory!$J$5:$J$544,((Ipotesi!$C$5-1)*60+4*12+1)+11)) -> 435994.33
A10: Ammortamenti | B10: € | C10: =SUM(INDEX(Motore_Advisory!$L$5:$L$544,(Ipotesi!$C$5-1)*60+0*12+1):INDEX(Motore_Advisory!$L$5:$L$544,((Ipotesi!$C$5-1)*60+0*12+1)+11)) -> 541.66667 | D10: =SUM(INDEX(Motore_Advisory!$L$5:$L$544,(Ipotesi!$C$5-1)*60+1*12+1):INDEX(Motore_Advisory!$L$5:$L$544,((Ipotesi!$C$5-1)*60+1*12+1)+11)) -> 1902.7778 | E10: =SUM(INDEX(Motore_Advisory!$L$5:$L$544,(Ipotesi!$C$5-1)*60+2*12+1):INDEX(Motore_Advisory!$L$5:$L$544,((Ipotesi!$C$5-1)*60+2*12+1)+11)) -> 3569.4444 | F10: =SUM(INDEX(Motore_Advisory!$L$5:$L$544,(Ipotesi!$C$5-1)*60+3*12+1):INDEX(Motore_Advisory!$L$5:$L$544,((Ipotesi!$C$5-1)*60+3*12+1)+11)) -> 5236.1111 | G10: =SUM(INDEX(Motore_Advisory!$L$5:$L$544,(Ipotesi!$C$5-1)*60+4*12+1):INDEX(Motore_Advisory!$L$5:$L$544,((Ipotesi!$C$5-1)*60+4*12+1)+11)) -> 6541.6667
A11: EBIT | B11: € | C11: =SUM(INDEX(Motore_Advisory!$M$5:$M$544,(Ipotesi!$C$5-1)*60+0*12+1):INDEX(Motore_Advisory!$M$5:$M$544,((Ipotesi!$C$5-1)*60+0*12+1)+11)) -> 48610.439 | D11: =SUM(INDEX(Motore_Advisory!$M$5:$M$544,(Ipotesi!$C$5-1)*60+1*12+1):INDEX(Motore_Advisory!$M$5:$M$544,((Ipotesi!$C$5-1)*60+1*12+1)+11)) -> 59247.926 | E11: =SUM(INDEX(Motore_Advisory!$M$5:$M$544,(Ipotesi!$C$5-1)*60+2*12+1):INDEX(Motore_Advisory!$M$5:$M$544,((Ipotesi!$C$5-1)*60+2*12+1)+11)) -> 167311.81 | F11: =SUM(INDEX(Motore_Advisory!$M$5:$M$544,(Ipotesi!$C$5-1)*60+3*12+1):INDEX(Motore_Advisory!$M$5:$M$544,((Ipotesi!$C$5-1)*60+3*12+1)+11)) -> 326701.81 | G11: =SUM(INDEX(Motore_Advisory!$M$5:$M$544,(Ipotesi!$C$5-1)*60+4*12+1):INDEX(Motore_Advisory!$M$5:$M$544,((Ipotesi!$C$5-1)*60+4*12+1)+11)) -> 429452.67
A12: Contributo SS gestionale | B12: € | C12: =SUM(INDEX(Motore_Advisory!$N$5:$N$544,(Ipotesi!$C$5-1)*60+0*12+1):INDEX(Motore_Advisory!$N$5:$N$544,((Ipotesi!$C$5-1)*60+0*12+1)+11)) -> 0 | D12: =SUM(INDEX(Motore_Advisory!$N$5:$N$544,(Ipotesi!$C$5-1)*60+1*12+1):INDEX(Motore_Advisory!$N$5:$N$544,((Ipotesi!$C$5-1)*60+1*12+1)+11)) -> 0 | E12: =SUM(INDEX(Motore_Advisory!$N$5:$N$544,(Ipotesi!$C$5-1)*60+2*12+1):INDEX(Motore_Advisory!$N$5:$N$544,((Ipotesi!$C$5-1)*60+2*12+1)+11)) -> 0 | F12: =SUM(INDEX(Motore_Advisory!$N$5:$N$544,(Ipotesi!$C$5-1)*60+3*12+1):INDEX(Motore_Advisory!$N$5:$N$544,((Ipotesi!$C$5-1)*60+3*12+1)+11)) -> 0 | G12: =SUM(INDEX(Motore_Advisory!$N$5:$N$544,(Ipotesi!$C$5-1)*60+4*12+1):INDEX(Motore_Advisory!$N$5:$N$544,((Ipotesi!$C$5-1)*60+4*12+1)+11)) -> 0
A13: Interessi e commissioni | B13: € | C13: =SUM(INDEX(Motore_Advisory!$O$5:$O$544,(Ipotesi!$C$5-1)*60+0*12+1):INDEX(Motore_Advisory!$O$5:$O$544,((Ipotesi!$C$5-1)*60+0*12+1)+11)) -> 0 | D13: =SUM(INDEX(Motore_Advisory!$O$5:$O$544,(Ipotesi!$C$5-1)*60+1*12+1):INDEX(Motore_Advisory!$O$5:$O$544,((Ipotesi!$C$5-1)*60+1*12+1)+11)) -> 0 | E13: =SUM(INDEX(Motore_Advisory!$O$5:$O$544,(Ipotesi!$C$5-1)*60+2*12+1):INDEX(Motore_Advisory!$O$5:$O$544,((Ipotesi!$C$5-1)*60+2*12+1)+11)) -> 0 | F13: =SUM(INDEX(Motore_Advisory!$O$5:$O$544,(Ipotesi!$C$5-1)*60+3*12+1):INDEX(Motore_Advisory!$O$5:$O$544,((Ipotesi!$C$5-1)*60+3*12+1)+11)) -> 0 | G13: =SUM(INDEX(Motore_Advisory!$O$5:$O$544,(Ipotesi!$C$5-1)*60+4*12+1):INDEX(Motore_Advisory!$O$5:$O$544,((Ipotesi!$C$5-1)*60+4*12+1)+11)) -> 0
A14: Risultato ante imposte | B14: € | C14: =SUM(INDEX(Motore_Advisory!$P$5:$P$544,(Ipotesi!$C$5-1)*60+0*12+1):INDEX(Motore_Advisory!$P$5:$P$544,((Ipotesi!$C$5-1)*60+0*12+1)+11)) -> 48610.439 | D14: =SUM(INDEX(Motore_Advisory!$P$5:$P$544,(Ipotesi!$C$5-1)*60+1*12+1):INDEX(Motore_Advisory!$P$5:$P$544,((Ipotesi!$C$5-1)*60+1*12+1)+11)) -> 59247.926 | E14: =SUM(INDEX(Motore_Advisory!$P$5:$P$544,(Ipotesi!$C$5-1)*60+2*12+1):INDEX(Motore_Advisory!$P$5:$P$544,((Ipotesi!$C$5-1)*60+2*12+1)+11)) -> 167311.81 | F14: =SUM(INDEX(Motore_Advisory!$P$5:$P$544,(Ipotesi!$C$5-1)*60+3*12+1):INDEX(Motore_Advisory!$P$5:$P$544,((Ipotesi!$C$5-1)*60+3*12+1)+11)) -> 326701.81 | G14: =SUM(INDEX(Motore_Advisory!$P$5:$P$544,(Ipotesi!$C$5-1)*60+4*12+1):INDEX(Motore_Advisory!$P$5:$P$544,((Ipotesi!$C$5-1)*60+4*12+1)+11)) -> 429452.67
A15: Imposte CE | B15: € | C15: =SUM(INDEX(Motore_Advisory!$X$5:$X$544,(Ipotesi!$C$5-1)*60+0*12+1):INDEX(Motore_Advisory!$X$5:$X$544,((Ipotesi!$C$5-1)*60+0*12+1)+11)) -> 13562.312 | D15: =SUM(INDEX(Motore_Advisory!$X$5:$X$544,(Ipotesi!$C$5-1)*60+1*12+1):INDEX(Motore_Advisory!$X$5:$X$544,((Ipotesi!$C$5-1)*60+1*12+1)+11)) -> 16530.171 | E15: =SUM(INDEX(Motore_Advisory!$X$5:$X$544,(Ipotesi!$C$5-1)*60+2*12+1):INDEX(Motore_Advisory!$X$5:$X$544,((Ipotesi!$C$5-1)*60+2*12+1)+11)) -> 46679.994 | F15: =SUM(INDEX(Motore_Advisory!$X$5:$X$544,(Ipotesi!$C$5-1)*60+3*12+1):INDEX(Motore_Advisory!$X$5:$X$544,((Ipotesi!$C$5-1)*60+3*12+1)+11)) -> 91149.805 | G15: =SUM(INDEX(Motore_Advisory!$X$5:$X$544,(Ipotesi!$C$5-1)*60+4*12+1):INDEX(Motore_Advisory!$X$5:$X$544,((Ipotesi!$C$5-1)*60+4*12+1)+11)) -> 119817.29
A16: Utile netto | B16: € | C16: =SUM(INDEX(Motore_Advisory!$Y$5:$Y$544,(Ipotesi!$C$5-1)*60+0*12+1):INDEX(Motore_Advisory!$Y$5:$Y$544,((Ipotesi!$C$5-1)*60+0*12+1)+11)) -> 35048.126 | D16: =SUM(INDEX(Motore_Advisory!$Y$5:$Y$544,(Ipotesi!$C$5-1)*60+1*12+1):INDEX(Motore_Advisory!$Y$5:$Y$544,((Ipotesi!$C$5-1)*60+1*12+1)+11)) -> 42717.755 | E16: =SUM(INDEX(Motore_Advisory!$Y$5:$Y$544,(Ipotesi!$C$5-1)*60+2*12+1):INDEX(Motore_Advisory!$Y$5:$Y$544,((Ipotesi!$C$5-1)*60+2*12+1)+11)) -> 120631.81 | F16: =SUM(INDEX(Motore_Advisory!$Y$5:$Y$544,(Ipotesi!$C$5-1)*60+3*12+1):INDEX(Motore_Advisory!$Y$5:$Y$544,((Ipotesi!$C$5-1)*60+3*12+1)+11)) -> 235552 | G16: =SUM(INDEX(Motore_Advisory!$Y$5:$Y$544,(Ipotesi!$C$5-1)*60+4*12+1):INDEX(Motore_Advisory!$Y$5:$Y$544,((Ipotesi!$C$5-1)*60+4*12+1)+11)) -> 309635.37
A18: Cassa teorica a fine anno / deficit | B18: € | C18: =INDEX(Motore_Advisory!$BH$5:$BH$544,((Ipotesi!$C$5-1)*60+0*12+1)+11) -> 26513.727 | D18: =INDEX(Motore_Advisory!$BH$5:$BH$544,((Ipotesi!$C$5-1)*60+1*12+1)+11) -> 15038.563 | E18: =INDEX(Motore_Advisory!$BH$5:$BH$544,((Ipotesi!$C$5-1)*60+2*12+1)+11) -> 99567.655 | F18: =INDEX(Motore_Advisory!$BH$5:$BH$544,((Ipotesi!$C$5-1)*60+3*12+1)+11) -> 218002.56 | G18: =INDEX(Motore_Advisory!$BH$5:$BH$544,((Ipotesi!$C$5-1)*60+4*12+1)+11) -> 341896.8
A19: Minimo mensile di cassa nell'anno | B19: € | C19: =MIN(INDEX(Motore_Advisory!$BH$5:$BH$544,(Ipotesi!$C$5-1)*60+0*12+1):INDEX(Motore_Advisory!$BH$5:$BH$544,((Ipotesi!$C$5-1)*60+0*12+1)+11)) -> -10462.852 | D19: =MIN(INDEX(Motore_Advisory!$BH$5:$BH$544,(Ipotesi!$C$5-1)*60+1*12+1):INDEX(Motore_Advisory!$BH$5:$BH$544,((Ipotesi!$C$5-1)*60+1*12+1)+11)) -> -9688.9021 | E19: =MIN(INDEX(Motore_Advisory!$BH$5:$BH$544,(Ipotesi!$C$5-1)*60+2*12+1):INDEX(Motore_Advisory!$BH$5:$BH$544,((Ipotesi!$C$5-1)*60+2*12+1)+11)) -> -16783.08 | F19: =MIN(INDEX(Motore_Advisory!$BH$5:$BH$544,(Ipotesi!$C$5-1)*60+3*12+1):INDEX(Motore_Advisory!$BH$5:$BH$544,((Ipotesi!$C$5-1)*60+3*12+1)+11)) -> 73892.896 | G19: =MIN(INDEX(Motore_Advisory!$BH$5:$BH$544,(Ipotesi!$C$5-1)*60+4*12+1):INDEX(Motore_Advisory!$BH$5:$BH$544,((Ipotesi!$C$5-1)*60+4*12+1)+11)) -> 169280.37
A20: Massimo fabbisogno per buffer nell'anno | B20: € | C20: =MAX(INDEX(Motore_Advisory!$BI$5:$BI$544,(Ipotesi!$C$5-1)*60+0*12+1):INDEX(Motore_Advisory!$BI$5:$BI$544,((Ipotesi!$C$5-1)*60+0*12+1)+11)) -> 20462.852 | D20: =MAX(INDEX(Motore_Advisory!$BI$5:$BI$544,(Ipotesi!$C$5-1)*60+1*12+1):INDEX(Motore_Advisory!$BI$5:$BI$544,((Ipotesi!$C$5-1)*60+1*12+1)+11)) -> 19688.902 | E20: =MAX(INDEX(Motore_Advisory!$BI$5:$BI$544,(Ipotesi!$C$5-1)*60+2*12+1):INDEX(Motore_Advisory!$BI$5:$BI$544,((Ipotesi!$C$5-1)*60+2*12+1)+11)) -> 26783.08 | F20: =MAX(INDEX(Motore_Advisory!$BI$5:$BI$544,(Ipotesi!$C$5-1)*60+3*12+1):INDEX(Motore_Advisory!$BI$5:$BI$544,((Ipotesi!$C$5-1)*60+3*12+1)+11)) -> 0 | G20: =MAX(INDEX(Motore_Advisory!$BI$5:$BI$544,(Ipotesi!$C$5-1)*60+4*12+1):INDEX(Motore_Advisory!$BI$5:$BI$544,((Ipotesi!$C$5-1)*60+4*12+1)+11)) -> 0
A21: Fido residuo fine anno | B21: € | C21: =INDEX(Motore_Advisory!$BG$5:$BG$544,((Ipotesi!$C$5-1)*60+0*12+1)+11) -> 0 | D21: =INDEX(Motore_Advisory!$BG$5:$BG$544,((Ipotesi!$C$5-1)*60+1*12+1)+11) -> 0 | E21: =INDEX(Motore_Advisory!$BG$5:$BG$544,((Ipotesi!$C$5-1)*60+2*12+1)+11) -> 0 | F21: =INDEX(Motore_Advisory!$BG$5:$BG$544,((Ipotesi!$C$5-1)*60+3*12+1)+11) -> 0 | G21: =INDEX(Motore_Advisory!$BG$5:$BG$544,((Ipotesi!$C$5-1)*60+4*12+1)+11) -> 0
A22: SS erogato nell'anno | B22: € | C22: =SUM(INDEX(Motore_Advisory!$BA$5:$BA$544,(Ipotesi!$C$5-1)*60+0*12+1):INDEX(Motore_Advisory!$BA$5:$BA$544,((Ipotesi!$C$5-1)*60+0*12+1)+11)) -> 0 | D22: =SUM(INDEX(Motore_Advisory!$BA$5:$BA$544,(Ipotesi!$C$5-1)*60+1*12+1):INDEX(Motore_Advisory!$BA$5:$BA$544,((Ipotesi!$C$5-1)*60+1*12+1)+11)) -> 0 | E22: =SUM(INDEX(Motore_Advisory!$BA$5:$BA$544,(Ipotesi!$C$5-1)*60+2*12+1):INDEX(Motore_Advisory!$BA$5:$BA$544,((Ipotesi!$C$5-1)*60+2*12+1)+11)) -> 0 | F22: =SUM(INDEX(Motore_Advisory!$BA$5:$BA$544,(Ipotesi!$C$5-1)*60+3*12+1):INDEX(Motore_Advisory!$BA$5:$BA$544,((Ipotesi!$C$5-1)*60+3*12+1)+11)) -> 0 | G22: =SUM(INDEX(Motore_Advisory!$BA$5:$BA$544,(Ipotesi!$C$5-1)*60+4*12+1):INDEX(Motore_Advisory!$BA$5:$BA$544,((Ipotesi!$C$5-1)*60+4*12+1)+11)) -> 0
A23: SS rimborsato nell'anno | B23: € | C23: =SUM(INDEX(Motore_Advisory!$BB$5:$BB$544,(Ipotesi!$C$5-1)*60+0*12+1):INDEX(Motore_Advisory!$BB$5:$BB$544,((Ipotesi!$C$5-1)*60+0*12+1)+11)) -> 0 | D23: =SUM(INDEX(Motore_Advisory!$BB$5:$BB$544,(Ipotesi!$C$5-1)*60+1*12+1):INDEX(Motore_Advisory!$BB$5:$BB$544,((Ipotesi!$C$5-1)*60+1*12+1)+11)) -> 0 | E23: =SUM(INDEX(Motore_Advisory!$BB$5:$BB$544,(Ipotesi!$C$5-1)*60+2*12+1):INDEX(Motore_Advisory!$BB$5:$BB$544,((Ipotesi!$C$5-1)*60+2*12+1)+11)) -> 0 | F23: =SUM(INDEX(Motore_Advisory!$BB$5:$BB$544,(Ipotesi!$C$5-1)*60+3*12+1):INDEX(Motore_Advisory!$BB$5:$BB$544,((Ipotesi!$C$5-1)*60+3*12+1)+11)) -> 0 | G23: =SUM(INDEX(Motore_Advisory!$BB$5:$BB$544,(Ipotesi!$C$5-1)*60+4*12+1):INDEX(Motore_Advisory!$BB$5:$BB$544,((Ipotesi!$C$5-1)*60+4*12+1)+11)) -> 0
A24: Debito SS residuo | B24: € | C24: =INDEX(Motore_Advisory!$BC$5:$BC$544,((Ipotesi!$C$5-1)*60+0*12+1)+11) -> 0 | D24: =INDEX(Motore_Advisory!$BC$5:$BC$544,((Ipotesi!$C$5-1)*60+1*12+1)+11) -> 0 | E24: =INDEX(Motore_Advisory!$BC$5:$BC$544,((Ipotesi!$C$5-1)*60+2*12+1)+11) -> 0 | F24: =INDEX(Motore_Advisory!$BC$5:$BC$544,((Ipotesi!$C$5-1)*60+3*12+1)+11) -> 0 | G24: =INDEX(Motore_Advisory!$BC$5:$BC$544,((Ipotesi!$C$5-1)*60+4*12+1)+11) -> 0
A25: Apporti iniziali | B25: € | C25: =SUM(INDEX(Motore_Advisory!$AW$5:$AW$544,(Ipotesi!$C$5-1)*60+0*12+1):INDEX(Motore_Advisory!$AW$5:$AW$544,((Ipotesi!$C$5-1)*60+0*12+1)+11)) -> 20000 | D25: =SUM(INDEX(Motore_Advisory!$AW$5:$AW$544,(Ipotesi!$C$5-1)*60+1*12+1):INDEX(Motore_Advisory!$AW$5:$AW$544,((Ipotesi!$C$5-1)*60+1*12+1)+11)) -> 0 | E25: =SUM(INDEX(Motore_Advisory!$AW$5:$AW$544,(Ipotesi!$C$5-1)*60+2*12+1):INDEX(Motore_Advisory!$AW$5:$AW$544,((Ipotesi!$C$5-1)*60+2*12+1)+11)) -> 0 | F25: =SUM(INDEX(Motore_Advisory!$AW$5:$AW$544,(Ipotesi!$C$5-1)*60+3*12+1):INDEX(Motore_Advisory!$AW$5:$AW$544,((Ipotesi!$C$5-1)*60+3*12+1)+11)) -> 0 | G25: =SUM(INDEX(Motore_Advisory!$AW$5:$AW$544,(Ipotesi!$C$5-1)*60+4*12+1):INDEX(Motore_Advisory!$AW$5:$AW$544,((Ipotesi!$C$5-1)*60+4*12+1)+11)) -> 0
A26: Round incassati | B26: € | C26: =SUM(INDEX(Motore_Advisory!$AX$5:$AX$544,(Ipotesi!$C$5-1)*60+0*12+1):INDEX(Motore_Advisory!$AX$5:$AX$544,((Ipotesi!$C$5-1)*60+0*12+1)+11)) -> 0 | D26: =SUM(INDEX(Motore_Advisory!$AX$5:$AX$544,(Ipotesi!$C$5-1)*60+1*12+1):INDEX(Motore_Advisory!$AX$5:$AX$544,((Ipotesi!$C$5-1)*60+1*12+1)+11)) -> 0 | E26: =SUM(INDEX(Motore_Advisory!$AX$5:$AX$544,(Ipotesi!$C$5-1)*60+2*12+1):INDEX(Motore_Advisory!$AX$5:$AX$544,((Ipotesi!$C$5-1)*60+2*12+1)+11)) -> 0 | F26: =SUM(INDEX(Motore_Advisory!$AX$5:$AX$544,(Ipotesi!$C$5-1)*60+3*12+1):INDEX(Motore_Advisory!$AX$5:$AX$544,((Ipotesi!$C$5-1)*60+3*12+1)+11)) -> 0 | G26: =SUM(INDEX(Motore_Advisory!$AX$5:$AX$544,(Ipotesi!$C$5-1)*60+4*12+1):INDEX(Motore_Advisory!$AX$5:$AX$544,((Ipotesi!$C$5-1)*60+4*12+1)+11)) -> 0
A27: Dividendi lordi distribuiti | B27: € | C27: =SUM(INDEX(Motore_Advisory!$AY$5:$AY$544,(Ipotesi!$C$5-1)*60+0*12+1):INDEX(Motore_Advisory!$AY$5:$AY$544,((Ipotesi!$C$5-1)*60+0*12+1)+11)) -> 0 | D27: =SUM(INDEX(Motore_Advisory!$AY$5:$AY$544,(Ipotesi!$C$5-1)*60+1*12+1):INDEX(Motore_Advisory!$AY$5:$AY$544,((Ipotesi!$C$5-1)*60+1*12+1)+11)) -> 0 | E27: =SUM(INDEX(Motore_Advisory!$AY$5:$AY$544,(Ipotesi!$C$5-1)*60+2*12+1):INDEX(Motore_Advisory!$AY$5:$AY$544,((Ipotesi!$C$5-1)*60+2*12+1)+11)) -> 0 | F27: =SUM(INDEX(Motore_Advisory!$AY$5:$AY$544,(Ipotesi!$C$5-1)*60+3*12+1):INDEX(Motore_Advisory!$AY$5:$AY$544,((Ipotesi!$C$5-1)*60+3*12+1)+11)) -> 60315.906 | G27: =SUM(INDEX(Motore_Advisory!$AY$5:$AY$544,(Ipotesi!$C$5-1)*60+4*12+1):INDEX(Motore_Advisory!$AY$5:$AY$544,((Ipotesi!$C$5-1)*60+4*12+1)+11)) -> 117776
A28: Dividendi reinvestiti dai soci | B28: € | C28: =SUM(INDEX(Motore_Advisory!$AZ$5:$AZ$544,(Ipotesi!$C$5-1)*60+0*12+1):INDEX(Motore_Advisory!$AZ$5:$AZ$544,((Ipotesi!$C$5-1)*60+0*12+1)+11)) -> 0 | D28: =SUM(INDEX(Motore_Advisory!$AZ$5:$AZ$544,(Ipotesi!$C$5-1)*60+1*12+1):INDEX(Motore_Advisory!$AZ$5:$AZ$544,((Ipotesi!$C$5-1)*60+1*12+1)+11)) -> 0 | E28: =SUM(INDEX(Motore_Advisory!$AZ$5:$AZ$544,(Ipotesi!$C$5-1)*60+2*12+1):INDEX(Motore_Advisory!$AZ$5:$AZ$544,((Ipotesi!$C$5-1)*60+2*12+1)+11)) -> 0 | F28: =SUM(INDEX(Motore_Advisory!$AZ$5:$AZ$544,(Ipotesi!$C$5-1)*60+3*12+1):INDEX(Motore_Advisory!$AZ$5:$AZ$544,((Ipotesi!$C$5-1)*60+3*12+1)+11)) -> 0 | G28: =SUM(INDEX(Motore_Advisory!$AZ$5:$AZ$544,(Ipotesi!$C$5-1)*60+4*12+1):INDEX(Motore_Advisory!$AZ$5:$AZ$544,((Ipotesi!$C$5-1)*60+4*12+1)+11)) -> 0
A30: Crediti esterni IVA inclusa | B30: € | C30: =INDEX(Motore_Advisory!$AD$5:$AD$544,((Ipotesi!$C$5-1)*60+0*12+1)+11) -> 59330.526 | D30: =INDEX(Motore_Advisory!$AD$5:$AD$544,((Ipotesi!$C$5-1)*60+1*12+1)+11) -> 124371.27 | E30: =INDEX(Motore_Advisory!$AD$5:$AD$544,((Ipotesi!$C$5-1)*60+2*12+1)+11) -> 221430 | F30: =INDEX(Motore_Advisory!$AD$5:$AD$544,((Ipotesi!$C$5-1)*60+3*12+1)+11) -> 330284.5 | G30: =INDEX(Motore_Advisory!$AD$5:$AD$544,((Ipotesi!$C$5-1)*60+4*12+1)+11) -> 424407.5
A31: Saldo infragruppo | B31: € | C31: =INDEX(Motore_Advisory!$AG$5:$AG$544,((Ipotesi!$C$5-1)*60+0*12+1)+11) -> 1977.6842 | D31: =INDEX(Motore_Advisory!$AG$5:$AG$544,((Ipotesi!$C$5-1)*60+1*12+1)+11) -> 4145.7089 | E31: =INDEX(Motore_Advisory!$AG$5:$AG$544,((Ipotesi!$C$5-1)*60+2*12+1)+11) -> 7381 | F31: =INDEX(Motore_Advisory!$AG$5:$AG$544,((Ipotesi!$C$5-1)*60+3*12+1)+11) -> 11009.483 | G31: =INDEX(Motore_Advisory!$AG$5:$AG$544,((Ipotesi!$C$5-1)*60+4*12+1)+11) -> 14146.917
A32: Debiti fornitori esterni | B32: € | C32: =INDEX(Motore_Advisory!$AJ$5:$AJ$544,((Ipotesi!$C$5-1)*60+0*12+1)+11) -> 12332.629 | D32: =INDEX(Motore_Advisory!$AJ$5:$AJ$544,((Ipotesi!$C$5-1)*60+1*12+1)+11) -> 22396.23 | E32: =INDEX(Motore_Advisory!$AJ$5:$AJ$544,((Ipotesi!$C$5-1)*60+2*12+1)+11) -> 34791.96 | F32: =INDEX(Motore_Advisory!$AJ$5:$AJ$544,((Ipotesi!$C$5-1)*60+3*12+1)+11) -> 46397.904 | G32: =INDEX(Motore_Advisory!$AJ$5:$AJ$544,((Ipotesi!$C$5-1)*60+4*12+1)+11) -> 55662.04
A33: Saldo IVA (debito + / credito -) | B33: € | C33: =INDEX(Motore_Advisory!$AM$5:$AM$544,((Ipotesi!$C$5-1)*60+0*12+1)+11) -> 2231.8344 | D33: =INDEX(Motore_Advisory!$AM$5:$AM$544,((Ipotesi!$C$5-1)*60+1*12+1)+11) -> 4960.7067 | E33: =INDEX(Motore_Advisory!$AM$5:$AM$544,((Ipotesi!$C$5-1)*60+2*12+1)+11) -> 9283.8533 | F33: =INDEX(Motore_Advisory!$AM$5:$AM$544,((Ipotesi!$C$5-1)*60+3*12+1)+11) -> 14249.231 | G33: =INDEX(Motore_Advisory!$AM$5:$AM$544,((Ipotesi!$C$5-1)*60+4*12+1)+11) -> 18647.897
A34: Saldo imposte (debito + / credito -) | B34: € | C34: =INDEX(Motore_Advisory!$AR$5:$AR$544,((Ipotesi!$C$5-1)*60+0*12+1)+11) -> 13562.312 | D34: =INDEX(Motore_Advisory!$AR$5:$AR$544,((Ipotesi!$C$5-1)*60+1*12+1)+11) -> 2967.8591 | E34: =INDEX(Motore_Advisory!$AR$5:$AR$544,((Ipotesi!$C$5-1)*60+2*12+1)+11) -> 30149.822 | F34: =INDEX(Motore_Advisory!$AR$5:$AR$544,((Ipotesi!$C$5-1)*60+3*12+1)+11) -> 44469.811 | G34: =INDEX(Motore_Advisory!$AR$5:$AR$544,((Ipotesi!$C$5-1)*60+4*12+1)+11) -> 28667.489
A35: Fondo TFR | B35: € | C35: =INDEX(Motore_Advisory!$AV$5:$AV$544,((Ipotesi!$C$5-1)*60+0*12+1)+11) -> 3150 | D35: =INDEX(Motore_Advisory!$AV$5:$AV$544,((Ipotesi!$C$5-1)*60+1*12+1)+11) -> 12729 | E35: =INDEX(Motore_Advisory!$AV$5:$AV$544,((Ipotesi!$C$5-1)*60+2*12+1)+11) -> 27979.438 | F35: =INDEX(Motore_Advisory!$AV$5:$AV$544,((Ipotesi!$C$5-1)*60+3*12+1)+11) -> 48276.842 | G35: =INDEX(Motore_Advisory!$AV$5:$AV$544,((Ipotesi!$C$5-1)*60+4*12+1)+11) -> 74895.125
A36: Immobilizzazioni nette | B36: € | C36: =INDEX(Motore_Advisory!$BL$5:$BL$544,((Ipotesi!$C$5-1)*60+0*12+1)+11) -> 2458.3333 | D36: =INDEX(Motore_Advisory!$BL$5:$BL$544,((Ipotesi!$C$5-1)*60+1*12+1)+11) -> 5555.5556 | E36: =INDEX(Motore_Advisory!$BL$5:$BL$544,((Ipotesi!$C$5-1)*60+2*12+1)+11) -> 6986.1111 | F36: =INDEX(Motore_Advisory!$BL$5:$BL$544,((Ipotesi!$C$5-1)*60+3*12+1)+11) -> 9750 | G36: =INDEX(Motore_Advisory!$BL$5:$BL$544,((Ipotesi!$C$5-1)*60+4*12+1)+11) -> 11208.333
A37: Patrimonio netto | B37: € | C37: =INDEX(Motore_Advisory!$BQ$5:$BQ$544,((Ipotesi!$C$5-1)*60+0*12+1)+11) -> 55048.126 | D37: =INDEX(Motore_Advisory!$BQ$5:$BQ$544,((Ipotesi!$C$5-1)*60+1*12+1)+11) -> 97765.881 | E37: =INDEX(Motore_Advisory!$BQ$5:$BQ$544,((Ipotesi!$C$5-1)*60+2*12+1)+11) -> 218397.69 | F37: =INDEX(Motore_Advisory!$BQ$5:$BQ$544,((Ipotesi!$C$5-1)*60+3*12+1)+11) -> 393633.79 | G37: =INDEX(Motore_Advisory!$BQ$5:$BQ$544,((Ipotesi!$C$5-1)*60+4*12+1)+11) -> 585493.16
A38: Totale attività teoriche | B38: € | C38: =INDEX(Motore_Advisory!$BR$5:$BR$544,((Ipotesi!$C$5-1)*60+0*12+1)+11) -> 88302.587 | D38: =INDEX(Motore_Advisory!$BR$5:$BR$544,((Ipotesi!$C$5-1)*60+1*12+1)+11) -> 144965.39 | E38: =INDEX(Motore_Advisory!$BR$5:$BR$544,((Ipotesi!$C$5-1)*60+2*12+1)+11) -> 327983.77 | F38: =INDEX(Motore_Advisory!$BR$5:$BR$544,((Ipotesi!$C$5-1)*60+3*12+1)+11) -> 558037.06 | G38: =INDEX(Motore_Advisory!$BR$5:$BR$544,((Ipotesi!$C$5-1)*60+4*12+1)+11) -> 777512.63
A39: Passività e patrimonio netto | B39: € | C39: =INDEX(Motore_Advisory!$BS$5:$BS$544,((Ipotesi!$C$5-1)*60+0*12+1)+11) -> 88302.587 | D39: =INDEX(Motore_Advisory!$BS$5:$BS$544,((Ipotesi!$C$5-1)*60+1*12+1)+11) -> 144965.39 | E39: =INDEX(Motore_Advisory!$BS$5:$BS$544,((Ipotesi!$C$5-1)*60+2*12+1)+11) -> 327983.77 | F39: =INDEX(Motore_Advisory!$BS$5:$BS$544,((Ipotesi!$C$5-1)*60+3*12+1)+11) -> 558037.06 | G39: =INDEX(Motore_Advisory!$BS$5:$BS$544,((Ipotesi!$C$5-1)*60+4*12+1)+11) -> 777512.63
A40: Quadratura SP fine anno | B40: € | C40: =INDEX(Motore_Advisory!$BT$5:$BT$544,((Ipotesi!$C$5-1)*60+0*12+1)+11) -> 0 | D40: =INDEX(Motore_Advisory!$BT$5:$BT$544,((Ipotesi!$C$5-1)*60+1*12+1)+11) -> 0 | E40: =INDEX(Motore_Advisory!$BT$5:$BT$544,((Ipotesi!$C$5-1)*60+2*12+1)+11) -> 0 | F40: =INDEX(Motore_Advisory!$BT$5:$BT$544,((Ipotesi!$C$5-1)*60+3*12+1)+11) -> 0 | G40: =INDEX(Motore_Advisory!$BT$5:$BT$544,((Ipotesi!$C$5-1)*60+4*12+1)+11) -> 0
A42: Investimenti pagati ex IVA | B42: € | C42: =SUM(INDEX(Motore_Advisory!$K$5:$K$544,(Ipotesi!$C$5-1)*60+0*12+1):INDEX(Motore_Advisory!$K$5:$K$544,((Ipotesi!$C$5-1)*60+0*12+1)+11)) -> 3000 | D42: =SUM(INDEX(Motore_Advisory!$K$5:$K$544,(Ipotesi!$C$5-1)*60+1*12+1):INDEX(Motore_Advisory!$K$5:$K$544,((Ipotesi!$C$5-1)*60+1*12+1)+11)) -> 5000 | E42: =SUM(INDEX(Motore_Advisory!$K$5:$K$544,(Ipotesi!$C$5-1)*60+2*12+1):INDEX(Motore_Advisory!$K$5:$K$544,((Ipotesi!$C$5-1)*60+2*12+1)+11)) -> 5000 | F42: =SUM(INDEX(Motore_Advisory!$K$5:$K$544,(Ipotesi!$C$5-1)*60+3*12+1):INDEX(Motore_Advisory!$K$5:$K$544,((Ipotesi!$C$5-1)*60+3*12+1)+11)) -> 8000 | G42: =SUM(INDEX(Motore_Advisory!$K$5:$K$544,(Ipotesi!$C$5-1)*60+4*12+1):INDEX(Motore_Advisory!$K$5:$K$544,((Ipotesi!$C$5-1)*60+4*12+1)+11)) -> 8000
A43: Imposte effettivamente pagate | B43: € | C43: =SUM(INDEX(Motore_Advisory!$AQ$5:$AQ$544,(Ipotesi!$C$5-1)*60+0*12+1):INDEX(Motore_Advisory!$AQ$5:$AQ$544,((Ipotesi!$C$5-1)*60+0*12+1)+11)) -> 0 | D43: =SUM(INDEX(Motore_Advisory!$AQ$5:$AQ$544,(Ipotesi!$C$5-1)*60+1*12+1):INDEX(Motore_Advisory!$AQ$5:$AQ$544,((Ipotesi!$C$5-1)*60+1*12+1)+11)) -> 27124.625 | E43: =SUM(INDEX(Motore_Advisory!$AQ$5:$AQ$544,(Ipotesi!$C$5-1)*60+2*12+1):INDEX(Motore_Advisory!$AQ$5:$AQ$544,((Ipotesi!$C$5-1)*60+2*12+1)+11)) -> 19498.031 | F43: =SUM(INDEX(Motore_Advisory!$AQ$5:$AQ$544,(Ipotesi!$C$5-1)*60+3*12+1):INDEX(Motore_Advisory!$AQ$5:$AQ$544,((Ipotesi!$C$5-1)*60+3*12+1)+11)) -> 76829.816 | G43: =SUM(INDEX(Motore_Advisory!$AQ$5:$AQ$544,(Ipotesi!$C$5-1)*60+4*12+1):INDEX(Motore_Advisory!$AQ$5:$AQ$544,((Ipotesi!$C$5-1)*60+4*12+1)+11)) -> 135619.62
A44: IVA versata | B44: € | C44: =SUM(INDEX(Motore_Advisory!$AL$5:$AL$544,(Ipotesi!$C$5-1)*60+0*12+1):INDEX(Motore_Advisory!$AL$5:$AL$544,((Ipotesi!$C$5-1)*60+0*12+1)+11)) -> 24550.178 | D44: =SUM(INDEX(Motore_Advisory!$AL$5:$AL$544,(Ipotesi!$C$5-1)*60+1*12+1):INDEX(Motore_Advisory!$AL$5:$AL$544,((Ipotesi!$C$5-1)*60+1*12+1)+11)) -> 56799.608 | E44: =SUM(INDEX(Motore_Advisory!$AL$5:$AL$544,(Ipotesi!$C$5-1)*60+2*12+1):INDEX(Motore_Advisory!$AL$5:$AL$544,((Ipotesi!$C$5-1)*60+2*12+1)+11)) -> 107083.09 | F44: =SUM(INDEX(Motore_Advisory!$AL$5:$AL$544,(Ipotesi!$C$5-1)*60+3*12+1):INDEX(Motore_Advisory!$AL$5:$AL$544,((Ipotesi!$C$5-1)*60+3*12+1)+11)) -> 166025.4 | G44: =SUM(INDEX(Motore_Advisory!$AL$5:$AL$544,(Ipotesi!$C$5-1)*60+4*12+1):INDEX(Motore_Advisory!$AL$5:$AL$544,((Ipotesi!$C$5-1)*60+4*12+1)+11)) -> 219376.09
A45: Contributo SS gestionale dell'anno | B45: € | C45: =SUM(INDEX(Motore_Advisory!$N$5:$N$544,(Ipotesi!$C$5-1)*60+0*12+1):INDEX(Motore_Advisory!$N$5:$N$544,((Ipotesi!$C$5-1)*60+0*12+1)+11)) -> 0 | D45: =SUM(INDEX(Motore_Advisory!$N$5:$N$544,(Ipotesi!$C$5-1)*60+1*12+1):INDEX(Motore_Advisory!$N$5:$N$544,((Ipotesi!$C$5-1)*60+1*12+1)+11)) -> 0 | E45: =SUM(INDEX(Motore_Advisory!$N$5:$N$544,(Ipotesi!$C$5-1)*60+2*12+1):INDEX(Motore_Advisory!$N$5:$N$544,((Ipotesi!$C$5-1)*60+2*12+1)+11)) -> 0 | F45: =SUM(INDEX(Motore_Advisory!$N$5:$N$544,(Ipotesi!$C$5-1)*60+3*12+1):INDEX(Motore_Advisory!$N$5:$N$544,((Ipotesi!$C$5-1)*60+3*12+1)+11)) -> 0 | G45: =SUM(INDEX(Motore_Advisory!$N$5:$N$544,(Ipotesi!$C$5-1)*60+4*12+1):INDEX(Motore_Advisory!$N$5:$N$544,((Ipotesi!$C$5-1)*60+4*12+1)+11)) -> 0

Sheet Tesoreria
A1: Tesoreria mensile | scenario selezionato
A2: Posizioni separate e fabbisogno simultaneo: non sommare picchi che si verificano in mesi diversi.
A4: Mese | B4: Cassa iniziale S | C4: Flusso operativo S incl. capex | D4: Fonti S ex fido | E4: Rimborso SS | F4: Fido netto | G4: Cassa finale S | H4: Gap S per buffer | I4: Cassa finale A | J4: Gap A per buffer | K4: Cassa gruppo | L4: Gap simultaneo S+A | M4: Deficit 0/1
A5: =INDEX(Motore_Startup!$C$5:$C$544,(Ipotesi!$C$5-1)*60+1) -> 46388 | B5: =0 -> 0 | C5: =INDEX(Motore_Startup!$BD$5:$BD$544,(Ipotesi!$C$5-1)*60+1)-(0)-(INDEX(Motore_Startup!$AW$5:$AW$544,(Ipotesi!$C$5-1)*60+1)+INDEX(Motore_Startup!$AX$5:$AX$544,(Ipotesi!$C$5-1)*60+1)+INDEX(Motore_Startup!$AZ$5:$AZ$544,(Ipotesi!$C$5-1)*60+1)+INDEX(Motore_Startup!$BA$5:$BA$544,(Ipotesi!$C$5-1)*60+1))+INDEX(Motore_Startup!$BB$5:$BB$544,(Ipotesi!$C$5-1)*60+1) -> -19054.167 | D5: =INDEX(Motore_Startup!$AW$5:$AW$544,(Ipotesi!$C$5-1)*60+1)+INDEX(Motore_Startup!$AX$5:$AX$544,(Ipotesi!$C$5-1)*60+1)+INDEX(Motore_Startup!$AZ$5:$AZ$544,(Ipotesi!$C$5-1)*60+1)+INDEX(Motore_Startup!$BA$5:$BA$544,(Ipotesi!$C$5-1)*60+1) -> 130000 | E5: =INDEX(Motore_Startup!$BB$5:$BB$544,(Ipotesi!$C$5-1)*60+1) -> 0 | F5: =INDEX(Motore_Startup!$BE$5:$BE$544,(Ipotesi!$C$5-1)*60+1)-INDEX(Motore_Startup!$BF$5:$BF$544,(Ipotesi!$C$5-1)*60+1) -> 0 | G5: =INDEX(Motore_Startup!$BH$5:$BH$544,(Ipotesi!$C$5-1)*60+1) -> 110945.83 | H5: =INDEX(Motore_Startup!$BI$5:$BI$544,(Ipotesi!$C$5-1)*60+1) -> 0 | I5: =INDEX(Motore_Advisory!$BH$5:$BH$544,(Ipotesi!$C$5-1)*60+1) -> 14707.5 | J5: =INDEX(Motore_Advisory!$BI$5:$BI$544,(Ipotesi!$C$5-1)*60+1) -> 0 | K5: =G5+I5 -> 125653.33 | L5: =H5+J5 -> 0 | M5: =IF(OR(G5<0,I5<0),1,0) -> 0
A6: =INDEX(Motore_Startup!$C$5:$C$544,(Ipotesi!$C$5-1)*60+2) -> 46419 | B6: =INDEX(Motore_Startup!$BH$5:$BH$544,(Ipotesi!$C$5-1)*60+1) -> 110945.83 | C6: =INDEX(Motore_Startup!$BD$5:$BD$544,(Ipotesi!$C$5-1)*60+2)-(INDEX(Motore_Startup!$BH$5:$BH$544,(Ipotesi!$C$5-1)*60+1))-(INDEX(Motore_Startup!$AW$5:$AW$544,(Ipotesi!$C$5-1)*60+2)+INDEX(Motore_Startup!$AX$5:$AX$544,(Ipotesi!$C$5-1)*60+2)+INDEX(Motore_Startup!$AZ$5:$AZ$544,(Ipotesi!$C$5-1)*60+2)+INDEX(Motore_Startup!$BA$5:$BA$544,(Ipotesi!$C$5-1)*60+2))+INDEX(Motore_Startup!$BB$5:$BB$544,(Ipotesi!$C$5-1)*60+2) -> -17076.482 | D6: =INDEX(Motore_Startup!$AW$5:$AW$544,(Ipotesi!$C$5-1)*60+2)+INDEX(Motore_Startup!$AX$5:$AX$544,(Ipotesi!$C$5-1)*60+2)+INDEX(Motore_Startup!$AZ$5:$AZ$544,(Ipotesi!$C$5-1)*60+2)+INDEX(Motore_Startup!$BA$5:$BA$544,(Ipotesi!$C$5-1)*60+2) -> 0 | E6: =INDEX(Motore_Startup!$BB$5:$BB$544,(Ipotesi!$C$5-1)*60+2) -> 0 | F6: =INDEX(Motore_Startup!$BE$5:$BE$544,(Ipotesi!$C$5-1)*60+2)-INDEX(Motore_Startup!$BF$5:$BF$544,(Ipotesi!$C$5-1)*60+2) -> 0 | G6: =INDEX(Motore_Startup!$BH$5:$BH$544,(Ipotesi!$C$5-1)*60+2) -> 93869.351 | H6: =INDEX(Motore_Startup!$BI$5:$BI$544,(Ipotesi!$C$5-1)*60+2) -> 0 | I6: =INDEX(Motore_Advisory!$BH$5:$BH$544,(Ipotesi!$C$5-1)*60+2) -> 5205.4814 | J6: =INDEX(Motore_Advisory!$BI$5:$BI$544,(Ipotesi!$C$5-1)*60+2) -> 4794.5186 | K6: =G6+I6 -> 99074.832 | L6: =H6+J6 -> 4794.5186 | M6: =IF(OR(G6<0,I6<0),1,0) -> 0
A7: =INDEX(Motore_Startup!$C$5:$C$544,(Ipotesi!$C$5-1)*60+3) -> 46447 | B7: =INDEX(Motore_Startup!$BH$5:$BH$544,(Ipotesi!$C$5-1)*60+2) -> 93869.351 | C7: =INDEX(Motore_Startup!$BD$5:$BD$544,(Ipotesi!$C$5-1)*60+3)-(INDEX(Motore_Startup!$BH$5:$BH$544,(Ipotesi!$C$5-1)*60+2))-(INDEX(Motore_Startup!$AW$5:$AW$544,(Ipotesi!$C$5-1)*60+3)+INDEX(Motore_Startup!$AX$5:$AX$544,(Ipotesi!$C$5-1)*60+3)+INDEX(Motore_Startup!$AZ$5:$AZ$544,(Ipotesi!$C$5-1)*60+3)+INDEX(Motore_Startup!$BA$5:$BA$544,(Ipotesi!$C$5-1)*60+3))+INDEX(Motore_Startup!$BB$5:$BB$544,(Ipotesi!$C$5-1)*60+3) -> -28734.66 | D7: =INDEX(Motore_Startup!$AW$5:$AW$544,(Ipotesi!$C$5-1)*60+3)+INDEX(Motore_Startup!$AX$5:$AX$544,(Ipotesi!$C$5-1)*60+3)+INDEX(Motore_Startup!$AZ$5:$AZ$544,(Ipotesi!$C$5-1)*60+3)+INDEX(Motore_Startup!$BA$5:$BA$544,(Ipotesi!$C$5-1)*60+3) -> 0 | E7: =INDEX(Motore_Startup!$BB$5:$BB$544,(Ipotesi!$C$5-1)*60+3) -> 0 | F7: =INDEX(Motore_Startup!$BE$5:$BE$544,(Ipotesi!$C$5-1)*60+3)-INDEX(Motore_Startup!$BF$5:$BF$544,(Ipotesi!$C$5-1)*60+3) -> 0 | G7: =INDEX(Motore_Startup!$BH$5:$BH$544,(Ipotesi!$C$5-1)*60+3) -> 65134.691 | H7: =INDEX(Motore_Startup!$BI$5:$BI$544,(Ipotesi!$C$5-1)*60+3) -> 0 | I7: =INDEX(Motore_Advisory!$BH$5:$BH$544,(Ipotesi!$C$5-1)*60+3) -> -10462.852 | J7: =INDEX(Motore_Advisory!$BI$5:$BI$544,(Ipotesi!$C$5-1)*60+3) -> 20462.852 | K7: =G7+I7 -> 54671.839 | L7: =H7+J7 -> 20462.852 | M7: =IF(OR(G7<0,I7<0),1,0) -> 1
A8: =INDEX(Motore_Startup!$C$5:$C$544,(Ipotesi!$C$5-1)*60+4) -> 46478 | B8: =INDEX(Motore_Startup!$BH$5:$BH$544,(Ipotesi!$C$5-1)*60+3) -> 65134.691 | C8: =INDEX(Motore_Startup!$BD$5:$BD$544,(Ipotesi!$C$5-1)*60+4)-(INDEX(Motore_Startup!$BH$5:$BH$544,(Ipotesi!$C$5-1)*60+3))-(INDEX(Motore_Startup!$AW$5:$AW$544,(Ipotesi!$C$5-1)*60+4)+INDEX(Motore_Startup!$AX$5:$AX$544,(Ipotesi!$C$5-1)*60+4)+INDEX(Motore_Startup!$AZ$5:$AZ$544,(Ipotesi!$C$5-1)*60+4)+INDEX(Motore_Startup!$BA$5:$BA$544,(Ipotesi!$C$5-1)*60+4))+INDEX(Motore_Startup!$BB$5:$BB$544,(Ipotesi!$C$5-1)*60+4) -> -19584.66 | D8: =INDEX(Motore_Startup!$AW$5:$AW$544,(Ipotesi!$C$5-1)*60+4)+INDEX(Motore_Startup!$AX$5:$AX$544,(Ipotesi!$C$5-1)*60+4)+INDEX(Motore_Startup!$AZ$5:$AZ$544,(Ipotesi!$C$5-1)*60+4)+INDEX(Motore_Startup!$BA$5:$BA$544,(Ipotesi!$C$5-1)*60+4) -> 0 | E8: =INDEX(Motore_Startup!$BB$5:$BB$544,(Ipotesi!$C$5-1)*60+4) -> 0 | F8: =INDEX(Motore_Startup!$BE$5:$BE$544,(Ipotesi!$C$5-1)*60+4)-INDEX(Motore_Startup!$BF$5:$BF$544,(Ipotesi!$C$5-1)*60+4) -> 0 | G8: =INDEX(Motore_Startup!$BH$5:$BH$544,(Ipotesi!$C$5-1)*60+4) -> 45550.03 | H8: =INDEX(Motore_Startup!$BI$5:$BI$544,(Ipotesi!$C$5-1)*60+4) -> 0 | I8: =INDEX(Motore_Advisory!$BH$5:$BH$544,(Ipotesi!$C$5-1)*60+4) -> -6354.3432 | J8: =INDEX(Motore_Advisory!$BI$5:$BI$544,(Ipotesi!$C$5-1)*60+4) -> 16354.343 | K8: =G8+I8 -> 39195.687 | L8: =H8+J8 -> 16354.343 | M8: =IF(OR(G8<0,I8<0),1,0) -> 1
A9: =INDEX(Motore_Startup!$C$5:$C$544,(Ipotesi!$C$5-1)*60+5) -> 46508 | B9: =INDEX(Motore_Startup!$BH$5:$BH$544,(Ipotesi!$C$5-1)*60+4) -> 45550.03 | C9: =INDEX(Motore_Startup!$BD$5:$BD$544,(Ipotesi!$C$5-1)*60+5)-(INDEX(Motore_Startup!$BH$5:$BH$544,(Ipotesi!$C$5-1)*60+4))-(INDEX(Motore_Startup!$AW$5:$AW$544,(Ipotesi!$C$5-1)*60+5)+INDEX(Motore_Startup!$AX$5:$AX$544,(Ipotesi!$C$5-1)*60+5)+INDEX(Motore_Startup!$AZ$5:$AZ$544,(Ipotesi!$C$5-1)*60+5)+INDEX(Motore_Startup!$BA$5:$BA$544,(Ipotesi!$C$5-1)*60+5))+INDEX(Motore_Startup!$BB$5:$BB$544,(Ipotesi!$C$5-1)*60+5) -> -19584.66 | D9: =INDEX(Motore_Startup!$AW$5:$AW$544,(Ipotesi!$C$5-1)*60+5)+INDEX(Motore_Startup!$AX$5:$AX$544,(Ipotesi!$C$5-1)*60+5)+INDEX(Motore_Startup!$AZ$5:$AZ$544,(Ipotesi!$C$5-1)*60+5)+INDEX(Motore_Startup!$BA$5:$BA$544,(Ipotesi!$C$5-1)*60+5) -> 0 | E9: =INDEX(Motore_Startup!$BB$5:$BB$544,(Ipotesi!$C$5-1)*60+5) -> 0 | F9: =INDEX(Motore_Startup!$BE$5:$BE$544,(Ipotesi!$C$5-1)*60+5)-INDEX(Motore_Startup!$BF$5:$BF$544,(Ipotesi!$C$5-1)*60+5) -> 0 | G9: =INDEX(Motore_Startup!$BH$5:$BH$544,(Ipotesi!$C$5-1)*60+5) -> 25965.37 | H9: =INDEX(Motore_Startup!$BI$5:$BI$544,(Ipotesi!$C$5-1)*60+5) -> 0 | I9: =INDEX(Motore_Advisory!$BH$5:$BH$544,(Ipotesi!$C$5-1)*60+5) -> -2245.8344 | J9: =INDEX(Motore_Advisory!$BI$5:$BI$544,(Ipotesi!$C$5-1)*60+5) -> 12245.834 | K9: =G9+I9 -> 23719.536 | L9: =H9+J9 -> 12245.834 | M9: =IF(OR(G9<0,I9<0),1,0) -> 1
A10: =INDEX(Motore_Startup!$C$5:$C$544,(Ipotesi!$C$5-1)*60+6) -> 46539 | B10: =INDEX(Motore_Startup!$BH$5:$BH$544,(Ipotesi!$C$5-1)*60+5) -> 25965.37 | C10: =INDEX(Motore_Startup!$BD$5:$BD$544,(Ipotesi!$C$5-1)*60+6)-(INDEX(Motore_Startup!$BH$5:$BH$544,(Ipotesi!$C$5-1)*60+5))-(INDEX(Motore_Startup!$AW$5:$AW$544,(Ipotesi!$C$5-1)*60+6)+INDEX(Motore_Startup!$AX$5:$AX$544,(Ipotesi!$C$5-1)*60+6)+INDEX(Motore_Startup!$AZ$5:$AZ$544,(Ipotesi!$C$5-1)*60+6)+INDEX(Motore_Startup!$BA$5:$BA$544,(Ipotesi!$C$5-1)*60+6))+INDEX(Motore_Startup!$BB$5:$BB$544,(Ipotesi!$C$5-1)*60+6) -> -19592.354 | D10: =INDEX(Motore_Startup!$AW$5:$AW$544,(Ipotesi!$C$5-1)*60+6)+INDEX(Motore_Startup!$AX$5:$AX$544,(Ipotesi!$C$5-1)*60+6)+INDEX(Motore_Startup!$AZ$5:$AZ$544,(Ipotesi!$C$5-1)*60+6)+INDEX(Motore_Startup!$BA$5:$BA$544,(Ipotesi!$C$5-1)*60+6) -> 0 | E10: =INDEX(Motore_Startup!$BB$5:$BB$544,(Ipotesi!$C$5-1)*60+6) -> 0 | F10: =INDEX(Motore_Startup!$BE$5:$BE$544,(Ipotesi!$C$5-1)*60+6)-INDEX(Motore_Startup!$BF$5:$BF$544,(Ipotesi!$C$5-1)*60+6) -> 18626.984 | G10: =INDEX(Motore_Startup!$BH$5:$BH$544,(Ipotesi!$C$5-1)*60+6) -> 25000 | H10: =INDEX(Motore_Startup!$BI$5:$BI$544,(Ipotesi!$C$5-1)*60+6) -> 0 | I10: =INDEX(Motore_Advisory!$BH$5:$BH$544,(Ipotesi!$C$5-1)*60+6) -> 1862.6744 | J10: =INDEX(Motore_Advisory!$BI$5:$BI$544,(Ipotesi!$C$5-1)*60+6) -> 8137.3256 | K10: =G10+I10 -> 26862.674 | L10: =H10+J10 -> 8137.3256 | M10: =IF(OR(G10<0,I10<0),1,0) -> 0
A11: =INDEX(Motore_Startup!$C$5:$C$544,(Ipotesi!$C$5-1)*60+7) -> 46569 | B11: =INDEX(Motore_Startup!$BH$5:$BH$544,(Ipotesi!$C$5-1)*60+6) -> 25000 | C11: =INDEX(Motore_Startup!$BD$5:$BD$544,(Ipotesi!$C$5-1)*60+7)-(INDEX(Motore_Startup!$BH$5:$BH$544,(Ipotesi!$C$5-1)*60+6))-(INDEX(Motore_Startup!$AW$5:$AW$544,(Ipotesi!$C$5-1)*60+7)+INDEX(Motore_Startup!$AX$5:$AX$544,(Ipotesi!$C$5-1)*60+7)+INDEX(Motore_Startup!$AZ$5:$AZ$544,(Ipotesi!$C$5-1)*60+7)+INDEX(Motore_Startup!$BA$5:$BA$544,(Ipotesi!$C$5-1)*60+7))+INDEX(Motore_Startup!$BB$5:$BB$544,(Ipotesi!$C$5-1)*60+7) -> -19644.394 | D11: =INDEX(Motore_Startup!$AW$5:$AW$544,(Ipotesi!$C$5-1)*60+7)+INDEX(Motore_Startup!$AX$5:$AX$544,(Ipotesi!$C$5-1)*60+7)+INDEX(Motore_Startup!$AZ$5:$AZ$544,(Ipotesi!$C$5-1)*60+7)+INDEX(Motore_Startup!$BA$5:$BA$544,(Ipotesi!$C$5-1)*60+7) -> 0 | E11: =INDEX(Motore_Startup!$BB$5:$BB$544,(Ipotesi!$C$5-1)*60+7) -> 0 | F11: =INDEX(Motore_Startup!$BE$5:$BE$544,(Ipotesi!$C$5-1)*60+7)-INDEX(Motore_Startup!$BF$5:$BF$544,(Ipotesi!$C$5-1)*60+7) -> 19644.394 | G11: =INDEX(Motore_Startup!$BH$5:$BH$544,(Ipotesi!$C$5-1)*60+7) -> 25000 | H11: =INDEX(Motore_Startup!$BI$5:$BI$544,(Ipotesi!$C$5-1)*60+7) -> 0 | I11: =INDEX(Motore_Advisory!$BH$5:$BH$544,(Ipotesi!$C$5-1)*60+7) -> 5971.1832 | J11: =INDEX(Motore_Advisory!$BI$5:$BI$544,(Ipotesi!$C$5-1)*60+7) -> 4028.8168 | K11: =G11+I11 -> 30971.183 | L11: =H11+J11 -> 4028.8168 | M11: =IF(OR(G11<0,I11<0),1,0) -> 0
A12: =INDEX(Motore_Startup!$C$5:$C$544,(Ipotesi!$C$5-1)*60+8) -> 46600 | B12: =INDEX(Motore_Startup!$BH$5:$BH$544,(Ipotesi!$C$5-1)*60+7) -> 25000 | C12: =INDEX(Motore_Startup!$BD$5:$BD$544,(Ipotesi!$C$5-1)*60+8)-(INDEX(Motore_Startup!$BH$5:$BH$544,(Ipotesi!$C$5-1)*60+7))-(INDEX(Motore_Startup!$AW$5:$AW$544,(Ipotesi!$C$5-1)*60+8)+INDEX(Motore_Startup!$AX$5:$AX$544,(Ipotesi!$C$5-1)*60+8)+INDEX(Motore_Startup!$AZ$5:$AZ$544,(Ipotesi!$C$5-1)*60+8)+INDEX(Motore_Startup!$BA$5:$BA$544,(Ipotesi!$C$5-1)*60+8))+INDEX(Motore_Startup!$BB$5:$BB$544,(Ipotesi!$C$5-1)*60+8) -> -19645.04 | D12: =INDEX(Motore_Startup!$AW$5:$AW$544,(Ipotesi!$C$5-1)*60+8)+INDEX(Motore_Startup!$AX$5:$AX$544,(Ipotesi!$C$5-1)*60+8)+INDEX(Motore_Startup!$AZ$5:$AZ$544,(Ipotesi!$C$5-1)*60+8)+INDEX(Motore_Startup!$BA$5:$BA$544,(Ipotesi!$C$5-1)*60+8) -> 0 | E12: =INDEX(Motore_Startup!$BB$5:$BB$544,(Ipotesi!$C$5-1)*60+8) -> 0 | F12: =INDEX(Motore_Startup!$BE$5:$BE$544,(Ipotesi!$C$5-1)*60+8)-INDEX(Motore_Startup!$BF$5:$BF$544,(Ipotesi!$C$5-1)*60+8) -> 19645.04 | G12: =INDEX(Motore_Startup!$BH$5:$BH$544,(Ipotesi!$C$5-1)*60+8) -> 25000 | H12: =INDEX(Motore_Startup!$BI$5:$BI$544,(Ipotesi!$C$5-1)*60+8) -> 0 | I12: =INDEX(Motore_Advisory!$BH$5:$BH$544,(Ipotesi!$C$5-1)*60+8) -> 10079.692 | J12: =INDEX(Motore_Advisory!$BI$5:$BI$544,(Ipotesi!$C$5-1)*60+8) -> 0 | K12: =G12+I12 -> 35079.692 | L12: =H12+J12 -> 0 | M12: =IF(OR(G12<0,I12<0),1,0) -> 0
A13: =INDEX(Motore_Startup!$C$5:$C$544,(Ipotesi!$C$5-1)*60+9) -> 46631 | B13: =INDEX(Motore_Startup!$BH$5:$BH$544,(Ipotesi!$C$5-1)*60+8) -> 25000 | C13: =INDEX(Motore_Startup!$BD$5:$BD$544,(Ipotesi!$C$5-1)*60+9)-(INDEX(Motore_Startup!$BH$5:$BH$544,(Ipotesi!$C$5-1)*60+8))-(INDEX(Motore_Startup!$AW$5:$AW$544,(Ipotesi!$C$5-1)*60+9)+INDEX(Motore_Startup!$AX$5:$AX$544,(Ipotesi!$C$5-1)*60+9)+INDEX(Motore_Startup!$AZ$5:$AZ$544,(Ipotesi!$C$5-1)*60+9)+INDEX(Motore_Startup!$BA$5:$BA$544,(Ipotesi!$C$5-1)*60+9))+INDEX(Motore_Startup!$BB$5:$BB$544,(Ipotesi!$C$5-1)*60+9) -> -19645.69 | D13: =INDEX(Motore_Startup!$AW$5:$AW$544,(Ipotesi!$C$5-1)*60+9)+INDEX(Motore_Startup!$AX$5:$AX$544,(Ipotesi!$C$5-1)*60+9)+INDEX(Motore_Startup!$AZ$5:$AZ$544,(Ipotesi!$C$5-1)*60+9)+INDEX(Motore_Startup!$BA$5:$BA$544,(Ipotesi!$C$5-1)*60+9) -> 0 | E13: =INDEX(Motore_Startup!$BB$5:$BB$544,(Ipotesi!$C$5-1)*60+9) -> 0 | F13: =INDEX(Motore_Startup!$BE$5:$BE$544,(Ipotesi!$C$5-1)*60+9)-INDEX(Motore_Startup!$BF$5:$BF$544,(Ipotesi!$C$5-1)*60+9) -> 19645.69 | G13: =INDEX(Motore_Startup!$BH$5:$BH$544,(Ipotesi!$C$5-1)*60+9) -> 25000 | H13: =INDEX(Motore_Startup!$BI$5:$BI$544,(Ipotesi!$C$5-1)*60+9) -> 0 | I13: =INDEX(Motore_Advisory!$BH$5:$BH$544,(Ipotesi!$C$5-1)*60+9) -> 14188.201 | J13: =INDEX(Motore_Advisory!$BI$5:$BI$544,(Ipotesi!$C$5-1)*60+9) -> 0 | K13: =G13+I13 -> 39188.201 | L13: =H13+J13 -> 0 | M13: =IF(OR(G13<0,I13<0),1,0) -> 0
A14: =INDEX(Motore_Startup!$C$5:$C$544,(Ipotesi!$C$5-1)*60+10) -> 46661 | B14: =INDEX(Motore_Startup!$BH$5:$BH$544,(Ipotesi!$C$5-1)*60+9) -> 25000 | C14: =INDEX(Motore_Startup!$BD$5:$BD$544,(Ipotesi!$C$5-1)*60+10)-(INDEX(Motore_Startup!$BH$5:$BH$544,(Ipotesi!$C$5-1)*60+9))-(INDEX(Motore_Startup!$AW$5:$AW$544,(Ipotesi!$C$5-1)*60+10)+INDEX(Motore_Startup!$AX$5:$AX$544,(Ipotesi!$C$5-1)*60+10)+INDEX(Motore_Startup!$AZ$5:$AZ$544,(Ipotesi!$C$5-1)*60+10)+INDEX(Motore_Startup!$BA$5:$BA$544,(Ipotesi!$C$5-1)*60+10))+INDEX(Motore_Startup!$BB$5:$BB$544,(Ipotesi!$C$5-1)*60+10) -> -19646.342 | D14: =INDEX(Motore_Startup!$AW$5:$AW$544,(Ipotesi!$C$5-1)*60+10)+INDEX(Motore_Startup!$AX$5:$AX$544,(Ipotesi!$C$5-1)*60+10)+INDEX(Motore_Startup!$AZ$5:$AZ$544,(Ipotesi!$C$5-1)*60+10)+INDEX(Motore_Startup!$BA$5:$BA$544,(Ipotesi!$C$5-1)*60+10) -> 0 | E14: =INDEX(Motore_Startup!$BB$5:$BB$544,(Ipotesi!$C$5-1)*60+10) -> 0 | F14: =INDEX(Motore_Startup!$BE$5:$BE$544,(Ipotesi!$C$5-1)*60+10)-INDEX(Motore_Startup!$BF$5:$BF$544,(Ipotesi!$C$5-1)*60+10) -> 19646.342 | G14: =INDEX(Motore_Startup!$BH$5:$BH$544,(Ipotesi!$C$5-1)*60+10) -> 25000 | H14: =INDEX(Motore_Startup!$BI$5:$BI$544,(Ipotesi!$C$5-1)*60+10) -> 0 | I14: =INDEX(Motore_Advisory!$BH$5:$BH$544,(Ipotesi!$C$5-1)*60+10) -> 18296.709 | J14: =INDEX(Motore_Advisory!$BI$5:$BI$544,(Ipotesi!$C$5-1)*60+10) -> 0 | K14: =G14+I14 -> 43296.709 | L14: =H14+J14 -> 0 | M14: =IF(OR(G14<0,I14<0),1,0) -> 0
A15: =INDEX(Motore_Startup!$C$5:$C$544,(Ipotesi!$C$5-1)*60+11) -> 46692 | B15: =INDEX(Motore_Startup!$BH$5:$BH$544,(Ipotesi!$C$5-1)*60+10) -> 25000 | C15: =INDEX(Motore_Startup!$BD$5:$BD$544,(Ipotesi!$C$5-1)*60+11)-(INDEX(Motore_Startup!$BH$5:$BH$544,(Ipotesi!$C$5-1)*60+10))-(INDEX(Motore_Startup!$AW$5:$AW$544,(Ipotesi!$C$5-1)*60+11)+INDEX(Motore_Startup!$AX$5:$AX$544,(Ipotesi!$C$5-1)*60+11)+INDEX(Motore_Startup!$AZ$5:$AZ$544,(Ipotesi!$C$5-1)*60+11)+INDEX(Motore_Startup!$BA$5:$BA$544,(Ipotesi!$C$5-1)*60+11))+INDEX(Motore_Startup!$BB$5:$BB$544,(Ipotesi!$C$5-1)*60+11) -> -19646.998 | D15: =INDEX(Motore_Startup!$AW$5:$AW$544,(Ipotesi!$C$5-1)*60+11)+INDEX(Motore_Startup!$AX$5:$AX$544,(Ipotesi!$C$5-1)*60+11)+INDEX(Motore_Startup!$AZ$5:$AZ$544,(Ipotesi!$C$5-1)*60+11)+INDEX(Motore_Startup!$BA$5:$BA$544,(Ipotesi!$C$5-1)*60+11) -> 0 | E15: =INDEX(Motore_Startup!$BB$5:$BB$544,(Ipotesi!$C$5-1)*60+11) -> 0 | F15: =INDEX(Motore_Startup!$BE$5:$BE$544,(Ipotesi!$C$5-1)*60+11)-INDEX(Motore_Startup!$BF$5:$BF$544,(Ipotesi!$C$5-1)*60+11) -> 19646.998 | G15: =INDEX(Motore_Startup!$BH$5:$BH$544,(Ipotesi!$C$5-1)*60+11) -> 25000 | H15: =INDEX(Motore_Startup!$BI$5:$BI$544,(Ipotesi!$C$5-1)*60+11) -> 0 | I15: =INDEX(Motore_Advisory!$BH$5:$BH$544,(Ipotesi!$C$5-1)*60+11) -> 22405.218 | J15: =INDEX(Motore_Advisory!$BI$5:$BI$544,(Ipotesi!$C$5-1)*60+11) -> 0 | K15: =G15+I15 -> 47405.218 | L15: =H15+J15 -> 0 | M15: =IF(OR(G15<0,I15<0),1,0) -> 0
A16: =INDEX(Motore_Startup!$C$5:$C$544,(Ipotesi!$C$5-1)*60+12) -> 46722 | B16: =INDEX(Motore_Startup!$BH$5:$BH$544,(Ipotesi!$C$5-1)*60+11) -> 25000 | C16: =INDEX(Motore_Startup!$BD$5:$BD$544,(Ipotesi!$C$5-1)*60+12)-(INDEX(Motore_Startup!$BH$5:$BH$544,(Ipotesi!$C$5-1)*60+11))-(INDEX(Motore_Startup!$AW$5:$AW$544,(Ipotesi!$C$5-1)*60+12)+INDEX(Motore_Startup!$AX$5:$AX$544,(Ipotesi!$C$5-1)*60+12)+INDEX(Motore_Startup!$AZ$5:$AZ$544,(Ipotesi!$C$5-1)*60+12)+INDEX(Motore_Startup!$BA$5:$BA$544,(Ipotesi!$C$5-1)*60+12))+INDEX(Motore_Startup!$BB$5:$BB$544,(Ipotesi!$C$5-1)*60+12) -> -19647.657 | D16: =INDEX(Motore_Startup!$AW$5:$AW$544,(Ipotesi!$C$5-1)*60+12)+INDEX(Motore_Startup!$AX$5:$AX$544,(Ipotesi!$C$5-1)*60+12)+INDEX(Motore_Startup!$AZ$5:$AZ$544,(Ipotesi!$C$5-1)*60+12)+INDEX(Motore_Startup!$BA$5:$BA$544,(Ipotesi!$C$5-1)*60+12) -> 52542.222 | E16: =INDEX(Motore_Startup!$BB$5:$BB$544,(Ipotesi!$C$5-1)*60+12) -> 0 | F16: =INDEX(Motore_Startup!$BE$5:$BE$544,(Ipotesi!$C$5-1)*60+12)-INDEX(Motore_Startup!$BF$5:$BF$544,(Ipotesi!$C$5-1)*60+12) -> -32894.565 | G16: =INDEX(Motore_Startup!$BH$5:$BH$544,(Ipotesi!$C$5-1)*60+12) -> 25000 | H16: =INDEX(Motore_Startup!$BI$5:$BI$544,(Ipotesi!$C$5-1)*60+12) -> 0 | I16: =INDEX(Motore_Advisory!$BH$5:$BH$544,(Ipotesi!$C$5-1)*60+12) -> 26513.727 | J16: =INDEX(Motore_Advisory!$BI$5:$BI$544,(Ipotesi!$C$5-1)*60+12) -> 0 | K16: =G16+I16 -> 51513.727 | L16: =H16+J16 -> 0 | M16: =IF(OR(G16<0,I16<0),1,0) -> 0
A17: =INDEX(Motore_Startup!$C$5:$C$544,(Ipotesi!$C$5-1)*60+13) -> 46753 | B17: =INDEX(Motore_Startup!$BH$5:$BH$544,(Ipotesi!$C$5-1)*60+12) -> 25000 | C17: =INDEX(Motore_Startup!$BD$5:$BD$544,(Ipotesi!$C$5-1)*60+13)-(INDEX(Motore_Startup!$BH$5:$BH$544,(Ipotesi!$C$5-1)*60+12))-(INDEX(Motore_Startup!$AW$5:$AW$544,(Ipotesi!$C$5-1)*60+13)+INDEX(Motore_Startup!$AX$5:$AX$544,(Ipotesi!$C$5-1)*60+13)+INDEX(Motore_Startup!$AZ$5:$AZ$544,(Ipotesi!$C$5-1)*60+13)+INDEX(Motore_Startup!$BA$5:$BA$544,(Ipotesi!$C$5-1)*60+13))+INDEX(Motore_Startup!$BB$5:$BB$544,(Ipotesi!$C$5-1)*60+13) -> -40647.483 | D17: =INDEX(Motore_Startup!$AW$5:$AW$544,(Ipotesi!$C$5-1)*60+13)+INDEX(Motore_Startup!$AX$5:$AX$544,(Ipotesi!$C$5-1)*60+13)+INDEX(Motore_Startup!$AZ$5:$AZ$544,(Ipotesi!$C$5-1)*60+13)+INDEX(Motore_Startup!$BA$5:$BA$544,(Ipotesi!$C$5-1)*60+13) -> 15096.111 | E17: =INDEX(Motore_Startup!$BB$5:$BB$544,(Ipotesi!$C$5-1)*60+13) -> 0 | F17: =INDEX(Motore_Startup!$BE$5:$BE$544,(Ipotesi!$C$5-1)*60+13)-INDEX(Motore_Startup!$BF$5:$BF$544,(Ipotesi!$C$5-1)*60+13) -> 25551.372 | G17: =INDEX(Motore_Startup!$BH$5:$BH$544,(Ipotesi!$C$5-1)*60+13) -> 25000 | H17: =INDEX(Motore_Startup!$BI$5:$BI$544,(Ipotesi!$C$5-1)*60+13) -> 0 | I17: =INDEX(Motore_Advisory!$BH$5:$BH$544,(Ipotesi!$C$5-1)*60+13) -> 20239.652 | J17: =INDEX(Motore_Advisory!$BI$5:$BI$544,(Ipotesi!$C$5-1)*60+13) -> 0 | K17: =G17+I17 -> 45239.652 | L17: =H17+J17 -> 0 | M17: =IF(OR(G17<0,I17<0),1,0) -> 0
A18: =INDEX(Motore_Startup!$C$5:$C$544,(Ipotesi!$C$5-1)*60+14) -> 46784 | B18: =INDEX(Motore_Startup!$BH$5:$BH$544,(Ipotesi!$C$5-1)*60+13) -> 25000 | C18: =INDEX(Motore_Startup!$BD$5:$BD$544,(Ipotesi!$C$5-1)*60+14)-(INDEX(Motore_Startup!$BH$5:$BH$544,(Ipotesi!$C$5-1)*60+13))-(INDEX(Motore_Startup!$AW$5:$AW$544,(Ipotesi!$C$5-1)*60+14)+INDEX(Motore_Startup!$AX$5:$AX$544,(Ipotesi!$C$5-1)*60+14)+INDEX(Motore_Startup!$AZ$5:$AZ$544,(Ipotesi!$C$5-1)*60+14)+INDEX(Motore_Startup!$BA$5:$BA$544,(Ipotesi!$C$5-1)*60+14))+INDEX(Motore_Startup!$BB$5:$BB$544,(Ipotesi!$C$5-1)*60+14) -> -39058.13 | D18: =INDEX(Motore_Startup!$AW$5:$AW$544,(Ipotesi!$C$5-1)*60+14)+INDEX(Motore_Startup!$AX$5:$AX$544,(Ipotesi!$C$5-1)*60+14)+INDEX(Motore_Startup!$AZ$5:$AZ$544,(Ipotesi!$C$5-1)*60+14)+INDEX(Motore_Startup!$BA$5:$BA$544,(Ipotesi!$C$5-1)*60+14) -> 12361.667 | E18: =INDEX(Motore_Startup!$BB$5:$BB$544,(Ipotesi!$C$5-1)*60+14) -> 0 | F18: =INDEX(Motore_Startup!$BE$5:$BE$544,(Ipotesi!$C$5-1)*60+14)-INDEX(Motore_Startup!$BF$5:$BF$544,(Ipotesi!$C$5-1)*60+14) -> 26696.464 | G18: =INDEX(Motore_Startup!$BH$5:$BH$544,(Ipotesi!$C$5-1)*60+14) -> 25000 | H18: =INDEX(Motore_Startup!$BI$5:$BI$544,(Ipotesi!$C$5-1)*60+14) -> 0 | I18: =INDEX(Motore_Advisory!$BH$5:$BH$544,(Ipotesi!$C$5-1)*60+14) -> 9068.6809 | J18: =INDEX(Motore_Advisory!$BI$5:$BI$544,(Ipotesi!$C$5-1)*60+14) -> 931.3191 | K18: =G18+I18 -> 34068.681 | L18: =H18+J18 -> 931.3191 | M18: =IF(OR(G18<0,I18<0),1,0) -> 0
A19: =INDEX(Motore_Startup!$C$5:$C$544,(Ipotesi!$C$5-1)*60+15) -> 46813 | B19: =INDEX(Motore_Startup!$BH$5:$BH$544,(Ipotesi!$C$5-1)*60+14) -> 25000 | C19: =INDEX(Motore_Startup!$BD$5:$BD$544,(Ipotesi!$C$5-1)*60+15)-(INDEX(Motore_Startup!$BH$5:$BH$544,(Ipotesi!$C$5-1)*60+14))-(INDEX(Motore_Startup!$AW$5:$AW$544,(Ipotesi!$C$5-1)*60+15)+INDEX(Motore_Startup!$AX$5:$AX$544,(Ipotesi!$C$5-1)*60+15)+INDEX(Motore_Startup!$AZ$5:$AZ$544,(Ipotesi!$C$5-1)*60+15)+INDEX(Motore_Startup!$BA$5:$BA$544,(Ipotesi!$C$5-1)*60+15))+INDEX(Motore_Startup!$BB$5:$BB$544,(Ipotesi!$C$5-1)*60+15) -> -49411.016 | D19: =INDEX(Motore_Startup!$AW$5:$AW$544,(Ipotesi!$C$5-1)*60+15)+INDEX(Motore_Startup!$AX$5:$AX$544,(Ipotesi!$C$5-1)*60+15)+INDEX(Motore_Startup!$AZ$5:$AZ$544,(Ipotesi!$C$5-1)*60+15)+INDEX(Motore_Startup!$BA$5:$BA$544,(Ipotesi!$C$5-1)*60+15) -> 0 | E19: =INDEX(Motore_Startup!$BB$5:$BB$544,(Ipotesi!$C$5-1)*60+15) -> 0 | F19: =INDEX(Motore_Startup!$BE$5:$BE$544,(Ipotesi!$C$5-1)*60+15)-INDEX(Motore_Startup!$BF$5:$BF$544,(Ipotesi!$C$5-1)*60+15) -> 13791.282 | G19: =INDEX(Motore_Startup!$BH$5:$BH$544,(Ipotesi!$C$5-1)*60+15) -> -10619.734 | H19: =INDEX(Motore_Startup!$BI$5:$BI$544,(Ipotesi!$C$5-1)*60+15) -> 35619.734 | I19: =INDEX(Motore_Advisory!$BH$5:$BH$544,(Ipotesi!$C$5-1)*60+15) -> -7134.0908 | J19: =INDEX(Motore_Advisory!$BI$5:$BI$544,(Ipotesi!$C$5-1)*60+15) -> 17134.091 | K19: =G19+I19 -> -17753.825 | L19: =H19+J19 -> 52753.825 | M19: =IF(OR(G19<0,I19<0),1,0) -> 1
A20: =INDEX(Motore_Startup!$C$5:$C$544,(Ipotesi!$C$5-1)*60+16) -> 46844 | B20: =INDEX(Motore_Startup!$BH$5:$BH$544,(Ipotesi!$C$5-1)*60+15) -> -10619.734 | C20: =INDEX(Motore_Startup!$BD$5:$BD$544,(Ipotesi!$C$5-1)*60+16)-(INDEX(Motore_Startup!$BH$5:$BH$544,(Ipotesi!$C$5-1)*60+15))-(INDEX(Motore_Startup!$AW$5:$AW$544,(Ipotesi!$C$5-1)*60+16)+INDEX(Motore_Startup!$AX$5:$AX$544,(Ipotesi!$C$5-1)*60+16)+INDEX(Motore_Startup!$AZ$5:$AZ$544,(Ipotesi!$C$5-1)*60+16)+INDEX(Motore_Startup!$BA$5:$BA$544,(Ipotesi!$C$5-1)*60+16))+INDEX(Motore_Startup!$BB$5:$BB$544,(Ipotesi!$C$5-1)*60+16) -> -31387.455 | D20: =INDEX(Motore_Startup!$AW$5:$AW$544,(Ipotesi!$C$5-1)*60+16)+INDEX(Motore_Startup!$AX$5:$AX$544,(Ipotesi!$C$5-1)*60+16)+INDEX(Motore_Startup!$AZ$5:$AZ$544,(Ipotesi!$C$5-1)*60+16)+INDEX(Motore_Startup!$BA$5:$BA$544,(Ipotesi!$C$5-1)*60+16) -> 0 | E20: =INDEX(Motore_Startup!$BB$5:$BB$544,(Ipotesi!$C$5-1)*60+16) -> 0 | F20: =INDEX(Motore_Startup!$BE$5:$BE$544,(Ipotesi!$C$5-1)*60+16)-INDEX(Motore_Startup!$BF$5:$BF$544,(Ipotesi!$C$5-1)*60+16) -> 0 | G20: =INDEX(Motore_Startup!$BH$5:$BH$544,(Ipotesi!$C$5-1)*60+16) -> -42007.189 | H20: =INDEX(Motore_Startup!$BI$5:$BI$544,(Ipotesi!$C$5-1)*60+16) -> 67007.189 | I20: =INDEX(Motore_Advisory!$BH$5:$BH$544,(Ipotesi!$C$5-1)*60+16) -> -1656.6155 | J20: =INDEX(Motore_Advisory!$BI$5:$BI$544,(Ipotesi!$C$5-1)*60+16) -> 11656.615 | K20: =G20+I20 -> -43663.804 | L20: =H20+J20 -> 78663.804 | M20: =IF(OR(G20<0,I20<0),1,0) -> 1
A21: =INDEX(Motore_Startup!$C$5:$C$544,(Ipotesi!$C$5-1)*60+17) -> 46874 | B21: =INDEX(Motore_Startup!$BH$5:$BH$544,(Ipotesi!$C$5-1)*60+16) -> -42007.189 | C21: =INDEX(Motore_Startup!$BD$5:$BD$544,(Ipotesi!$C$5-1)*60+17)-(INDEX(Motore_Startup!$BH$5:$BH$544,(Ipotesi!$C$5-1)*60+16))-(INDEX(Motore_Startup!$AW$5:$AW$544,(Ipotesi!$C$5-1)*60+17)+INDEX(Motore_Startup!$AX$5:$AX$544,(Ipotesi!$C$5-1)*60+17)+INDEX(Motore_Startup!$AZ$5:$AZ$544,(Ipotesi!$C$5-1)*60+17)+INDEX(Motore_Startup!$BA$5:$BA$544,(Ipotesi!$C$5-1)*60+17))+INDEX(Motore_Startup!$BB$5:$BB$544,(Ipotesi!$C$5-1)*60+17) -> -31131.571 | D21: =INDEX(Motore_Startup!$AW$5:$AW$544,(Ipotesi!$C$5-1)*60+17)+INDEX(Motore_Startup!$AX$5:$AX$544,(Ipotesi!$C$5-1)*60+17)+INDEX(Motore_Startup!$AZ$5:$AZ$544,(Ipotesi!$C$5-1)*60+17)+INDEX(Motore_Startup!$BA$5:$BA$544,(Ipotesi!$C$5-1)*60+17) -> 0 | E21: =INDEX(Motore_Startup!$BB$5:$BB$544,(Ipotesi!$C$5-1)*60+17) -> 0 | F21: =INDEX(Motore_Startup!$BE$5:$BE$544,(Ipotesi!$C$5-1)*60+17)-INDEX(Motore_Startup!$BF$5:$BF$544,(Ipotesi!$C$5-1)*60+17) -> 0 | G21: =INDEX(Motore_Startup!$BH$5:$BH$544,(Ipotesi!$C$5-1)*60+17) -> -73138.76 | H21: =INDEX(Motore_Startup!$BI$5:$BI$544,(Ipotesi!$C$5-1)*60+17) -> 98138.76 | I21: =INDEX(Motore_Advisory!$BH$5:$BH$544,(Ipotesi!$C$5-1)*60+17) -> 3820.8599 | J21: =INDEX(Motore_Advisory!$BI$5:$BI$544,(Ipotesi!$C$5-1)*60+17) -> 6179.1401 | K21: =G21+I21 -> -69317.9 | L21: =H21+J21 -> 104317.9 | M21: =IF(OR(G21<0,I21<0),1,0) -> 1
A22: =INDEX(Motore_Startup!$C$5:$C$544,(Ipotesi!$C$5-1)*60+18) -> 46905 | B22: =INDEX(Motore_Startup!$BH$5:$BH$544,(Ipotesi!$C$5-1)*60+17) -> -73138.76 | C22: =INDEX(Motore_Startup!$BD$5:$BD$544,(Ipotesi!$C$5-1)*60+18)-(INDEX(Motore_Startup!$BH$5:$BH$544,(Ipotesi!$C$5-1)*60+17))-(INDEX(Motore_Startup!$AW$5:$AW$544,(Ipotesi!$C$5-1)*60+18)+INDEX(Motore_Startup!$AX$5:$AX$544,(Ipotesi!$C$5-1)*60+18)+INDEX(Motore_Startup!$AZ$5:$AZ$544,(Ipotesi!$C$5-1)*60+18)+INDEX(Motore_Startup!$BA$5:$BA$544,(Ipotesi!$C$5-1)*60+18))+INDEX(Motore_Startup!$BB$5:$BB$544,(Ipotesi!$C$5-1)*60+18) -> -30982.787 | D22: =INDEX(Motore_Startup!$AW$5:$AW$544,(Ipotesi!$C$5-1)*60+18)+INDEX(Motore_Startup!$AX$5:$AX$544,(Ipotesi!$C$5-1)*60+18)+INDEX(Motore_Startup!$AZ$5:$AZ$544,(Ipotesi!$C$5-1)*60+18)+INDEX(Motore_Startup!$BA$5:$BA$544,(Ipotesi!$C$5-1)*60+18) -> 300000 | E22: =INDEX(Motore_Startup!$BB$5:$BB$544,(Ipotesi!$C$5-1)*60+18) -> 0 | F22: =INDEX(Motore_Startup!$BE$5:$BE$544,(Ipotesi!$C$5-1)*60+18)-INDEX(Motore_Startup!$BF$5:$BF$544,(Ipotesi!$C$5-1)*60+18) -> -150000 | G22: =INDEX(Motore_Startup!$BH$5:$BH$544,(Ipotesi!$C$5-1)*60+18) -> 45878.453 | H22: =INDEX(Motore_Startup!$BI$5:$BI$544,(Ipotesi!$C$5-1)*60+18) -> 0 | I22: =INDEX(Motore_Advisory!$BH$5:$BH$544,(Ipotesi!$C$5-1)*60+18) -> -9688.9021 | J22: =INDEX(Motore_Advisory!$BI$5:$BI$544,(Ipotesi!$C$5-1)*60+18) -> 19688.902 | K22: =G22+I22 -> 36189.551 | L22: =H22+J22 -> 19688.902 | M22: =IF(OR(G22<0,I22<0),1,0) -> 1
A23: =INDEX(Motore_Startup!$C$5:$C$544,(Ipotesi!$C$5-1)*60+19) -> 46935 | B23: =INDEX(Motore_Startup!$BH$5:$BH$544,(Ipotesi!$C$5-1)*60+18) -> 45878.453 | C23: =INDEX(Motore_Startup!$BD$5:$BD$544,(Ipotesi!$C$5-1)*60+19)-(INDEX(Motore_Startup!$BH$5:$BH$544,(Ipotesi!$C$5-1)*60+18))-(INDEX(Motore_Startup!$AW$5:$AW$544,(Ipotesi!$C$5-1)*60+19)+INDEX(Motore_Startup!$AX$5:$AX$544,(Ipotesi!$C$5-1)*60+19)+INDEX(Motore_Startup!$AZ$5:$AZ$544,(Ipotesi!$C$5-1)*60+19)+INDEX(Motore_Startup!$BA$5:$BA$544,(Ipotesi!$C$5-1)*60+19))+INDEX(Motore_Startup!$BB$5:$BB$544,(Ipotesi!$C$5-1)*60+19) -> -29778.341 | D23: =INDEX(Motore_Startup!$AW$5:$AW$544,(Ipotesi!$C$5-1)*60+19)+INDEX(Motore_Startup!$AX$5:$AX$544,(Ipotesi!$C$5-1)*60+19)+INDEX(Motore_Startup!$AZ$5:$AZ$544,(Ipotesi!$C$5-1)*60+19)+INDEX(Motore_Startup!$BA$5:$BA$544,(Ipotesi!$C$5-1)*60+19) -> 0 | E23: =INDEX(Motore_Startup!$BB$5:$BB$544,(Ipotesi!$C$5-1)*60+19) -> 0 | F23: =INDEX(Motore_Startup!$BE$5:$BE$544,(Ipotesi!$C$5-1)*60+19)-INDEX(Motore_Startup!$BF$5:$BF$544,(Ipotesi!$C$5-1)*60+19) -> 8899.8876 | G23: =INDEX(Motore_Startup!$BH$5:$BH$544,(Ipotesi!$C$5-1)*60+19) -> 25000 | H23: =INDEX(Motore_Startup!$BI$5:$BI$544,(Ipotesi!$C$5-1)*60+19) -> 0 | I23: =INDEX(Motore_Advisory!$BH$5:$BH$544,(Ipotesi!$C$5-1)*60+19) -> -4211.4267 | J23: =INDEX(Motore_Advisory!$BI$5:$BI$544,(Ipotesi!$C$5-1)*60+19) -> 14211.427 | K23: =G23+I23 -> 20788.573 | L23: =H23+J23 -> 14211.427 | M23: =IF(OR(G23<0,I23<0),1,0) -> 1
A24: =INDEX(Motore_Startup!$C$5:$C$544,(Ipotesi!$C$5-1)*60+20) -> 46966 | B24: =INDEX(Motore_Startup!$BH$5:$BH$544,(Ipotesi!$C$5-1)*60+19) -> 25000 | C24: =INDEX(Motore_Startup!$BD$5:$BD$544,(Ipotesi!$C$5-1)*60+20)-(INDEX(Motore_Startup!$BH$5:$BH$544,(Ipotesi!$C$5-1)*60+19))-(INDEX(Motore_Startup!$AW$5:$AW$544,(Ipotesi!$C$5-1)*60+20)+INDEX(Motore_Startup!$AX$5:$AX$544,(Ipotesi!$C$5-1)*60+20)+INDEX(Motore_Startup!$AZ$5:$AZ$544,(Ipotesi!$C$5-1)*60+20)+INDEX(Motore_Startup!$BA$5:$BA$544,(Ipotesi!$C$5-1)*60+20))+INDEX(Motore_Startup!$BB$5:$BB$544,(Ipotesi!$C$5-1)*60+20) -> -29017 | D24: =INDEX(Motore_Startup!$AW$5:$AW$544,(Ipotesi!$C$5-1)*60+20)+INDEX(Motore_Startup!$AX$5:$AX$544,(Ipotesi!$C$5-1)*60+20)+INDEX(Motore_Startup!$AZ$5:$AZ$544,(Ipotesi!$C$5-1)*60+20)+INDEX(Motore_Startup!$BA$5:$BA$544,(Ipotesi!$C$5-1)*60+20) -> 0 | E24: =INDEX(Motore_Startup!$BB$5:$BB$544,(Ipotesi!$C$5-1)*60+20) -> 0 | F24: =INDEX(Motore_Startup!$BE$5:$BE$544,(Ipotesi!$C$5-1)*60+20)-INDEX(Motore_Startup!$BF$5:$BF$544,(Ipotesi!$C$5-1)*60+20) -> 29017 | G24: =INDEX(Motore_Startup!$BH$5:$BH$544,(Ipotesi!$C$5-1)*60+20) -> 25000 | H24: =INDEX(Motore_Startup!$BI$5:$BI$544,(Ipotesi!$C$5-1)*60+20) -> 0 | I24: =INDEX(Motore_Advisory!$BH$5:$BH$544,(Ipotesi!$C$5-1)*60+20) -> 1266.0486 | J24: =INDEX(Motore_Advisory!$BI$5:$BI$544,(Ipotesi!$C$5-1)*60+20) -> 8733.9514 | K24: =G24+I24 -> 26266.049 | L24: =H24+J24 -> 8733.9514 | M24: =IF(OR(G24<0,I24<0),1,0) -> 0
A25: =INDEX(Motore_Startup!$C$5:$C$544,(Ipotesi!$C$5-1)*60+21) -> 46997 | B25: =INDEX(Motore_Startup!$BH$5:$BH$544,(Ipotesi!$C$5-1)*60+20) -> 25000 | C25: =INDEX(Motore_Startup!$BD$5:$BD$544,(Ipotesi!$C$5-1)*60+21)-(INDEX(Motore_Startup!$BH$5:$BH$544,(Ipotesi!$C$5-1)*60+20))-(INDEX(Motore_Startup!$AW$5:$AW$544,(Ipotesi!$C$5-1)*60+21)+INDEX(Motore_Startup!$AX$5:$AX$544,(Ipotesi!$C$5-1)*60+21)+INDEX(Motore_Startup!$AZ$5:$AZ$544,(Ipotesi!$C$5-1)*60+21)+INDEX(Motore_Startup!$BA$5:$BA$544,(Ipotesi!$C$5-1)*60+21))+INDEX(Motore_Startup!$BB$5:$BB$544,(Ipotesi!$C$5-1)*60+21) -> -28363.289 | D25: =INDEX(Motore_Startup!$AW$5:$AW$544,(Ipotesi!$C$5-1)*60+21)+INDEX(Motore_Startup!$AX$5:$AX$544,(Ipotesi!$C$5-1)*60+21)+INDEX(Motore_Startup!$AZ$5:$AZ$544,(Ipotesi!$C$5-1)*60+21)+INDEX(Motore_Startup!$BA$5:$BA$544,(Ipotesi!$C$5-1)*60+21) -> 0 | E25: =INDEX(Motore_Startup!$BB$5:$BB$544,(Ipotesi!$C$5-1)*60+21) -> 0 | F25: =INDEX(Motore_Startup!$BE$5:$BE$544,(Ipotesi!$C$5-1)*60+21)-INDEX(Motore_Startup!$BF$5:$BF$544,(Ipotesi!$C$5-1)*60+21) -> 28363.289 | G25: =INDEX(Motore_Startup!$BH$5:$BH$544,(Ipotesi!$C$5-1)*60+21) -> 25000 | H25: =INDEX(Motore_Startup!$BI$5:$BI$544,(Ipotesi!$C$5-1)*60+21) -> 0 | I25: =INDEX(Motore_Advisory!$BH$5:$BH$544,(Ipotesi!$C$5-1)*60+21) -> 6743.524 | J25: =INDEX(Motore_Advisory!$BI$5:$BI$544,(Ipotesi!$C$5-1)*60+21) -> 3256.476 | K25: =G25+I25 -> 31743.524 | L25: =H25+J25 -> 3256.476 | M25: =IF(OR(G25<0,I25<0),1,0) -> 0
A26: =INDEX(Motore_Startup!$C$5:$C$544,(Ipotesi!$C$5-1)*60+22) -> 47027 | B26: =INDEX(Motore_Startup!$BH$5:$BH$544,(Ipotesi!$C$5-1)*60+21) -> 25000 | C26: =INDEX(Motore_Startup!$BD$5:$BD$544,(Ipotesi!$C$5-1)*60+22)-(INDEX(Motore_Startup!$BH$5:$BH$544,(Ipotesi!$C$5-1)*60+21))-(INDEX(Motore_Startup!$AW$5:$AW$544,(Ipotesi!$C$5-1)*60+22)+INDEX(Motore_Startup!$AX$5:$AX$544,(Ipotesi!$C$5-1)*60+22)+INDEX(Motore_Startup!$AZ$5:$AZ$544,(Ipotesi!$C$5-1)*60+22)+INDEX(Motore_Startup!$BA$5:$BA$544,(Ipotesi!$C$5-1)*60+22))+INDEX(Motore_Startup!$BB$5:$BB$544,(Ipotesi!$C$5-1)*60+22) -> -27713.292 | D26: =INDEX(Motore_Startup!$AW$5:$AW$544,(Ipotesi!$C$5-1)*60+22)+INDEX(Motore_Startup!$AX$5:$AX$544,(Ipotesi!$C$5-1)*60+22)+INDEX(Motore_Startup!$AZ$5:$AZ$544,(Ipotesi!$C$5-1)*60+22)+INDEX(Motore_Startup!$BA$5:$BA$544,(Ipotesi!$C$5-1)*60+22) -> 0 | E26: =INDEX(Motore_Startup!$BB$5:$BB$544,(Ipotesi!$C$5-1)*60+22) -> 0 | F26: =INDEX(Motore_Startup!$BE$5:$BE$544,(Ipotesi!$C$5-1)*60+22)-INDEX(Motore_Startup!$BF$5:$BF$544,(Ipotesi!$C$5-1)*60+22) -> 27713.292 | G26: =INDEX(Motore_Startup!$BH$5:$BH$544,(Ipotesi!$C$5-1)*60+22) -> 25000 | H26: =INDEX(Motore_Startup!$BI$5:$BI$544,(Ipotesi!$C$5-1)*60+22) -> 0 | I26: =INDEX(Motore_Advisory!$BH$5:$BH$544,(Ipotesi!$C$5-1)*60+22) -> 12220.999 | J26: =INDEX(Motore_Advisory!$BI$5:$BI$544,(Ipotesi!$C$5-1)*60+22) -> 0 | K26: =G26+I26 -> 37220.999 | L26: =H26+J26 -> 0 | M26: =IF(OR(G26<0,I26<0),1,0) -> 0
A27: =INDEX(Motore_Startup!$C$5:$C$544,(Ipotesi!$C$5-1)*60+23) -> 47058 | B27: =INDEX(Motore_Startup!$BH$5:$BH$544,(Ipotesi!$C$5-1)*60+22) -> 25000 | C27: =INDEX(Motore_Startup!$BD$5:$BD$544,(Ipotesi!$C$5-1)*60+23)-(INDEX(Motore_Startup!$BH$5:$BH$544,(Ipotesi!$C$5-1)*60+22))-(INDEX(Motore_Startup!$AW$5:$AW$544,(Ipotesi!$C$5-1)*60+23)+INDEX(Motore_Startup!$AX$5:$AX$544,(Ipotesi!$C$5-1)*60+23)+INDEX(Motore_Startup!$AZ$5:$AZ$544,(Ipotesi!$C$5-1)*60+23)+INDEX(Motore_Startup!$BA$5:$BA$544,(Ipotesi!$C$5-1)*60+23))+INDEX(Motore_Startup!$BB$5:$BB$544,(Ipotesi!$C$5-1)*60+23) -> -27066.967 | D27: =INDEX(Motore_Startup!$AW$5:$AW$544,(Ipotesi!$C$5-1)*60+23)+INDEX(Motore_Startup!$AX$5:$AX$544,(Ipotesi!$C$5-1)*60+23)+INDEX(Motore_Startup!$AZ$5:$AZ$544,(Ipotesi!$C$5-1)*60+23)+INDEX(Motore_Startup!$BA$5:$BA$544,(Ipotesi!$C$5-1)*60+23) -> 0 | E27: =INDEX(Motore_Startup!$BB$5:$BB$544,(Ipotesi!$C$5-1)*60+23) -> 0 | F27: =INDEX(Motore_Startup!$BE$5:$BE$544,(Ipotesi!$C$5-1)*60+23)-INDEX(Motore_Startup!$BF$5:$BF$544,(Ipotesi!$C$5-1)*60+23) -> 27066.967 | G27: =INDEX(Motore_Startup!$BH$5:$BH$544,(Ipotesi!$C$5-1)*60+23) -> 25000 | H27: =INDEX(Motore_Startup!$BI$5:$BI$544,(Ipotesi!$C$5-1)*60+23) -> 0 | I27: =INDEX(Motore_Advisory!$BH$5:$BH$544,(Ipotesi!$C$5-1)*60+23) -> 9561.0872 | J27: =INDEX(Motore_Advisory!$BI$5:$BI$544,(Ipotesi!$C$5-1)*60+23) -> 438.91276 | K27: =G27+I27 -> 34561.087 | L27: =H27+J27 -> 438.91276 | M27: =IF(OR(G27<0,I27<0),1,0) -> 0
A28: =INDEX(Motore_Startup!$C$5:$C$544,(Ipotesi!$C$5-1)*60+24) -> 47088 | B28: =INDEX(Motore_Startup!$BH$5:$BH$544,(Ipotesi!$C$5-1)*60+23) -> 25000 | C28: =INDEX(Motore_Startup!$BD$5:$BD$544,(Ipotesi!$C$5-1)*60+24)-(INDEX(Motore_Startup!$BH$5:$BH$544,(Ipotesi!$C$5-1)*60+23))-(INDEX(Motore_Startup!$AW$5:$AW$544,(Ipotesi!$C$5-1)*60+24)+INDEX(Motore_Startup!$AX$5:$AX$544,(Ipotesi!$C$5-1)*60+24)+INDEX(Motore_Startup!$AZ$5:$AZ$544,(Ipotesi!$C$5-1)*60+24)+INDEX(Motore_Startup!$BA$5:$BA$544,(Ipotesi!$C$5-1)*60+24))+INDEX(Motore_Startup!$BB$5:$BB$544,(Ipotesi!$C$5-1)*60+24) -> -26424.272 | D28: =INDEX(Motore_Startup!$AW$5:$AW$544,(Ipotesi!$C$5-1)*60+24)+INDEX(Motore_Startup!$AX$5:$AX$544,(Ipotesi!$C$5-1)*60+24)+INDEX(Motore_Startup!$AZ$5:$AZ$544,(Ipotesi!$C$5-1)*60+24)+INDEX(Motore_Startup!$BA$5:$BA$544,(Ipotesi!$C$5-1)*60+24) -> 162621.5 | E28: =INDEX(Motore_Startup!$BB$5:$BB$544,(Ipotesi!$C$5-1)*60+24) -> 0 | F28: =INDEX(Motore_Startup!$BE$5:$BE$544,(Ipotesi!$C$5-1)*60+24)-INDEX(Motore_Startup!$BF$5:$BF$544,(Ipotesi!$C$5-1)*60+24) -> -121060.44 | G28: =INDEX(Motore_Startup!$BH$5:$BH$544,(Ipotesi!$C$5-1)*60+24) -> 40136.79 | H28: =INDEX(Motore_Startup!$BI$5:$BI$544,(Ipotesi!$C$5-1)*60+24) -> 0 | I28: =INDEX(Motore_Advisory!$BH$5:$BH$544,(Ipotesi!$C$5-1)*60+24) -> 15038.563 | J28: =INDEX(Motore_Advisory!$BI$5:$BI$544,(Ipotesi!$C$5-1)*60+24) -> 0 | K28: =G28+I28 -> 55175.353 | L28: =H28+J28 -> 0 | M28: =IF(OR(G28<0,I28<0),1,0) -> 0
A29: =INDEX(Motore_Startup!$C$5:$C$544,(Ipotesi!$C$5-1)*60+25) -> 47119 | B29: =INDEX(Motore_Startup!$BH$5:$BH$544,(Ipotesi!$C$5-1)*60+24) -> 40136.79 | C29: =INDEX(Motore_Startup!$BD$5:$BD$544,(Ipotesi!$C$5-1)*60+25)-(INDEX(Motore_Startup!$BH$5:$BH$544,(Ipotesi!$C$5-1)*60+24))-(INDEX(Motore_Startup!$AW$5:$AW$544,(Ipotesi!$C$5-1)*60+25)+INDEX(Motore_Startup!$AX$5:$AX$544,(Ipotesi!$C$5-1)*60+25)+INDEX(Motore_Startup!$AZ$5:$AZ$544,(Ipotesi!$C$5-1)*60+25)+INDEX(Motore_Startup!$BA$5:$BA$544,(Ipotesi!$C$5-1)*60+25))+INDEX(Motore_Startup!$BB$5:$BB$544,(Ipotesi!$C$5-1)*60+25) -> -58341.682 | D29: =INDEX(Motore_Startup!$AW$5:$AW$544,(Ipotesi!$C$5-1)*60+25)+INDEX(Motore_Startup!$AX$5:$AX$544,(Ipotesi!$C$5-1)*60+25)+INDEX(Motore_Startup!$AZ$5:$AZ$544,(Ipotesi!$C$5-1)*60+25)+INDEX(Motore_Startup!$BA$5:$BA$544,(Ipotesi!$C$5-1)*60+25) -> 24900.125 | E29: =INDEX(Motore_Startup!$BB$5:$BB$544,(Ipotesi!$C$5-1)*60+25) -> 0 | F29: =INDEX(Motore_Startup!$BE$5:$BE$544,(Ipotesi!$C$5-1)*60+25)-INDEX(Motore_Startup!$BF$5:$BF$544,(Ipotesi!$C$5-1)*60+25) -> 18304.767 | G29: =INDEX(Motore_Startup!$BH$5:$BH$544,(Ipotesi!$C$5-1)*60+25) -> 25000 | H29: =INDEX(Motore_Startup!$BI$5:$BI$544,(Ipotesi!$C$5-1)*60+25) -> 0 | I29: =INDEX(Motore_Advisory!$BH$5:$BH$544,(Ipotesi!$C$5-1)*60+25) -> 11536.262 | J29: =INDEX(Motore_Advisory!$BI$5:$BI$544,(Ipotesi!$C$5-1)*60+25) -> 0 | K29: =G29+I29 -> 36536.262 | L29: =H29+J29 -> 0 | M29: =IF(OR(G29<0,I29<0),1,0) -> 0
A30: =INDEX(Motore_Startup!$C$5:$C$544,(Ipotesi!$C$5-1)*60+26) -> 47150 | B30: =INDEX(Motore_Startup!$BH$5:$BH$544,(Ipotesi!$C$5-1)*60+25) -> 25000 | C30: =INDEX(Motore_Startup!$BD$5:$BD$544,(Ipotesi!$C$5-1)*60+26)-(INDEX(Motore_Startup!$BH$5:$BH$544,(Ipotesi!$C$5-1)*60+25))-(INDEX(Motore_Startup!$AW$5:$AW$544,(Ipotesi!$C$5-1)*60+26)+INDEX(Motore_Startup!$AX$5:$AX$544,(Ipotesi!$C$5-1)*60+26)+INDEX(Motore_Startup!$AZ$5:$AZ$544,(Ipotesi!$C$5-1)*60+26)+INDEX(Motore_Startup!$BA$5:$BA$544,(Ipotesi!$C$5-1)*60+26))+INDEX(Motore_Startup!$BB$5:$BB$544,(Ipotesi!$C$5-1)*60+26) -> -56055.497 | D30: =INDEX(Motore_Startup!$AW$5:$AW$544,(Ipotesi!$C$5-1)*60+26)+INDEX(Motore_Startup!$AX$5:$AX$544,(Ipotesi!$C$5-1)*60+26)+INDEX(Motore_Startup!$AZ$5:$AZ$544,(Ipotesi!$C$5-1)*60+26)+INDEX(Motore_Startup!$BA$5:$BA$544,(Ipotesi!$C$5-1)*60+26) -> 12478.377 | E30: =INDEX(Motore_Startup!$BB$5:$BB$544,(Ipotesi!$C$5-1)*60+26) -> 0 | F30: =INDEX(Motore_Startup!$BE$5:$BE$544,(Ipotesi!$C$5-1)*60+26)-INDEX(Motore_Startup!$BF$5:$BF$544,(Ipotesi!$C$5-1)*60+26) -> 43577.119 | G30: =INDEX(Motore_Startup!$BH$5:$BH$544,(Ipotesi!$C$5-1)*60+26) -> 25000 | H30: =INDEX(Motore_Startup!$BI$5:$BI$544,(Ipotesi!$C$5-1)*60+26) -> 0 | I30: =INDEX(Motore_Advisory!$BH$5:$BH$544,(Ipotesi!$C$5-1)*60+26) -> 475.52347 | J30: =INDEX(Motore_Advisory!$BI$5:$BI$544,(Ipotesi!$C$5-1)*60+26) -> 9524.4765 | K30: =G30+I30 -> 25475.523 | L30: =H30+J30 -> 9524.4765 | M30: =IF(OR(G30<0,I30<0),1,0) -> 0
A31: =INDEX(Motore_Startup!$C$5:$C$544,(Ipotesi!$C$5-1)*60+27) -> 47178 | B31: =INDEX(Motore_Startup!$BH$5:$BH$544,(Ipotesi!$C$5-1)*60+26) -> 25000 | C31: =INDEX(Motore_Startup!$BD$5:$BD$544,(Ipotesi!$C$5-1)*60+27)-(INDEX(Motore_Startup!$BH$5:$BH$544,(Ipotesi!$C$5-1)*60+26))-(INDEX(Motore_Startup!$AW$5:$AW$544,(Ipotesi!$C$5-1)*60+27)+INDEX(Motore_Startup!$AX$5:$AX$544,(Ipotesi!$C$5-1)*60+27)+INDEX(Motore_Startup!$AZ$5:$AZ$544,(Ipotesi!$C$5-1)*60+27)+INDEX(Motore_Startup!$BA$5:$BA$544,(Ipotesi!$C$5-1)*60+27))+INDEX(Motore_Startup!$BB$5:$BB$544,(Ipotesi!$C$5-1)*60+27) -> -82193.462 | D31: =INDEX(Motore_Startup!$AW$5:$AW$544,(Ipotesi!$C$5-1)*60+27)+INDEX(Motore_Startup!$AX$5:$AX$544,(Ipotesi!$C$5-1)*60+27)+INDEX(Motore_Startup!$AZ$5:$AZ$544,(Ipotesi!$C$5-1)*60+27)+INDEX(Motore_Startup!$BA$5:$BA$544,(Ipotesi!$C$5-1)*60+27) -> 0 | E31: =INDEX(Motore_Startup!$BB$5:$BB$544,(Ipotesi!$C$5-1)*60+27) -> 0 | F31: =INDEX(Motore_Startup!$BE$5:$BE$544,(Ipotesi!$C$5-1)*60+27)-INDEX(Motore_Startup!$BF$5:$BF$544,(Ipotesi!$C$5-1)*60+27) -> 82193.462 | G31: =INDEX(Motore_Startup!$BH$5:$BH$544,(Ipotesi!$C$5-1)*60+27) -> 25000 | H31: =INDEX(Motore_Startup!$BI$5:$BI$544,(Ipotesi!$C$5-1)*60+27) -> 0 | I31: =INDEX(Motore_Advisory!$BH$5:$BH$544,(Ipotesi!$C$5-1)*60+27) -> -16783.08 | J31: =INDEX(Motore_Advisory!$BI$5:$BI$544,(Ipotesi!$C$5-1)*60+27) -> 26783.08 | K31: =G31+I31 -> 8216.92 | L31: =H31+J31 -> 26783.08 | M31: =IF(OR(G31<0,I31<0),1,0) -> 1
A32: =INDEX(Motore_Startup!$C$5:$C$544,(Ipotesi!$C$5-1)*60+28) -> 47209 | B32: =INDEX(Motore_Startup!$BH$5:$BH$544,(Ipotesi!$C$5-1)*60+27) -> 25000 | C32: =INDEX(Motore_Startup!$BD$5:$BD$544,(Ipotesi!$C$5-1)*60+28)-(INDEX(Motore_Startup!$BH$5:$BH$544,(Ipotesi!$C$5-1)*60+27))-(INDEX(Motore_Startup!$AW$5:$AW$544,(Ipotesi!$C$5-1)*60+28)+INDEX(Motore_Startup!$AX$5:$AX$544,(Ipotesi!$C$5-1)*60+28)+INDEX(Motore_Startup!$AZ$5:$AZ$544,(Ipotesi!$C$5-1)*60+28)+INDEX(Motore_Startup!$BA$5:$BA$544,(Ipotesi!$C$5-1)*60+28))+INDEX(Motore_Startup!$BB$5:$BB$544,(Ipotesi!$C$5-1)*60+28) -> -52171.488 | D32: =INDEX(Motore_Startup!$AW$5:$AW$544,(Ipotesi!$C$5-1)*60+28)+INDEX(Motore_Startup!$AX$5:$AX$544,(Ipotesi!$C$5-1)*60+28)+INDEX(Motore_Startup!$AZ$5:$AZ$544,(Ipotesi!$C$5-1)*60+28)+INDEX(Motore_Startup!$BA$5:$BA$544,(Ipotesi!$C$5-1)*60+28) -> 0 | E32: =INDEX(Motore_Startup!$BB$5:$BB$544,(Ipotesi!$C$5-1)*60+28) -> 0 | F32: =INDEX(Motore_Startup!$BE$5:$BE$544,(Ipotesi!$C$5-1)*60+28)-INDEX(Motore_Startup!$BF$5:$BF$544,(Ipotesi!$C$5-1)*60+28) -> 5924.6511 | G32: =INDEX(Motore_Startup!$BH$5:$BH$544,(Ipotesi!$C$5-1)*60+28) -> -21246.836 | H32: =INDEX(Motore_Startup!$BI$5:$BI$544,(Ipotesi!$C$5-1)*60+28) -> 46246.836 | I32: =INDEX(Motore_Advisory!$BH$5:$BH$544,(Ipotesi!$C$5-1)*60+28) -> -1688.7727 | J32: =INDEX(Motore_Advisory!$BI$5:$BI$544,(Ipotesi!$C$5-1)*60+28) -> 11688.773 | K32: =G32+I32 -> -22935.609 | L32: =H32+J32 -> 57935.609 | M32: =IF(OR(G32<0,I32<0),1,0) -> 1
A33: =INDEX(Motore_Startup!$C$5:$C$544,(Ipotesi!$C$5-1)*60+29) -> 47239 | B33: =INDEX(Motore_Startup!$BH$5:$BH$544,(Ipotesi!$C$5-1)*60+28) -> -21246.836 | C33: =INDEX(Motore_Startup!$BD$5:$BD$544,(Ipotesi!$C$5-1)*60+29)-(INDEX(Motore_Startup!$BH$5:$BH$544,(Ipotesi!$C$5-1)*60+28))-(INDEX(Motore_Startup!$AW$5:$AW$544,(Ipotesi!$C$5-1)*60+29)+INDEX(Motore_Startup!$AX$5:$AX$544,(Ipotesi!$C$5-1)*60+29)+INDEX(Motore_Startup!$AZ$5:$AZ$544,(Ipotesi!$C$5-1)*60+29)+INDEX(Motore_Startup!$BA$5:$BA$544,(Ipotesi!$C$5-1)*60+29))+INDEX(Motore_Startup!$BB$5:$BB$544,(Ipotesi!$C$5-1)*60+29) -> -51831.726 | D33: =INDEX(Motore_Startup!$AW$5:$AW$544,(Ipotesi!$C$5-1)*60+29)+INDEX(Motore_Startup!$AX$5:$AX$544,(Ipotesi!$C$5-1)*60+29)+INDEX(Motore_Startup!$AZ$5:$AZ$544,(Ipotesi!$C$5-1)*60+29)+INDEX(Motore_Startup!$BA$5:$BA$544,(Ipotesi!$C$5-1)*60+29) -> 0 | E33: =INDEX(Motore_Startup!$BB$5:$BB$544,(Ipotesi!$C$5-1)*60+29) -> 0 | F33: =INDEX(Motore_Startup!$BE$5:$BE$544,(Ipotesi!$C$5-1)*60+29)-INDEX(Motore_Startup!$BF$5:$BF$544,(Ipotesi!$C$5-1)*60+29) -> 0 | G33: =INDEX(Motore_Startup!$BH$5:$BH$544,(Ipotesi!$C$5-1)*60+29) -> -73078.563 | H33: =INDEX(Motore_Startup!$BI$5:$BI$544,(Ipotesi!$C$5-1)*60+29) -> 98078.563 | I33: =INDEX(Motore_Advisory!$BH$5:$BH$544,(Ipotesi!$C$5-1)*60+29) -> 13405.535 | J33: =INDEX(Motore_Advisory!$BI$5:$BI$544,(Ipotesi!$C$5-1)*60+29) -> 0 | K33: =G33+I33 -> -59673.028 | L33: =H33+J33 -> 98078.563 | M33: =IF(OR(G33<0,I33<0),1,0) -> 1
A34: =INDEX(Motore_Startup!$C$5:$C$544,(Ipotesi!$C$5-1)*60+30) -> 47270 | B34: =INDEX(Motore_Startup!$BH$5:$BH$544,(Ipotesi!$C$5-1)*60+29) -> -73078.563 | C34: =INDEX(Motore_Startup!$BD$5:$BD$544,(Ipotesi!$C$5-1)*60+30)-(INDEX(Motore_Startup!$BH$5:$BH$544,(Ipotesi!$C$5-1)*60+29))-(INDEX(Motore_Startup!$AW$5:$AW$544,(Ipotesi!$C$5-1)*60+30)+INDEX(Motore_Startup!$AX$5:$AX$544,(Ipotesi!$C$5-1)*60+30)+INDEX(Motore_Startup!$AZ$5:$AZ$544,(Ipotesi!$C$5-1)*60+30)+INDEX(Motore_Startup!$BA$5:$BA$544,(Ipotesi!$C$5-1)*60+30))+INDEX(Motore_Startup!$BB$5:$BB$544,(Ipotesi!$C$5-1)*60+30) -> -51836.829 | D34: =INDEX(Motore_Startup!$AW$5:$AW$544,(Ipotesi!$C$5-1)*60+30)+INDEX(Motore_Startup!$AX$5:$AX$544,(Ipotesi!$C$5-1)*60+30)+INDEX(Motore_Startup!$AZ$5:$AZ$544,(Ipotesi!$C$5-1)*60+30)+INDEX(Motore_Startup!$BA$5:$BA$544,(Ipotesi!$C$5-1)*60+30) -> 988847.14 | E34: =INDEX(Motore_Startup!$BB$5:$BB$544,(Ipotesi!$C$5-1)*60+30) -> 0 | F34: =INDEX(Motore_Startup!$BE$5:$BE$544,(Ipotesi!$C$5-1)*60+30)-INDEX(Motore_Startup!$BF$5:$BF$544,(Ipotesi!$C$5-1)*60+30) -> -150000 | G34: =INDEX(Motore_Startup!$BH$5:$BH$544,(Ipotesi!$C$5-1)*60+30) -> 713931.75 | H34: =INDEX(Motore_Startup!$BI$5:$BI$544,(Ipotesi!$C$5-1)*60+30) -> 0 | I34: =INDEX(Motore_Advisory!$BH$5:$BH$544,(Ipotesi!$C$5-1)*60+30) -> 18919.914 | J34: =INDEX(Motore_Advisory!$BI$5:$BI$544,(Ipotesi!$C$5-1)*60+30) -> 0 | K34: =G34+I34 -> 732851.66 | L34: =H34+J34 -> 0 | M34: =IF(OR(G34<0,I34<0),1,0) -> 0
A35: =INDEX(Motore_Startup!$C$5:$C$544,(Ipotesi!$C$5-1)*60+31) -> 47300 | B35: =INDEX(Motore_Startup!$BH$5:$BH$544,(Ipotesi!$C$5-1)*60+30) -> 713931.75 | C35: =INDEX(Motore_Startup!$BD$5:$BD$544,(Ipotesi!$C$5-1)*60+31)-(INDEX(Motore_Startup!$BH$5:$BH$544,(Ipotesi!$C$5-1)*60+30))-(INDEX(Motore_Startup!$AW$5:$AW$544,(Ipotesi!$C$5-1)*60+31)+INDEX(Motore_Startup!$AX$5:$AX$544,(Ipotesi!$C$5-1)*60+31)+INDEX(Motore_Startup!$AZ$5:$AZ$544,(Ipotesi!$C$5-1)*60+31)+INDEX(Motore_Startup!$BA$5:$BA$544,(Ipotesi!$C$5-1)*60+31))+INDEX(Motore_Startup!$BB$5:$BB$544,(Ipotesi!$C$5-1)*60+31) -> -50005.111 | D35: =INDEX(Motore_Startup!$AW$5:$AW$544,(Ipotesi!$C$5-1)*60+31)+INDEX(Motore_Startup!$AX$5:$AX$544,(Ipotesi!$C$5-1)*60+31)+INDEX(Motore_Startup!$AZ$5:$AZ$544,(Ipotesi!$C$5-1)*60+31)+INDEX(Motore_Startup!$BA$5:$BA$544,(Ipotesi!$C$5-1)*60+31) -> 0 | E35: =INDEX(Motore_Startup!$BB$5:$BB$544,(Ipotesi!$C$5-1)*60+31) -> 0 | F35: =INDEX(Motore_Startup!$BE$5:$BE$544,(Ipotesi!$C$5-1)*60+31)-INDEX(Motore_Startup!$BF$5:$BF$544,(Ipotesi!$C$5-1)*60+31) -> 0 | G35: =INDEX(Motore_Startup!$BH$5:$BH$544,(Ipotesi!$C$5-1)*60+31) -> 663926.64 | H35: =INDEX(Motore_Startup!$BI$5:$BI$544,(Ipotesi!$C$5-1)*60+31) -> 0 | I35: =INDEX(Motore_Advisory!$BH$5:$BH$544,(Ipotesi!$C$5-1)*60+31) -> 34014.221 | J35: =INDEX(Motore_Advisory!$BI$5:$BI$544,(Ipotesi!$C$5-1)*60+31) -> 0 | K35: =G35+I35 -> 697940.86 | L35: =H35+J35 -> 0 | M35: =IF(OR(G35<0,I35<0),1,0) -> 0
A36: =INDEX(Motore_Startup!$C$5:$C$544,(Ipotesi!$C$5-1)*60+32) -> 47331 | B36: =INDEX(Motore_Startup!$BH$5:$BH$544,(Ipotesi!$C$5-1)*60+31) -> 663926.64 | C36: =INDEX(Motore_Startup!$BD$5:$BD$544,(Ipotesi!$C$5-1)*60+32)-(INDEX(Motore_Startup!$BH$5:$BH$544,(Ipotesi!$C$5-1)*60+31))-(INDEX(Motore_Startup!$AW$5:$AW$544,(Ipotesi!$C$5-1)*60+32)+INDEX(Motore_Startup!$AX$5:$AX$544,(Ipotesi!$C$5-1)*60+32)+INDEX(Motore_Startup!$AZ$5:$AZ$544,(Ipotesi!$C$5-1)*60+32)+INDEX(Motore_Startup!$BA$5:$BA$544,(Ipotesi!$C$5-1)*60+32))+INDEX(Motore_Startup!$BB$5:$BB$544,(Ipotesi!$C$5-1)*60+32) -> -47674.697 | D36: =INDEX(Motore_Startup!$AW$5:$AW$544,(Ipotesi!$C$5-1)*60+32)+INDEX(Motore_Startup!$AX$5:$AX$544,(Ipotesi!$C$5-1)*60+32)+INDEX(Motore_Startup!$AZ$5:$AZ$544,(Ipotesi!$C$5-1)*60+32)+INDEX(Motore_Startup!$BA$5:$BA$544,(Ipotesi!$C$5-1)*60+32) -> 0 | E36: =INDEX(Motore_Startup!$BB$5:$BB$544,(Ipotesi!$C$5-1)*60+32) -> 0 | F36: =INDEX(Motore_Startup!$BE$5:$BE$544,(Ipotesi!$C$5-1)*60+32)-INDEX(Motore_Startup!$BF$5:$BF$544,(Ipotesi!$C$5-1)*60+32) -> 0 | G36: =INDEX(Motore_Startup!$BH$5:$BH$544,(Ipotesi!$C$5-1)*60+32) -> 616251.94 | H36: =INDEX(Motore_Startup!$BI$5:$BI$544,(Ipotesi!$C$5-1)*60+32) -> 0 | I36: =INDEX(Motore_Advisory!$BH$5:$BH$544,(Ipotesi!$C$5-1)*60+32) -> 49108.529 | J36: =INDEX(Motore_Advisory!$BI$5:$BI$544,(Ipotesi!$C$5-1)*60+32) -> 0 | K36: =G36+I36 -> 665360.47 | L36: =H36+J36 -> 0 | M36: =IF(OR(G36<0,I36<0),1,0) -> 0
A37: =INDEX(Motore_Startup!$C$5:$C$544,(Ipotesi!$C$5-1)*60+33) -> 47362 | B37: =INDEX(Motore_Startup!$BH$5:$BH$544,(Ipotesi!$C$5-1)*60+32) -> 616251.94 | C37: =INDEX(Motore_Startup!$BD$5:$BD$544,(Ipotesi!$C$5-1)*60+33)-(INDEX(Motore_Startup!$BH$5:$BH$544,(Ipotesi!$C$5-1)*60+32))-(INDEX(Motore_Startup!$AW$5:$AW$544,(Ipotesi!$C$5-1)*60+33)+INDEX(Motore_Startup!$AX$5:$AX$544,(Ipotesi!$C$5-1)*60+33)+INDEX(Motore_Startup!$AZ$5:$AZ$544,(Ipotesi!$C$5-1)*60+33)+INDEX(Motore_Startup!$BA$5:$BA$544,(Ipotesi!$C$5-1)*60+33))+INDEX(Motore_Startup!$BB$5:$BB$544,(Ipotesi!$C$5-1)*60+33) -> -45364.654 | D37: =INDEX(Motore_Startup!$AW$5:$AW$544,(Ipotesi!$C$5-1)*60+33)+INDEX(Motore_Startup!$AX$5:$AX$544,(Ipotesi!$C$5-1)*60+33)+INDEX(Motore_Startup!$AZ$5:$AZ$544,(Ipotesi!$C$5-1)*60+33)+INDEX(Motore_Startup!$BA$5:$BA$544,(Ipotesi!$C$5-1)*60+33) -> 0 | E37: =INDEX(Motore_Startup!$BB$5:$BB$544,(Ipotesi!$C$5-1)*60+33) -> 0 | F37: =INDEX(Motore_Startup!$BE$5:$BE$544,(Ipotesi!$C$5-1)*60+33)-INDEX(Motore_Startup!$BF$5:$BF$544,(Ipotesi!$C$5-1)*60+33) -> 0 | G37: =INDEX(Motore_Startup!$BH$5:$BH$544,(Ipotesi!$C$5-1)*60+33) -> 570887.29 | H37: =INDEX(Motore_Startup!$BI$5:$BI$544,(Ipotesi!$C$5-1)*60+33) -> 0 | I37: =INDEX(Motore_Advisory!$BH$5:$BH$544,(Ipotesi!$C$5-1)*60+33) -> 64202.836 | J37: =INDEX(Motore_Advisory!$BI$5:$BI$544,(Ipotesi!$C$5-1)*60+33) -> 0 | K37: =G37+I37 -> 635090.12 | L37: =H37+J37 -> 0 | M37: =IF(OR(G37<0,I37<0),1,0) -> 0
A38: =INDEX(Motore_Startup!$C$5:$C$544,(Ipotesi!$C$5-1)*60+34) -> 47392 | B38: =INDEX(Motore_Startup!$BH$5:$BH$544,(Ipotesi!$C$5-1)*60+33) -> 570887.29 | C38: =INDEX(Motore_Startup!$BD$5:$BD$544,(Ipotesi!$C$5-1)*60+34)-(INDEX(Motore_Startup!$BH$5:$BH$544,(Ipotesi!$C$5-1)*60+33))-(INDEX(Motore_Startup!$AW$5:$AW$544,(Ipotesi!$C$5-1)*60+34)+INDEX(Motore_Startup!$AX$5:$AX$544,(Ipotesi!$C$5-1)*60+34)+INDEX(Motore_Startup!$AZ$5:$AZ$544,(Ipotesi!$C$5-1)*60+34)+INDEX(Motore_Startup!$BA$5:$BA$544,(Ipotesi!$C$5-1)*60+34))+INDEX(Motore_Startup!$BB$5:$BB$544,(Ipotesi!$C$5-1)*60+34) -> -43074.805 | D38: =INDEX(Motore_Startup!$AW$5:$AW$544,(Ipotesi!$C$5-1)*60+34)+INDEX(Motore_Startup!$AX$5:$AX$544,(Ipotesi!$C$5-1)*60+34)+INDEX(Motore_Startup!$AZ$5:$AZ$544,(Ipotesi!$C$5-1)*60+34)+INDEX(Motore_Startup!$BA$5:$BA$544,(Ipotesi!$C$5-1)*60+34) -> 0 | E38: =INDEX(Motore_Startup!$BB$5:$BB$544,(Ipotesi!$C$5-1)*60+34) -> 0 | F38: =INDEX(Motore_Startup!$BE$5:$BE$544,(Ipotesi!$C$5-1)*60+34)-INDEX(Motore_Startup!$BF$5:$BF$544,(Ipotesi!$C$5-1)*60+34) -> 0 | G38: =INDEX(Motore_Startup!$BH$5:$BH$544,(Ipotesi!$C$5-1)*60+34) -> 527812.48 | H38: =INDEX(Motore_Startup!$BI$5:$BI$544,(Ipotesi!$C$5-1)*60+34) -> 0 | I38: =INDEX(Motore_Advisory!$BH$5:$BH$544,(Ipotesi!$C$5-1)*60+34) -> 79297.143 | J38: =INDEX(Motore_Advisory!$BI$5:$BI$544,(Ipotesi!$C$5-1)*60+34) -> 0 | K38: =G38+I38 -> 607109.62 | L38: =H38+J38 -> 0 | M38: =IF(OR(G38<0,I38<0),1,0) -> 0
A39: =INDEX(Motore_Startup!$C$5:$C$544,(Ipotesi!$C$5-1)*60+35) -> 47423 | B39: =INDEX(Motore_Startup!$BH$5:$BH$544,(Ipotesi!$C$5-1)*60+34) -> 527812.48 | C39: =INDEX(Motore_Startup!$BD$5:$BD$544,(Ipotesi!$C$5-1)*60+35)-(INDEX(Motore_Startup!$BH$5:$BH$544,(Ipotesi!$C$5-1)*60+34))-(INDEX(Motore_Startup!$AW$5:$AW$544,(Ipotesi!$C$5-1)*60+35)+INDEX(Motore_Startup!$AX$5:$AX$544,(Ipotesi!$C$5-1)*60+35)+INDEX(Motore_Startup!$AZ$5:$AZ$544,(Ipotesi!$C$5-1)*60+35)+INDEX(Motore_Startup!$BA$5:$BA$544,(Ipotesi!$C$5-1)*60+35))+INDEX(Motore_Startup!$BB$5:$BB$544,(Ipotesi!$C$5-1)*60+35) -> -40804.973 | D39: =INDEX(Motore_Startup!$AW$5:$AW$544,(Ipotesi!$C$5-1)*60+35)+INDEX(Motore_Startup!$AX$5:$AX$544,(Ipotesi!$C$5-1)*60+35)+INDEX(Motore_Startup!$AZ$5:$AZ$544,(Ipotesi!$C$5-1)*60+35)+INDEX(Motore_Startup!$BA$5:$BA$544,(Ipotesi!$C$5-1)*60+35) -> 0 | E39: =INDEX(Motore_Startup!$BB$5:$BB$544,(Ipotesi!$C$5-1)*60+35) -> 0 | F39: =INDEX(Motore_Startup!$BE$5:$BE$544,(Ipotesi!$C$5-1)*60+35)-INDEX(Motore_Startup!$BF$5:$BF$544,(Ipotesi!$C$5-1)*60+35) -> 0 | G39: =INDEX(Motore_Startup!$BH$5:$BH$544,(Ipotesi!$C$5-1)*60+35) -> 487007.51 | H39: =INDEX(Motore_Startup!$BI$5:$BI$544,(Ipotesi!$C$5-1)*60+35) -> 0 | I39: =INDEX(Motore_Advisory!$BH$5:$BH$544,(Ipotesi!$C$5-1)*60+35) -> 84473.348 | J39: =INDEX(Motore_Advisory!$BI$5:$BI$544,(Ipotesi!$C$5-1)*60+35) -> 0 | K39: =G39+I39 -> 571480.86 | L39: =H39+J39 -> 0 | M39: =IF(OR(G39<0,I39<0),1,0) -> 0
A40: =INDEX(Motore_Startup!$C$5:$C$544,(Ipotesi!$C$5-1)*60+36) -> 47453 | B40: =INDEX(Motore_Startup!$BH$5:$BH$544,(Ipotesi!$C$5-1)*60+35) -> 487007.51 | C40: =INDEX(Motore_Startup!$BD$5:$BD$544,(Ipotesi!$C$5-1)*60+36)-(INDEX(Motore_Startup!$BH$5:$BH$544,(Ipotesi!$C$5-1)*60+35))-(INDEX(Motore_Startup!$AW$5:$AW$544,(Ipotesi!$C$5-1)*60+36)+INDEX(Motore_Startup!$AX$5:$AX$544,(Ipotesi!$C$5-1)*60+36)+INDEX(Motore_Startup!$AZ$5:$AZ$544,(Ipotesi!$C$5-1)*60+36)+INDEX(Motore_Startup!$BA$5:$BA$544,(Ipotesi!$C$5-1)*60+36))+INDEX(Motore_Startup!$BB$5:$BB$544,(Ipotesi!$C$5-1)*60+36) -> -38554.983 | D40: =INDEX(Motore_Startup!$AW$5:$AW$544,(Ipotesi!$C$5-1)*60+36)+INDEX(Motore_Startup!$AX$5:$AX$544,(Ipotesi!$C$5-1)*60+36)+INDEX(Motore_Startup!$AZ$5:$AZ$544,(Ipotesi!$C$5-1)*60+36)+INDEX(Motore_Startup!$BA$5:$BA$544,(Ipotesi!$C$5-1)*60+36) -> 0 | E40: =INDEX(Motore_Startup!$BB$5:$BB$544,(Ipotesi!$C$5-1)*60+36) -> 0 | F40: =INDEX(Motore_Startup!$BE$5:$BE$544,(Ipotesi!$C$5-1)*60+36)-INDEX(Motore_Startup!$BF$5:$BF$544,(Ipotesi!$C$5-1)*60+36) -> 0 | G40: =INDEX(Motore_Startup!$BH$5:$BH$544,(Ipotesi!$C$5-1)*60+36) -> 448452.52 | H40: =INDEX(Motore_Startup!$BI$5:$BI$544,(Ipotesi!$C$5-1)*60+36) -> 0 | I40: =INDEX(Motore_Advisory!$BH$5:$BH$544,(Ipotesi!$C$5-1)*60+36) -> 99567.655 | J40: =INDEX(Motore_Advisory!$BI$5:$BI$544,(Ipotesi!$C$5-1)*60+36) -> 0 | K40: =G40+I40 -> 548020.18 | L40: =H40+J40 -> 0 | M40: =IF(OR(G40<0,I40<0),1,0) -> 0
A41: =INDEX(Motore_Startup!$C$5:$C$544,(Ipotesi!$C$5-1)*60+37) -> 47484 | B41: =INDEX(Motore_Startup!$BH$5:$BH$544,(Ipotesi!$C$5-1)*60+36) -> 448452.52 | C41: =INDEX(Motore_Startup!$BD$5:$BD$544,(Ipotesi!$C$5-1)*60+37)-(INDEX(Motore_Startup!$BH$5:$BH$544,(Ipotesi!$C$5-1)*60+36))-(INDEX(Motore_Startup!$AW$5:$AW$544,(Ipotesi!$C$5-1)*60+37)+INDEX(Motore_Startup!$AX$5:$AX$544,(Ipotesi!$C$5-1)*60+37)+INDEX(Motore_Startup!$AZ$5:$AZ$544,(Ipotesi!$C$5-1)*60+37)+INDEX(Motore_Startup!$BA$5:$BA$544,(Ipotesi!$C$5-1)*60+37))+INDEX(Motore_Startup!$BB$5:$BB$544,(Ipotesi!$C$5-1)*60+37) -> -58430.774 | D41: =INDEX(Motore_Startup!$AW$5:$AW$544,(Ipotesi!$C$5-1)*60+37)+INDEX(Motore_Startup!$AX$5:$AX$544,(Ipotesi!$C$5-1)*60+37)+INDEX(Motore_Startup!$AZ$5:$AZ$544,(Ipotesi!$C$5-1)*60+37)+INDEX(Motore_Startup!$BA$5:$BA$544,(Ipotesi!$C$5-1)*60+37) -> 0 | E41: =INDEX(Motore_Startup!$BB$5:$BB$544,(Ipotesi!$C$5-1)*60+37) -> 0 | F41: =INDEX(Motore_Startup!$BE$5:$BE$544,(Ipotesi!$C$5-1)*60+37)-INDEX(Motore_Startup!$BF$5:$BF$544,(Ipotesi!$C$5-1)*60+37) -> 0 | G41: =INDEX(Motore_Startup!$BH$5:$BH$544,(Ipotesi!$C$5-1)*60+37) -> 390021.75 | H41: =INDEX(Motore_Startup!$BI$5:$BI$544,(Ipotesi!$C$5-1)*60+37) -> 0 | I41: =INDEX(Motore_Advisory!$BH$5:$BH$544,(Ipotesi!$C$5-1)*60+37) -> 106365.93 | J41: =INDEX(Motore_Advisory!$BI$5:$BI$544,(Ipotesi!$C$5-1)*60+37) -> 0 | K41: =G41+I41 -> 496387.68 | L41: =H41+J41 -> 0 | M41: =IF(OR(G41<0,I41<0),1,0) -> 0
A42: =INDEX(Motore_Startup!$C$5:$C$544,(Ipotesi!$C$5-1)*60+38) -> 47515 | B42: =INDEX(Motore_Startup!$BH$5:$BH$544,(Ipotesi!$C$5-1)*60+37) -> 390021.75 | C42: =INDEX(Motore_Startup!$BD$5:$BD$544,(Ipotesi!$C$5-1)*60+38)-(INDEX(Motore_Startup!$BH$5:$BH$544,(Ipotesi!$C$5-1)*60+37))-(INDEX(Motore_Startup!$AW$5:$AW$544,(Ipotesi!$C$5-1)*60+38)+INDEX(Motore_Startup!$AX$5:$AX$544,(Ipotesi!$C$5-1)*60+38)+INDEX(Motore_Startup!$AZ$5:$AZ$544,(Ipotesi!$C$5-1)*60+38)+INDEX(Motore_Startup!$BA$5:$BA$544,(Ipotesi!$C$5-1)*60+38))+INDEX(Motore_Startup!$BB$5:$BB$544,(Ipotesi!$C$5-1)*60+38) -> -56337.508 | D42: =INDEX(Motore_Startup!$AW$5:$AW$544,(Ipotesi!$C$5-1)*60+38)+INDEX(Motore_Startup!$AX$5:$AX$544,(Ipotesi!$C$5-1)*60+38)+INDEX(Motore_Startup!$AZ$5:$AZ$544,(Ipotesi!$C$5-1)*60+38)+INDEX(Motore_Startup!$BA$5:$BA$544,(Ipotesi!$C$5-1)*60+38) -> 0 | E42: =INDEX(Motore_Startup!$BB$5:$BB$544,(Ipotesi!$C$5-1)*60+38) -> 0 | F42: =INDEX(Motore_Startup!$BE$5:$BE$544,(Ipotesi!$C$5-1)*60+38)-INDEX(Motore_Startup!$BF$5:$BF$544,(Ipotesi!$C$5-1)*60+38) -> 0 | G42: =INDEX(Motore_Startup!$BH$5:$BH$544,(Ipotesi!$C$5-1)*60+38) -> 333684.24 | H42: =INDEX(Motore_Startup!$BI$5:$BI$544,(Ipotesi!$C$5-1)*60+38) -> 0 | I42: =INDEX(Motore_Advisory!$BH$5:$BH$544,(Ipotesi!$C$5-1)*60+38) -> 104570.35 | J42: =INDEX(Motore_Advisory!$BI$5:$BI$544,(Ipotesi!$C$5-1)*60+38) -> 0 | K42: =G42+I42 -> 438254.59 | L42: =H42+J42 -> 0 | M42: =IF(OR(G42<0,I42<0),1,0) -> 0
A43: =INDEX(Motore_Startup!$C$5:$C$544,(Ipotesi!$C$5-1)*60+39) -> 47543 | B43: =INDEX(Motore_Startup!$BH$5:$BH$544,(Ipotesi!$C$5-1)*60+38) -> 333684.24 | C43: =INDEX(Motore_Startup!$BD$5:$BD$544,(Ipotesi!$C$5-1)*60+39)-(INDEX(Motore_Startup!$BH$5:$BH$544,(Ipotesi!$C$5-1)*60+38))-(INDEX(Motore_Startup!$AW$5:$AW$544,(Ipotesi!$C$5-1)*60+39)+INDEX(Motore_Startup!$AX$5:$AX$544,(Ipotesi!$C$5-1)*60+39)+INDEX(Motore_Startup!$AZ$5:$AZ$544,(Ipotesi!$C$5-1)*60+39)+INDEX(Motore_Startup!$BA$5:$BA$544,(Ipotesi!$C$5-1)*60+39))+INDEX(Motore_Startup!$BB$5:$BB$544,(Ipotesi!$C$5-1)*60+39) -> -70467.708 | D43: =INDEX(Motore_Startup!$AW$5:$AW$544,(Ipotesi!$C$5-1)*60+39)+INDEX(Motore_Startup!$AX$5:$AX$544,(Ipotesi!$C$5-1)*60+39)+INDEX(Motore_Startup!$AZ$5:$AZ$544,(Ipotesi!$C$5-1)*60+39)+INDEX(Motore_Startup!$BA$5:$BA$544,(Ipotesi!$C$5-1)*60+39) -> 0 | E43: =INDEX(Motore_Startup!$BB$5:$BB$544,(Ipotesi!$C$5-1)*60+39) -> 0 | F43: =INDEX(Motore_Startup!$BE$5:$BE$544,(Ipotesi!$C$5-1)*60+39)-INDEX(Motore_Startup!$BF$5:$BF$544,(Ipotesi!$C$5-1)*60+39) -> 0 | G43: =INDEX(Motore_Startup!$BH$5:$BH$544,(Ipotesi!$C$5-1)*60+39) -> 263216.53 | H43: =INDEX(Motore_Startup!$BI$5:$BI$544,(Ipotesi!$C$5-1)*60+39) -> 0 | I43: =INDEX(Motore_Advisory!$BH$5:$BH$544,(Ipotesi!$C$5-1)*60+39) -> 96971.791 | J43: =INDEX(Motore_Advisory!$BI$5:$BI$544,(Ipotesi!$C$5-1)*60+39) -> 0 | K43: =G43+I43 -> 360188.33 | L43: =H43+J43 -> 0 | M43: =IF(OR(G43<0,I43<0),1,0) -> 0
A44: =INDEX(Motore_Startup!$C$5:$C$544,(Ipotesi!$C$5-1)*60+40) -> 47574 | B44: =INDEX(Motore_Startup!$BH$5:$BH$544,(Ipotesi!$C$5-1)*60+39) -> 263216.53 | C44: =INDEX(Motore_Startup!$BD$5:$BD$544,(Ipotesi!$C$5-1)*60+40)-(INDEX(Motore_Startup!$BH$5:$BH$544,(Ipotesi!$C$5-1)*60+39))-(INDEX(Motore_Startup!$AW$5:$AW$544,(Ipotesi!$C$5-1)*60+40)+INDEX(Motore_Startup!$AX$5:$AX$544,(Ipotesi!$C$5-1)*60+40)+INDEX(Motore_Startup!$AZ$5:$AZ$544,(Ipotesi!$C$5-1)*60+40)+INDEX(Motore_Startup!$BA$5:$BA$544,(Ipotesi!$C$5-1)*60+40))+INDEX(Motore_Startup!$BB$5:$BB$544,(Ipotesi!$C$5-1)*60+40) -> -35721.326 | D44: =INDEX(Motore_Startup!$AW$5:$AW$544,(Ipotesi!$C$5-1)*60+40)+INDEX(Motore_Startup!$AX$5:$AX$544,(Ipotesi!$C$5-1)*60+40)+INDEX(Motore_Startup!$AZ$5:$AZ$544,(Ipotesi!$C$5-1)*60+40)+INDEX(Motore_Startup!$BA$5:$BA$544,(Ipotesi!$C$5-1)*60+40) -> 0 | E44: =INDEX(Motore_Startup!$BB$5:$BB$544,(Ipotesi!$C$5-1)*60+40) -> 0 | F44: =INDEX(Motore_Startup!$BE$5:$BE$544,(Ipotesi!$C$5-1)*60+40)-INDEX(Motore_Startup!$BF$5:$BF$544,(Ipotesi!$C$5-1)*60+40) -> 0 | G44: =INDEX(Motore_Startup!$BH$5:$BH$544,(Ipotesi!$C$5-1)*60+40) -> 227495.21 | H44: =INDEX(Motore_Startup!$BI$5:$BI$544,(Ipotesi!$C$5-1)*60+40) -> 0 | I44: =INDEX(Motore_Advisory!$BH$5:$BH$544,(Ipotesi!$C$5-1)*60+40) -> 125658.07 | J44: =INDEX(Motore_Advisory!$BI$5:$BI$544,(Ipotesi!$C$5-1)*60+40) -> 0 | K44: =G44+I44 -> 353153.28 | L44: =H44+J44 -> 0 | M44: =IF(OR(G44<0,I44<0),1,0) -> 0
A45: =INDEX(Motore_Startup!$C$5:$C$544,(Ipotesi!$C$5-1)*60+41) -> 47604 | B45: =INDEX(Motore_Startup!$BH$5:$BH$544,(Ipotesi!$C$5-1)*60+40) -> 227495.21 | C45: =INDEX(Motore_Startup!$BD$5:$BD$544,(Ipotesi!$C$5-1)*60+41)-(INDEX(Motore_Startup!$BH$5:$BH$544,(Ipotesi!$C$5-1)*60+40))-(INDEX(Motore_Startup!$AW$5:$AW$544,(Ipotesi!$C$5-1)*60+41)+INDEX(Motore_Startup!$AX$5:$AX$544,(Ipotesi!$C$5-1)*60+41)+INDEX(Motore_Startup!$AZ$5:$AZ$544,(Ipotesi!$C$5-1)*60+41)+INDEX(Motore_Startup!$BA$5:$BA$544,(Ipotesi!$C$5-1)*60+41))+INDEX(Motore_Startup!$BB$5:$BB$544,(Ipotesi!$C$5-1)*60+41) -> -33908.887 | D45: =INDEX(Motore_Startup!$AW$5:$AW$544,(Ipotesi!$C$5-1)*60+41)+INDEX(Motore_Startup!$AX$5:$AX$544,(Ipotesi!$C$5-1)*60+41)+INDEX(Motore_Startup!$AZ$5:$AZ$544,(Ipotesi!$C$5-1)*60+41)+INDEX(Motore_Startup!$BA$5:$BA$544,(Ipotesi!$C$5-1)*60+41) -> 0 | E45: =INDEX(Motore_Startup!$BB$5:$BB$544,(Ipotesi!$C$5-1)*60+41) -> 0 | F45: =INDEX(Motore_Startup!$BE$5:$BE$544,(Ipotesi!$C$5-1)*60+41)-INDEX(Motore_Startup!$BF$5:$BF$544,(Ipotesi!$C$5-1)*60+41) -> 0 | G45: =INDEX(Motore_Startup!$BH$5:$BH$544,(Ipotesi!$C$5-1)*60+41) -> 193586.32 | H45: =INDEX(Motore_Startup!$BI$5:$BI$544,(Ipotesi!$C$5-1)*60+41) -> 0 | I45: =INDEX(Motore_Advisory!$BH$5:$BH$544,(Ipotesi!$C$5-1)*60+41) -> 154344.35 | J45: =INDEX(Motore_Advisory!$BI$5:$BI$544,(Ipotesi!$C$5-1)*60+41) -> 0 | K45: =G45+I45 -> 347930.67 | L45: =H45+J45 -> 0 | M45: =IF(OR(G45<0,I45<0),1,0) -> 0
A46: =INDEX(Motore_Startup!$C$5:$C$544,(Ipotesi!$C$5-1)*60+42) -> 47635 | B46: =INDEX(Motore_Startup!$BH$5:$BH$544,(Ipotesi!$C$5-1)*60+41) -> 193586.32 | C46: =INDEX(Motore_Startup!$BD$5:$BD$544,(Ipotesi!$C$5-1)*60+42)-(INDEX(Motore_Startup!$BH$5:$BH$544,(Ipotesi!$C$5-1)*60+41))-(INDEX(Motore_Startup!$AW$5:$AW$544,(Ipotesi!$C$5-1)*60+42)+INDEX(Motore_Startup!$AX$5:$AX$544,(Ipotesi!$C$5-1)*60+42)+INDEX(Motore_Startup!$AZ$5:$AZ$544,(Ipotesi!$C$5-1)*60+42)+INDEX(Motore_Startup!$BA$5:$BA$544,(Ipotesi!$C$5-1)*60+42))+INDEX(Motore_Startup!$BB$5:$BB$544,(Ipotesi!$C$5-1)*60+42) -> -32279.081 | D46: =INDEX(Motore_Startup!$AW$5:$AW$544,(Ipotesi!$C$5-1)*60+42)+INDEX(Motore_Startup!$AX$5:$AX$544,(Ipotesi!$C$5-1)*60+42)+INDEX(Motore_Startup!$AZ$5:$AZ$544,(Ipotesi!$C$5-1)*60+42)+INDEX(Motore_Startup!$BA$5:$BA$544,(Ipotesi!$C$5-1)*60+42) -> 35707.016 | E46: =INDEX(Motore_Startup!$BB$5:$BB$544,(Ipotesi!$C$5-1)*60+42) -> 13269.65 | F46: =INDEX(Motore_Startup!$BE$5:$BE$544,(Ipotesi!$C$5-1)*60+42)-INDEX(Motore_Startup!$BF$5:$BF$544,(Ipotesi!$C$5-1)*60+42) -> 0 | G46: =INDEX(Motore_Startup!$BH$5:$BH$544,(Ipotesi!$C$5-1)*60+42) -> 183744.61 | H46: =INDEX(Motore_Startup!$BI$5:$BI$544,(Ipotesi!$C$5-1)*60+42) -> 0 | I46: =INDEX(Motore_Advisory!$BH$5:$BH$544,(Ipotesi!$C$5-1)*60+42) -> 73892.896 | J46: =INDEX(Motore_Advisory!$BI$5:$BI$544,(Ipotesi!$C$5-1)*60+42) -> 0 | K46: =G46+I46 -> 257637.5 | L46: =H46+J46 -> 0 | M46: =IF(OR(G46<0,I46<0),1,0) -> 0
A47: =INDEX(Motore_Startup!$C$5:$C$544,(Ipotesi!$C$5-1)*60+43) -> 47665 | B47: =INDEX(Motore_Startup!$BH$5:$BH$544,(Ipotesi!$C$5-1)*60+42) -> 183744.61 | C47: =INDEX(Motore_Startup!$BD$5:$BD$544,(Ipotesi!$C$5-1)*60+43)-(INDEX(Motore_Startup!$BH$5:$BH$544,(Ipotesi!$C$5-1)*60+42))-(INDEX(Motore_Startup!$AW$5:$AW$544,(Ipotesi!$C$5-1)*60+43)+INDEX(Motore_Startup!$AX$5:$AX$544,(Ipotesi!$C$5-1)*60+43)+INDEX(Motore_Startup!$AZ$5:$AZ$544,(Ipotesi!$C$5-1)*60+43)+INDEX(Motore_Startup!$BA$5:$BA$544,(Ipotesi!$C$5-1)*60+43))+INDEX(Motore_Startup!$BB$5:$BB$544,(Ipotesi!$C$5-1)*60+43) -> -30175.285 | D47: =INDEX(Motore_Startup!$AW$5:$AW$544,(Ipotesi!$C$5-1)*60+43)+INDEX(Motore_Startup!$AX$5:$AX$544,(Ipotesi!$C$5-1)*60+43)+INDEX(Motore_Startup!$AZ$5:$AZ$544,(Ipotesi!$C$5-1)*60+43)+INDEX(Motore_Startup!$BA$5:$BA$544,(Ipotesi!$C$5-1)*60+43) -> 0 | E47: =INDEX(Motore_Startup!$BB$5:$BB$544,(Ipotesi!$C$5-1)*60+43) -> 0 | F47: =INDEX(Motore_Startup!$BE$5:$BE$544,(Ipotesi!$C$5-1)*60+43)-INDEX(Motore_Startup!$BF$5:$BF$544,(Ipotesi!$C$5-1)*60+43) -> 0 | G47: =INDEX(Motore_Startup!$BH$5:$BH$544,(Ipotesi!$C$5-1)*60+43) -> 153569.32 | H47: =INDEX(Motore_Startup!$BI$5:$BI$544,(Ipotesi!$C$5-1)*60+43) -> 0 | I47: =INDEX(Motore_Advisory!$BH$5:$BH$544,(Ipotesi!$C$5-1)*60+43) -> 102579.17 | J47: =INDEX(Motore_Advisory!$BI$5:$BI$544,(Ipotesi!$C$5-1)*60+43) -> 0 | K47: =G47+I47 -> 256148.5 | L47: =H47+J47 -> 0 | M47: =IF(OR(G47<0,I47<0),1,0) -> 0
A48: =INDEX(Motore_Startup!$C$5:$C$544,(Ipotesi!$C$5-1)*60+44) -> 47696 | B48: =INDEX(Motore_Startup!$BH$5:$BH$544,(Ipotesi!$C$5-1)*60+43) -> 153569.32 | C48: =INDEX(Motore_Startup!$BD$5:$BD$544,(Ipotesi!$C$5-1)*60+44)-(INDEX(Motore_Startup!$BH$5:$BH$544,(Ipotesi!$C$5-1)*60+43))-(INDEX(Motore_Startup!$AW$5:$AW$544,(Ipotesi!$C$5-1)*60+44)+INDEX(Motore_Startup!$AX$5:$AX$544,(Ipotesi!$C$5-1)*60+44)+INDEX(Motore_Startup!$AZ$5:$AZ$544,(Ipotesi!$C$5-1)*60+44)+INDEX(Motore_Startup!$BA$5:$BA$544,(Ipotesi!$C$5-1)*60+44))+INDEX(Motore_Startup!$BB$5:$BB$544,(Ipotesi!$C$5-1)*60+44) -> -27524.65 | D48: =INDEX(Motore_Startup!$AW$5:$AW$544,(Ipotesi!$C$5-1)*60+44)+INDEX(Motore_Startup!$AX$5:$AX$544,(Ipotesi!$C$5-1)*60+44)+INDEX(Motore_Startup!$AZ$5:$AZ$544,(Ipotesi!$C$5-1)*60+44)+INDEX(Motore_Startup!$BA$5:$BA$544,(Ipotesi!$C$5-1)*60+44) -> 0 | E48: =INDEX(Motore_Startup!$BB$5:$BB$544,(Ipotesi!$C$5-1)*60+44) -> 0 | F48: =INDEX(Motore_Startup!$BE$5:$BE$544,(Ipotesi!$C$5-1)*60+44)-INDEX(Motore_Startup!$BF$5:$BF$544,(Ipotesi!$C$5-1)*60+44) -> 0 | G48: =INDEX(Motore_Startup!$BH$5:$BH$544,(Ipotesi!$C$5-1)*60+44) -> 126044.67 | H48: =INDEX(Motore_Startup!$BI$5:$BI$544,(Ipotesi!$C$5-1)*60+44) -> 0 | I48: =INDEX(Motore_Advisory!$BH$5:$BH$544,(Ipotesi!$C$5-1)*60+44) -> 131265.45 | J48: =INDEX(Motore_Advisory!$BI$5:$BI$544,(Ipotesi!$C$5-1)*60+44) -> 0 | K48: =G48+I48 -> 257310.12 | L48: =H48+J48 -> 0 | M48: =IF(OR(G48<0,I48<0),1,0) -> 0
A49: =INDEX(Motore_Startup!$C$5:$C$544,(Ipotesi!$C$5-1)*60+45) -> 47727 | B49: =INDEX(Motore_Startup!$BH$5:$BH$544,(Ipotesi!$C$5-1)*60+44) -> 126044.67 | C49: =INDEX(Motore_Startup!$BD$5:$BD$544,(Ipotesi!$C$5-1)*60+45)-(INDEX(Motore_Startup!$BH$5:$BH$544,(Ipotesi!$C$5-1)*60+44))-(INDEX(Motore_Startup!$AW$5:$AW$544,(Ipotesi!$C$5-1)*60+45)+INDEX(Motore_Startup!$AX$5:$AX$544,(Ipotesi!$C$5-1)*60+45)+INDEX(Motore_Startup!$AZ$5:$AZ$544,(Ipotesi!$C$5-1)*60+45)+INDEX(Motore_Startup!$BA$5:$BA$544,(Ipotesi!$C$5-1)*60+45))+INDEX(Motore_Startup!$BB$5:$BB$544,(Ipotesi!$C$5-1)*60+45) -> -24897.186 | D49: =INDEX(Motore_Startup!$AW$5:$AW$544,(Ipotesi!$C$5-1)*60+45)+INDEX(Motore_Startup!$AX$5:$AX$544,(Ipotesi!$C$5-1)*60+45)+INDEX(Motore_Startup!$AZ$5:$AZ$544,(Ipotesi!$C$5-1)*60+45)+INDEX(Motore_Startup!$BA$5:$BA$544,(Ipotesi!$C$5-1)*60+45) -> 0 | E49: =INDEX(Motore_Startup!$BB$5:$BB$544,(Ipotesi!$C$5-1)*60+45) -> 0 | F49: =INDEX(Motore_Startup!$BE$5:$BE$544,(Ipotesi!$C$5-1)*60+45)-INDEX(Motore_Startup!$BF$5:$BF$544,(Ipotesi!$C$5-1)*60+45) -> 0 | G49: =INDEX(Motore_Startup!$BH$5:$BH$544,(Ipotesi!$C$5-1)*60+45) -> 101147.49 | H49: =INDEX(Motore_Startup!$BI$5:$BI$544,(Ipotesi!$C$5-1)*60+45) -> 0 | I49: =INDEX(Motore_Advisory!$BH$5:$BH$544,(Ipotesi!$C$5-1)*60+45) -> 159951.73 | J49: =INDEX(Motore_Advisory!$BI$5:$BI$544,(Ipotesi!$C$5-1)*60+45) -> 0 | K49: =G49+I49 -> 261099.21 | L49: =H49+J49 -> 0 | M49: =IF(OR(G49<0,I49<0),1,0) -> 0
A50: =INDEX(Motore_Startup!$C$5:$C$544,(Ipotesi!$C$5-1)*60+46) -> 47757 | B50: =INDEX(Motore_Startup!$BH$5:$BH$544,(Ipotesi!$C$5-1)*60+45) -> 101147.49 | C50: =INDEX(Motore_Startup!$BD$5:$BD$544,(Ipotesi!$C$5-1)*60+46)-(INDEX(Motore_Startup!$BH$5:$BH$544,(Ipotesi!$C$5-1)*60+45))-(INDEX(Motore_Startup!$AW$5:$AW$544,(Ipotesi!$C$5-1)*60+46)+INDEX(Motore_Startup!$AX$5:$AX$544,(Ipotesi!$C$5-1)*60+46)+INDEX(Motore_Startup!$AZ$5:$AZ$544,(Ipotesi!$C$5-1)*60+46)+INDEX(Motore_Startup!$BA$5:$BA$544,(Ipotesi!$C$5-1)*60+46))+INDEX(Motore_Startup!$BB$5:$BB$544,(Ipotesi!$C$5-1)*60+46) -> -22292.69 | D50: =INDEX(Motore_Startup!$AW$5:$AW$544,(Ipotesi!$C$5-1)*60+46)+INDEX(Motore_Startup!$AX$5:$AX$544,(Ipotesi!$C$5-1)*60+46)+INDEX(Motore_Startup!$AZ$5:$AZ$544,(Ipotesi!$C$5-1)*60+46)+INDEX(Motore_Startup!$BA$5:$BA$544,(Ipotesi!$C$5-1)*60+46) -> 0 | E50: =INDEX(Motore_Startup!$BB$5:$BB$544,(Ipotesi!$C$5-1)*60+46) -> 0 | F50: =INDEX(Motore_Startup!$BE$5:$BE$544,(Ipotesi!$C$5-1)*60+46)-INDEX(Motore_Startup!$BF$5:$BF$544,(Ipotesi!$C$5-1)*60+46) -> 0 | G50: =INDEX(Motore_Startup!$BH$5:$BH$544,(Ipotesi!$C$5-1)*60+46) -> 78854.795 | H50: =INDEX(Motore_Startup!$BI$5:$BI$544,(Ipotesi!$C$5-1)*60+46) -> 0 | I50: =INDEX(Motore_Advisory!$BH$5:$BH$544,(Ipotesi!$C$5-1)*60+46) -> 188638 | J50: =INDEX(Motore_Advisory!$BI$5:$BI$544,(Ipotesi!$C$5-1)*60+46) -> 0 | K50: =G50+I50 -> 267492.8 | L50: =H50+J50 -> 0 | M50: =IF(OR(G50<0,I50<0),1,0) -> 0
A51: =INDEX(Motore_Startup!$C$5:$C$544,(Ipotesi!$C$5-1)*60+47) -> 47788 | B51: =INDEX(Motore_Startup!$BH$5:$BH$544,(Ipotesi!$C$5-1)*60+46) -> 78854.795 | C51: =INDEX(Motore_Startup!$BD$5:$BD$544,(Ipotesi!$C$5-1)*60+47)-(INDEX(Motore_Startup!$BH$5:$BH$544,(Ipotesi!$C$5-1)*60+46))-(INDEX(Motore_Startup!$AW$5:$AW$544,(Ipotesi!$C$5-1)*60+47)+INDEX(Motore_Startup!$AX$5:$AX$544,(Ipotesi!$C$5-1)*60+47)+INDEX(Motore_Startup!$AZ$5:$AZ$544,(Ipotesi!$C$5-1)*60+47)+INDEX(Motore_Startup!$BA$5:$BA$544,(Ipotesi!$C$5-1)*60+47))+INDEX(Motore_Startup!$BB$5:$BB$544,(Ipotesi!$C$5-1)*60+47) -> -19710.962 | D51: =INDEX(Motore_Startup!$AW$5:$AW$544,(Ipotesi!$C$5-1)*60+47)+INDEX(Motore_Startup!$AX$5:$AX$544,(Ipotesi!$C$5-1)*60+47)+INDEX(Motore_Startup!$AZ$5:$AZ$544,(Ipotesi!$C$5-1)*60+47)+INDEX(Motore_Startup!$BA$5:$BA$544,(Ipotesi!$C$5-1)*60+47) -> 0 | E51: =INDEX(Motore_Startup!$BB$5:$BB$544,(Ipotesi!$C$5-1)*60+47) -> 0 | F51: =INDEX(Motore_Startup!$BE$5:$BE$544,(Ipotesi!$C$5-1)*60+47)-INDEX(Motore_Startup!$BF$5:$BF$544,(Ipotesi!$C$5-1)*60+47) -> 0 | G51: =INDEX(Motore_Startup!$BH$5:$BH$544,(Ipotesi!$C$5-1)*60+47) -> 59143.833 | H51: =INDEX(Motore_Startup!$BI$5:$BI$544,(Ipotesi!$C$5-1)*60+47) -> 0 | I51: =INDEX(Motore_Advisory!$BH$5:$BH$544,(Ipotesi!$C$5-1)*60+47) -> 189316.28 | J51: =INDEX(Motore_Advisory!$BI$5:$BI$544,(Ipotesi!$C$5-1)*60+47) -> 0 | K51: =G51+I51 -> 248460.12 | L51: =H51+J51 -> 0 | M51: =IF(OR(G51<0,I51<0),1,0) -> 0
A52: =INDEX(Motore_Startup!$C$5:$C$544,(Ipotesi!$C$5-1)*60+48) -> 47818 | B52: =INDEX(Motore_Startup!$BH$5:$BH$544,(Ipotesi!$C$5-1)*60+47) -> 59143.833 | C52: =INDEX(Motore_Startup!$BD$5:$BD$544,(Ipotesi!$C$5-1)*60+48)-(INDEX(Motore_Startup!$BH$5:$BH$544,(Ipotesi!$C$5-1)*60+47))-(INDEX(Motore_Startup!$AW$5:$AW$544,(Ipotesi!$C$5-1)*60+48)+INDEX(Motore_Startup!$AX$5:$AX$544,(Ipotesi!$C$5-1)*60+48)+INDEX(Motore_Startup!$AZ$5:$AZ$544,(Ipotesi!$C$5-1)*60+48)+INDEX(Motore_Startup!$BA$5:$BA$544,(Ipotesi!$C$5-1)*60+48))+INDEX(Motore_Startup!$BB$5:$BB$544,(Ipotesi!$C$5-1)*60+48) -> -17151.802 | D52: =INDEX(Motore_Startup!$AW$5:$AW$544,(Ipotesi!$C$5-1)*60+48)+INDEX(Motore_Startup!$AX$5:$AX$544,(Ipotesi!$C$5-1)*60+48)+INDEX(Motore_Startup!$AZ$5:$AZ$544,(Ipotesi!$C$5-1)*60+48)+INDEX(Motore_Startup!$BA$5:$BA$544,(Ipotesi!$C$5-1)*60+48) -> 0 | E52: =INDEX(Motore_Startup!$BB$5:$BB$544,(Ipotesi!$C$5-1)*60+48) -> 13269.65 | F52: =INDEX(Motore_Startup!$BE$5:$BE$544,(Ipotesi!$C$5-1)*60+48)-INDEX(Motore_Startup!$BF$5:$BF$544,(Ipotesi!$C$5-1)*60+48) -> 0 | G52: =INDEX(Motore_Startup!$BH$5:$BH$544,(Ipotesi!$C$5-1)*60+48) -> 28722.381 | H52: =INDEX(Motore_Startup!$BI$5:$BI$544,(Ipotesi!$C$5-1)*60+48) -> 0 | I52: =INDEX(Motore_Advisory!$BH$5:$BH$544,(Ipotesi!$C$5-1)*60+48) -> 218002.56 | J52: =INDEX(Motore_Advisory!$BI$5:$BI$544,(Ipotesi!$C$5-1)*60+48) -> 0 | K52: =G52+I52 -> 246724.94 | L52: =H52+J52 -> 0 | M52: =IF(OR(G52<0,I52<0),1,0) -> 0
A53: =INDEX(Motore_Startup!$C$5:$C$544,(Ipotesi!$C$5-1)*60+49) -> 47849 | B53: =INDEX(Motore_Startup!$BH$5:$BH$544,(Ipotesi!$C$5-1)*60+48) -> 28722.381 | C53: =INDEX(Motore_Startup!$BD$5:$BD$544,(Ipotesi!$C$5-1)*60+49)-(INDEX(Motore_Startup!$BH$5:$BH$544,(Ipotesi!$C$5-1)*60+48))-(INDEX(Motore_Startup!$AW$5:$AW$544,(Ipotesi!$C$5-1)*60+49)+INDEX(Motore_Startup!$AX$5:$AX$544,(Ipotesi!$C$5-1)*60+49)+INDEX(Motore_Startup!$AZ$5:$AZ$544,(Ipotesi!$C$5-1)*60+49)+INDEX(Motore_Startup!$BA$5:$BA$544,(Ipotesi!$C$5-1)*60+49))+INDEX(Motore_Startup!$BB$5:$BB$544,(Ipotesi!$C$5-1)*60+49) -> -37485.713 | D53: =INDEX(Motore_Startup!$AW$5:$AW$544,(Ipotesi!$C$5-1)*60+49)+INDEX(Motore_Startup!$AX$5:$AX$544,(Ipotesi!$C$5-1)*60+49)+INDEX(Motore_Startup!$AZ$5:$AZ$544,(Ipotesi!$C$5-1)*60+49)+INDEX(Motore_Startup!$BA$5:$BA$544,(Ipotesi!$C$5-1)*60+49) -> 0 | E53: =INDEX(Motore_Startup!$BB$5:$BB$544,(Ipotesi!$C$5-1)*60+49) -> 0 | F53: =INDEX(Motore_Startup!$BE$5:$BE$544,(Ipotesi!$C$5-1)*60+49)-INDEX(Motore_Startup!$BF$5:$BF$544,(Ipotesi!$C$5-1)*60+49) -> 33763.332 | G53: =INDEX(Motore_Startup!$BH$5:$BH$544,(Ipotesi!$C$5-1)*60+49) -> 25000 | H53: =INDEX(Motore_Startup!$BI$5:$BI$544,(Ipotesi!$C$5-1)*60+49) -> 0 | I53: =INDEX(Motore_Advisory!$BH$5:$BH$544,(Ipotesi!$C$5-1)*60+49) -> 236680.78 | J53: =INDEX(Motore_Advisory!$BI$5:$BI$544,(Ipotesi!$C$5-1)*60+49) -> 0 | K53: =G53+I53 -> 261680.78 | L53: =H53+J53 -> 0 | M53: =IF(OR(G53<0,I53<0),1,0) -> 0
A54: =INDEX(Motore_Startup!$C$5:$C$544,(Ipotesi!$C$5-1)*60+50) -> 47880 | B54: =INDEX(Motore_Startup!$BH$5:$BH$544,(Ipotesi!$C$5-1)*60+49) -> 25000 | C54: =INDEX(Motore_Startup!$BD$5:$BD$544,(Ipotesi!$C$5-1)*60+50)-(INDEX(Motore_Startup!$BH$5:$BH$544,(Ipotesi!$C$5-1)*60+49))-(INDEX(Motore_Startup!$AW$5:$AW$544,(Ipotesi!$C$5-1)*60+50)+INDEX(Motore_Startup!$AX$5:$AX$544,(Ipotesi!$C$5-1)*60+50)+INDEX(Motore_Startup!$AZ$5:$AZ$544,(Ipotesi!$C$5-1)*60+50)+INDEX(Motore_Startup!$BA$5:$BA$544,(Ipotesi!$C$5-1)*60+50))+INDEX(Motore_Startup!$BB$5:$BB$544,(Ipotesi!$C$5-1)*60+50) -> -35849.743 | D54: =INDEX(Motore_Startup!$AW$5:$AW$544,(Ipotesi!$C$5-1)*60+50)+INDEX(Motore_Startup!$AX$5:$AX$544,(Ipotesi!$C$5-1)*60+50)+INDEX(Motore_Startup!$AZ$5:$AZ$544,(Ipotesi!$C$5-1)*60+50)+INDEX(Motore_Startup!$BA$5:$BA$544,(Ipotesi!$C$5-1)*60+50) -> 0 | E54: =INDEX(Motore_Startup!$BB$5:$BB$544,(Ipotesi!$C$5-1)*60+50) -> 0 | F54: =INDEX(Motore_Startup!$BE$5:$BE$544,(Ipotesi!$C$5-1)*60+50)-INDEX(Motore_Startup!$BF$5:$BF$544,(Ipotesi!$C$5-1)*60+50) -> 35849.743 | G54: =INDEX(Motore_Startup!$BH$5:$BH$544,(Ipotesi!$C$5-1)*60+50) -> 25000 | H54: =INDEX(Motore_Startup!$BI$5:$BI$544,(Ipotesi!$C$5-1)*60+50) -> 0 | I54: =INDEX(Motore_Advisory!$BH$5:$BH$544,(Ipotesi!$C$5-1)*60+50) -> 247822.9 | J54: =INDEX(Motore_Advisory!$BI$5:$BI$544,(Ipotesi!$C$5-1)*60+50) -> 0 | K54: =G54+I54 -> 272822.9 | L54: =H54+J54 -> 0 | M54: =IF(OR(G54<0,I54<0),1,0) -> 0
A55: =INDEX(Motore_Startup!$C$5:$C$544,(Ipotesi!$C$5-1)*60+51) -> 47908 | B55: =INDEX(Motore_Startup!$BH$5:$BH$544,(Ipotesi!$C$5-1)*60+50) -> 25000 | C55: =INDEX(Motore_Startup!$BD$5:$BD$544,(Ipotesi!$C$5-1)*60+51)-(INDEX(Motore_Startup!$BH$5:$BH$544,(Ipotesi!$C$5-1)*60+50))-(INDEX(Motore_Startup!$AW$5:$AW$544,(Ipotesi!$C$5-1)*60+51)+INDEX(Motore_Startup!$AX$5:$AX$544,(Ipotesi!$C$5-1)*60+51)+INDEX(Motore_Startup!$AZ$5:$AZ$544,(Ipotesi!$C$5-1)*60+51)+INDEX(Motore_Startup!$BA$5:$BA$544,(Ipotesi!$C$5-1)*60+51))+INDEX(Motore_Startup!$BB$5:$BB$544,(Ipotesi!$C$5-1)*60+51) -> -50011.582 | D55: =INDEX(Motore_Startup!$AW$5:$AW$544,(Ipotesi!$C$5-1)*60+51)+INDEX(Motore_Startup!$AX$5:$AX$544,(Ipotesi!$C$5-1)*60+51)+INDEX(Motore_Startup!$AZ$5:$AZ$544,(Ipotesi!$C$5-1)*60+51)+INDEX(Motore_Startup!$BA$5:$BA$544,(Ipotesi!$C$5-1)*60+51) -> 0 | E55: =INDEX(Motore_Startup!$BB$5:$BB$544,(Ipotesi!$C$5-1)*60+51) -> 0 | F55: =INDEX(Motore_Startup!$BE$5:$BE$544,(Ipotesi!$C$5-1)*60+51)-INDEX(Motore_Startup!$BF$5:$BF$544,(Ipotesi!$C$5-1)*60+51) -> 50011.582 | G55: =INDEX(Motore_Startup!$BH$5:$BH$544,(Ipotesi!$C$5-1)*60+51) -> 25000 | H55: =INDEX(Motore_Startup!$BI$5:$BI$544,(Ipotesi!$C$5-1)*60+51) -> 0 | I55: =INDEX(Motore_Advisory!$BH$5:$BH$544,(Ipotesi!$C$5-1)*60+51) -> 254332.95 | J55: =INDEX(Motore_Advisory!$BI$5:$BI$544,(Ipotesi!$C$5-1)*60+51) -> 0 | K55: =G55+I55 -> 279332.95 | L55: =H55+J55 -> 0 | M55: =IF(OR(G55<0,I55<0),1,0) -> 0
A56: =INDEX(Motore_Startup!$C$5:$C$544,(Ipotesi!$C$5-1)*60+52) -> 47939 | B56: =INDEX(Motore_Startup!$BH$5:$BH$544,(Ipotesi!$C$5-1)*60+51) -> 25000 | C56: =INDEX(Motore_Startup!$BD$5:$BD$544,(Ipotesi!$C$5-1)*60+52)-(INDEX(Motore_Startup!$BH$5:$BH$544,(Ipotesi!$C$5-1)*60+51))-(INDEX(Motore_Startup!$AW$5:$AW$544,(Ipotesi!$C$5-1)*60+52)+INDEX(Motore_Startup!$AX$5:$AX$544,(Ipotesi!$C$5-1)*60+52)+INDEX(Motore_Startup!$AZ$5:$AZ$544,(Ipotesi!$C$5-1)*60+52)+INDEX(Motore_Startup!$BA$5:$BA$544,(Ipotesi!$C$5-1)*60+52))+INDEX(Motore_Startup!$BB$5:$BB$544,(Ipotesi!$C$5-1)*60+52) -> -14086.255 | D56: =INDEX(Motore_Startup!$AW$5:$AW$544,(Ipotesi!$C$5-1)*60+52)+INDEX(Motore_Startup!$AX$5:$AX$544,(Ipotesi!$C$5-1)*60+52)+INDEX(Motore_Startup!$AZ$5:$AZ$544,(Ipotesi!$C$5-1)*60+52)+INDEX(Motore_Startup!$BA$5:$BA$544,(Ipotesi!$C$5-1)*60+52) -> 0 | E56: =INDEX(Motore_Startup!$BB$5:$BB$544,(Ipotesi!$C$5-1)*60+52) -> 0 | F56: =INDEX(Motore_Startup!$BE$5:$BE$544,(Ipotesi!$C$5-1)*60+52)-INDEX(Motore_Startup!$BF$5:$BF$544,(Ipotesi!$C$5-1)*60+52) -> 14086.255 | G56: =INDEX(Motore_Startup!$BH$5:$BH$544,(Ipotesi!$C$5-1)*60+52) -> 25000 | H56: =INDEX(Motore_Startup!$BI$5:$BI$544,(Ipotesi!$C$5-1)*60+52) -> 0 | I56: =INDEX(Motore_Advisory!$BH$5:$BH$544,(Ipotesi!$C$5-1)*60+52) -> 292217.34 | J56: =INDEX(Motore_Advisory!$BI$5:$BI$544,(Ipotesi!$C$5-1)*60+52) -> 0 | K56: =G56+I56 -> 317217.34 | L56: =H56+J56 -> 0 | M56: =IF(OR(G56<0,I56<0),1,0) -> 0
A57: =INDEX(Motore_Startup!$C$5:$C$544,(Ipotesi!$C$5-1)*60+53) -> 47969 | B57: =INDEX(Motore_Startup!$BH$5:$BH$544,(Ipotesi!$C$5-1)*60+52) -> 25000 | C57: =INDEX(Motore_Startup!$BD$5:$BD$544,(Ipotesi!$C$5-1)*60+53)-(INDEX(Motore_Startup!$BH$5:$BH$544,(Ipotesi!$C$5-1)*60+52))-(INDEX(Motore_Startup!$AW$5:$AW$544,(Ipotesi!$C$5-1)*60+53)+INDEX(Motore_Startup!$AX$5:$AX$544,(Ipotesi!$C$5-1)*60+53)+INDEX(Motore_Startup!$AZ$5:$AZ$544,(Ipotesi!$C$5-1)*60+53)+INDEX(Motore_Startup!$BA$5:$BA$544,(Ipotesi!$C$5-1)*60+53))+INDEX(Motore_Startup!$BB$5:$BB$544,(Ipotesi!$C$5-1)*60+53) -> -11953.881 | D57: =INDEX(Motore_Startup!$AW$5:$AW$544,(Ipotesi!$C$5-1)*60+53)+INDEX(Motore_Startup!$AX$5:$AX$544,(Ipotesi!$C$5-1)*60+53)+INDEX(Motore_Startup!$AZ$5:$AZ$544,(Ipotesi!$C$5-1)*60+53)+INDEX(Motore_Startup!$BA$5:$BA$544,(Ipotesi!$C$5-1)*60+53) -> 0 | E57: =INDEX(Motore_Startup!$BB$5:$BB$544,(Ipotesi!$C$5-1)*60+53) -> 0 | F57: =INDEX(Motore_Startup!$BE$5:$BE$544,(Ipotesi!$C$5-1)*60+53)-INDEX(Motore_Startup!$BF$5:$BF$544,(Ipotesi!$C$5-1)*60+53) -> 11953.881 | G57: =INDEX(Motore_Startup!$BH$5:$BH$544,(Ipotesi!$C$5-1)*60+53) -> 25000 | H57: =INDEX(Motore_Startup!$BI$5:$BI$544,(Ipotesi!$C$5-1)*60+53) -> 0 | I57: =INDEX(Motore_Advisory!$BH$5:$BH$544,(Ipotesi!$C$5-1)*60+53) -> 330101.72 | J57: =INDEX(Motore_Advisory!$BI$5:$BI$544,(Ipotesi!$C$5-1)*60+53) -> 0 | K57: =G57+I57 -> 355101.72 | L57: =H57+J57 -> 0 | M57: =IF(OR(G57<0,I57<0),1,0) -> 0
A58: =INDEX(Motore_Startup!$C$5:$C$544,(Ipotesi!$C$5-1)*60+54) -> 48000 | B58: =INDEX(Motore_Startup!$BH$5:$BH$544,(Ipotesi!$C$5-1)*60+53) -> 25000 | C58: =INDEX(Motore_Startup!$BD$5:$BD$544,(Ipotesi!$C$5-1)*60+54)-(INDEX(Motore_Startup!$BH$5:$BH$544,(Ipotesi!$C$5-1)*60+53))-(INDEX(Motore_Startup!$AW$5:$AW$544,(Ipotesi!$C$5-1)*60+54)+INDEX(Motore_Startup!$AX$5:$AX$544,(Ipotesi!$C$5-1)*60+54)+INDEX(Motore_Startup!$AZ$5:$AZ$544,(Ipotesi!$C$5-1)*60+54)+INDEX(Motore_Startup!$BA$5:$BA$544,(Ipotesi!$C$5-1)*60+54))+INDEX(Motore_Startup!$BB$5:$BB$544,(Ipotesi!$C$5-1)*60+54) -> -9991.7986 | D58: =INDEX(Motore_Startup!$AW$5:$AW$544,(Ipotesi!$C$5-1)*60+54)+INDEX(Motore_Startup!$AX$5:$AX$544,(Ipotesi!$C$5-1)*60+54)+INDEX(Motore_Startup!$AZ$5:$AZ$544,(Ipotesi!$C$5-1)*60+54)+INDEX(Motore_Startup!$BA$5:$BA$544,(Ipotesi!$C$5-1)*60+54) -> 69723.393 | E58: =INDEX(Motore_Startup!$BB$5:$BB$544,(Ipotesi!$C$5-1)*60+54) -> 13269.65 | F58: =INDEX(Motore_Startup!$BE$5:$BE$544,(Ipotesi!$C$5-1)*60+54)-INDEX(Motore_Startup!$BF$5:$BF$544,(Ipotesi!$C$5-1)*60+54) -> -46461.945 | G58: =INDEX(Motore_Startup!$BH$5:$BH$544,(Ipotesi!$C$5-1)*60+54) -> 25000 | H58: =INDEX(Motore_Startup!$BI$5:$BI$544,(Ipotesi!$C$5-1)*60+54) -> 0 | I58: =INDEX(Motore_Advisory!$BH$5:$BH$544,(Ipotesi!$C$5-1)*60+54) -> 169280.37 | J58: =INDEX(Motore_Advisory!$BI$5:$BI$544,(Ipotesi!$C$5-1)*60+54) -> 0 | K58: =G58+I58 -> 194280.37 | L58: =H58+J58 -> 0 | M58: =IF(OR(G58<0,I58<0),1,0) -> 0
A59: =INDEX(Motore_Startup!$C$5:$C$544,(Ipotesi!$C$5-1)*60+55) -> 48030 | B59: =INDEX(Motore_Startup!$BH$5:$BH$544,(Ipotesi!$C$5-1)*60+54) -> 25000 | C59: =INDEX(Motore_Startup!$BD$5:$BD$544,(Ipotesi!$C$5-1)*60+55)-(INDEX(Motore_Startup!$BH$5:$BH$544,(Ipotesi!$C$5-1)*60+54))-(INDEX(Motore_Startup!$AW$5:$AW$544,(Ipotesi!$C$5-1)*60+55)+INDEX(Motore_Startup!$AX$5:$AX$544,(Ipotesi!$C$5-1)*60+55)+INDEX(Motore_Startup!$AZ$5:$AZ$544,(Ipotesi!$C$5-1)*60+55)+INDEX(Motore_Startup!$BA$5:$BA$544,(Ipotesi!$C$5-1)*60+55))+INDEX(Motore_Startup!$BB$5:$BB$544,(Ipotesi!$C$5-1)*60+55) -> -7281.9796 | D59: =INDEX(Motore_Startup!$AW$5:$AW$544,(Ipotesi!$C$5-1)*60+55)+INDEX(Motore_Startup!$AX$5:$AX$544,(Ipotesi!$C$5-1)*60+55)+INDEX(Motore_Startup!$AZ$5:$AZ$544,(Ipotesi!$C$5-1)*60+55)+INDEX(Motore_Startup!$BA$5:$BA$544,(Ipotesi!$C$5-1)*60+55) -> 0 | E59: =INDEX(Motore_Startup!$BB$5:$BB$544,(Ipotesi!$C$5-1)*60+55) -> 0 | F59: =INDEX(Motore_Startup!$BE$5:$BE$544,(Ipotesi!$C$5-1)*60+55)-INDEX(Motore_Startup!$BF$5:$BF$544,(Ipotesi!$C$5-1)*60+55) -> 7281.9796 | G59: =INDEX(Motore_Startup!$BH$5:$BH$544,(Ipotesi!$C$5-1)*60+55) -> 25000 | H59: =INDEX(Motore_Startup!$BI$5:$BI$544,(Ipotesi!$C$5-1)*60+55) -> 0 | I59: =INDEX(Motore_Advisory!$BH$5:$BH$544,(Ipotesi!$C$5-1)*60+55) -> 207164.75 | J59: =INDEX(Motore_Advisory!$BI$5:$BI$544,(Ipotesi!$C$5-1)*60+55) -> 0 | K59: =G59+I59 -> 232164.75 | L59: =H59+J59 -> 0 | M59: =IF(OR(G59<0,I59<0),1,0) -> 0
A60: =INDEX(Motore_Startup!$C$5:$C$544,(Ipotesi!$C$5-1)*60+56) -> 48061 | B60: =INDEX(Motore_Startup!$BH$5:$BH$544,(Ipotesi!$C$5-1)*60+55) -> 25000 | C60: =INDEX(Motore_Startup!$BD$5:$BD$544,(Ipotesi!$C$5-1)*60+56)-(INDEX(Motore_Startup!$BH$5:$BH$544,(Ipotesi!$C$5-1)*60+55))-(INDEX(Motore_Startup!$AW$5:$AW$544,(Ipotesi!$C$5-1)*60+56)+INDEX(Motore_Startup!$AX$5:$AX$544,(Ipotesi!$C$5-1)*60+56)+INDEX(Motore_Startup!$AZ$5:$AZ$544,(Ipotesi!$C$5-1)*60+56)+INDEX(Motore_Startup!$BA$5:$BA$544,(Ipotesi!$C$5-1)*60+56))+INDEX(Motore_Startup!$BB$5:$BB$544,(Ipotesi!$C$5-1)*60+56) -> -4314.5651 | D60: =INDEX(Motore_Startup!$AW$5:$AW$544,(Ipotesi!$C$5-1)*60+56)+INDEX(Motore_Startup!$AX$5:$AX$544,(Ipotesi!$C$5-1)*60+56)+INDEX(Motore_Startup!$AZ$5:$AZ$544,(Ipotesi!$C$5-1)*60+56)+INDEX(Motore_Startup!$BA$5:$BA$544,(Ipotesi!$C$5-1)*60+56) -> 0 | E60: =INDEX(Motore_Startup!$BB$5:$BB$544,(Ipotesi!$C$5-1)*60+56) -> 0 | F60: =INDEX(Motore_Startup!$BE$5:$BE$544,(Ipotesi!$C$5-1)*60+56)-INDEX(Motore_Startup!$BF$5:$BF$544,(Ipotesi!$C$5-1)*60+56) -> 4314.5651 | G60: =INDEX(Motore_Startup!$BH$5:$BH$544,(Ipotesi!$C$5-1)*60+56) -> 25000 | H60: =INDEX(Motore_Startup!$BI$5:$BI$544,(Ipotesi!$C$5-1)*60+56) -> 0 | I60: =INDEX(Motore_Advisory!$BH$5:$BH$544,(Ipotesi!$C$5-1)*60+56) -> 245049.14 | J60: =INDEX(Motore_Advisory!$BI$5:$BI$544,(Ipotesi!$C$5-1)*60+56) -> 0 | K60: =G60+I60 -> 270049.14 | L60: =H60+J60 -> 0 | M60: =IF(OR(G60<0,I60<0),1,0) -> 0
A61: =INDEX(Motore_Startup!$C$5:$C$544,(Ipotesi!$C$5-1)*60+57) -> 48092 | B61: =INDEX(Motore_Startup!$BH$5:$BH$544,(Ipotesi!$C$5-1)*60+56) -> 25000 | C61: =INDEX(Motore_Startup!$BD$5:$BD$544,(Ipotesi!$C$5-1)*60+57)-(INDEX(Motore_Startup!$BH$5:$BH$544,(Ipotesi!$C$5-1)*60+56))-(INDEX(Motore_Startup!$AW$5:$AW$544,(Ipotesi!$C$5-1)*60+57)+INDEX(Motore_Startup!$AX$5:$AX$544,(Ipotesi!$C$5-1)*60+57)+INDEX(Motore_Startup!$AZ$5:$AZ$544,(Ipotesi!$C$5-1)*60+57)+INDEX(Motore_Startup!$BA$5:$BA$544,(Ipotesi!$C$5-1)*60+57))+INDEX(Motore_Startup!$BB$5:$BB$544,(Ipotesi!$C$5-1)*60+57) -> -1358.5719 | D61: =INDEX(Motore_Startup!$AW$5:$AW$544,(Ipotesi!$C$5-1)*60+57)+INDEX(Motore_Startup!$AX$5:$AX$544,(Ipotesi!$C$5-1)*60+57)+INDEX(Motore_Startup!$AZ$5:$AZ$544,(Ipotesi!$C$5-1)*60+57)+INDEX(Motore_Startup!$BA$5:$BA$544,(Ipotesi!$C$5-1)*60+57) -> 0 | E61: =INDEX(Motore_Startup!$BB$5:$BB$544,(Ipotesi!$C$5-1)*60+57) -> 0 | F61: =INDEX(Motore_Startup!$BE$5:$BE$544,(Ipotesi!$C$5-1)*60+57)-INDEX(Motore_Startup!$BF$5:$BF$544,(Ipotesi!$C$5-1)*60+57) -> 1358.5719 | G61: =INDEX(Motore_Startup!$BH$5:$BH$544,(Ipotesi!$C$5-1)*60+57) -> 25000 | H61: =INDEX(Motore_Startup!$BI$5:$BI$544,(Ipotesi!$C$5-1)*60+57) -> 0 | I61: =INDEX(Motore_Advisory!$BH$5:$BH$544,(Ipotesi!$C$5-1)*60+57) -> 282933.52 | J61: =INDEX(Motore_Advisory!$BI$5:$BI$544,(Ipotesi!$C$5-1)*60+57) -> 0 | K61: =G61+I61 -> 307933.52 | L61: =H61+J61 -> 0 | M61: =IF(OR(G61<0,I61<0),1,0) -> 0
A62: =INDEX(Motore_Startup!$C$5:$C$544,(Ipotesi!$C$5-1)*60+58) -> 48122 | B62: =INDEX(Motore_Startup!$BH$5:$BH$544,(Ipotesi!$C$5-1)*60+57) -> 25000 | C62: =INDEX(Motore_Startup!$BD$5:$BD$544,(Ipotesi!$C$5-1)*60+58)-(INDEX(Motore_Startup!$BH$5:$BH$544,(Ipotesi!$C$5-1)*60+57))-(INDEX(Motore_Startup!$AW$5:$AW$544,(Ipotesi!$C$5-1)*60+58)+INDEX(Motore_Startup!$AX$5:$AX$544,(Ipotesi!$C$5-1)*60+58)+INDEX(Motore_Startup!$AZ$5:$AZ$544,(Ipotesi!$C$5-1)*60+58)+INDEX(Motore_Startup!$BA$5:$BA$544,(Ipotesi!$C$5-1)*60+58))+INDEX(Motore_Startup!$BB$5:$BB$544,(Ipotesi!$C$5-1)*60+58) -> 1586.1727 | D62: =INDEX(Motore_Startup!$AW$5:$AW$544,(Ipotesi!$C$5-1)*60+58)+INDEX(Motore_Startup!$AX$5:$AX$544,(Ipotesi!$C$5-1)*60+58)+INDEX(Motore_Startup!$AZ$5:$AZ$544,(Ipotesi!$C$5-1)*60+58)+INDEX(Motore_Startup!$BA$5:$BA$544,(Ipotesi!$C$5-1)*60+58) -> 0 | E62: =INDEX(Motore_Startup!$BB$5:$BB$544,(Ipotesi!$C$5-1)*60+58) -> 0 | F62: =INDEX(Motore_Startup!$BE$5:$BE$544,(Ipotesi!$C$5-1)*60+58)-INDEX(Motore_Startup!$BF$5:$BF$544,(Ipotesi!$C$5-1)*60+58) -> -1586.1727 | G62: =INDEX(Motore_Startup!$BH$5:$BH$544,(Ipotesi!$C$5-1)*60+58) -> 25000 | H62: =INDEX(Motore_Startup!$BI$5:$BI$544,(Ipotesi!$C$5-1)*60+58) -> 0 | I62: =INDEX(Motore_Advisory!$BH$5:$BH$544,(Ipotesi!$C$5-1)*60+58) -> 320817.91 | J62: =INDEX(Motore_Advisory!$BI$5:$BI$544,(Ipotesi!$C$5-1)*60+58) -> 0 | K62: =G62+I62 -> 345817.91 | L62: =H62+J62 -> 0 | M62: =IF(OR(G62<0,I62<0),1,0) -> 0
A63: =INDEX(Motore_Startup!$C$5:$C$544,(Ipotesi!$C$5-1)*60+59) -> 48153 | B63: =INDEX(Motore_Startup!$BH$5:$BH$544,(Ipotesi!$C$5-1)*60+58) -> 25000 | C63: =INDEX(Motore_Startup!$BD$5:$BD$544,(Ipotesi!$C$5-1)*60+59)-(INDEX(Motore_Startup!$BH$5:$BH$544,(Ipotesi!$C$5-1)*60+58))-(INDEX(Motore_Startup!$AW$5:$AW$544,(Ipotesi!$C$5-1)*60+59)+INDEX(Motore_Startup!$AX$5:$AX$544,(Ipotesi!$C$5-1)*60+59)+INDEX(Motore_Startup!$AZ$5:$AZ$544,(Ipotesi!$C$5-1)*60+59)+INDEX(Motore_Startup!$BA$5:$BA$544,(Ipotesi!$C$5-1)*60+59))+INDEX(Motore_Startup!$BB$5:$BB$544,(Ipotesi!$C$5-1)*60+59) -> 4519.8397 | D63: =INDEX(Motore_Startup!$AW$5:$AW$544,(Ipotesi!$C$5-1)*60+59)+INDEX(Motore_Startup!$AX$5:$AX$544,(Ipotesi!$C$5-1)*60+59)+INDEX(Motore_Startup!$AZ$5:$AZ$544,(Ipotesi!$C$5-1)*60+59)+INDEX(Motore_Startup!$BA$5:$BA$544,(Ipotesi!$C$5-1)*60+59) -> 0 | E63: =INDEX(Motore_Startup!$BB$5:$BB$544,(Ipotesi!$C$5-1)*60+59) -> 0 | F63: =INDEX(Motore_Startup!$BE$5:$BE$544,(Ipotesi!$C$5-1)*60+59)-INDEX(Motore_Startup!$BF$5:$BF$544,(Ipotesi!$C$5-1)*60+59) -> -4519.8397 | G63: =INDEX(Motore_Startup!$BH$5:$BH$544,(Ipotesi!$C$5-1)*60+59) -> 25000 | H63: =INDEX(Motore_Startup!$BI$5:$BI$544,(Ipotesi!$C$5-1)*60+59) -> 0 | I63: =INDEX(Motore_Advisory!$BH$5:$BH$544,(Ipotesi!$C$5-1)*60+59) -> 304012.41 | J63: =INDEX(Motore_Advisory!$BI$5:$BI$544,(Ipotesi!$C$5-1)*60+59) -> 0 | K63: =G63+I63 -> 329012.41 | L63: =H63+J63 -> 0 | M63: =IF(OR(G63<0,I63<0),1,0) -> 0
A64: =INDEX(Motore_Startup!$C$5:$C$544,(Ipotesi!$C$5-1)*60+60) -> 48183 | B64: =INDEX(Motore_Startup!$BH$5:$BH$544,(Ipotesi!$C$5-1)*60+59) -> 25000 | C64: =INDEX(Motore_Startup!$BD$5:$BD$544,(Ipotesi!$C$5-1)*60+60)-(INDEX(Motore_Startup!$BH$5:$BH$544,(Ipotesi!$C$5-1)*60+59))-(INDEX(Motore_Startup!$AW$5:$AW$544,(Ipotesi!$C$5-1)*60+60)+INDEX(Motore_Startup!$AX$5:$AX$544,(Ipotesi!$C$5-1)*60+60)+INDEX(Motore_Startup!$AZ$5:$AZ$544,(Ipotesi!$C$5-1)*60+60)+INDEX(Motore_Startup!$BA$5:$BA$544,(Ipotesi!$C$5-1)*60+60))+INDEX(Motore_Startup!$BB$5:$BB$544,(Ipotesi!$C$5-1)*60+60) -> 7442.5994 | D64: =INDEX(Motore_Startup!$AW$5:$AW$544,(Ipotesi!$C$5-1)*60+60)+INDEX(Motore_Startup!$AX$5:$AX$544,(Ipotesi!$C$5-1)*60+60)+INDEX(Motore_Startup!$AZ$5:$AZ$544,(Ipotesi!$C$5-1)*60+60)+INDEX(Motore_Startup!$BA$5:$BA$544,(Ipotesi!$C$5-1)*60+60) -> 0 | E64: =INDEX(Motore_Startup!$BB$5:$BB$544,(Ipotesi!$C$5-1)*60+60) -> 13269.65 | F64: =INDEX(Motore_Startup!$BE$5:$BE$544,(Ipotesi!$C$5-1)*60+60)-INDEX(Motore_Startup!$BF$5:$BF$544,(Ipotesi!$C$5-1)*60+60) -> 5827.0504 | G64: =INDEX(Motore_Startup!$BH$5:$BH$544,(Ipotesi!$C$5-1)*60+60) -> 25000 | H64: =INDEX(Motore_Startup!$BI$5:$BI$544,(Ipotesi!$C$5-1)*60+60) -> 0 | I64: =INDEX(Motore_Advisory!$BH$5:$BH$544,(Ipotesi!$C$5-1)*60+60) -> 341896.8 | J64: =INDEX(Motore_Advisory!$BI$5:$BI$544,(Ipotesi!$C$5-1)*60+60) -> 0 | K64: =G64+I64 -> 366896.8 | L64: =H64+J64 -> 0 | M64: =IF(OR(G64<0,I64<0),1,0) -> 0

Sheet Grafici
A1: Liquidità mensile per società
A2: Importi in euro. I saldi negativi indicano deficit non finanziati; i fondi previsti restano condizionati.

Sheet Confronto_Scenari
A1: Nove scenari | confronto live
A2: Importi in euro salvo clienti. Tutte le celle dipendono dalle formule dei motori; nessuno snapshot manuale.
A4: Scenario | B4: Indicatore | C4: 2027 | D4: 2028 | E4: 2029 | F4: 2030 | G4: 2031
A5: Prudente | B5: Ricavi esterni | C5: =SUM(Motore_Startup!F5:F16)+SUM(Motore_Advisory!F5:F16) -> 219750 | D5: =SUM(Motore_Startup!F17:F28)+SUM(Motore_Advisory!F17:F28) -> 588832.51 | E5: =SUM(Motore_Startup!F29:F40)+SUM(Motore_Advisory!F29:F40) -> 1192809.3 | F5: =SUM(Motore_Startup!F41:F52)+SUM(Motore_Advisory!F41:F52) -> 1980154.1 | G5: =SUM(Motore_Startup!F53:F64)+SUM(Motore_Advisory!F53:F64) -> 2807346.1
A6: Prudente | B6: EBITDA gruppo | C6: =SUM(Motore_Startup!J5:J16)+SUM(Motore_Advisory!J5:J16) -> -235190 | D6: =SUM(Motore_Startup!J17:J28)+SUM(Motore_Advisory!J17:J28) -> -396301.54 | E6: =SUM(Motore_Startup!J29:J40)+SUM(Motore_Advisory!J29:J40) -> -663238.72 | F6: =SUM(Motore_Startup!J41:J52)+SUM(Motore_Advisory!J41:J52) -> -498508.77 | G6: =SUM(Motore_Startup!J53:J64)+SUM(Motore_Advisory!J53:J64) -> -327486.83
A7: Prudente | B7: Cassa finale startup | C7: =Motore_Startup!BH16 -> 25000 | D7: =Motore_Startup!BH28 -> 25000 | E7: =Motore_Startup!BH40 -> 188805.1 | F7: =Motore_Startup!BH52 -> -421638.18 | G7: =Motore_Startup!BH64 -> -1049964.7
A8: Prudente | B8: Minimo mensile startup | C8: =MIN(Motore_Startup!BH5:BH16) -> 25000 | D8: =MIN(Motore_Startup!BH17:BH28) -> -114582.28 | E8: =MIN(Motore_Startup!BH29:BH40) -> -215059.56 | F8: =MIN(Motore_Startup!BH41:BH52) -> -421638.18 | G8: =MIN(Motore_Startup!BH53:BH64) -> -1049964.7
A9: Prudente | B9: Fabbisogno startup con buffer | C9: =MAX(Motore_Startup!BI5:BI16) -> 0 | D9: =MAX(Motore_Startup!BI17:BI28) -> 139582.28 | E9: =MAX(Motore_Startup!BI29:BI40) -> 240059.56 | F9: =MAX(Motore_Startup!BI41:BI52) -> 446638.18 | G9: =MAX(Motore_Startup!BI53:BI64) -> 1074964.7
A10: Prudente | B10: Minimo mensile Advisory | C10: =MIN(Motore_Advisory!BH5:BH16) -> -7904.6667 | D10: =MIN(Motore_Advisory!BH17:BH28) -> -41360.483 | E10: =MIN(Motore_Advisory!BH29:BH40) -> -72161.675 | F10: =MIN(Motore_Advisory!BH41:BH52) -> -46795.733 | G10: =MIN(Motore_Advisory!BH53:BH64) -> 11697.019
A11: Prudente | B11: Fabbisogno Advisory con buffer | C11: =MAX(Motore_Advisory!BI5:BI16) -> 17904.667 | D11: =MAX(Motore_Advisory!BI17:BI28) -> 51360.483 | E11: =MAX(Motore_Advisory!BI29:BI40) -> 82161.675 | F11: =MAX(Motore_Advisory!BI41:BI52) -> 56795.733 | G11: =MAX(Motore_Advisory!BI53:BI64) -> 0
A12: Prudente | B12: Patrimonio netto startup | C12: =Motore_Startup!BQ16 -> -108763.41 | D12: =Motore_Startup!BQ28 -> -186450.02 | E12: =Motore_Startup!BQ40 -> 2377.2566 | F12: =Motore_Startup!BQ52 -> -649500.13 | G12: =Motore_Startup!BQ64 -> -1165946.8
A13: Prudente | B13: Clienti SaaS finali | C13: =Motore_Operativo!BD16 -> 3 | D13: =Motore_Operativo!BD28 -> 21 | E13: =Motore_Operativo!BD40 -> 67.965303 | F13: =Motore_Operativo!BD52 -> 124.06676 | G13: =Motore_Operativo!BD64 -> 186.23031
A15: Base | B15: Ricavi esterni | C15: =SUM(Motore_Startup!F65:F76)+SUM(Motore_Advisory!F65:F76) -> 288276.32 | D15: =SUM(Motore_Startup!F77:F88)+SUM(Motore_Advisory!F77:F88) -> 732688.61 | E15: =SUM(Motore_Startup!F89:F100)+SUM(Motore_Advisory!F89:F100) -> 1533406.2 | F15: =SUM(Motore_Startup!F101:F112)+SUM(Motore_Advisory!F101:F112) -> 2580413.9 | G15: =SUM(Motore_Startup!F113:F124)+SUM(Motore_Advisory!F113:F124) -> 3651225.3
A16: Base | B16: EBITDA gruppo | C16: =SUM(Motore_Startup!J65:J76)+SUM(Motore_Advisory!J65:J76) -> -171028.84 | D16: =SUM(Motore_Startup!J77:J88)+SUM(Motore_Advisory!J77:J88) -> -263199.15 | E16: =SUM(Motore_Startup!J89:J100)+SUM(Motore_Advisory!J89:J100) -> -350161.38 | F16: =SUM(Motore_Startup!J101:J112)+SUM(Motore_Advisory!J101:J112) -> 52824.185 | G16: =SUM(Motore_Startup!J113:J124)+SUM(Motore_Advisory!J113:J124) -> 446595.61
A17: Base | B17: Cassa finale startup | C17: =Motore_Startup!BH76 -> 25000 | D17: =Motore_Startup!BH88 -> 40136.79 | E17: =Motore_Startup!BH100 -> 448452.52 | F17: =Motore_Startup!BH112 -> 28722.381 | G17: =Motore_Startup!BH124 -> 25000
A18: Base | B18: Minimo mensile startup | C18: =MIN(Motore_Startup!BH65:BH76) -> 25000 | D18: =MIN(Motore_Startup!BH77:BH88) -> -73138.76 | E18: =MIN(Motore_Startup!BH89:BH100) -> -73078.563 | F18: =MIN(Motore_Startup!BH101:BH112) -> 28722.381 | G18: =MIN(Motore_Startup!BH113:BH124) -> 25000
A19: Base | B19: Fabbisogno startup con buffer | C19: =MAX(Motore_Startup!BI65:BI76) -> 0 | D19: =MAX(Motore_Startup!BI77:BI88) -> 98138.76 | E19: =MAX(Motore_Startup!BI89:BI100) -> 98078.563 | F19: =MAX(Motore_Startup!BI101:BI112) -> 0 | G19: =MAX(Motore_Startup!BI113:BI124) -> 0
A20: Base | B20: Minimo mensile Advisory | C20: =MIN(Motore_Advisory!BH65:BH76) -> -10462.852 | D20: =MIN(Motore_Advisory!BH77:BH88) -> -9688.9021 | E20: =MIN(Motore_Advisory!BH89:BH100) -> -16783.08 | F20: =MIN(Motore_Advisory!BH101:BH112) -> 73892.896 | G20: =MIN(Motore_Advisory!BH113:BH124) -> 169280.37
A21: Base | B21: Fabbisogno Advisory con buffer | C21: =MAX(Motore_Advisory!BI65:BI76) -> 20462.852 | D21: =MAX(Motore_Advisory!BI77:BI88) -> 19688.902 | E21: =MAX(Motore_Advisory!BI89:BI100) -> 26783.08 | F21: =MAX(Motore_Advisory!BI101:BI112) -> 0 | G21: =MAX(Motore_Advisory!BI113:BI124) -> 0
A22: Base | B22: Patrimonio netto startup | C22: =Motore_Startup!BQ76 -> -81501.596 | D22: =Motore_Startup!BQ88 -> -70427.385 | E22: =Motore_Startup!BQ100 -> 322479.7 | F22: =Motore_Startup!BQ112 -> 50461.874 | G22: =Motore_Startup!BQ124 -> 88867.762
A23: Base | B23: Clienti SaaS finali | C23: =Motore_Operativo!BD76 -> 5 | D23: =Motore_Operativo!BD88 -> 32.63937 | E23: =Motore_Operativo!BD100 -> 88.253797 | F23: =Motore_Operativo!BD112 -> 154.906 | G23: =Motore_Operativo!BD124 -> 228.89967
A25: Ottimistico | B25: Ricavi esterni | C25: =SUM(Motore_Startup!F125:F136)+SUM(Motore_Advisory!F125:F136) -> 310656.32 | D25: =SUM(Motore_Startup!F137:F148)+SUM(Motore_Advisory!F137:F148) -> 787707.91 | E25: =SUM(Motore_Startup!F149:F160)+SUM(Motore_Advisory!F149:F160) -> 1666712.1 | F25: =SUM(Motore_Startup!F161:F172)+SUM(Motore_Advisory!F161:F172) -> 2826399.4 | G25: =SUM(Motore_Startup!F173:F184)+SUM(Motore_Advisory!F173:F184) -> 4080293.9
A26: Ottimistico | B26: EBITDA gruppo | C26: =SUM(Motore_Startup!J125:J136)+SUM(Motore_Advisory!J125:J136) -> -150111.64 | D26: =SUM(Motore_Startup!J137:J148)+SUM(Motore_Advisory!J137:J148) -> -212994.55 | E26: =SUM(Motore_Startup!J149:J160)+SUM(Motore_Advisory!J149:J160) -> -231166.32 | F26: =SUM(Motore_Startup!J161:J172)+SUM(Motore_Advisory!J161:J172) -> 269478.86 | G26: =SUM(Motore_Startup!J173:J184)+SUM(Motore_Advisory!J173:J184) -> 826652.88
A27: Ottimistico | B27: Cassa finale startup | C27: =Motore_Startup!BH136 -> 25000 | D27: =Motore_Startup!BH148 -> 95906.059 | E27: =Motore_Startup!BH160 -> 599339.37 | F27: =Motore_Startup!BH172 -> 364952.17 | G27: =Motore_Startup!BH184 -> 552333.5
A28: Ottimistico | B28: Minimo mensile startup | C28: =MIN(Motore_Startup!BH125:BH136) -> 25000 | D28: =MIN(Motore_Startup!BH137:BH148) -> -46717.83 | E28: =MIN(Motore_Startup!BH149:BH160) -> 11255.626 | F28: =MIN(Motore_Startup!BH161:BH172) -> 364952.17 | G28: =MIN(Motore_Startup!BH173:BH184) -> 303867.88
A29: Ottimistico | B29: Fabbisogno startup con buffer | C29: =MAX(Motore_Startup!BI125:BI136) -> 0 | D29: =MAX(Motore_Startup!BI137:BI148) -> 71717.83 | E29: =MAX(Motore_Startup!BI149:BI160) -> 13744.374 | F29: =MAX(Motore_Startup!BI161:BI172) -> 0 | G29: =MAX(Motore_Startup!BI173:BI184) -> 0
A30: Ottimistico | B30: Minimo mensile Advisory | C30: =MIN(Motore_Advisory!BH125:BH136) -> -10462.852 | D30: =MIN(Motore_Advisory!BH137:BH148) -> -9688.9021 | E30: =MIN(Motore_Advisory!BH149:BH160) -> -16783.08 | F30: =MIN(Motore_Advisory!BH161:BH172) -> 73892.896 | G30: =MIN(Motore_Advisory!BH173:BH184) -> 179472.48
A31: Ottimistico | B31: Fabbisogno Advisory con buffer | C31: =MAX(Motore_Advisory!BI125:BI136) -> 20462.852 | D31: =MAX(Motore_Advisory!BI137:BI148) -> 19688.902 | E31: =MAX(Motore_Advisory!BI149:BI160) -> 26783.08 | F31: =MAX(Motore_Advisory!BI161:BI172) -> 0 | G31: =MAX(Motore_Advisory!BI173:BI184) -> 0
A32: Ottimistico | B32: Patrimonio netto startup | C32: =Motore_Startup!BQ136 -> -60279.856 | D32: =Motore_Startup!BQ148 -> 2449.15 | E32: =Motore_Startup!BQ160 -> 515678.12 | F32: =Motore_Startup!BQ172 -> 460314.97 | G32: =Motore_Startup!BQ184 -> 816757.55
A33: Ottimistico | B33: Clienti SaaS finali | C33: =Motore_Operativo!BD136 -> 7 | D33: =Motore_Operativo!BD148 -> 41.192743 | E33: =Motore_Operativo!BD160 -> 110.67142 | F33: =Motore_Operativo!BD172 -> 193.95126 | G33: =Motore_Operativo!BD184 -> 270
A35: Worst case | B35: Ricavi esterni | C35: =SUM(Motore_Startup!F185:F196)+SUM(Motore_Advisory!F185:F196) -> 144900 | D35: =SUM(Motore_Startup!F197:F208)+SUM(Motore_Advisory!F197:F208) -> 384410.45 | E35: =SUM(Motore_Startup!F209:F220)+SUM(Motore_Advisory!F209:F220) -> 769563.59 | F35: =SUM(Motore_Startup!F221:F232)+SUM(Motore_Advisory!F221:F232) -> 1318227.3 | G35: =SUM(Motore_Startup!F233:F244)+SUM(Motore_Advisory!F233:F244) -> 1936192.6
A36: Worst case | B36: EBITDA gruppo | C36: =SUM(Motore_Startup!J185:J196)+SUM(Motore_Advisory!J185:J196) -> -305324 | D36: =SUM(Motore_Startup!J197:J208)+SUM(Motore_Advisory!J197:J208) -> -586565.56 | E36: =SUM(Motore_Startup!J209:J220)+SUM(Motore_Advisory!J209:J220) -> -1052981 | F36: =SUM(Motore_Startup!J221:J232)+SUM(Motore_Advisory!J221:J232) -> -1105313.3 | G36: =SUM(Motore_Startup!J233:J244)+SUM(Motore_Advisory!J233:J244) -> -1125992.2
A37: Worst case | B37: Cassa finale startup | C37: =Motore_Startup!BH196 -> -17680.277 | D37: =Motore_Startup!BH208 -> -484309.88 | E37: =Motore_Startup!BH220 -> -983115.12 | F37: =Motore_Startup!BH232 -> -1978058.2 | G37: =Motore_Startup!BH244 -> -3118705.2
A38: Worst case | B38: Minimo mensile startup | C38: =MIN(Motore_Startup!BH185:BH196) -> -17680.277 | D38: =MIN(Motore_Startup!BH197:BH208) -> -521695.34 | E38: =MIN(Motore_Startup!BH209:BH220) -> -1106035.9 | F38: =MIN(Motore_Startup!BH221:BH232) -> -1978058.2 | G38: =MIN(Motore_Startup!BH233:BH244) -> -3118705.2
A39: Worst case | B39: Fabbisogno startup con buffer | C39: =MAX(Motore_Startup!BI185:BI196) -> 42680.277 | D39: =MAX(Motore_Startup!BI197:BI208) -> 546695.34 | E39: =MAX(Motore_Startup!BI209:BI220) -> 1131035.9 | F39: =MAX(Motore_Startup!BI221:BI232) -> 2003058.2 | G39: =MAX(Motore_Startup!BI233:BI244) -> 3143705.2
A40: Worst case | B40: Minimo mensile Advisory | C40: =MIN(Motore_Advisory!BH185:BH196) -> -38244.547 | D40: =MIN(Motore_Advisory!BH197:BH208) -> -161998.7 | E40: =MIN(Motore_Advisory!BH209:BH220) -> -312221.58 | F40: =MIN(Motore_Advisory!BH221:BH232) -> -468553.47 | G40: =MIN(Motore_Advisory!BH233:BH244) -> -651349.49
A41: Worst case | B41: Fabbisogno Advisory con buffer | C41: =MAX(Motore_Advisory!BI185:BI196) -> 48244.547 | D41: =MAX(Motore_Advisory!BI197:BI208) -> 171998.7 | E41: =MAX(Motore_Advisory!BI209:BI220) -> 322221.58 | F41: =MAX(Motore_Advisory!BI221:BI232) -> 478553.47 | G41: =MAX(Motore_Advisory!BI233:BI244) -> 661349.49
A42: Worst case | B42: Patrimonio netto startup | C42: =Motore_Startup!BQ196 -> -150952.66 | D42: =Motore_Startup!BQ208 -> -649891.25 | E42: =Motore_Startup!BQ220 -> -1266169.7 | F42: =Motore_Startup!BQ232 -> -2263651.5 | G42: =Motore_Startup!BQ244 -> -3280544.3
A43: Worst case | B43: Clienti SaaS finali | C43: =Motore_Operativo!BD196 -> 2 | D43: =Motore_Operativo!BD208 -> 12 | E43: =Motore_Operativo!BD220 -> 46 | F43: =Motore_Operativo!BD232 -> 99.459682 | G43: =Motore_Operativo!BD244 -> 158.34776
A45: Sopravvivenza | B45: Ricavi esterni | C45: =SUM(Motore_Startup!F245:F256)+SUM(Motore_Advisory!F245:F256) -> 141597.95 | D45: =SUM(Motore_Startup!F257:F268)+SUM(Motore_Advisory!F257:F268) -> 341035.51 | E45: =SUM(Motore_Startup!F269:F280)+SUM(Motore_Advisory!F269:F280) -> 659185.51 | F45: =SUM(Motore_Startup!F281:F292)+SUM(Motore_Advisory!F281:F292) -> 1040207.9 | G45: =SUM(Motore_Startup!F293:F304)+SUM(Motore_Advisory!F293:F304) -> 1416371.7
A46: Sopravvivenza | B46: EBITDA gruppo | C46: =SUM(Motore_Startup!J245:J256)+SUM(Motore_Advisory!J245:J256) -> -137559.89 | D46: =SUM(Motore_Startup!J257:J268)+SUM(Motore_Advisory!J257:J268) -> -185493.73 | E46: =SUM(Motore_Startup!J269:J280)+SUM(Motore_Advisory!J269:J280) -> -215536.27 | F46: =SUM(Motore_Startup!J281:J292)+SUM(Motore_Advisory!J281:J292) -> -108695.47 | G46: =SUM(Motore_Startup!J293:J304)+SUM(Motore_Advisory!J293:J304) -> -11055.956
A47: Sopravvivenza | B47: Cassa finale startup | C47: =Motore_Startup!BH256 -> 25000 | D47: =Motore_Startup!BH268 -> -85650.019 | E47: =Motore_Startup!BH280 -> 22342.855 | F47: =Motore_Startup!BH292 -> -236188.13 | G47: =Motore_Startup!BH304 -> -541211.96
A48: Sopravvivenza | B48: Minimo mensile startup | C48: =MIN(Motore_Startup!BH245:BH256) -> 25000 | D48: =MIN(Motore_Startup!BH257:BH268) -> -117436.15 | E48: =MIN(Motore_Startup!BH269:BH280) -> -222585.83 | F48: =MIN(Motore_Startup!BH281:BH292) -> -236188.13 | G48: =MIN(Motore_Startup!BH293:BH304) -> -541211.96
A49: Sopravvivenza | B49: Fabbisogno startup con buffer | C49: =MAX(Motore_Startup!BI245:BI256) -> 0 | D49: =MAX(Motore_Startup!BI257:BI268) -> 142436.15 | E49: =MAX(Motore_Startup!BI269:BI280) -> 247585.83 | F49: =MAX(Motore_Startup!BI281:BI292) -> 261188.13 | G49: =MAX(Motore_Startup!BI293:BI304) -> 566211.96
A50: Sopravvivenza | B50: Minimo mensile Advisory | C50: =MIN(Motore_Advisory!BH245:BH256) -> -6702.2117 | D50: =MIN(Motore_Advisory!BH257:BH268) -> -33347.775 | E50: =MIN(Motore_Advisory!BH269:BH280) -> -60116.911 | F50: =MIN(Motore_Advisory!BH281:BH292) -> -43540.16 | G50: =MIN(Motore_Advisory!BH293:BH304) -> 17565.958
A51: Sopravvivenza | B51: Fabbisogno Advisory con buffer | C51: =MAX(Motore_Advisory!BI245:BI256) -> 16702.212 | D51: =MAX(Motore_Advisory!BI257:BI268) -> 43347.775 | E51: =MAX(Motore_Advisory!BI269:BI280) -> 70116.911 | F51: =MAX(Motore_Advisory!BI281:BI292) -> 53540.16 | G51: =MAX(Motore_Advisory!BI293:BI304) -> 0
A52: Sopravvivenza | B52: Patrimonio netto startup | C52: =Motore_Startup!BQ256 -> -17912.4 | D52: =Motore_Startup!BQ268 -> -222929.61 | E52: =Motore_Startup!BQ280 -> -184541.77 | F52: =Motore_Startup!BQ292 -> -436155.57 | G52: =Motore_Startup!BQ304 -> -663082.49
A53: Sopravvivenza | B53: Clienti SaaS finali | C53: =Motore_Operativo!BD256 -> 1.1221154 | D53: =Motore_Operativo!BD268 -> 6.3353619 | E53: =Motore_Operativo!BD280 -> 16.421028 | F53: =Motore_Operativo!BD292 -> 28.381451 | G53: =Motore_Operativo!BD304 -> 41.59988
A55: Senza Smart&Start | B55: Ricavi esterni | C55: =SUM(Motore_Startup!F305:F316)+SUM(Motore_Advisory!F305:F316) -> 288276.32 | D55: =SUM(Motore_Startup!F317:F328)+SUM(Motore_Advisory!F317:F328) -> 732688.61 | E55: =SUM(Motore_Startup!F329:F340)+SUM(Motore_Advisory!F329:F340) -> 1533406.2 | F55: =SUM(Motore_Startup!F341:F352)+SUM(Motore_Advisory!F341:F352) -> 2580413.9 | G55: =SUM(Motore_Startup!F353:F364)+SUM(Motore_Advisory!F353:F364) -> 3651225.3
A56: Senza Smart&Start | B56: EBITDA gruppo | C56: =SUM(Motore_Startup!J305:J316)+SUM(Motore_Advisory!J305:J316) -> -171028.84 | D56: =SUM(Motore_Startup!J317:J328)+SUM(Motore_Advisory!J317:J328) -> -263199.15 | E56: =SUM(Motore_Startup!J329:J340)+SUM(Motore_Advisory!J329:J340) -> -350161.38 | F56: =SUM(Motore_Startup!J341:J352)+SUM(Motore_Advisory!J341:J352) -> 52824.185 | G56: =SUM(Motore_Startup!J353:J364)+SUM(Motore_Advisory!J353:J364) -> 446595.61
A57: Senza Smart&Start | B57: Cassa finale startup | C57: =Motore_Startup!BH316 -> 25000 | D57: =Motore_Startup!BH328 -> -54960.381 | E57: =Motore_Startup!BH340 -> 75251.023 | F57: =Motore_Startup!BH352 -> -174980.25 | G57: =Motore_Startup!BH364 -> -267304.11
A58: Senza Smart&Start | B58: Minimo mensile startup | C58: =MIN(Motore_Startup!BH305:BH316) -> 25000 | D58: =MIN(Motore_Startup!BH317:BH328) -> -153672.87 | E58: =MIN(Motore_Startup!BH329:BH340) -> -357432.93 | F58: =MIN(Motore_Startup!BH341:BH352) -> -174980.25 | G58: =MIN(Motore_Startup!BH353:BH364) -> -326333.87
A59: Senza Smart&Start | B59: Fabbisogno startup con buffer | C59: =MAX(Motore_Startup!BI305:BI316) -> 0 | D59: =MAX(Motore_Startup!BI317:BI328) -> 178672.87 | E59: =MAX(Motore_Startup!BI329:BI340) -> 382432.93 | F59: =MAX(Motore_Startup!BI341:BI352) -> 199980.25 | G59: =MAX(Motore_Startup!BI353:BI364) -> 351333.87
A60: Senza Smart&Start | B60: Minimo mensile Advisory | C60: =MIN(Motore_Advisory!BH305:BH316) -> -10462.852 | D60: =MIN(Motore_Advisory!BH317:BH328) -> -9688.9021 | E60: =MIN(Motore_Advisory!BH329:BH340) -> -16783.08 | F60: =MIN(Motore_Advisory!BH341:BH352) -> 73892.896 | G60: =MIN(Motore_Advisory!BH353:BH364) -> 169280.37
A61: Senza Smart&Start | B61: Fabbisogno Advisory con buffer | C61: =MAX(Motore_Advisory!BI305:BI316) -> 20462.852 | D61: =MAX(Motore_Advisory!BI317:BI328) -> 19688.902 | E61: =MAX(Motore_Advisory!BI329:BI340) -> 26783.08 | F61: =MAX(Motore_Advisory!BI341:BI352) -> 0 | G61: =MAX(Motore_Advisory!BI353:BI364) -> 0
A62: Senza Smart&Start | B62: Patrimonio netto startup | C62: =Motore_Startup!BQ316 -> -95824.262 | D62: =Motore_Startup!BQ328 -> -139369.51 | E62: =Motore_Startup!BQ340 -> 214671.2 | F62: =Motore_Startup!BQ352 -> -64387.064 | G62: =Motore_Startup!BQ364 -> -29242.947
A63: Senza Smart&Start | B63: Clienti SaaS finali | C63: =Motore_Operativo!BD316 -> 5 | D63: =Motore_Operativo!BD328 -> 32.63937 | E63: =Motore_Operativo!BD340 -> 88.253797 | F63: =Motore_Operativo!BD352 -> 154.906 | G63: =Motore_Operativo!BD364 -> 228.89967
A65: Senza round | B65: Ricavi esterni | C65: =SUM(Motore_Startup!F365:F376)+SUM(Motore_Advisory!F365:F376) -> 288276.32 | D65: =SUM(Motore_Startup!F377:F388)+SUM(Motore_Advisory!F377:F388) -> 732688.61 | E65: =SUM(Motore_Startup!F389:F400)+SUM(Motore_Advisory!F389:F400) -> 1533406.2 | F65: =SUM(Motore_Startup!F401:F412)+SUM(Motore_Advisory!F401:F412) -> 2580413.9 | G65: =SUM(Motore_Startup!F413:F424)+SUM(Motore_Advisory!F413:F424) -> 3651225.3
A66: Senza round | B66: EBITDA gruppo | C66: =SUM(Motore_Startup!J365:J376)+SUM(Motore_Advisory!J365:J376) -> -171028.84 | D66: =SUM(Motore_Startup!J377:J388)+SUM(Motore_Advisory!J377:J388) -> -263199.15 | E66: =SUM(Motore_Startup!J389:J400)+SUM(Motore_Advisory!J389:J400) -> -350161.38 | F66: =SUM(Motore_Startup!J401:J412)+SUM(Motore_Advisory!J401:J412) -> 52824.185 | G66: =SUM(Motore_Startup!J413:J424)+SUM(Motore_Advisory!J413:J424) -> 446595.61
A67: Senza round | B67: Cassa finale startup | C67: =Motore_Startup!BH376 -> 25000 | D67: =Motore_Startup!BH388 -> -112722.46 | E67: =Motore_Startup!BH400 -> -610785.41 | F67: =Motore_Startup!BH412 -> -1039515.6 | G67: =Motore_Startup!BH424 -> -1158378.7
A68: Senza round | B68: Minimo mensile startup | C68: =MIN(Motore_Startup!BH365:BH376) -> 25000 | D68: =MIN(Motore_Startup!BH377:BH388) -> -248774.98 | E68: =MIN(Motore_Startup!BH389:BH400) -> -610785.41 | F68: =MIN(Motore_Startup!BH401:BH412) -> -1039515.6 | G68: =MIN(Motore_Startup!BH413:BH424) -> -1190869.2
A69: Senza round | B69: Fabbisogno startup con buffer | C69: =MAX(Motore_Startup!BI365:BI376) -> 0 | D69: =MAX(Motore_Startup!BI377:BI388) -> 273774.98 | E69: =MAX(Motore_Startup!BI389:BI400) -> 635785.41 | F69: =MAX(Motore_Startup!BI401:BI412) -> 1064515.6 | G69: =MAX(Motore_Startup!BI413:BI424) -> 1215869.2
A70: Senza round | B70: Minimo mensile Advisory | C70: =MIN(Motore_Advisory!BH365:BH376) -> -10462.852 | D70: =MIN(Motore_Advisory!BH377:BH388) -> -9688.9021 | E70: =MIN(Motore_Advisory!BH389:BH400) -> -16783.08 | F70: =MIN(Motore_Advisory!BH401:BH412) -> 73892.896 | G70: =MIN(Motore_Advisory!BH413:BH424) -> 169280.37
A71: Senza round | B71: Fabbisogno Advisory con buffer | C71: =MAX(Motore_Advisory!BI365:BI376) -> 20462.852 | D71: =MAX(Motore_Advisory!BI377:BI388) -> 19688.902 | E71: =MAX(Motore_Advisory!BI389:BI400) -> 26783.08 | F71: =MAX(Motore_Advisory!BI401:BI412) -> 0 | G71: =MAX(Motore_Advisory!BI413:BI424) -> 0
A72: Senza round | B72: Patrimonio netto startup | C72: =Motore_Startup!BQ376 -> -81501.596 | D72: =Motore_Startup!BQ388 -> -373286.63 | E72: =Motore_Startup!BQ400 -> -886758.23 | F72: =Motore_Startup!BQ412 -> -1167776.1 | G72: =Motore_Startup!BQ424 -> -1132631.9
A73: Senza round | B73: Clienti SaaS finali | C73: =Motore_Operativo!BD376 -> 5 | D73: =Motore_Operativo!BD388 -> 32.63937 | E73: =Motore_Operativo!BD400 -> 88.253797 | F73: =Motore_Operativo!BD412 -> 154.906 | G73: =Motore_Operativo!BD424 -> 228.89967
A75: Senza banca | B75: Ricavi esterni | C75: =SUM(Motore_Startup!F425:F436)+SUM(Motore_Advisory!F425:F436) -> 288276.32 | D75: =SUM(Motore_Startup!F437:F448)+SUM(Motore_Advisory!F437:F448) -> 732688.61 | E75: =SUM(Motore_Startup!F449:F460)+SUM(Motore_Advisory!F449:F460) -> 1533406.2 | F75: =SUM(Motore_Startup!F461:F472)+SUM(Motore_Advisory!F461:F472) -> 2580413.9 | G75: =SUM(Motore_Startup!F473:F484)+SUM(Motore_Advisory!F473:F484) -> 3651225.3
A76: Senza banca | B76: EBITDA gruppo | C76: =SUM(Motore_Startup!J425:J436)+SUM(Motore_Advisory!J425:J436) -> -171028.84 | D76: =SUM(Motore_Startup!J437:J448)+SUM(Motore_Advisory!J437:J448) -> -263199.15 | E76: =SUM(Motore_Startup!J449:J460)+SUM(Motore_Advisory!J449:J460) -> -350161.38 | F76: =SUM(Motore_Startup!J461:J472)+SUM(Motore_Advisory!J461:J472) -> 52824.185 | G76: =SUM(Motore_Startup!J473:J484)+SUM(Motore_Advisory!J473:J484) -> 446595.61
A77: Senza banca | B77: Cassa finale startup | C77: =Motore_Startup!BH436 -> -56928.678 | D77: =Motore_Startup!BH448 -> 47708.158 | E77: =Motore_Startup!BH460 -> 458645.2 | F77: =Motore_Startup!BH472 -> 38915.058 | G77: =Motore_Startup!BH484 -> -70948.098
A78: Senza banca | B78: Minimo mensile startup | C78: =MIN(Motore_Startup!BH425:BH436) -> -90407.521 | D78: =MIN(Motore_Startup!BH437:BH448) -> -217958.15 | E78: =MIN(Motore_Startup!BH449:BH460) -> -213635.89 | F78: =MIN(Motore_Startup!BH461:BH472) -> 38915.058 | G78: =MIN(Motore_Startup!BH473:BH484) -> -108688.56
A79: Senza banca | B79: Fabbisogno startup con buffer | C79: =MAX(Motore_Startup!BI425:BI436) -> 115407.52 | D79: =MAX(Motore_Startup!BI437:BI448) -> 242958.15 | E79: =MAX(Motore_Startup!BI449:BI460) -> 238635.89 | F79: =MAX(Motore_Startup!BI461:BI472) -> 0 | G79: =MAX(Motore_Startup!BI473:BI484) -> 133688.56
A80: Senza banca | B80: Minimo mensile Advisory | C80: =MIN(Motore_Advisory!BH425:BH436) -> -10462.852 | D80: =MIN(Motore_Advisory!BH437:BH448) -> -9688.9021 | E80: =MIN(Motore_Advisory!BH449:BH460) -> -16783.08 | F80: =MIN(Motore_Advisory!BH461:BH472) -> 73892.896 | G80: =MIN(Motore_Advisory!BH473:BH484) -> 169280.37
A81: Senza banca | B81: Fabbisogno Advisory con buffer | C81: =MAX(Motore_Advisory!BI425:BI436) -> 20462.852 | D81: =MAX(Motore_Advisory!BI437:BI448) -> 19688.902 | E81: =MAX(Motore_Advisory!BI449:BI460) -> 26783.08 | F81: =MAX(Motore_Advisory!BI461:BI472) -> 0 | G81: =MAX(Motore_Advisory!BI473:BI484) -> 0
A82: Senza banca | B82: Patrimonio netto startup | C82: =Motore_Startup!BQ436 -> -79469.392 | D82: =Motore_Startup!BQ448 -> -62856.018 | E82: =Motore_Startup!BQ460 -> 332672.38 | F82: =Motore_Startup!BQ472 -> 60654.552 | G82: =Motore_Startup!BQ484 -> 104798.67
A83: Senza banca | B83: Clienti SaaS finali | C83: =Motore_Operativo!BD436 -> 5 | D83: =Motore_Operativo!BD448 -> 32.63937 | E83: =Motore_Operativo!BD460 -> 88.253797 | F83: =Motore_Operativo!BD472 -> 154.906 | G83: =Motore_Operativo!BD484 -> 228.89967
A85: Senza fonti esterne | B85: Ricavi esterni | C85: =SUM(Motore_Startup!F485:F496)+SUM(Motore_Advisory!F485:F496) -> 288276.32 | D85: =SUM(Motore_Startup!F497:F508)+SUM(Motore_Advisory!F497:F508) -> 732688.61 | E85: =SUM(Motore_Startup!F509:F520)+SUM(Motore_Advisory!F509:F520) -> 1533406.2 | F85: =SUM(Motore_Startup!F521:F532)+SUM(Motore_Advisory!F521:F532) -> 2580413.9 | G85: =SUM(Motore_Startup!F533:F544)+SUM(Motore_Advisory!F533:F544) -> 3651225.3
A86: Senza fonti esterne | B86: EBITDA gruppo | C86: =SUM(Motore_Startup!J485:J496)+SUM(Motore_Advisory!J485:J496) -> -171028.84 | D86: =SUM(Motore_Startup!J497:J508)+SUM(Motore_Advisory!J497:J508) -> -263199.15 | E86: =SUM(Motore_Startup!J509:J520)+SUM(Motore_Advisory!J509:J520) -> -350161.38 | F86: =SUM(Motore_Startup!J521:J532)+SUM(Motore_Advisory!J521:J532) -> 52824.185 | G86: =SUM(Motore_Startup!J533:J544)+SUM(Motore_Advisory!J533:J544) -> 446595.61
A87: Senza fonti esterne | B87: Cassa finale startup | C87: =Motore_Startup!BH496 -> -109470.9 | D87: =Motore_Startup!BH508 -> -494913.34 | E87: =Motore_Startup!BH520 -> -1110201.9 | F87: =Motore_Startup!BH532 -> -1503392.8 | G87: =Motore_Startup!BH544 -> -1586716.6
A88: Senza fonti esterne | B88: Minimo mensile startup | C88: =MIN(Motore_Startup!BH485:BH496) -> -109470.9 | D88: =MIN(Motore_Startup!BH497:BH508) -> -494913.34 | E88: =MIN(Motore_Startup!BH509:BH520) -> -1110201.9 | F88: =MIN(Motore_Startup!BH521:BH532) -> -1503392.8 | G88: =MIN(Motore_Startup!BH533:BH544) -> -1650996.4
A89: Senza fonti esterne | B89: Fabbisogno startup con buffer | C89: =MAX(Motore_Startup!BI485:BI496) -> 134470.9 | D89: =MAX(Motore_Startup!BI497:BI508) -> 519913.34 | E89: =MAX(Motore_Startup!BI509:BI520) -> 1135201.9 | F89: =MAX(Motore_Startup!BI521:BI532) -> 1528392.8 | G89: =MAX(Motore_Startup!BI533:BI544) -> 1675996.4
A90: Senza fonti esterne | B90: Minimo mensile Advisory | C90: =MIN(Motore_Advisory!BH485:BH496) -> -10462.852 | D90: =MIN(Motore_Advisory!BH497:BH508) -> -9688.9021 | E90: =MIN(Motore_Advisory!BH509:BH520) -> -16783.08 | F90: =MIN(Motore_Advisory!BH521:BH532) -> 73892.896 | G90: =MIN(Motore_Advisory!BH533:BH544) -> 169280.37
A91: Senza fonti esterne | B91: Fabbisogno Advisory con buffer | C91: =MAX(Motore_Advisory!BI485:BI496) -> 20462.852 | D91: =MAX(Motore_Advisory!BI497:BI508) -> 19688.902 | E91: =MAX(Motore_Advisory!BI509:BI520) -> 26783.08 | F91: =MAX(Motore_Advisory!BI521:BI532) -> 0 | G91: =MAX(Motore_Advisory!BI533:BI544) -> 0
A92: Senza fonti esterne | B92: Patrimonio netto startup | C92: =Motore_Startup!BQ496 -> -93792.058 | D92: =Motore_Startup!BQ508 -> -429322.47 | E92: =Motore_Startup!BQ520 -> -970781.76 | F92: =Motore_Startup!BQ532 -> -1242799.6 | G92: =Motore_Startup!BQ544 -> -1198655.5
A93: Senza fonti esterne | B93: Clienti SaaS finali | C93: =Motore_Operativo!BD496 -> 5 | D93: =Motore_Operativo!BD508 -> 32.63937 | E93: =Motore_Operativo!BD520 -> 88.253797 | F93: =Motore_Operativo!BD532 -> 154.906 | G93: =Motore_Operativo!BD544 -> 228.89967

Sheet Ipotesi
A1: Ipotesi — struttura a due società: LexShield AI S.r.l. (startup) e LexShield Advisory S.r.l. (consulenza)
A2: Celle blu = input modificabili · celle gialle = ipotesi chiave · nero = formule · verde = collegamenti ad altri fogli. Importi in euro.
A4: Scenario
A5: Scenario attivo: 1 Prudente, 2 Base, 3 Ottimistico, 4 Worst, 5 Sopravvivenza, 6 No SS, 7 No round, 8 No banca, 9 No esterni | B5: indice | C5: 2 | H5: Usare un indice da 1 a 9; Cruscotto e riepiloghi seguono questa scelta.
A6: Leve per scenario | C6: Prudente | D6: Base | E6: Ottimistico | F6: Worst case | G6: Sopravvivenza | H6: Senza Smart&Start | I6: Senza round | J6: Senza banca | K6: Senza fonti esterne
A7: Volumi servizi (giornate di consulenza, test, formazione) | B7: x | C7: 0.75 | D7: 1 | E7: 1.25 | F7: 0.55 | G7: 0.55 | H7: 1 | I7: 1 | J7: 1 | K7: 1 | M7: Worst case: -45% di giornate vendute.
A8: Clienti piattaforma SaaS | B8: x | C8: 0.6 | D8: 1 | E8: 1.4 | F8: 0.35 | G8: 0.35 | H8: 1 | I8: 1 | J8: 1 | K8: 1 | M8: Worst case: adozione della piattaforma al 35% del piano.
A9: Prezzi (tariffe e abbonamenti) | B9: x | C9: 1 | D9: 1 | E9: 1 | F9: 0.9 | G9: 0.9 | H9: 1 | I9: 1 | J9: 1 | K9: 1 | M9: Worst case: sconti del 10%.
A10: Organico non fondatori (FTE, entrambe le società) | B10: x | C10: 1 | D10: 1 | E10: 1 | F10: 1 | G10: 0.3 | H10: 1 | I10: 1 | J10: 1 | K10: 1 | M10: Piano di sopravvivenza: organico al 30% (con due società serve un taglio più forte che nel modello unico).
A11: Budget marketing | B11: x | C11: 1 | D11: 1 | E11: 1 | F11: 1 | G11: 0.2 | H11: 1 | I11: 1 | J11: 1 | K11: 1 | M11: Piano di sopravvivenza: marketing al 20%.
A12: Compensi del CEO (stipendio startup e compenso da amministratore di Advisory) | B12: x | C12: 1 | D12: 1 | E12: 1 | F12: 1 | G12: 0.6 | H12: 1 | I12: 1 | J12: 1 | K12: 1 | M12: Piano di sopravvivenza: -40%.
A13: Giorni medi di incasso clienti (DSO) | B13: giorni | C13: 90 | D13: 90 | E13: 90 | F13: 120 | G13: 120 | H13: 90 | I13: 90 | J13: 90 | K13: 90 | M13: Worst case: clienti che pagano a 120 giorni.
A14: Ritardo erogazioni Smart&Start | B14: anni | C14: 0 | D14: 0 | E14: 0 | F14: 1 | G14: 1 | H14: 0 | I14: 0 | J14: 0 | K14: 0 | M14: Worst case: un anno di ritardo.
A15: Ritardo dei round di investimento | B15: anni | C15: 0 | D15: 0 | E15: 0 | F15: 1 | G15: 1 | H15: 0 | I15: 0 | J15: 0 | K15: 0 | M15: Worst case: pre-seed nel 2029.
A16: Round seed raccolto | B16: quota | C16: 1 | D16: 1 | E16: 1 | F16: 0 | G16: 0 | H16: 1 | I16: 1 | J16: 1 | K16: 1 | M16: Worst case: il seed non si chiude.
A17: Volumi servizi (giornate di consulenza, test, formazione): valore attivo | B17: x | C17: =INDEX($C$7:$K$7,1,$C$5) -> 1
A18: Clienti piattaforma SaaS: valore attivo | B18: x | C18: =INDEX($C$8:$K$8,1,$C$5) -> 1
A19: Prezzi (tariffe e abbonamenti): valore attivo | B19: x | C19: =INDEX($C$9:$K$9,1,$C$5) -> 1
A20: Organico non fondatori (FTE, entrambe le società): valore attivo | B20: x | C20: =INDEX($C$10:$K$10,1,$C$5) -> 1
A21: Budget marketing: valore attivo | B21: x | C21: =INDEX($C$11:$K$11,1,$C$5) -> 1
A22: Compensi del CEO (stipendio startup e compenso da amministratore di Advisory): valore attivo | B22: x | C22: =INDEX($C$12:$K$12,1,$C$5) -> 1
A23: Giorni medi di incasso clienti (DSO): valore attivo | B23: giorni | C23: =INDEX($C$13:$K$13,1,$C$5) -> 90
A24: Ritardo erogazioni Smart&Start: valore attivo | B24: anni | C24: =INDEX($C$14:$K$14,1,$C$5) -> 0
A25: Ritardo dei round di investimento: valore attivo | B25: anni | C25: =INDEX($C$15:$K$15,1,$C$5) -> 0
A26: Round seed raccolto: valore attivo | B26: quota | C26: =INDEX($C$16:$K$16,1,$C$5) -> 1
A27: Moltiplicatore CAC (budget/CAC) | B27: x | C27: 1.2 | D27: 1 | E27: 0.8 | F27: 1.3 | G27: 1.3 | H27: 1 | I27: 1 | J27: 1 | K27: 1 | M27: v3.1: leva CAC per scenario; valori proposti da validare. Usata in Motore_Operativo!BA.
A28: Voce | B28: Unità | C28: 2027 | D28: 2028 | E28: 2029 | F28: 2030 | G28: 2031 | H28: Note / fonte
A29: LexShield AI S.r.l. (startup innovativa) — ricavi tecnologici
A30: Servizi tecnici di sicurezza AI: giornate (base) | B30: giorni | C30: 100 | D30: 270 | E30: 500 | F30: 740 | G30: 980 | H30: Red teaming, test di prompt injection, audit dei modelli con strumenti proprietari del laboratorio.
A31: Servizi tecnici: tariffa media | B31: €/giorno | C31: 900 | D31: 950 | E31: 1000 | F31: 1050 | G31: 1100
A32: Piattaforma: clienti a fine anno (base) | B32: n. | C32: 5 | D32: 35 | E32: 130 | F32: 310 | G32: 560 | H32: Prima versione anticipata al 2027 con 5 clienti pilota.
A33: Piattaforma: ricavo medio annuo per cliente | B33: €/anno | C33: 2000 | D33: 4000 | E33: 5500 | F33: 6000 | G33: 6200 | H33: Prezzo pilota nel 2027.
A34: Piattaforma: churn annuo | B34: % | C34: 0 | D34: 0.1 | E34: 0.1 | F34: 0.1 | G34: 0.1
A35: CAC acquisizione SaaS (budget marketing + personale acquisizione) | B35: €/cliente | C35: 5000 | D35: 3000 | E35: 5000 | F35: 6000 | G35: 6500
A36: Obiettivo margine lordo SaaS (solo confronto, non costo imposto) | B36: % | C36: 0.8 | H36: Ora confrontato con il margine derivato dai costi, non utilizzato per inventare profitti.
A37: Canone infragruppo per piattaforma e metodologia | B37: % ricavi Advisory | C37: 0.1 | D37: 0.1 | E37: 0.1 | F37: 0.1 | G37: 0.1 | H37: Pagato da LexShield Advisory alla startup a valore di mercato (contratto di licenza). Da validare con il commercialista.
A39: LexShield AI S.r.l. — organico (FTE medi nell'anno)
A40: CEO (socio manager) | B40: FTE | C40: 1 | D40: 1 | E40: 1 | F40: 1 | G40: 1
A41: CTO | B41: FTE | C41: 0.75 | D41: 1 | E41: 1 | F41: 1 | G41: 1
A42: Security engineer / AI red teamer | B42: FTE | C42: 1 | D42: 2.5 | E42: 4.5 | F42: 6.5 | G42: 8.5
A43: Sviluppatori piattaforma | B43: FTE | C43: 1 | D43: 2.5 | E43: 5 | F43: 6 | G43: 7 | H43: Anticipato a 1 FTE nel 2027 per la prima versione della piattaforma.
A44: Commerciali e customer success | B44: FTE | C44: 0.5 | D44: 1.5 | E44: 4 | F44: 5 | G44: 6
A45: Amministrazione | B45: FTE | C45: 0 | D45: 0.5 | E45: 1 | F45: 1.5 | G45: 2
A47: LexShield Advisory S.r.l. (consulenza e formazione) — ricavi e organico
A48: Consulenza di conformità: giornate (base) | B48: giorni | C48: 200 | D48: 450 | E48: 720 | F48: 950 | G48: 1150
A49: Consulenza: tariffa media | B49: €/giorno | C49: 750 | D49: 800 | E49: 850 | F49: 900 | G49: 950
A50: Formazione: giornate d'aula (base) | B50: giornate | C50: 25 | D50: 55 | E50: 80 | F50: 100 | G50: 115
A51: Formazione: prezzo per giornata | B51: €/giornata | C51: 2000 | D51: 2000 | E51: 2250 | F51: 2500 | G51: 2600
A52: Consulenti di conformità | B52: FTE | C52: 1.5 | D52: 3 | E52: 5 | F52: 7 | G52: 9 | H52: 1,5 FTE nel 2027: i fondatori non lavorano più per la consulenza, che diventa autonoma.
A53: Responsabile operativo della consulenza | B53: FTE | C53: 0 | D53: 1 | E53: 1 | F53: 1 | G53: 1 | H53: Gestisce Advisory dal 2028; il socio avvocato non può avere deleghe operative.
A54: Amministrazione | B54: FTE | C54: 0 | D54: 0 | E54: 0.5 | F54: 0.5 | G54: 1
A55: Compenso amministratore (CEO) | B55: €/anno | C55: 6000 | D55: 12000 | E55: 18000 | F55: 24000 | G55: 24000 | H55: Il CEO è amministratore di entrambe le società.
A57: Costi del personale — costo aziendale per FTE (2027) e compensi
A58: CEO — stipendio nella startup | B58: €/anno | C58: 40000 | D58: 60000 | E58: 85000 | F58: 95000 | G58: 100000
A59: CTO | B59: €/FTE | C59: 70000
A60: Security engineer | B60: €/FTE | C60: 50000
A61: Sviluppatore | B61: €/FTE | C61: 50000
A62: Commerciale / customer success | B62: €/FTE | C62: 45000
A63: Amministrazione | B63: €/FTE | C63: 35000
A64: Consulente di conformità | B64: €/FTE | C64: 42000
A65: Responsabile operativo consulenza | B65: €/FTE | C65: 60000
A66: Crescita annua costo del lavoro | B66: % | C66: 0.03
A67: Provvigioni commerciali | B67: % ricavi esterni | C67: 0.03
A68: Compenso professionale totale del socio avvocato (a fattura) | B68: €/anno | C68: 30000 | D68: 48000 | E68: 72000 | F68: 90000 | G68: 100000
A69: Quota del compenso a carico della startup | B69: % | C69: 0.4 | H69: Il resto lo paga Advisory (metodologia legale, formazione). I pareri legali restano allo studio dell'avvocato.
A71: Altri costi operativi
A72: Startup — software e cloud, quota fissa | B72: €/anno | C72: 15000 | D72: 15000 | E72: 15000 | F72: 15000 | G72: 15000
A73: Startup — hosting della piattaforma | B73: % ricavi SaaS | C73: 0.08
A74: Startup — uffici e laboratorio | B74: €/anno | C74: 12000 | D74: 22000 | E74: 35000 | F74: 50000 | G74: 65000
A75: Startup — marketing della piattaforma | B75: €/anno | C75: 25000 | D75: 55000 | E75: 240000 | F75: 335000 | G75: 430000
A76: Startup — assicurazioni (cyber, responsabilità prodotto) | B76: €/anno | C76: 6000 | D76: 9000 | E76: 13000 | F76: 18000 | G76: 23000
A77: Startup — certificazioni ISO 27001 / 42001 | B77: €/anno | C77: 15000 | D77: 20000 | E77: 25000 | F77: 25000 | G77: 30000
A78: Startup — consulenze esterne (commercialista, notaio, bandi) | B78: €/anno | C78: 12000 | D78: 15000 | E78: 20000 | F78: 24000 | G78: 28000
A79: Startup — investimenti (hardware, laboratorio) | B79: €/anno | C79: 20000 | D79: 25000 | E79: 30000 | F79: 40000 | G79: 50000
A80: Advisory — uffici (subaffitto o coworking) | B80: €/anno | C80: 6000 | D80: 10000 | E80: 15000 | F80: 20000 | G80: 25000
A81: Advisory — eventi, associazioni, contenuti | B81: €/anno | C81: 5000 | D81: 10000 | E81: 15000 | F81: 20000 | G81: 25000
A82: Advisory — responsabilità professionale | B82: €/anno | C82: 5000 | D82: 8000 | E82: 12000 | F82: 15000 | G82: 18000 | H82: Massimali da rivedere dopo il D.Lgs. 160/2026.
A83: Advisory — commercialista e consulenze | B83: €/anno | C83: 6000 | D83: 7000 | E83: 8000 | F83: 9000 | G83: 10000
