Workbook

Sheet Istruzioni
A1: Business case canale YouTube — Studio di diritto militare
A2: Modello a 36 mesi, tre scenari. Tutti i valori sono ipotesi di esempio da sostituire con i dati dello studio.
A4: Come si usa
A5: 1. | B5: Vai al foglio «Ipotesi» e sostituisci i valori in BLU con i dati reali dello studio (tariffe, ore, costi).
A6: 2. | B6: Le celle con sfondo GIALLO sono le leve che spostano di più il risultato: verificale per prime.
A7: 3. | B7: I fogli «Scenario Prudente», «Scenario Medio» e «Scenario Buono» calcolano mese per mese: non vanno modificati.
A8: 4. | B8: Il foglio «Riepilogo» confronta i tre scenari: ricavi, margine, ROI, mese di pareggio, cassa.
A9: 5. | B9: Il foglio «Social» stima costi e contatti in più di Facebook, LinkedIn, Substack, Instagram/TikTok e X. Metti 0 nella colonna «Attivo» per escludere un canale.
A11: Legenda colori
A12: Blu | B12: Dato inserito a mano (ipotesi modificabile).
A13: Nero | B13: Formula calcolata: non modificare.
A14: Verde | B14: Valore preso da un altro foglio.
A15: Giallo | B15: Ipotesi chiave da verificare per prima.
A17: Logica del modello
A18: Imbuto | B18: Visualizzazioni → contatti → consulenze iniziali a pagamento → incarichi.
A19: Capacità | B19: Gli incarichi acquisiti non possono superare le ore disponibili dello studio: l'eccedenza è riportata come «incarichi persi».
A20: Altri social | B20: Ogni video viene riadattato per gli altri canali: i contatti in più sono una percentuale dei contatti YouTube e passano per la stessa consulenza e lo stesso limite di capacità.
A21: Standardizzazione | B21: Dal mese 13 i ricorsi sui concorsi richiedono meno ore (modelli e ricorsi collettivi): la capacità aumenta.
A22: Margine | B22: Ricavi − costi del canale (cassa + tempo dell'avvocato) − costo di erogazione degli incarichi (ore × costo interno).
A23: Cassa | B23: Gli onorari si incassano in acconto + saldo dopo N mesi; il tempo dell'avvocato sul canale non è un'uscita di cassa.
A24: Esclusi | B24: Spese vive e contributo unificato (rimborsati dal cliente), IVA, Cassa Forense, imposte.
A26: Avvertenze
A27: ! | B27: I tassi di conversione e le visualizzazioni sono stime indicative, non dati di mercato: dopo 3–6 mesi sostituiscili con i dati reali di YouTube Studio e del gestionale.
A28: ! | B28: Il pareggio è calcolato sul margine di contribuzione, non sul fatturato: per questo servono più incarichi rispetto a un calcolo sui soli ricavi.

Sheet Riepilogo
A1: Riepilogo e confronto scenari
A2: Valori collegati ai fogli di scenario (verde). Margine = ricavi − costi del canale − costo di erogazione degli incarichi.
A4: 1. Sintesi sui 36 mesi
A5: Indicatore | B5: Prudente | C5: Medio | D5: Buono | E5: Unità
A6: Incarichi acquisiti | B6: =SUM('Scenario Prudente'!J5:J40) -> 30.282127 | C6: =SUM('Scenario Medio'!J5:J40) -> 188.12253 | D6: =SUM('Scenario Buono'!J5:J40) -> 323.52277 | E6: n.
A7: Incarichi persi per mancanza di capacità | B7: =SUM('Scenario Prudente'!K5:K40) -> 0 | C7: =SUM('Scenario Medio'!K5:K40) -> 0 | D7: =SUM('Scenario Buono'!K5:K40) -> 335.22623 | E7: n.
A8: Ricavi totali | B8: =SUM('Scenario Prudente'!P5:P40) -> 64101.756 | C8: =SUM('Scenario Medio'!P5:P40) -> 413370.84 | D8: =SUM('Scenario Buono'!P5:P40) -> 777808.07 | E8: €
A9: Costi del canale (cassa + tempo avvocato) | B9: =SUM('Scenario Prudente'!Q5:R40) -> 61960 | C9: =SUM('Scenario Medio'!Q5:R40) -> 61960 | D9: =SUM('Scenario Buono'!Q5:R40) -> 61960 | E9: €
A10: Costo di erogazione degli incarichi | B10: =SUM('Scenario Prudente'!S5:S40) -> 16738.995 | C10: =SUM('Scenario Medio'!S5:S40) -> 103714.39 | D10: =SUM('Scenario Buono'!S5:S40) -> 179544.38 | E10: €
A11: Margine economico | B11: =SUM('Scenario Prudente'!T5:T40) -> -14597.239 | C11: =SUM('Scenario Medio'!T5:T40) -> 247696.45 | D11: =SUM('Scenario Buono'!T5:T40) -> 536303.69 | E11: €
A12: ROI del canale (margine / costi del canale) | B12: =IFERROR(B11/B9,0) -> -0.23559133 | C12: =IFERROR(C11/C9,0) -> 3.9976832 | D12: =IFERROR(D11/D9,0) -> 8.6556438 | E12: volte
A13: Costo di acquisizione per incarico (CAC) | B13: =IFERROR(B9/B6,0) -> 2046.0914 | C13: =IFERROR(C9/C6,0) -> 329.35981 | D13: =IFERROR(D9/D6,0) -> 191.51666 | E13: €/incarico
A14: Mese di pareggio (margine cumulato ≥ 0) | B14: =IF(MIN('Scenario Prudente'!Y5:Y40)=999,"Oltre 36 mesi",MIN('Scenario Prudente'!Y5:Y40)) -> Oltre 36 mesi | C14: =IF(MIN('Scenario Medio'!Y5:Y40)=999,"Oltre 36 mesi",MIN('Scenario Medio'!Y5:Y40)) -> 6 | D14: =IF(MIN('Scenario Buono'!Y5:Y40)=999,"Oltre 36 mesi",MIN('Scenario Buono'!Y5:Y40)) -> 3 | E14: mese n.
A15: Cassa cumulata a fine mese 36 | B15: ='Scenario Prudente'!X40 -> 15827.508 | C15: ='Scenario Medio'!X40 -> 236883.95 | D15: ='Scenario Buono'!X40 -> 512438.25 | E15: €
A17: Incarichi in più necessari per coprire i costi del 1° anno | B17: =IFERROR((SUMIFS('Scenario Prudente'!Q5:Q40,'Scenario Prudente'!B5:B40,1)+SUMIFS('Scenario Prudente'!R5:R40,'Scenario Prudente'!B5:B40,1))/Ipotesi!$B$41,0) -> 15.471236 | C17: =IFERROR((SUMIFS('Scenario Medio'!Q5:Q40,'Scenario Medio'!B5:B40,1)+SUMIFS('Scenario Medio'!R5:R40,'Scenario Medio'!B5:B40,1))/Ipotesi!$B$41,0) -> 15.471236 | D17: =IFERROR((SUMIFS('Scenario Buono'!Q5:Q40,'Scenario Buono'!B5:B40,1)+SUMIFS('Scenario Buono'!R5:R40,'Scenario Buono'!B5:B40,1))/Ipotesi!$B$41,0) -> 15.471236 | E17: n. (su margine)
A18: Stessa soglia calcolata sul solo fatturato (per confronto) | B18: =IFERROR((SUMIFS('Scenario Prudente'!Q5:Q40,'Scenario Prudente'!B5:B40,1)+SUMIFS('Scenario Prudente'!R5:R40,'Scenario Prudente'!B5:B40,1))/Ipotesi!$B$37,0) -> 10.869779 | C18: =IFERROR((SUMIFS('Scenario Medio'!Q5:Q40,'Scenario Medio'!B5:B40,1)+SUMIFS('Scenario Medio'!R5:R40,'Scenario Medio'!B5:B40,1))/Ipotesi!$B$37,0) -> 10.869779 | D18: =IFERROR((SUMIFS('Scenario Buono'!Q5:Q40,'Scenario Buono'!B5:B40,1)+SUMIFS('Scenario Buono'!R5:R40,'Scenario Buono'!B5:B40,1))/Ipotesi!$B$37,0) -> 10.869779 | E18: n. (su ricavi)
A20: 2. Dettaglio per anno
A21: Scenario Prudente | B21: Anno 1 | C21: Anno 2 | D21: Anno 3 | E21: Totale
A22: Visualizzazioni | B22: =SUMIFS('Scenario Prudente'!E5:E40,'Scenario Prudente'!B5:B40,1) -> 17500 | C22: =SUMIFS('Scenario Prudente'!E5:E40,'Scenario Prudente'!B5:B40,2) -> 27179.944 | D22: =SUMIFS('Scenario Prudente'!E5:E40,'Scenario Prudente'!B5:B40,3) -> 33974.93 | E22: =SUM(B22:D22) -> 78654.874
A23: Contatti | B23: =SUMIFS('Scenario Prudente'!F5:F40,'Scenario Prudente'!B5:B40,1) -> 35 | C23: =SUMIFS('Scenario Prudente'!F5:F40,'Scenario Prudente'!B5:B40,2) -> 54.359888 | D23: =SUMIFS('Scenario Prudente'!F5:F40,'Scenario Prudente'!B5:B40,3) -> 67.949861 | E23: =SUM(B23:D23) -> 157.30975
A24: Consulenze a pagamento | B24: =SUMIFS('Scenario Prudente'!G5:G40,'Scenario Prudente'!B5:B40,1) -> 12.25 | C24: =SUMIFS('Scenario Prudente'!G5:G40,'Scenario Prudente'!B5:B40,2) -> 19.025961 | D24: =SUMIFS('Scenario Prudente'!G5:G40,'Scenario Prudente'!B5:B40,3) -> 23.782451 | E24: =SUM(B24:D24) -> 55.058412
A25: Incarichi acquisiti | B25: =SUMIFS('Scenario Prudente'!J5:J40,'Scenario Prudente'!B5:B40,1) -> 6.7375 | C25: =SUMIFS('Scenario Prudente'!J5:J40,'Scenario Prudente'!B5:B40,2) -> 10.464279 | D25: =SUMIFS('Scenario Prudente'!J5:J40,'Scenario Prudente'!B5:B40,3) -> 13.080348 | E25: =SUM(B25:D25) -> 30.282127
A26: Incarichi persi per capacità | B26: =SUMIFS('Scenario Prudente'!K5:K40,'Scenario Prudente'!B5:B40,1) -> 0 | C26: =SUMIFS('Scenario Prudente'!K5:K40,'Scenario Prudente'!B5:B40,2) -> 0 | D26: =SUMIFS('Scenario Prudente'!K5:K40,'Scenario Prudente'!B5:B40,3) -> 0 | E26: =SUM(B26:D26) -> 0
A27: Ricavi totali (€) | B27: =SUMIFS('Scenario Prudente'!P5:P40,'Scenario Prudente'!B5:B40,1) -> 14262.062 | C27: =SUMIFS('Scenario Prudente'!P5:P40,'Scenario Prudente'!B5:B40,2) -> 22150.975 | D27: =SUMIFS('Scenario Prudente'!P5:P40,'Scenario Prudente'!B5:B40,3) -> 27688.719 | E27: =SUM(B27:D27) -> 64101.756
A28: Costi canale cassa (€) | B28: =SUMIFS('Scenario Prudente'!Q5:Q40,'Scenario Prudente'!B5:B40,1) -> 9640 | C28: =SUMIFS('Scenario Prudente'!Q5:Q40,'Scenario Prudente'!B5:B40,2) -> 7440 | D28: =SUMIFS('Scenario Prudente'!Q5:Q40,'Scenario Prudente'!B5:B40,3) -> 7440 | E28: =SUM(B28:D28) -> 24520
A29: Tempo avvocato sul canale (€) | B29: =SUMIFS('Scenario Prudente'!R5:R40,'Scenario Prudente'!B5:B40,1) -> 12480 | C29: =SUMIFS('Scenario Prudente'!R5:R40,'Scenario Prudente'!B5:B40,2) -> 12480 | D29: =SUMIFS('Scenario Prudente'!R5:R40,'Scenario Prudente'!B5:B40,3) -> 12480 | E29: =SUM(B29:D29) -> 37440
A30: Costo erogazione incarichi (€) | B30: =SUMIFS('Scenario Prudente'!S5:S40,'Scenario Prudente'!B5:B40,1) -> 4077.8719 | C30: =SUMIFS('Scenario Prudente'!S5:S40,'Scenario Prudente'!B5:B40,2) -> 5627.1658 | D30: =SUMIFS('Scenario Prudente'!S5:S40,'Scenario Prudente'!B5:B40,3) -> 7033.9572 | E30: =SUM(B30:D30) -> 16738.995
A31: Margine economico (€) | B31: =SUMIFS('Scenario Prudente'!T5:T40,'Scenario Prudente'!B5:B40,1) -> -11935.809 | C31: =SUMIFS('Scenario Prudente'!T5:T40,'Scenario Prudente'!B5:B40,2) -> -3396.1907 | D31: =SUMIFS('Scenario Prudente'!T5:T40,'Scenario Prudente'!B5:B40,3) -> 734.76157 | E31: =SUM(B31:D31) -> -14597.239
A32: Incassi (€) | B32: =SUMIFS('Scenario Prudente'!V5:V40,'Scenario Prudente'!B5:B40,1) -> 9561.2125 | C32: =SUMIFS('Scenario Prudente'!V5:V40,'Scenario Prudente'!B5:B40,2) -> 21239.622 | D32: =SUMIFS('Scenario Prudente'!V5:V40,'Scenario Prudente'!B5:B40,3) -> 26285.668 | E32: =SUM(B32:D32) -> 57086.503
A33: Flusso di cassa (€) | B33: =SUMIFS('Scenario Prudente'!W5:W40,'Scenario Prudente'!B5:B40,1) -> -4156.6594 | C33: =SUMIFS('Scenario Prudente'!W5:W40,'Scenario Prudente'!B5:B40,2) -> 8172.4567 | D33: =SUMIFS('Scenario Prudente'!W5:W40,'Scenario Prudente'!B5:B40,3) -> 11811.711 | E33: =SUM(B33:D33) -> 15827.508
A34: ROI dell'anno (margine / costi del canale) | B34: =IFERROR(B31/(B28+B29),0) -> -0.53959355 | C34: =IFERROR(C31/(C28+C29),0) -> -0.1704915 | D34: =IFERROR(D31/(D28+D29),0) -> 0.036885621 | E34: =IFERROR(E31/(E28+E29),0) -> -0.23559133
A36: Scenario Medio | B36: Anno 1 | C36: Anno 2 | D36: Anno 3 | E36: Totale
A37: Visualizzazioni | B37: =SUMIFS('Scenario Medio'!E5:E40,'Scenario Medio'!B5:B40,1) -> 52500 | C37: =SUMIFS('Scenario Medio'!E5:E40,'Scenario Medio'!B5:B40,2) -> 86992.202 | D37: =SUMIFS('Scenario Medio'!E5:E40,'Scenario Medio'!B5:B40,3) -> 121789.08 | E37: =SUM(B37:D37) -> 261281.28
A38: Contatti | B38: =SUMIFS('Scenario Medio'!F5:F40,'Scenario Medio'!B5:B40,1) -> 157.5 | C38: =SUMIFS('Scenario Medio'!F5:F40,'Scenario Medio'!B5:B40,2) -> 260.97661 | D38: =SUMIFS('Scenario Medio'!F5:F40,'Scenario Medio'!B5:B40,3) -> 365.36725 | E38: =SUM(B38:D38) -> 783.84385
A39: Consulenze a pagamento | B39: =SUMIFS('Scenario Medio'!G5:G40,'Scenario Medio'!B5:B40,1) -> 63 | C39: =SUMIFS('Scenario Medio'!G5:G40,'Scenario Medio'!B5:B40,2) -> 104.39064 | D39: =SUMIFS('Scenario Medio'!G5:G40,'Scenario Medio'!B5:B40,3) -> 146.1469 | E39: =SUM(B39:D39) -> 313.53754
A40: Incarichi acquisiti | B40: =SUMIFS('Scenario Medio'!J5:J40,'Scenario Medio'!B5:B40,1) -> 37.8 | C40: =SUMIFS('Scenario Medio'!J5:J40,'Scenario Medio'!B5:B40,2) -> 62.634385 | D40: =SUMIFS('Scenario Medio'!J5:J40,'Scenario Medio'!B5:B40,3) -> 87.68814 | E40: =SUM(B40:D40) -> 188.12253
A41: Incarichi persi per capacità | B41: =SUMIFS('Scenario Medio'!K5:K40,'Scenario Medio'!B5:B40,1) -> 0 | C41: =SUMIFS('Scenario Medio'!K5:K40,'Scenario Medio'!B5:B40,2) -> 0 | D41: =SUMIFS('Scenario Medio'!K5:K40,'Scenario Medio'!B5:B40,3) -> 0 | E41: =SUM(B41:D41) -> 0
A42: Ricavi totali (€) | B42: =SUMIFS('Scenario Medio'!P5:P40,'Scenario Medio'!B5:B40,1) -> 79443 | C42: =SUMIFS('Scenario Medio'!P5:P40,'Scenario Medio'!B5:B40,2) -> 137636.6 | D42: =SUMIFS('Scenario Medio'!P5:P40,'Scenario Medio'!B5:B40,3) -> 196291.24 | E42: =SUM(B42:D42) -> 413370.84
A43: Costi canale cassa (€) | B43: =SUMIFS('Scenario Medio'!Q5:Q40,'Scenario Medio'!B5:B40,1) -> 9640 | C43: =SUMIFS('Scenario Medio'!Q5:Q40,'Scenario Medio'!B5:B40,2) -> 7440 | D43: =SUMIFS('Scenario Medio'!Q5:Q40,'Scenario Medio'!B5:B40,3) -> 7440 | E43: =SUM(B43:D43) -> 24520
A44: Tempo avvocato sul canale (€) | B44: =SUMIFS('Scenario Medio'!R5:R40,'Scenario Medio'!B5:B40,1) -> 12480 | C44: =SUMIFS('Scenario Medio'!R5:R40,'Scenario Medio'!B5:B40,2) -> 12480 | D44: =SUMIFS('Scenario Medio'!R5:R40,'Scenario Medio'!B5:B40,3) -> 12480 | E44: =SUM(B44:D44) -> 37440
A45: Costo erogazione incarichi (€) | B45: =SUMIFS('Scenario Medio'!S5:S40,'Scenario Medio'!B5:B40,1) -> 22878.45 | C45: =SUMIFS('Scenario Medio'!S5:S40,'Scenario Medio'!B5:B40,2) -> 33681.641 | D45: =SUMIFS('Scenario Medio'!S5:S40,'Scenario Medio'!B5:B40,3) -> 47154.297 | E45: =SUM(B45:D45) -> 103714.39
A46: Margine economico (€) | B46: =SUMIFS('Scenario Medio'!T5:T40,'Scenario Medio'!B5:B40,1) -> 34444.55 | C46: =SUMIFS('Scenario Medio'!T5:T40,'Scenario Medio'!B5:B40,2) -> 84034.959 | D46: =SUMIFS('Scenario Medio'!T5:T40,'Scenario Medio'!B5:B40,3) -> 129216.94 | E46: =SUM(B46:D46) -> 247696.45
A47: Incassi (€) | B47: =SUMIFS('Scenario Medio'!V5:V40,'Scenario Medio'!B5:B40,1) -> 53069.4 | C47: =SUMIFS('Scenario Medio'!V5:V40,'Scenario Medio'!B5:B40,2) -> 129544.13 | D47: =SUMIFS('Scenario Medio'!V5:V40,'Scenario Medio'!B5:B40,3) -> 182504.81 | E47: =SUM(B47:D47) -> 365118.34
A48: Flusso di cassa (€) | B48: =SUMIFS('Scenario Medio'!W5:W40,'Scenario Medio'!B5:B40,1) -> 20550.95 | C48: =SUMIFS('Scenario Medio'!W5:W40,'Scenario Medio'!B5:B40,2) -> 88422.486 | D48: =SUMIFS('Scenario Medio'!W5:W40,'Scenario Medio'!B5:B40,3) -> 127910.51 | E48: =SUM(B48:D48) -> 236883.95
A49: ROI dell'anno (margine / costi del canale) | B49: =IFERROR(B46/(B43+B44),0) -> 1.5571677 | C49: =IFERROR(C46/(C43+C44),0) -> 4.2186225 | D49: =IFERROR(D46/(D43+D44),0) -> 6.4867943 | E49: =IFERROR(E46/(E43+E44),0) -> 3.9976832
A51: Scenario Buono | B51: Anno 1 | C51: Anno 2 | D51: Anno 3 | E51: Totale
A52: Visualizzazioni | B52: =SUMIFS('Scenario Buono'!E5:E40,'Scenario Buono'!B5:B40,1) -> 131250 | C52: =SUMIFS('Scenario Buono'!E5:E40,'Scenario Buono'!B5:B40,2) -> 226335.56 | D52: =SUMIFS('Scenario Buono'!E5:E40,'Scenario Buono'!B5:B40,3) -> 339503.33 | E52: =SUM(B52:D52) -> 697088.89
A53: Contatti | B53: =SUMIFS('Scenario Buono'!F5:F40,'Scenario Buono'!B5:B40,1) -> 459.375 | C53: =SUMIFS('Scenario Buono'!F5:F40,'Scenario Buono'!B5:B40,2) -> 792.17445 | D53: =SUMIFS('Scenario Buono'!F5:F40,'Scenario Buono'!B5:B40,3) -> 1188.2617 | E53: =SUM(B53:D53) -> 2439.8111
A54: Consulenze a pagamento | B54: =SUMIFS('Scenario Buono'!G5:G40,'Scenario Buono'!B5:B40,1) -> 206.71875 | C54: =SUMIFS('Scenario Buono'!G5:G40,'Scenario Buono'!B5:B40,2) -> 356.4785 | D54: =SUMIFS('Scenario Buono'!G5:G40,'Scenario Buono'!B5:B40,3) -> 534.71775 | E54: =SUM(B54:D54) -> 1097.915
A55: Incarichi acquisiti | B55: =SUMIFS('Scenario Buono'!J5:J40,'Scenario Buono'!B5:B40,1) -> 82.51859 | C55: =SUMIFS('Scenario Buono'!J5:J40,'Scenario Buono'!B5:B40,2) -> 120.50209 | D55: =SUMIFS('Scenario Buono'!J5:J40,'Scenario Buono'!B5:B40,3) -> 120.50209 | E55: =SUM(B55:D55) -> 323.52277
A56: Incarichi persi per capacità | B56: =SUMIFS('Scenario Buono'!K5:K40,'Scenario Buono'!B5:B40,1) -> 41.51266 | C56: =SUMIFS('Scenario Buono'!K5:K40,'Scenario Buono'!B5:B40,2) -> 93.385008 | D56: =SUMIFS('Scenario Buono'!K5:K40,'Scenario Buono'!B5:B40,3) -> 200.32856 | E56: =SUM(B56:D56) -> 335.22623
A57: Ricavi totali (€) | B57: =SUMIFS('Scenario Buono'!P5:P40,'Scenario Buono'!B5:B40,1) -> 180345.35 | C57: =SUMIFS('Scenario Buono'!P5:P40,'Scenario Buono'!B5:B40,2) -> 280819.4 | D57: =SUMIFS('Scenario Buono'!P5:P40,'Scenario Buono'!B5:B40,3) -> 316643.32 | E57: =SUM(B57:D57) -> 777808.07
A58: Costi canale cassa (€) | B58: =SUMIFS('Scenario Buono'!Q5:Q40,'Scenario Buono'!B5:B40,1) -> 9640 | C58: =SUMIFS('Scenario Buono'!Q5:Q40,'Scenario Buono'!B5:B40,2) -> 7440 | D58: =SUMIFS('Scenario Buono'!Q5:Q40,'Scenario Buono'!B5:B40,3) -> 7440 | E58: =SUM(B58:D58) -> 24520
A59: Tempo avvocato sul canale (€) | B59: =SUMIFS('Scenario Buono'!R5:R40,'Scenario Buono'!B5:B40,1) -> 12480 | C59: =SUMIFS('Scenario Buono'!R5:R40,'Scenario Buono'!B5:B40,2) -> 12480 | D59: =SUMIFS('Scenario Buono'!R5:R40,'Scenario Buono'!B5:B40,3) -> 12480 | E59: =SUM(B59:D59) -> 37440
A60: Costo erogazione incarichi (€) | B60: =SUMIFS('Scenario Buono'!S5:S40,'Scenario Buono'!B5:B40,1) -> 49944.376 | C60: =SUMIFS('Scenario Buono'!S5:S40,'Scenario Buono'!B5:B40,2) -> 64800 | D60: =SUMIFS('Scenario Buono'!S5:S40,'Scenario Buono'!B5:B40,3) -> 64800 | E60: =SUM(B60:D60) -> 179544.38
A61: Margine economico (€) | B61: =SUMIFS('Scenario Buono'!T5:T40,'Scenario Buono'!B5:B40,1) -> 108280.97 | C61: =SUMIFS('Scenario Buono'!T5:T40,'Scenario Buono'!B5:B40,2) -> 196099.4 | D61: =SUMIFS('Scenario Buono'!T5:T40,'Scenario Buono'!B5:B40,3) -> 231923.32 | E61: =SUM(B61:D61) -> 536303.69
A62: Incassi (€) | B62: =SUMIFS('Scenario Buono'!V5:V40,'Scenario Buono'!B5:B40,1) -> 125876.94 | C62: =SUMIFS('Scenario Buono'!V5:V40,'Scenario Buono'!B5:B40,2) -> 273982.36 | D62: =SUMIFS('Scenario Buono'!V5:V40,'Scenario Buono'!B5:B40,3) -> 316643.32 | E62: =SUM(B62:D62) -> 716502.63
A63: Flusso di cassa (€) | B63: =SUMIFS('Scenario Buono'!W5:W40,'Scenario Buono'!B5:B40,1) -> 66292.568 | C63: =SUMIFS('Scenario Buono'!W5:W40,'Scenario Buono'!B5:B40,2) -> 201742.36 | D63: =SUMIFS('Scenario Buono'!W5:W40,'Scenario Buono'!B5:B40,3) -> 244403.32 | E63: =SUM(B63:D63) -> 512438.25
A64: ROI dell'anno (margine / costi del canale) | B64: =IFERROR(B61/(B58+B59),0) -> 4.8951614 | C64: =IFERROR(C61/(C58+C59),0) -> 9.8443473 | D64: =IFERROR(D61/(D58+D59),0) -> 11.642737 | E64: =IFERROR(E61/(E58+E59),0) -> 8.6556438
A66: 3. Altri social (Facebook, LinkedIn, Substack, Instagram/TikTok, X) — 36 mesi
A67: Indicatore | B67: Prudente | C67: Medio | D67: Buono | E67: Unità
A68: Contatti in più dagli altri social | B68: =SUM('Scenario Prudente'!Z5:Z40) -> 47.124591 | C68: =SUM('Scenario Medio'!Z5:Z40) -> 234.84566 | D68: =SUM('Scenario Buono'!Z5:Z40) -> 731.04646 | E68: n.
A69: Incarichi in più | B69: =SUM('Scenario Prudente'!AC5:AC40) -> 9.0714838 | C69: =SUM('Scenario Medio'!AC5:AC40) -> 50.88374 | D69: =SUM('Scenario Buono'!AC5:AC40) -> 3.1007812 | E69: n.
A70: Incarichi in più persi per mancanza di capacità | B70: =SUM('Scenario Prudente'!AB5:AB40)-SUM('Scenario Prudente'!AC5:AC40) -> 0 | C70: =SUM('Scenario Medio'!AB5:AB40)-SUM('Scenario Medio'!AC5:AC40) -> 5.479218 | D70: =SUM('Scenario Buono'!AB5:AB40)-SUM('Scenario Buono'!AC5:AC40) -> 194.28176 | E70: n.
A71: Ricavi in più | B71: =SUM('Scenario Prudente'!AD5:AD40) -> 19202.682 | C71: =SUM('Scenario Medio'!AD5:AD40) -> 107853.86 | D71: =SUM('Scenario Buono'!AD5:AD40) -> 38897.102 | E71: €
A72: Costi dei social (cassa + tempo avvocato) | B72: =SUM('Scenario Prudente'!AE5:AF40) -> 47030 | C72: =SUM('Scenario Medio'!AE5:AF40) -> 47030 | D72: =SUM('Scenario Buono'!AE5:AF40) -> 47030 | E72: €
A73: Costo di erogazione degli incarichi in più | B73: =SUM('Scenario Prudente'!AG5:AG40) -> 5013.7369 | C73: =SUM('Scenario Medio'!AG5:AG40) -> 28123.199 | D73: =SUM('Scenario Buono'!AG5:AG40) -> 1876.7479 | E73: €
A74: Margine in più dai social | B74: =SUM('Scenario Prudente'!AH5:AH40) -> -32841.055 | C74: =SUM('Scenario Medio'!AH5:AH40) -> 32700.663 | D74: =SUM('Scenario Buono'!AH5:AH40) -> -10009.645 | E74: €
A75: Ritorno dei social (margine / costi dei social) | B75: =IFERROR(B74/B72,0) -> -0.69830013 | C75: =IFERROR(C74/C72,0) -> 0.69531497 | D75: =IFERROR(D74/D72,0) -> -0.21283533 | E75: volte
A76: Margine totale YouTube + social | B76: =SUM('Scenario Prudente'!T5:T40)+SUM('Scenario Prudente'!AH5:AH40) -> -47438.294 | C76: =SUM('Scenario Medio'!T5:T40)+SUM('Scenario Medio'!AH5:AH40) -> 280397.12 | D76: =SUM('Scenario Buono'!T5:T40)+SUM('Scenario Buono'!AH5:AH40) -> 526294.05 | E76: €
A77: Mese di pareggio totale | B77: =IF(MIN('Scenario Prudente'!AM5:AM40)=999,"Oltre 36 mesi",MIN('Scenario Prudente'!AM5:AM40)) -> Oltre 36 mesi | C77: =IF(MIN('Scenario Medio'!AM5:AM40)=999,"Oltre 36 mesi",MIN('Scenario Medio'!AM5:AM40)) -> 6 | D77: =IF(MIN('Scenario Buono'!AM5:AM40)=999,"Oltre 36 mesi",MIN('Scenario Buono'!AM5:AM40)) -> 4 | E77: mese n.
A78: Cassa cumulata totale a fine mese 36 | B78: ='Scenario Prudente'!AL40 -> -4558.1227 | C78: ='Scenario Medio'!AL40 -> 274102.68 | D78: ='Scenario Buono'!AL40 -> 516988.61 | E78: €
A79: Margine in più dai social – anno 1 | B79: =SUMIFS('Scenario Prudente'!AH5:AH40,'Scenario Prudente'!B5:B40,1) -> -11514.626 | C79: =SUMIFS('Scenario Medio'!AH5:AH40,'Scenario Medio'!B5:B40,1) -> 2308.9295 | D79: =SUMIFS('Scenario Buono'!AH5:AH40,'Scenario Buono'!B5:B40,1) -> -4265.533 | E79: €
A80: Margine in più dai social – anno 2 | B80: =SUMIFS('Scenario Prudente'!AH5:AH40,'Scenario Prudente'!B5:B40,2) -> -11282.857 | C80: =SUMIFS('Scenario Medio'!AH5:AH40,'Scenario Medio'!B5:B40,2) -> 13146.488 | D80: =SUMIFS('Scenario Buono'!AH5:AH40,'Scenario Buono'!B5:B40,2) -> -5545.645 | E80: €
A81: Margine in più dai social – anno 3 | B81: =SUMIFS('Scenario Prudente'!AH5:AH40,'Scenario Prudente'!B5:B40,3) -> -10043.572 | C81: =SUMIFS('Scenario Medio'!AH5:AH40,'Scenario Medio'!B5:B40,3) -> 17245.246 | D81: =SUMIFS('Scenario Buono'!AH5:AH40,'Scenario Buono'!B5:B40,3) -> -198.46748 | E81: €
A83: 4. Margine cumulato mese per mese, solo YouTube (dati del grafico)
A84: Mese n. | B84: Prudente | C84: Medio | D84: Buono
A85: 1 | B85: ='Scenario Prudente'!U5 -> -3827.6692 | C85: ='Scenario Medio'!U5 -> -3680.43 | D85: ='Scenario Buono'!U5 -> -3270.7859
A86: 2 | B86: ='Scenario Prudente'!U6 -> -5384.2108 | C86: ='Scenario Medio'!U6 -> -4765.806 | D86: ='Scenario Buono'!U6 -> -3045.3009
A87: 3 | B87: ='Scenario Prudente'!U7 -> -6782.3316 | C87: ='Scenario Medio'!U7 -> -4971.289 | D87: ='Scenario Buono'!U7 -> 67.332969
A88: 4 | B88: ='Scenario Prudente'!U8 -> -7925.0394 | C88: ='Scenario Medio'!U8 -> -3758.169 | D88: ='Scenario Buono'!U8 -> 7834.758
A89: 5 | B89: ='Scenario Prudente'!U9 -> -8695.9434 | C89: ='Scenario Medio'!U9 -> -479.994 | D89: ='Scenario Buono'!U9 -> 19843.386
A90: 6 | B90: ='Scenario Prudente'!U10 -> -8959.2544 | C90: ='Scenario Medio'!U10 -> 5617.43 | D90: ='Scenario Buono'!U10 -> 32882.327
A91: 7 | B91: ='Scenario Prudente'!U11 -> -9338.9561 | C91: ='Scenario Medio'!U11 -> 11068.402 | D91: ='Scenario Buono'!U11 -> 45685.017
A92: 8 | B92: ='Scenario Prudente'!U12 -> -9835.0486 | C92: ='Scenario Medio'!U12 -> 15872.922 | D92: ='Scenario Buono'!U12 -> 58251.458
A93: 9 | B93: ='Scenario Prudente'!U13 -> -10331.141 | C93: ='Scenario Medio'!U13 -> 20677.442 | D93: ='Scenario Buono'!U13 -> 70817.898
A94: 10 | B94: ='Scenario Prudente'!U14 -> -11176.406 | C94: ='Scenario Medio'!U14 -> 23542.606 | D94: ='Scenario Buono'!U14 -> 82675.589
A95: 11 | B95: ='Scenario Prudente'!U15 -> -11556.108 | C95: ='Scenario Medio'!U15 -> 28993.578 | D95: ='Scenario Buono'!U15 -> 95478.279
A96: 12 | B96: ='Scenario Prudente'!U16 -> -11935.809 | C96: ='Scenario Medio'!U16 -> 34444.55 | D96: ='Scenario Buono'!U16 -> 108280.97
... A120: 36 | B120: ='Scenario Prudente'!U40 -> -14597.239 | C120: ='Scenario Medio'!U40 -> 247696.45 | D120: ='Scenario Buono'!U40 -> 536303.69

Sheet Ipotesi
A1: Ipotesi del modello
A2: Modifica solo le celle in blu. Valori di esempio da sostituire con quelli dello studio.
A6: A. Parametri comuni a tutti gli scenari | B6: Valore | C6: Unità | E6: Nota / fonte
A7: Mese di avvio del canale (1 = gennaio) | B7: 11 | C7: mese | E7: Ipotesi: avvio a novembre. Serve per applicare la stagionalità corretta.
A8: Video lunghi pubblicati al mese | B8: 4 | C8: n. | E8: 1 a settimana, come da piano editoriale; gli Shorts sono ricavati dagli stessi video.
A9: Costo montaggio per video lungo (Shorts inclusi) | B9: 80 | C9: €/video | E9: Stima per montatore freelance; chiedere 2–3 preventivi.
A10: Attrezzatura (una tantum, mese 1) | B10: 1200 | C10: € | E10: Microfono, luci, smartphone/telecamera, treppiede.
A11: Pagine dedicate sul sito (una tantum, mese 1) | B11: 1000 | C11: € | E11: Una pagina per area (concorsi, disciplina, trasferimenti, salute, penale) collegata ai video.
A12: Strumenti, copertine, sottotitoli | B12: 40 | C12: €/mese | E12: Software di grafica e sottotitolazione.
A13: Budget Google Ads (facoltativo) | B13: 0 | C13: €/mese | E13: Lasciato a zero: il modello misura il solo canale organico.
A14: Ore settimanali dell'avvocato sul canale | B14: 3 | C14: ore/sett. | E14: Registrazione a blocchi + revisione testi + controllo deontologico.
A15: Costo opportunità di un'ora dell'avvocato | B15: 80 | C15: €/ora | E15: Valore di un'ora fatturabile persa. Non è un'uscita di cassa.
A16: Ore settimanali del praticante sul canale | B16: 3 | C16: ore/sett. | E16: Ricerca, scalette, risposte ai commenti.
A17: Costo orario del praticante | B17: 20 | C17: €/ora | E17: Rimborso/compenso orario stimato.
A18: Mesi di avviamento (rampa delle visualizzazioni) | B18: 6 | C18: mesi | E18: Crescita lenta all'inizio (curva quadratica): al mese 1 circa il 3% del livello a regime, al mese 3 il 25%, pieno regime alla fine del periodo.
... A27: Mese di avvio di formazione e prodotti digitali | B27: 25 | C27: mese n. | E27: Dal terzo anno: webinar, corsi per delegati, guide.
A29: B. Mix degli incarichi per area
A30: Area | B30: Quota sul totale | C30: Onorario medio (€) | D30: Ore medie per incarico | E30: Nota
A31: Concorsi (esclusioni, ricorsi TAR) | B31: 0.5 | C31: 1500 | D31: 10 | E31: Volume alto, pratiche simili e standardizzabili.
A32: Disciplinare e trasferimenti | B32: 0.3 | C32: 2200 | D32: 14 | E32: Sanzioni, trasferimenti d'autorità, L. 104, art. 42-bis.
A33: Causa di servizio e pensioni | B33: 0.15 | C33: 3000 | D33: 20 | E33: Equo indennizzo, pensione privilegiata, vittime del dovere.
A34: Penale militare | B34: 0.05 | C34: 3500 | D34: 25 | E34: Reati militari davanti ai tribunali militari.
A35: Totale / media ponderata | B35: =SUM(B31:B34) -> 1 | C35: =SUMPRODUCT(B31:B34,C31:C34) -> 2035 | D35: =SUMPRODUCT(B31:B34,D31:D34) -> 13.45 | E35: =IF(ABS(B35-1)<0.0001,"OK: il mix somma 100%","ATTENZIONE: il mix deve sommare 100%") -> OK: il mix somma 100%
A36: Valori derivati (calcolati, non modificare)
A37: Onorario medio ponderato per incarico | B37: =C35 -> 2035 | C37: €
A38: Ore medie per incarico (anno 1) | B38: =D35 -> 13.45 | C38: ore
A39: Ore medie per incarico (dal mese 13) | B39: =D35-B31*D31*B24 -> 11.95 | C39: ore
A40: Costo di erogazione per incarico (anno 1) | B40: =B38*B22 -> 605.25 | C40: €
A41: Margine di contribuzione per incarico (anno 1) | B41: =B37-B40 -> 1429.75 | C41: €
A42: Capacità: incarichi gestibili al mese (anno 1) | B42: =IFERROR(B23/B38,0) -> 8.9219331 | C42: incarichi/mese
A43: Capacità: incarichi gestibili al mese (dal mese 13) | B43: =IFERROR(B23/B39,0) -> 10.041841 | C43: incarichi/mese
A45: C. Ipotesi per scenario
A46: Ipotesi | B46: Prudente | C46: Medio | D46: Buono | E46: Nota
A47: Visualizzazioni al mese a fine avviamento | B47: 2000 | C47: 6000 | D47: 15000 | E47: Stima indicativa per un canale di nicchia; sostituire con i dati di YouTube Studio dopo 3–6 mesi.
A48: Crescita annua delle visualizzazioni dopo il 1° anno | B48: 0.25 | C48: 0.4 | D48: 0.5 | E48: I video già pubblicati continuano a portare visite: l'archivio cresce.
A49: Tasso di contatto (contatti / visualizzazioni) | B49: 0.002 | C49: 0.003 | D49: 0.0035 | E49: Ricerche con un problema urgente: tasso più alto di un canale generalista. Ipotesi da verificare.
A50: Contatti che prenotano la consulenza a pagamento | B50: 0.35 | C50: 0.4 | D50: 0.45 | E50: Gli altri ricevono solo informazioni generali.
A51: Consulenze che diventano incarico | B51: 0.55 | C51: 0.6 | D51: 0.6 | E51: Dal gestionale dello studio: incarichi / consulenze iniziali.
A52: Convenzioni con sindacati militari (numero) | B52: 0 | C52: 1 | D52: 2 | E52: Attive dal mese indicato in B26.
A53: Formazione e prodotti digitali | B53: 0 | C53: 500 | D53: 1500 | E53: €/mese dal mese indicato in B27.
A54: Conversione complessiva contatto → incarico | B54: =B50*B51 -> 0.1925 | C54: =C50*C51 -> 0.24 | D54: =D50*D51 -> 0.27 | E54: Calcolato.
A56: D. Stagionalità (bandi, visite mediche, esiti dei concorsi)
A57: Mese | B57: Indice
A58: Gennaio | B58: 0.9 | E58: Indice 1,00 = mese medio. Ipotesi generica: aggiornare con il calendario reale dei bandi seguiti.
A59: Febbraio | B59: 1
A60: Marzo | B60: 1.1
A61: Aprile | B61: 1.2
A62: Maggio | B62: 1.1
A63: Giugno | B63: 1
A64: Luglio | B64: 1
A65: Agosto | B65: 0.7
A66: Settembre | B66: 1.1
A67: Ottobre | B67: 1.1
A68: Novembre | B68: 1
A69: Dicembre | B69: 0.8
A70: Media (deve essere 1,00) | B70: =AVERAGE(B58:B69) -> 1

Sheet Social
A1: Altri social: costi e contatti per canale
A2: Ogni canale riusa i video di YouTube. Modifica le celle blu; 0 in «Attivo» esclude il canale da tutto il modello.
A4: A. Canali (modifica le celle blu)
A5: Canale | B5: Attivo (1=sì) | C5: Mese di avvio | D5: Ore social manager / sett. | E5: Ore avvocato / sett. | F5: Ore praticante / sett. | G5: Pubblicità (€/mese) | H5: Strumenti (€/mese) | I5: Contatti in più (% dei contatti YouTube) | J5: Costo cassa (€/mese) | K5: Tempo avvocato (€/mese) | L5: Costo totale (€/anno) | M5: Ruolo del canale
A6: Facebook | B6: 1 | C6: 1 | D6: 3 | E6: 0 | F6: 0 | G6: 0 | H6: 0 | I6: 0.15 | J6: =B6*(D6*52/12*$B$15+F6*52/12*$B$17+G6+H6) -> 325 | K6: =B6*E6*52/12*$B$16 -> 0 | L6: =(J6+K6)*12 -> 3900 | M6: Video e post nei gruppi militari: contatti per disciplina, trasferimenti, causa di servizio.
A7: LinkedIn | B7: 1 | C7: 4 | D7: 2 | E7: 1 | F7: 0 | G7: 0 | H7: 0 | I7: 0.05 | J7: =B7*(D7*52/12*$B$15+F7*52/12*$B$17+G7+H7) -> 216.66667 | K7: =B7*E7*52/12*$B$16 -> 346.66667 | L7: =(J7+K7)*12 -> 6760 | M7: Autorevolezza, segnalazioni da colleghi, rapporti con i sindacati militari.
A8: Substack (newsletter) | B8: 1 | C8: 1 | D8: 0 | E8: 0.25 | F8: 1 | G8: 0 | H8: 0 | I8: 0.05 | J8: =B8*(D8*52/12*$B$15+F8*52/12*$B$17+G8+H8) -> 86.666667 | K8: =B8*E8*52/12*$B$16 -> 86.666667 | L8: =(J8+K8)*12 -> 2080 | M8: Newsletter ogni 2 settimane dalle scalette dei video: pubblico di proprietà dello studio.
A9: Instagram e TikTok | B9: 1 | C9: 1 | D9: 1 | E9: 0 | F9: 0 | G9: 0 | H9: 0 | I9: 0.05 | J9: =B9*(D9*52/12*$B$15+F9*52/12*$B$17+G9+H9) -> 108.33333 | K9: =B9*E9*52/12*$B$16 -> 0 | L9: =(J9+K9)*12 -> 1300 | M9: Gli stessi Shorts di YouTube per i candidati ai concorsi (18–30 anni).
A10: X | B10: 1 | C10: 1 | D10: 1 | E10: 0 | F10: 0 | G10: 0 | H10: 0 | I10: 0 | J10: =B10*(D10*52/12*$B$15+F10*52/12*$B$17+G10+H10) -> 108.33333 | K10: =B10*E10*52/12*$B$16 -> 0 | L10: =(J10+K10)*12 -> 1300 | M10: Giornalisti e dibattito sulla Difesa: visibilità, quasi nessun cliente.
A11: Strumenti comuni | B11: 1 | C11: 1 | D11: 0 | E11: 0 | F11: 0 | G11: 0 | H11: 75 | I11: 0 | J11: =B11*(D11*52/12*$B$15+F11*52/12*$B$17+G11+H11) -> 75 | K11: =B11*E11*52/12*$B$16 -> 0 | L11: =(J11+K11)*12 -> 900 | M11: Programmazione dei post, grafica, monitoraggio dei concorrenti.
A12: Totale canali attivi | I12: =SUMPRODUCT(B6:B11,I6:I11) -> 0.3 | J12: =SUM(J6:J11) -> 920 | K12: =SUM(K6:K11) -> 433.33333 | L12: =SUM(L6:L11) -> 16240
A15: Costo orario social manager (freelance) | B15: 25 | D15: Le percentuali di contatti in più sono stime da verificare dopo 3–6 mesi con i dati di ogni canale (modulo «come ci ha conosciuto?»).
A16: Costo orario avvocato | B16: =Ipotesi!B15 -> 80
A17: Costo orario praticante | B17: =Ipotesi!B17 -> 20
A19: B. Valutazione per canale (scenario medio, 2° anno)
A20: Canale | B20: Costo annuo (€) | D20: Contatti in più all'anno | E20: Costo per contatto (€) | F20: Incarichi in più all'anno | G20: Margine stimato (€) | H20: Margine − costo (€) | I20: Giudizio
A21: =A6 -> Facebook | B21: =L6 -> 3900 | D21: =B6*I6*SUMIFS('Scenario Medio'!$F$5:$F$40,'Scenario Medio'!$B$5:$B$40,2) -> 39.146491 | E21: =IF(D21=0,"-",B21/D21) -> 99.625788 | F21: =D21*Ipotesi!$C$54 -> 9.3951578 | G21: =F21*Ipotesi!$B$41 -> 13432.727 | H21: =G21-B21 -> 9532.7269 | I21: =IF(B21=0,"Non attivo",IF(G21>=1.5*B21,"Conviene",IF(G21>=B21,"In pareggio","Non si ripaga da solo"))) -> Conviene
A22: =A7 -> LinkedIn | B22: =L7 -> 6760 | D22: =B7*I7*SUMIFS('Scenario Medio'!$F$5:$F$40,'Scenario Medio'!$B$5:$B$40,2) -> 13.04883 | E22: =IF(D22=0,"-",B22/D22) -> 518.0541 | F22: =D22*Ipotesi!$C$54 -> 3.1317193 | G22: =F22*Ipotesi!$B$41 -> 4477.5756 | H22: =G22-B22 -> -2282.4244 | I22: =IF(B22=0,"Non attivo",IF(G22>=1.5*B22,"Conviene",IF(G22>=B22,"In pareggio","Non si ripaga da solo"))) -> Non si ripaga da solo
A23: =A8 -> Substack (newsletter) | B23: =L8 -> 2080 | D23: =B8*I8*SUMIFS('Scenario Medio'!$F$5:$F$40,'Scenario Medio'!$B$5:$B$40,2) -> 13.04883 | E23: =IF(D23=0,"-",B23/D23) -> 159.40126 | F23: =D23*Ipotesi!$C$54 -> 3.1317193 | G23: =F23*Ipotesi!$B$41 -> 4477.5756 | H23: =G23-B23 -> 2397.5756 | I23: =IF(B23=0,"Non attivo",IF(G23>=1.5*B23,"Conviene",IF(G23>=B23,"In pareggio","Non si ripaga da solo"))) -> Conviene
A24: =A9 -> Instagram e TikTok | B24: =L9 -> 1300 | D24: =B9*I9*SUMIFS('Scenario Medio'!$F$5:$F$40,'Scenario Medio'!$B$5:$B$40,2) -> 13.04883 | E24: =IF(D24=0,"-",B24/D24) -> 99.625788 | F24: =D24*Ipotesi!$C$54 -> 3.1317193 | G24: =F24*Ipotesi!$B$41 -> 4477.5756 | H24: =G24-B24 -> 3177.5756 | I24: =IF(B24=0,"Non attivo",IF(G24>=1.5*B24,"Conviene",IF(G24>=B24,"In pareggio","Non si ripaga da solo"))) -> Conviene
A25: =A10 -> X | B25: =L10 -> 1300 | D25: =B10*I10*SUMIFS('Scenario Medio'!$F$5:$F$40,'Scenario Medio'!$B$5:$B$40,2) -> 0 | E25: =IF(D25=0,"-",B25/D25) -> - | F25: =D25*Ipotesi!$C$54 -> 0 | G25: =F25*Ipotesi!$B$41 -> 0 | H25: =G25-B25 -> -1300 | I25: =IF(B25=0,"Non attivo",IF(G25>=1.5*B25,"Conviene",IF(G25>=B25,"In pareggio","Non si ripaga da solo"))) -> Non si ripaga da solo
A26: =A11 -> Strumenti comuni | B26: =L11 -> 900 | D26: =B11*I11*SUMIFS('Scenario Medio'!$F$5:$F$40,'Scenario Medio'!$B$5:$B$40,2) -> 0 | E26: =IF(D26=0,"-",B26/D26) -> - | F26: =D26*Ipotesi!$C$54 -> 0 | G26: =F26*Ipotesi!$B$41 -> 0 | H26: =G26-B26 -> -900 | I26: Costo comune
A27: Totale | B27: =SUM(B21:B26) -> 16240 | D27: =SUM(D21:D26) -> 78.292982 | E27: =IF(D27=0,"-",B27/D27) -> 207.426 | F27: =SUM(F21:F26) -> 18.790316 | G27: =SUM(G21:G26) -> 26865.454 | H27: =SUM(H21:H26) -> 10625.454 | I27: =IF(G27>=1.5*B27,"Conviene",IF(G27>=B27,"In pareggio","Non si ripaga")) -> Conviene
A28: Stima senza limite di capacità; nei fogli di scenario gli incarichi in più sono limitati dalle ore disponibili dello studio.
A30: C. Livelli di presenza a confronto (costo annuo a regime)
A31: Livello | B31: Costo annuo (€) | D31: Costo in più del solo YouTube (€) | E31: Incarichi in più necessari all'anno | I31: Cosa comprende
A32: A. Solo YouTube | B32: =SUMIFS('Scenario Medio'!$Q$5:$Q$40,'Scenario Medio'!$B$5:$B$40,2)+SUMIFS('Scenario Medio'!$R$5:$R$40,'Scenario Medio'!$B$5:$B$40,2) -> 19920 | D32: =B32-$B$32 -> 0 | E32: =IFERROR(D32/Ipotesi!$B$41,0) -> 0 | I32: 1 video + 3 Shorts a settimana (piano attuale).
A33: B. Multicanale (consigliato) | B33: =B32+L12 -> 36160 | D33: =B33-$B$32 -> 16240 | E33: =IFERROR(D33/Ipotesi!$B$41,0) -> 11.358629 | I33: YouTube + i canali attivi della tabella A, tutti alimentati dagli stessi video.
A34: C. Primi nella nicchia | B34: 80000 | D34: =B34-$B$32 -> 60080 | E34: =IFERROR(D34/Ipotesi!$B$41,0) -> 42.021332 | I34: B + 2 video a settimana, pubblicità a pagamento, monitoraggio concorrenti, social manager quasi a metà tempo (stima €70–90.000).
A35: D. Primi su tutto, con agenzia | B35: 120000 | D35: =B35-$B$32 -> 100080 | E35: =IFERROR(D35/Ipotesi!$B$41,0) -> 69.998251 | I35: Agenzia completa e pubblicità su tutti i canali (stima da €120.000 in su).

Sheet Scenario Prudente
A1: Scenario Prudente — modello mensile su 36 mesi
A2: Calcolato dalle ipotesi: non modificare. Valori in euro, al netto di IVA, Cassa Forense e imposte.
A4: Mese n. | B4: Anno | C4: Mese calendario | D4: Stagionalità | E4: Visualizzazioni | F4: Contatti | G4: Consulenze a pagamento | H4: Incarichi richiesti | I4: Capacità (incarichi) | J4: Incarichi acquisiti | K4: Incarichi persi per capacità | L4: Ricavi incarichi (€) | M4: Ricavi consulenze (€) | N4: Ricavi convenzioni (€) | O4: Ricavi formazione (€) | P4: Ricavi totali (€) | Q4: Costi canale cassa (€) | R4: Tempo avvocato canale (€) | S4: Costo erogazione incarichi (€) | T4: Margine economico (€) | U4: Margine cumulato (€) | V4: Incassi (€) | W4: Flusso di cassa (€) | X4: Cassa cumulata (€) | Y4: Aiuto: mese di pareggio | Z4: Contatti da altri social | AA4: Consulenze da altri social | AB4: Incarichi social richiesti | AC4: Incarichi social acquisiti | AD4: Ricavi da altri social (€) | AE4: Costi social cassa (€) | AF4: Tempo avvocato social (€) | AG4: Costo erogazione social (€) | AH4: Margine altri social (€) | AI4: Margine social cumulato (€) | AJ4: Margine totale cumulato (€) | AK4: Incassi da altri social (€) | AL4: Cassa cumulata totale (€) | AM4: Aiuto: pareggio totale
A5: 1 | B5: =INT((A5-1)/12)+1 -> 1 | C5: =MOD(Ipotesi!$B$7-1+A5-1,12)+1 -> 11 | D5: =INDEX(Ipotesi!$B$58:$B$69,C5) -> 1 | E5: =Ipotesi!$B$47*MIN(1,(A5/Ipotesi!$B$18)^2)*(1+Ipotesi!$B$48)^(MAX(0,A5-12)/12)*D5 -> 55.555556 | F5: =E5*Ipotesi!$B$49 -> 0.11111111 | G5: =F5*Ipotesi!$B$50 -> 0.038888889 | H5: =G5*Ipotesi!$B$51 -> 0.021388889 | I5: =IF(A5<=12,Ipotesi!$B$42,Ipotesi!$B$43) -> 8.9219331 | J5: =MIN(H5,I5) -> 0.021388889 | K5: =H5-J5 -> 0 | L5: =J5*Ipotesi!$B$37 -> 43.526389 | M5: =(G5-J5)*Ipotesi!$B$19 -> 1.75 | N5: =IF(A5>=Ipotesi!$B$26,Ipotesi!$B$52*Ipotesi!$B$25/12,0) -> 0 | O5: =IF(A5>=Ipotesi!$B$27,Ipotesi!$B$53,0) -> 0 | P5: =SUM(L5:O5) -> 45.276389 | Q5: =IF(A5=1,Ipotesi!$B$10+Ipotesi!$B$11,0)+Ipotesi!$B$8*Ipotesi!$B$9+Ipotesi!$B$12+Ipotesi!$B$13+Ipotesi!$B$16*52/12*Ipotesi!$B$17 -> 2820 | R5: =Ipotesi!$B$14*52/12*Ipotesi!$B$15 -> 1040 | S5: =J5*IF(A5<=12,Ipotesi!$B$38,Ipotesi!$B$39)*Ipotesi!$B$22 -> 12.945625 | T5: =P5-Q5-R5-S5 -> -3827.6692 | U5: =T5 -> -3827.6692 | V5: =L5*Ipotesi!$B$20+IF(A5>Ipotesi!$B$21,INDEX($L$5:$L$40,A5-Ipotesi!$B$21)*(1-Ipotesi!$B$20),0)+M5+N5+O5 -> 23.513194 | W5: =V5-Q5-S5 -> -2809.4324 | X5: =W5 -> -2809.4324 | Y5: =IF(U5>=0,A5,999) -> 999 | Z5: =F5*SUMPRODUCT((Social!$C$6:$C$11<=A5)*Social!$B$6:$B$11*Social!$I$6:$I$11) -> 0.027777778 | AA5: =Z5*Ipotesi!$B$50 -> 0.0097222222 | AB5: =AA5*Ipotesi!$B$51 -> 0.0053472222 | AC5: =MIN(AB5,MAX(0,I5-J5)) -> 0.0053472222 | AD5: =AC5*Ipotesi!$B$37+(AA5-AC5)*Ipotesi!$B$19 -> 11.319097 | AE5: =SUMPRODUCT((Social!$C$6:$C$11<=A5)*Social!$J$6:$J$11) -> 703.33333 | AF5: =SUMPRODUCT((Social!$C$6:$C$11<=A5)*Social!$K$6:$K$11) -> 86.666667 | AG5: =AC5*IF(A5<=12,Ipotesi!$B$38,Ipotesi!$B$39)*Ipotesi!$B$22 -> 3.2364062 | AH5: =AD5-AE5-AF5-AG5 -> -781.91731 | AI5: =AH5 -> -781.91731 | AJ5: =U5+AI5 -> -4609.5865 | AK5: =AC5*Ipotesi!$B$37*Ipotesi!$B$20+IF(A5>Ipotesi!$B$21,INDEX($AC$5:$AC$40,A5-Ipotesi!$B$21)*Ipotesi!$B$37*(1-Ipotesi!$B$20),0)+(AA5-AC5)*Ipotesi!$B$19 -> 5.8782986 | AL5: =X5+SUM($AK$5:AK5)-SUM($AE$5:AE5)-SUM($AG$5:AG5) -> -3510.1239 | AM5: =IF(AJ5>=0,A5,999) -> 999
A6: 2 | B6: =INT((A6-1)/12)+1 -> 1 | C6: =MOD(Ipotesi!$B$7-1+A6-1,12)+1 -> 12 | D6: =INDEX(Ipotesi!$B$58:$B$69,C6) -> 0.8 | E6: =Ipotesi!$B$47*MIN(1,(A6/Ipotesi!$B$18)^2)*(1+Ipotesi!$B$48)^(MAX(0,A6-12)/12)*D6 -> 177.77778 | F6: =E6*Ipotesi!$B$49 -> 0.35555556 | G6: =F6*Ipotesi!$B$50 -> 0.12444444 | H6: =G6*Ipotesi!$B$51 -> 0.068444444 | I6: =IF(A6<=12,Ipotesi!$B$42,Ipotesi!$B$43) -> 8.9219331 | J6: =MIN(H6,I6) -> 0.068444444 | K6: =H6-J6 -> 0 | L6: =J6*Ipotesi!$B$37 -> 139.28444 | M6: =(G6-J6)*Ipotesi!$B$19 -> 5.6 | N6: =IF(A6>=Ipotesi!$B$26,Ipotesi!$B$52*Ipotesi!$B$25/12,0) -> 0 | O6: =IF(A6>=Ipotesi!$B$27,Ipotesi!$B$53,0) -> 0 | P6: =SUM(L6:O6) -> 144.88444 | Q6: =IF(A6=1,Ipotesi!$B$10+Ipotesi!$B$11,0)+Ipotesi!$B$8*Ipotesi!$B$9+Ipotesi!$B$12+Ipotesi!$B$13+Ipotesi!$B$16*52/12*Ipotesi!$B$17 -> 620 | R6: =Ipotesi!$B$14*52/12*Ipotesi!$B$15 -> 1040 | S6: =J6*IF(A6<=12,Ipotesi!$B$38,Ipotesi!$B$39)*Ipotesi!$B$22 -> 41.426 | T6: =P6-Q6-R6-S6 -> -1556.5416 | U6: =U5+T6 -> -5384.2108 | V6: =L6*Ipotesi!$B$20+IF(A6>Ipotesi!$B$21,INDEX($L$5:$L$40,A6-Ipotesi!$B$21)*(1-Ipotesi!$B$20),0)+M6+N6+O6 -> 75.242222 | W6: =V6-Q6-S6 -> -586.18378 | X6: =X5+W6 -> -3395.6162 | Y6: =IF(U6>=0,A6,999) -> 999 | Z6: =F6*SUMPRODUCT((Social!$C$6:$C$11<=A6)*Social!$B$6:$B$11*Social!$I$6:$I$11) -> 0.088888889 | AA6: =Z6*Ipotesi!$B$50 -> 0.031111111 | AB6: =AA6*Ipotesi!$B$51 -> 0.017111111 | AC6: =MIN(AB6,MAX(0,I6-J6)) -> 0.017111111 | AD6: =AC6*Ipotesi!$B$37+(AA6-AC6)*Ipotesi!$B$19 -> 36.221111 | AE6: =SUMPRODUCT((Social!$C$6:$C$11<=A6)*Social!$J$6:$J$11) -> 703.33333 | AF6: =SUMPRODUCT((Social!$C$6:$C$11<=A6)*Social!$K$6:$K$11) -> 86.666667 | AG6: =AC6*IF(A6<=12,Ipotesi!$B$38,Ipotesi!$B$39)*Ipotesi!$B$22 -> 10.3565 | AH6: =AD6-AE6-AF6-AG6 -> -764.13539 | AI6: =AI5+AH6 -> -1546.0527 | AJ6: =U6+AI6 -> -6930.2635 | AK6: =AC6*Ipotesi!$B$37*Ipotesi!$B$20+IF(A6>Ipotesi!$B$21,INDEX($AC$5:$AC$40,A6-Ipotesi!$B$21)*Ipotesi!$B$37*(1-Ipotesi!$B$20),0)+(AA6-AC6)*Ipotesi!$B$19 -> 18.810556 | AL6: =X6+SUM($AK$5:AK6)-SUM($AE$5:AE6)-SUM($AG$5:AG6) -> -4791.1869 | AM6: =IF(AJ6>=0,A6,999) -> 999
A7: 3 | B7: =INT((A7-1)/12)+1 -> 1 | C7: =MOD(Ipotesi!$B$7-1+A7-1,12)+1 -> 1 | D7: =INDEX(Ipotesi!$B$58:$B$69,C7) -> 0.9 | E7: =Ipotesi!$B$47*MIN(1,(A7/Ipotesi!$B$18)^2)*(1+Ipotesi!$B$48)^(MAX(0,A7-12)/12)*D7 -> 450 | F7: =E7*Ipotesi!$B$49 -> 0.9 | G7: =F7*Ipotesi!$B$50 -> 0.315 | H7: =G7*Ipotesi!$B$51 -> 0.17325 | I7: =IF(A7<=12,Ipotesi!$B$42,Ipotesi!$B$43) -> 8.9219331 | J7: =MIN(H7,I7) -> 0.17325 | K7: =H7-J7 -> 0 | L7: =J7*Ipotesi!$B$37 -> 352.56375 | M7: =(G7-J7)*Ipotesi!$B$19 -> 14.175 | N7: =IF(A7>=Ipotesi!$B$26,Ipotesi!$B$52*Ipotesi!$B$25/12,0) -> 0 | O7: =IF(A7>=Ipotesi!$B$27,Ipotesi!$B$53,0) -> 0 | P7: =SUM(L7:O7) -> 366.73875 | Q7: =IF(A7=1,Ipotesi!$B$10+Ipotesi!$B$11,0)+Ipotesi!$B$8*Ipotesi!$B$9+Ipotesi!$B$12+Ipotesi!$B$13+Ipotesi!$B$16*52/12*Ipotesi!$B$17 -> 620 | R7: =Ipotesi!$B$14*52/12*Ipotesi!$B$15 -> 1040 | S7: =J7*IF(A7<=12,Ipotesi!$B$38,Ipotesi!$B$39)*Ipotesi!$B$22 -> 104.85956 | T7: =P7-Q7-R7-S7 -> -1398.1208 | U7: =U6+T7 -> -6782.3316 | V7: =L7*Ipotesi!$B$20+IF(A7>Ipotesi!$B$21,INDEX($L$5:$L$40,A7-Ipotesi!$B$21)*(1-Ipotesi!$B$20),0)+M7+N7+O7 -> 190.45687 | W7: =V7-Q7-S7 -> -534.40269 | X7: =X6+W7 -> -3930.0189 | Y7: =IF(U7>=0,A7,999) -> 999 | Z7: =F7*SUMPRODUCT((Social!$C$6:$C$11<=A7)*Social!$B$6:$B$11*Social!$I$6:$I$11) -> 0.225 | AA7: =Z7*Ipotesi!$B$50 -> 0.07875 | AB7: =AA7*Ipotesi!$B$51 -> 0.0433125 | AC7: =MIN(AB7,MAX(0,I7-J7)) -> 0.0433125 | AD7: =AC7*Ipotesi!$B$37+(AA7-AC7)*Ipotesi!$B$19 -> 91.684687 | AE7: =SUMPRODUCT((Social!$C$6:$C$11<=A7)*Social!$J$6:$J$11) -> 703.33333 | AF7: =SUMPRODUCT((Social!$C$6:$C$11<=A7)*Social!$K$6:$K$11) -> 86.666667 | AG7: =AC7*IF(A7<=12,Ipotesi!$B$38,Ipotesi!$B$39)*Ipotesi!$B$22 -> 26.214891 | AH7: =AD7-AE7-AF7-AG7 -> -724.5302 | AI7: =AI6+AH7 -> -2270.5829 | AJ7: =U7+AI7 -> -9052.9145 | AK7: =AC7*Ipotesi!$B$37*Ipotesi!$B$20+IF(A7>Ipotesi!$B$21,INDEX($AC$5:$AC$40,A7-Ipotesi!$B$21)*Ipotesi!$B$37*(1-Ipotesi!$B$20),0)+(AA7-AC7)*Ipotesi!$B$19 -> 47.614219 | AL7: =X7+SUM($AK$5:AK7)-SUM($AE$5:AE7)-SUM($AG$5:AG7) -> -6007.5236 | AM7: =IF(AJ7>=0,A7,999) -> 999
A8: 4 | B8: =INT((A8-1)/12)+1 -> 1 | C8: =MOD(Ipotesi!$B$7-1+A8-1,12)+1 -> 2 | D8: =INDEX(Ipotesi!$B$58:$B$69,C8) -> 1 | E8: =Ipotesi!$B$47*MIN(1,(A8/Ipotesi!$B$18)^2)*(1+Ipotesi!$B$48)^(MAX(0,A8-12)/12)*D8 -> 888.88889 | F8: =E8*Ipotesi!$B$49 -> 1.7777778 | G8: =F8*Ipotesi!$B$50 -> 0.62222222 | H8: =G8*Ipotesi!$B$51 -> 0.34222222 | I8: =IF(A8<=12,Ipotesi!$B$42,Ipotesi!$B$43) -> 8.9219331 | J8: =MIN(H8,I8) -> 0.34222222 | K8: =H8-J8 -> 0 | L8: =J8*Ipotesi!$B$37 -> 696.42222 | M8: =(G8-J8)*Ipotesi!$B$19 -> 28 | N8: =IF(A8>=Ipotesi!$B$26,Ipotesi!$B$52*Ipotesi!$B$25/12,0) -> 0 | O8: =IF(A8>=Ipotesi!$B$27,Ipotesi!$B$53,0) -> 0 | P8: =SUM(L8:O8) -> 724.42222 | Q8: =IF(A8=1,Ipotesi!$B$10+Ipotesi!$B$11,0)+Ipotesi!$B$8*Ipotesi!$B$9+Ipotesi!$B$12+Ipotesi!$B$13+Ipotesi!$B$16*52/12*Ipotesi!$B$17 -> 620 | R8: =Ipotesi!$B$14*52/12*Ipotesi!$B$15 -> 1040 | S8: =J8*IF(A8<=12,Ipotesi!$B$38,Ipotesi!$B$39)*Ipotesi!$B$22 -> 207.13 | T8: =P8-Q8-R8-S8 -> -1142.7078 | U8: =U7+T8 -> -7925.0394 | V8: =L8*Ipotesi!$B$20+IF(A8>Ipotesi!$B$21,INDEX($L$5:$L$40,A8-Ipotesi!$B$21)*(1-Ipotesi!$B$20),0)+M8+N8+O8 -> 376.21111 | W8: =V8-Q8-S8 -> -450.91889 | X8: =X7+W8 -> -4380.9378 | Y8: =IF(U8>=0,A8,999) -> 999 | Z8: =F8*SUMPRODUCT((Social!$C$6:$C$11<=A8)*Social!$B$6:$B$11*Social!$I$6:$I$11) -> 0.53333333 | AA8: =Z8*Ipotesi!$B$50 -> 0.18666667 | AB8: =AA8*Ipotesi!$B$51 -> 0.10266667 | AC8: =MIN(AB8,MAX(0,I8-J8)) -> 0.10266667 | AD8: =AC8*Ipotesi!$B$37+(AA8-AC8)*Ipotesi!$B$19 -> 217.32667 | AE8: =SUMPRODUCT((Social!$C$6:$C$11<=A8)*Social!$J$6:$J$11) -> 920 | AF8: =SUMPRODUCT((Social!$C$6:$C$11<=A8)*Social!$K$6:$K$11) -> 433.33333 | AG8: =AC8*IF(A8<=12,Ipotesi!$B$38,Ipotesi!$B$39)*Ipotesi!$B$22 -> 62.139 | AH8: =AD8-AE8-AF8-AG8 -> -1198.1457 | AI8: =AI7+AH8 -> -3468.7286 | AJ8: =U8+AI8 -> -11393.768 | AK8: =AC8*Ipotesi!$B$37*Ipotesi!$B$20+IF(A8>Ipotesi!$B$21,INDEX($AC$5:$AC$40,A8-Ipotesi!$B$21)*Ipotesi!$B$37*(1-Ipotesi!$B$20),0)+(AA8-AC8)*Ipotesi!$B$19 -> 112.86333 | AL8: =X8+SUM($AK$5:AK8)-SUM($AE$5:AE8)-SUM($AG$5:AG8) -> -7327.7182 | AM8: =IF(AJ8>=0,A8,999) -> 999
A9: 5 | B9: =INT((A9-1)/12)+1 -> 1 | C9: =MOD(Ipotesi!$B$7-1+A9-1,12)+1 -> 3 | D9: =INDEX(Ipotesi!$B$58:$B$69,C9) -> 1.1 | E9: =Ipotesi!$B$47*MIN(1,(A9/Ipotesi!$B$18)^2)*(1+Ipotesi!$B$48)^(MAX(0,A9-12)/12)*D9 -> 1527.7778 | F9: =E9*Ipotesi!$B$49 -> 3.0555556 | G9: =F9*Ipotesi!$B$50 -> 1.0694444 | H9: =G9*Ipotesi!$B$51 -> 0.58819444 | I9: =IF(A9<=12,Ipotesi!$B$42,Ipotesi!$B$43) -> 8.9219331 | J9: =MIN(H9,I9) -> 0.58819444 | K9: =H9-J9 -> 0 | L9: =J9*Ipotesi!$B$37 -> 1196.9757 | M9: =(G9-J9)*Ipotesi!$B$19 -> 48.125 | N9: =IF(A9>=Ipotesi!$B$26,Ipotesi!$B$52*Ipotesi!$B$25/12,0) -> 0 | O9: =IF(A9>=Ipotesi!$B$27,Ipotesi!$B$53,0) -> 0 | P9: =SUM(L9:O9) -> 1245.1007 | Q9: =IF(A9=1,Ipotesi!$B$10+Ipotesi!$B$11,0)+Ipotesi!$B$8*Ipotesi!$B$9+Ipotesi!$B$12+Ipotesi!$B$13+Ipotesi!$B$16*52/12*Ipotesi!$B$17 -> 620 | R9: =Ipotesi!$B$14*52/12*Ipotesi!$B$15 -> 1040 | S9: =J9*IF(A9<=12,Ipotesi!$B$38,Ipotesi!$B$39)*Ipotesi!$B$22 -> 356.00469 | T9: =P9-Q9-R9-S9 -> -770.90399 | U9: =U8+T9 -> -8695.9434 | V9: =L9*Ipotesi!$B$20+IF(A9>Ipotesi!$B$21,INDEX($L$5:$L$40,A9-Ipotesi!$B$21)*(1-Ipotesi!$B$20),0)+M9+N9+O9 -> 646.61285 | W9: =V9-Q9-S9 -> -329.39184 | X9: =X8+W9 -> -4710.3296 | Y9: =IF(U9>=0,A9,999) -> 999 | Z9: =F9*SUMPRODUCT((Social!$C$6:$C$11<=A9)*Social!$B$6:$B$11*Social!$I$6:$I$11) -> 0.91666667 | AA9: =Z9*Ipotesi!$B$50 -> 0.32083333 | AB9: =AA9*Ipotesi!$B$51 -> 0.17645833 | AC9: =MIN(AB9,MAX(0,I9-J9)) -> 0.17645833 | AD9: =AC9*Ipotesi!$B$37+(AA9-AC9)*Ipotesi!$B$19 -> 373.53021 | AE9: =SUMPRODUCT((Social!$C$6:$C$11<=A9)*Social!$J$6:$J$11) -> 920 | AF9: =SUMPRODUCT((Social!$C$6:$C$11<=A9)*Social!$K$6:$K$11) -> 433.33333 | AG9: =AC9*IF(A9<=12,Ipotesi!$B$38,Ipotesi!$B$39)*Ipotesi!$B$22 -> 106.80141 | AH9: =AD9-AE9-AF9-AG9 -> -1086.6045 | AI9: =AI8+AH9 -> -4555.3331 | AJ9: =U9+AI9 -> -13251.276 | AK9: =AC9*Ipotesi!$B$37*Ipotesi!$B$20+IF(A9>Ipotesi!$B$21,INDEX($AC$5:$AC$40,A9-Ipotesi!$B$21)*Ipotesi!$B$37*(1-Ipotesi!$B$20),0)+(AA9-AC9)*Ipotesi!$B$19 -> 193.98385 | AL9: =X9+SUM($AK$5:AK9)-SUM($AE$5:AE9)-SUM($AG$5:AG9) -> -8489.9276 | AM9: =IF(AJ9>=0,A9,999) -> 999
A10: 6 | B10: =INT((A10-1)/12)+1 -> 1 | C10: =MOD(Ipotesi!$B$7-1+A10-1,12)+1 -> 4 | D10: =INDEX(Ipotesi!$B$58:$B$69,C10) -> 1.2 | E10: =Ipotesi!$B$47*MIN(1,(A10/Ipotesi!$B$18)^2)*(1+Ipotesi!$B$48)^(MAX(0,A10-12)/12)*D10 -> 2400 | F10: =E10*Ipotesi!$B$49 -> 4.8 | G10: =F10*Ipotesi!$B$50 -> 1.68 | H10: =G10*Ipotesi!$B$51 -> 0.924 | I10: =IF(A10<=12,Ipotesi!$B$42,Ipotesi!$B$43) -> 8.9219331 | J10: =MIN(H10,I10) -> 0.924 | K10: =H10-J10 -> 0 | L10: =J10*Ipotesi!$B$37 -> 1880.34 | M10: =(G10-J10)*Ipotesi!$B$19 -> 75.6 | N10: =IF(A10>=Ipotesi!$B$26,Ipotesi!$B$52*Ipotesi!$B$25/12,0) -> 0 | O10: =IF(A10>=Ipotesi!$B$27,Ipotesi!$B$53,0) -> 0 | P10: =SUM(L10:O10) -> 1955.94 | Q10: =IF(A10=1,Ipotesi!$B$10+Ipotesi!$B$11,0)+Ipotesi!$B$8*Ipotesi!$B$9+Ipotesi!$B$12+Ipotesi!$B$13+Ipotesi!$B$16*52/12*Ipotesi!$B$17 -> 620 | R10: =Ipotesi!$B$14*52/12*Ipotesi!$B$15 -> 1040 | S10: =J10*IF(A10<=12,Ipotesi!$B$38,Ipotesi!$B$39)*Ipotesi!$B$22 -> 559.251 | T10: =P10-Q10-R10-S10 -> -263.311 | U10: =U9+T10 -> -8959.2544 | V10: =L10*Ipotesi!$B$20+IF(A10>Ipotesi!$B$21,INDEX($L$5:$L$40,A10-Ipotesi!$B$21)*(1-Ipotesi!$B$20),0)+M10+N10+O10 -> 1015.77 | W10: =V10-Q10-S10 -> -163.481 | X10: =X9+W10 -> -4873.8106 | Y10: =IF(U10>=0,A10,999) -> 999 | Z10: =F10*SUMPRODUCT((Social!$C$6:$C$11<=A10)*Social!$B$6:$B$11*Social!$I$6:$I$11) -> 1.44 | AA10: =Z10*Ipotesi!$B$50 -> 0.504 | AB10: =AA10*Ipotesi!$B$51 -> 0.2772 | AC10: =MIN(AB10,MAX(0,I10-J10)) -> 0.2772 | AD10: =AC10*Ipotesi!$B$37+(AA10-AC10)*Ipotesi!$B$19 -> 586.782 | AE10: =SUMPRODUCT((Social!$C$6:$C$11<=A10)*Social!$J$6:$J$11) -> 920 | AF10: =SUMPRODUCT((Social!$C$6:$C$11<=A10)*Social!$K$6:$K$11) -> 433.33333 | AG10: =AC10*IF(A10<=12,Ipotesi!$B$38,Ipotesi!$B$39)*Ipotesi!$B$22 -> 167.7753 | AH10: =AD10-AE10-AF10-AG10 -> -934.32663 | AI10: =AI9+AH10 -> -5489.6597 | AJ10: =U10+AI10 -> -14448.914 | AK10: =AC10*Ipotesi!$B$37*Ipotesi!$B$20+IF(A10>Ipotesi!$B$21,INDEX($AC$5:$AC$40,A10-Ipotesi!$B$21)*Ipotesi!$B$37*(1-Ipotesi!$B$20),0)+(AA10-AC10)*Ipotesi!$B$19 -> 304.731 | AL10: =X10+SUM($AK$5:AK10)-SUM($AE$5:AE10)-SUM($AG$5:AG10) -> -9436.4529 | AM10: =IF(AJ10>=0,A10,999) -> 999
A11: 7 | B11: =INT((A11-1)/12)+1 -> 1 | C11: =MOD(Ipotesi!$B$7-1+A11-1,12)+1 -> 5 | D11: =INDEX(Ipotesi!$B$58:$B$69,C11) -> 1.1 | E11: =Ipotesi!$B$47*MIN(1,(A11/Ipotesi!$B$18)^2)*(1+Ipotesi!$B$48)^(MAX(0,A11-12)/12)*D11 -> 2200 | F11: =E11*Ipotesi!$B$49 -> 4.4 | G11: =F11*Ipotesi!$B$50 -> 1.54 | H11: =G11*Ipotesi!$B$51 -> 0.847 | I11: =IF(A11<=12,Ipotesi!$B$42,Ipotesi!$B$43) -> 8.9219331 | J11: =MIN(H11,I11) -> 0.847 | K11: =H11-J11 -> 0 | L11: =J11*Ipotesi!$B$37 -> 1723.645 | M11: =(G11-J11)*Ipotesi!$B$19 -> 69.3 | N11: =IF(A11>=Ipotesi!$B$26,Ipotesi!$B$52*Ipotesi!$B$25/12,0) -> 0 | O11: =IF(A11>=Ipotesi!$B$27,Ipotesi!$B$53,0) -> 0 | P11: =SUM(L11:O11) -> 1792.945 | Q11: =IF(A11=1,Ipotesi!$B$10+Ipotesi!$B$11,0)+Ipotesi!$B$8*Ipotesi!$B$9+Ipotesi!$B$12+Ipotesi!$B$13+Ipotesi!$B$16*52/12*Ipotesi!$B$17 -> 620 | R11: =Ipotesi!$B$14*52/12*Ipotesi!$B$15 -> 1040 | S11: =J11*IF(A11<=12,Ipotesi!$B$38,Ipotesi!$B$39)*Ipotesi!$B$22 -> 512.64675 | T11: =P11-Q11-R11-S11 -> -379.70175 | U11: =U10+T11 -> -9338.9561 | V11: =L11*Ipotesi!$B$20+IF(A11>Ipotesi!$B$21,INDEX($L$5:$L$40,A11-Ipotesi!$B$21)*(1-Ipotesi!$B$20),0)+M11+N11+O11 -> 952.88569 | W11: =V11-Q11-S11 -> -179.76106 | X11: =X10+W11 -> -5053.5717 | Y11: =IF(U11>=0,A11,999) -> 999 | Z11: =F11*SUMPRODUCT((Social!$C$6:$C$11<=A11)*Social!$B$6:$B$11*Social!$I$6:$I$11) -> 1.32 | AA11: =Z11*Ipotesi!$B$50 -> 0.462 | AB11: =AA11*Ipotesi!$B$51 -> 0.2541 | AC11: =MIN(AB11,MAX(0,I11-J11)) -> 0.2541 | AD11: =AC11*Ipotesi!$B$37+(AA11-AC11)*Ipotesi!$B$19 -> 537.8835 | AE11: =SUMPRODUCT((Social!$C$6:$C$11<=A11)*Social!$J$6:$J$11) -> 920 | AF11: =SUMPRODUCT((Social!$C$6:$C$11<=A11)*Social!$K$6:$K$11) -> 433.33333 | AG11: =AC11*IF(A11<=12,Ipotesi!$B$38,Ipotesi!$B$39)*Ipotesi!$B$22 -> 153.79403 | AH11: =AD11-AE11-AF11-AG11 -> -969.24386 | AI11: =AI10+AH11 -> -6458.9036 | AJ11: =U11+AI11 -> -15797.86 | AK11: =AC11*Ipotesi!$B$37*Ipotesi!$B$20+IF(A11>Ipotesi!$B$21,INDEX($AC$5:$AC$40,A11-Ipotesi!$B$21)*Ipotesi!$B$37*(1-Ipotesi!$B$20),0)+(AA11-AC11)*Ipotesi!$B$19 -> 284.77755 | AL11: =X11+SUM($AK$5:AK11)-SUM($AE$5:AE11)-SUM($AG$5:AG11) -> -10405.23 | AM11: =IF(AJ11>=0,A11,999) -> 999
A12: 8 | B12: =INT((A12-1)/12)+1 -> 1 | C12: =MOD(Ipotesi!$B$7-1+A12-1,12)+1 -> 6 | D12: =INDEX(Ipotesi!$B$58:$B$69,C12) -> 1 | E12: =Ipotesi!$B$47*MIN(1,(A12/Ipotesi!$B$18)^2)*(1+Ipotesi!$B$48)^(MAX(0,A12-12)/12)*D12 -> 2000 | F12: =E12*Ipotesi!$B$49 -> 4 | G12: =F12*Ipotesi!$B$50 -> 1.4 | H12: =G12*Ipotesi!$B$51 -> 0.77 | I12: =IF(A12<=12,Ipotesi!$B$42,Ipotesi!$B$43) -> 8.9219331 | J12: =MIN(H12,I12) -> 0.77 | K12: =H12-J12 -> 0 | L12: =J12*Ipotesi!$B$37 -> 1566.95 | M12: =(G12-J12)*Ipotesi!$B$19 -> 63 | N12: =IF(A12>=Ipotesi!$B$26,Ipotesi!$B$52*Ipotesi!$B$25/12,0) -> 0 | O12: =IF(A12>=Ipotesi!$B$27,Ipotesi!$B$53,0) -> 0 | P12: =SUM(L12:O12) -> 1629.95 | Q12: =IF(A12=1,Ipotesi!$B$10+Ipotesi!$B$11,0)+Ipotesi!$B$8*Ipotesi!$B$9+Ipotesi!$B$12+Ipotesi!$B$13+Ipotesi!$B$16*52/12*Ipotesi!$B$17 -> 620 | R12: =Ipotesi!$B$14*52/12*Ipotesi!$B$15 -> 1040 | S12: =J12*IF(A12<=12,Ipotesi!$B$38,Ipotesi!$B$39)*Ipotesi!$B$22 -> 466.0425 | T12: =P12-Q12-R12-S12 -> -496.0925 | U12: =U11+T12 -> -9835.0486 | V12: =L12*Ipotesi!$B$20+IF(A12>Ipotesi!$B$21,INDEX($L$5:$L$40,A12-Ipotesi!$B$21)*(1-Ipotesi!$B$20),0)+M12+N12+O12 -> 916.11722 | W12: =V12-Q12-S12 -> -169.92528 | X12: =X11+W12 -> -5223.497 | Y12: =IF(U12>=0,A12,999) -> 999 | Z12: =F12*SUMPRODUCT((Social!$C$6:$C$11<=A12)*Social!$B$6:$B$11*Social!$I$6:$I$11) -> 1.2 | AA12: =Z12*Ipotesi!$B$50 -> 0.42 | AB12: =AA12*Ipotesi!$B$51 -> 0.231 | AC12: =MIN(AB12,MAX(0,I12-J12)) -> 0.231 | AD12: =AC12*Ipotesi!$B$37+(AA12-AC12)*Ipotesi!$B$19 -> 488.985 | AE12: =SUMPRODUCT((Social!$C$6:$C$11<=A12)*Social!$J$6:$J$11) -> 920 | AF12: =SUMPRODUCT((Social!$C$6:$C$11<=A12)*Social!$K$6:$K$11) -> 433.33333 | AG12: =AC12*IF(A12<=12,Ipotesi!$B$38,Ipotesi!$B$39)*Ipotesi!$B$22 -> 139.81275 | AH12: =AD12-AE12-AF12-AG12 -> -1004.1611 | AI12: =AI11+AH12 -> -7463.0647 | AJ12: =U12+AI12 -> -17298.113 | AK12: =AC12*Ipotesi!$B$37*Ipotesi!$B$20+IF(A12>Ipotesi!$B$21,INDEX($AC$5:$AC$40,A12-Ipotesi!$B$21)*Ipotesi!$B$37*(1-Ipotesi!$B$20),0)+(AA12-AC12)*Ipotesi!$B$19 -> 271.35306 | AL12: =X12+SUM($AK$5:AK12)-SUM($AE$5:AE12)-SUM($AG$5:AG12) -> -11363.615 | AM12: =IF(AJ12>=0,A12,999) -> 999
A13: 9 | B13: =INT((A13-1)/12)+1 -> 1 | C13: =MOD(Ipotesi!$B$7-1+A13-1,12)+1 -> 7 | D13: =INDEX(Ipotesi!$B$58:$B$69,C13) -> 1 | E13: =Ipotesi!$B$47*MIN(1,(A13/Ipotesi!$B$18)^2)*(1+Ipotesi!$B$48)^(MAX(0,A13-12)/12)*D13 -> 2000 | F13: =E13*Ipotesi!$B$49 -> 4 | G13: =F13*Ipotesi!$B$50 -> 1.4 | H13: =G13*Ipotesi!$B$51 -> 0.77 | I13: =IF(A13<=12,Ipotesi!$B$42,Ipotesi!$B$43) -> 8.9219331 | J13: =MIN(H13,I13) -> 0.77 | K13: =H13-J13 -> 0 | L13: =J13*Ipotesi!$B$37 -> 1566.95 | M13: =(G13-J13)*Ipotesi!$B$19 -> 63 | N13: =IF(A13>=Ipotesi!$B$26,Ipotesi!$B$52*Ipotesi!$B$25/12,0) -> 0 | O13: =IF(A13>=Ipotesi!$B$27,Ipotesi!$B$53,0) -> 0 | P13: =SUM(L13:O13) -> 1629.95 | Q13: =IF(A13=1,Ipotesi!$B$10+Ipotesi!$B$11,0)+Ipotesi!$B$8*Ipotesi!$B$9+Ipotesi!$B$12+Ipotesi!$B$13+Ipotesi!$B$16*52/12*Ipotesi!$B$17 -> 620 | R13: =Ipotesi!$B$14*52/12*Ipotesi!$B$15 -> 1040 | S13: =J13*IF(A13<=12,Ipotesi!$B$38,Ipotesi!$B$39)*Ipotesi!$B$22 -> 466.0425 | T13: =P13-Q13-R13-S13 -> -496.0925 | U13: =U12+T13 -> -10331.141 | V13: =L13*Ipotesi!$B$20+IF(A13>Ipotesi!$B$21,INDEX($L$5:$L$40,A13-Ipotesi!$B$21)*(1-Ipotesi!$B$20),0)+M13+N13+O13 -> 1022.7569 | W13: =V13-Q13-S13 -> -63.285625 | X13: =X12+W13 -> -5286.7826 | Y13: =IF(U13>=0,A13,999) -> 999 | Z13: =F13*SUMPRODUCT((Social!$C$6:$C$11<=A13)*Social!$B$6:$B$11*Social!$I$6:$I$11) -> 1.2 | AA13: =Z13*Ipotesi!$B$50 -> 0.42 | AB13: =AA13*Ipotesi!$B$51 -> 0.231 | AC13: =MIN(AB13,MAX(0,I13-J13)) -> 0.231 | AD13: =AC13*Ipotesi!$B$37+(AA13-AC13)*Ipotesi!$B$19 -> 488.985 | AE13: =SUMPRODUCT((Social!$C$6:$C$11<=A13)*Social!$J$6:$J$11) -> 920 | AF13: =SUMPRODUCT((Social!$C$6:$C$11<=A13)*Social!$K$6:$K$11) -> 433.33333 | AG13: =AC13*IF(A13<=12,Ipotesi!$B$38,Ipotesi!$B$39)*Ipotesi!$B$22 -> 139.81275 | AH13: =AD13-AE13-AF13-AG13 -> -1004.1611 | AI13: =AI12+AH13 -> -8467.2258 | AJ13: =U13+AI13 -> -18798.367 | AK13: =AC13*Ipotesi!$B$37*Ipotesi!$B$20+IF(A13>Ipotesi!$B$21,INDEX($AC$5:$AC$40,A13-Ipotesi!$B$21)*Ipotesi!$B$37*(1-Ipotesi!$B$20),0)+(AA13-AC13)*Ipotesi!$B$19 -> 298.01297 | AL13: =X13+SUM($AK$5:AK13)-SUM($AE$5:AE13)-SUM($AG$5:AG13) -> -12188.701 | AM13: =IF(AJ13>=0,A13,999) -> 999
A14: 10 | B14: =INT((A14-1)/12)+1 -> 1 | C14: =MOD(Ipotesi!$B$7-1+A14-1,12)+1 -> 8 | D14: =INDEX(Ipotesi!$B$58:$B$69,C14) -> 0.7 | E14: =Ipotesi!$B$47*MIN(1,(A14/Ipotesi!$B$18)^2)*(1+Ipotesi!$B$48)^(MAX(0,A14-12)/12)*D14 -> 1400 | F14: =E14*Ipotesi!$B$49 -> 2.8 | G14: =F14*Ipotesi!$B$50 -> 0.98 | H14: =G14*Ipotesi!$B$51 -> 0.539 | I14: =IF(A14<=12,Ipotesi!$B$42,Ipotesi!$B$43) -> 8.9219331 | J14: =MIN(H14,I14) -> 0.539 | K14: =H14-J14 -> 0 | L14: =J14*Ipotesi!$B$37 -> 1096.865 | M14: =(G14-J14)*Ipotesi!$B$19 -> 44.1 | N14: =IF(A14>=Ipotesi!$B$26,Ipotesi!$B$52*Ipotesi!$B$25/12,0) -> 0 | O14: =IF(A14>=Ipotesi!$B$27,Ipotesi!$B$53,0) -> 0 | P14: =SUM(L14:O14) -> 1140.965 | Q14: =IF(A14=1,Ipotesi!$B$10+Ipotesi!$B$11,0)+Ipotesi!$B$8*Ipotesi!$B$9+Ipotesi!$B$12+Ipotesi!$B$13+Ipotesi!$B$16*52/12*Ipotesi!$B$17 -> 620 | R14: =Ipotesi!$B$14*52/12*Ipotesi!$B$15 -> 1040 | S14: =J14*IF(A14<=12,Ipotesi!$B$38,Ipotesi!$B$39)*Ipotesi!$B$22 -> 326.22975 | T14: =P14-Q14-R14-S14 -> -845.26475 | U14: =U13+T14 -> -11176.406 | V14: =L14*Ipotesi!$B$20+IF(A14>Ipotesi!$B$21,INDEX($L$5:$L$40,A14-Ipotesi!$B$21)*(1-Ipotesi!$B$20),0)+M14+N14+O14 -> 940.74361 | W14: =V14-Q14-S14 -> -5.4861389 | X14: =X13+W14 -> -5292.2687 | Y14: =IF(U14>=0,A14,999) -> 999 | Z14: =F14*SUMPRODUCT((Social!$C$6:$C$11<=A14)*Social!$B$6:$B$11*Social!$I$6:$I$11) -> 0.84 | AA14: =Z14*Ipotesi!$B$50 -> 0.294 | AB14: =AA14*Ipotesi!$B$51 -> 0.1617 | AC14: =MIN(AB14,MAX(0,I14-J14)) -> 0.1617 | AD14: =AC14*Ipotesi!$B$37+(AA14-AC14)*Ipotesi!$B$19 -> 342.2895 | AE14: =SUMPRODUCT((Social!$C$6:$C$11<=A14)*Social!$J$6:$J$11) -> 920 | AF14: =SUMPRODUCT((Social!$C$6:$C$11<=A14)*Social!$K$6:$K$11) -> 433.33333 | AG14: =AC14*IF(A14<=12,Ipotesi!$B$38,Ipotesi!$B$39)*Ipotesi!$B$22 -> 97.868925 | AH14: =AD14-AE14-AF14-AG14 -> -1108.9128 | AI14: =AI13+AH14 -> -9576.1385 | AJ14: =U14+AI14 -> -20752.544 | AK14: =AC14*Ipotesi!$B$37*Ipotesi!$B$20+IF(A14>Ipotesi!$B$21,INDEX($AC$5:$AC$40,A14-Ipotesi!$B$21)*Ipotesi!$B$37*(1-Ipotesi!$B$20),0)+(AA14-AC14)*Ipotesi!$B$19 -> 282.22308 | AL14: =X14+SUM($AK$5:AK14)-SUM($AE$5:AE14)-SUM($AG$5:AG14) -> -12929.833 | AM14: =IF(AJ14>=0,A14,999) -> 999
A15: 11 | B15: =INT((A15-1)/12)+1 -> 1 | C15: =MOD(Ipotesi!$B$7-1+A15-1,12)+1 -> 9 | D15: =INDEX(Ipotesi!$B$58:$B$69,C15) -> 1.1 | E15: =Ipotesi!$B$47*MIN(1,(A15/Ipotesi!$B$18)^2)*(1+Ipotesi!$B$48)^(MAX(0,A15-12)/12)*D15 -> 2200 | F15: =E15*Ipotesi!$B$49 -> 4.4 | G15: =F15*Ipotesi!$B$50 -> 1.54 | H15: =G15*Ipotesi!$B$51 -> 0.847 | I15: =IF(A15<=12,Ipotesi!$B$42,Ipotesi!$B$43) -> 8.9219331 | J15: =MIN(H15,I15) -> 0.847 | K15: =H15-J15 -> 0 | L15: =J15*Ipotesi!$B$37 -> 1723.645 | M15: =(G15-J15)*Ipotesi!$B$19 -> 69.3 | N15: =IF(A15>=Ipotesi!$B$26,Ipotesi!$B$52*Ipotesi!$B$25/12,0) -> 0 | O15: =IF(A15>=Ipotesi!$B$27,Ipotesi!$B$53,0) -> 0 | P15: =SUM(L15:O15) -> 1792.945 | Q15: =IF(A15=1,Ipotesi!$B$10+Ipotesi!$B$11,0)+Ipotesi!$B$8*Ipotesi!$B$9+Ipotesi!$B$12+Ipotesi!$B$13+Ipotesi!$B$16*52/12*Ipotesi!$B$17 -> 620 | R15: =Ipotesi!$B$14*52/12*Ipotesi!$B$15 -> 1040 | S15: =J15*IF(A15<=12,Ipotesi!$B$38,Ipotesi!$B$39)*Ipotesi!$B$22 -> 512.64675 | T15: =P15-Q15-R15-S15 -> -379.70175 | U15: =U14+T15 -> -11556.108 | V15: =L15*Ipotesi!$B$20+IF(A15>Ipotesi!$B$21,INDEX($L$5:$L$40,A15-Ipotesi!$B$21)*(1-Ipotesi!$B$20),0)+M15+N15+O15 -> 1529.6103 | W15: =V15-Q15-S15 -> 396.9636 | X15: =X14+W15 -> -4895.3051 | Y15: =IF(U15>=0,A15,999) -> 999 | Z15: =F15*SUMPRODUCT((Social!$C$6:$C$11<=A15)*Social!$B$6:$B$11*Social!$I$6:$I$11) -> 1.32 | AA15: =Z15*Ipotesi!$B$50 -> 0.462 | AB15: =AA15*Ipotesi!$B$51 -> 0.2541 | AC15: =MIN(AB15,MAX(0,I15-J15)) -> 0.2541 | AD15: =AC15*Ipotesi!$B$37+(AA15-AC15)*Ipotesi!$B$19 -> 537.8835 | AE15: =SUMPRODUCT((Social!$C$6:$C$11<=A15)*Social!$J$6:$J$11) -> 920 | AF15: =SUMPRODUCT((Social!$C$6:$C$11<=A15)*Social!$K$6:$K$11) -> 433.33333 | AG15: =AC15*IF(A15<=12,Ipotesi!$B$38,Ipotesi!$B$39)*Ipotesi!$B$22 -> 153.79403 | AH15: =AD15-AE15-AF15-AG15 -> -969.24386 | AI15: =AI14+AH15 -> -10545.382 | AJ15: =U15+AI15 -> -22101.49 | AK15: =AC15*Ipotesi!$B$37*Ipotesi!$B$20+IF(A15>Ipotesi!$B$21,INDEX($AC$5:$AC$40,A15-Ipotesi!$B$21)*Ipotesi!$B$37*(1-Ipotesi!$B$20),0)+(AA15-AC15)*Ipotesi!$B$19 -> 458.8831 | AL15: =X15+SUM($AK$5:AK15)-SUM($AE$5:AE15)-SUM($AG$5:AG15) -> -13147.78 | AM15: =IF(AJ15>=0,A15,999) -> 999
A16: 12 | B16: =INT((A16-1)/12)+1 -> 1 | C16: =MOD(Ipotesi!$B$7-1+A16-1,12)+1 -> 10 | D16: =INDEX(Ipotesi!$B$58:$B$69,C16) -> 1.1 | E16: =Ipotesi!$B$47*MIN(1,(A16/Ipotesi!$B$18)^2)*(1+Ipotesi!$B$48)^(MAX(0,A16-12)/12)*D16 -> 2200 | F16: =E16*Ipotesi!$B$49 -> 4.4 | G16: =F16*Ipotesi!$B$50 -> 1.54 | H16: =G16*Ipotesi!$B$51 -> 0.847 | I16: =IF(A16<=12,Ipotesi!$B$42,Ipotesi!$B$43) -> 8.9219331 | J16: =MIN(H16,I16) -> 0.847 | K16: =H16-J16 -> 0 | L16: =J16*Ipotesi!$B$37 -> 1723.645 | M16: =(G16-J16)*Ipotesi!$B$19 -> 69.3 | N16: =IF(A16>=Ipotesi!$B$26,Ipotesi!$B$52*Ipotesi!$B$25/12,0) -> 0 | O16: =IF(A16>=Ipotesi!$B$27,Ipotesi!$B$53,0) -> 0 | P16: =SUM(L16:O16) -> 1792.945 | Q16: =IF(A16=1,Ipotesi!$B$10+Ipotesi!$B$11,0)+Ipotesi!$B$8*Ipotesi!$B$9+Ipotesi!$B$12+Ipotesi!$B$13+Ipotesi!$B$16*52/12*Ipotesi!$B$17 -> 620 | R16: =Ipotesi!$B$14*52/12*Ipotesi!$B$15 -> 1040 | S16: =J16*IF(A16<=12,Ipotesi!$B$38,Ipotesi!$B$39)*Ipotesi!$B$22 -> 512.64675 | T16: =P16-Q16-R16-S16 -> -379.70175 | U16: =U15+T16 -> -11935.809 | V16: =L16*Ipotesi!$B$20+IF(A16>Ipotesi!$B$21,INDEX($L$5:$L$40,A16-Ipotesi!$B$21)*(1-Ipotesi!$B$20),0)+M16+N16+O16 -> 1871.2925 | W16: =V16-Q16-S16 -> 738.64575 | X16: =X15+W16 -> -4156.6594 | Y16: =IF(U16>=0,A16,999) -> 999 | Z16: =F16*SUMPRODUCT((Social!$C$6:$C$11<=A16)*Social!$B$6:$B$11*Social!$I$6:$I$11) -> 1.32 | AA16: =Z16*Ipotesi!$B$50 -> 0.462 | AB16: =AA16*Ipotesi!$B$51 -> 0.2541 | AC16: =MIN(AB16,MAX(0,I16-J16)) -> 0.2541 | AD16: =AC16*Ipotesi!$B$37+(AA16-AC16)*Ipotesi!$B$19 -> 537.8835 | AE16: =SUMPRODUCT((Social!$C$6:$C$11<=A16)*Social!$J$6:$J$11) -> 920 | AF16: =SUMPRODUCT((Social!$C$6:$C$11<=A16)*Social!$K$6:$K$11) -> 433.33333 | AG16: =AC16*IF(A16<=12,Ipotesi!$B$38,Ipotesi!$B$39)*Ipotesi!$B$22 -> 153.79403 | AH16: =AD16-AE16-AF16-AG16 -> -969.24386 | AI16: =AI15+AH16 -> -11514.626 | AJ16: =U16+AI16 -> -23450.436 | AK16: =AC16*Ipotesi!$B$37*Ipotesi!$B$20+IF(A16>Ipotesi!$B$21,INDEX($AC$5:$AC$40,A16-Ipotesi!$B$21)*Ipotesi!$B$37*(1-Ipotesi!$B$20),0)+(AA16-AC16)*Ipotesi!$B$19 -> 561.38775 | AL16: =X16+SUM($AK$5:AK16)-SUM($AE$5:AE16)-SUM($AG$5:AG16) -> -12921.541 | AM16: =IF(AJ16>=0,A16,999) -> 999
A17: 13 | B17: =INT((A17-1)/12)+1 -> 2 | C17: =MOD(Ipotesi!$B$7-1+A17-1,12)+1 -> 11 | D17: =INDEX(Ipotesi!$B$58:$B$69,C17) -> 1 | E17: =Ipotesi!$B$47*MIN(1,(A17/Ipotesi!$B$18)^2)*(1+Ipotesi!$B$48)^(MAX(0,A17-12)/12)*D17 -> 2037.5385 | F17: =E17*Ipotesi!$B$49 -> 4.0750771 | G17: =F17*Ipotesi!$B$50 -> 1.426277 | H17: =G17*Ipotesi!$B$51 -> 0.78445233 | I17: =IF(A17<=12,Ipotesi!$B$42,Ipotesi!$B$43) -> 10.041841 | J17: =MIN(H17,I17) -> 0.78445233 | K17: =H17-J17 -> 0 | L17: =J17*Ipotesi!$B$37 -> 1596.3605 | M17: =(G17-J17)*Ipotesi!$B$19 -> 64.182464 | N17: =IF(A17>=Ipotesi!$B$26,Ipotesi!$B$52*Ipotesi!$B$25/12,0) -> 0 | O17: =IF(A17>=Ipotesi!$B$27,Ipotesi!$B$53,0) -> 0 | P17: =SUM(L17:O17) -> 1660.543 | Q17: =IF(A17=1,Ipotesi!$B$10+Ipotesi!$B$11,0)+Ipotesi!$B$8*Ipotesi!$B$9+Ipotesi!$B$12+Ipotesi!$B$13+Ipotesi!$B$16*52/12*Ipotesi!$B$17 -> 620 | R17: =Ipotesi!$B$14*52/12*Ipotesi!$B$15 -> 1040 | S17: =J17*IF(A17<=12,Ipotesi!$B$38,Ipotesi!$B$39)*Ipotesi!$B$22 -> 421.83924 | T17: =P17-Q17-R17-S17 -> -421.29628 | U17: =U16+T17 -> -12357.106 | V17: =L17*Ipotesi!$B$20+IF(A17>Ipotesi!$B$21,INDEX($L$5:$L$40,A17-Ipotesi!$B$21)*(1-Ipotesi!$B$20),0)+M17+N17+O17 -> 1724.1852 | W17: =V17-Q17-S17 -> 682.34597 | X17: =X16+W17 -> -3474.3134 | Y17: =IF(U17>=0,A17,999) -> 999 | Z17: =F17*SUMPRODUCT((Social!$C$6:$C$11<=A17)*Social!$B$6:$B$11*Social!$I$6:$I$11) -> 1.2225231 | AA17: =Z17*Ipotesi!$B$50 -> 0.42788309 | AB17: =AA17*Ipotesi!$B$51 -> 0.2353357 | AC17: =MIN(AB17,MAX(0,I17-J17)) -> 0.2353357 | AD17: =AC17*Ipotesi!$B$37+(AA17-AC17)*Ipotesi!$B$19 -> 498.16289 | AE17: =SUMPRODUCT((Social!$C$6:$C$11<=A17)*Social!$J$6:$J$11) -> 920 | AF17: =SUMPRODUCT((Social!$C$6:$C$11<=A17)*Social!$K$6:$K$11) -> 433.33333 | AG17: =AC17*IF(A17<=12,Ipotesi!$B$38,Ipotesi!$B$39)*Ipotesi!$B$22 -> 126.55177 | AH17: =AD17-AE17-AF17-AG17 -> -981.72222 | AI17: =AI16+AH17 -> -12496.348 | AJ17: =U17+AI17 -> -24853.454 | AK17: =AC17*Ipotesi!$B$37*Ipotesi!$B$20+IF(A17>Ipotesi!$B$21,INDEX($AC$5:$AC$40,A17-Ipotesi!$B$21)*Ipotesi!$B$37*(1-Ipotesi!$B$20),0)+(AA17-AC17)*Ipotesi!$B$19 -> 517.25556 | AL17: =X17+SUM($AK$5:AK17)-SUM($AE$5:AE17)-SUM($AG$5:AG17) -> -12768.491 | AM17: =IF(AJ17>=0,A17,999) -> 999
... A40: 36 | B40: =INT((A40-1)/12)+1 -> 3 | C40: =MOD(Ipotesi!$B$7-1+A40-1,12)+1 -> 10 | D40: =INDEX(Ipotesi!$B$58:$B$69,C40) -> 1.1 | E40: =Ipotesi!$B$47*MIN(1,(A40/Ipotesi!$B$18)^2)*(1+Ipotesi!$B$48)^(MAX(0,A40-12)/12)*D40 -> 3437.5 | F40: =E40*Ipotesi!$B$49 -> 6.875 | G40: =F40*Ipotesi!$B$50 -> 2.40625 | H40: =G40*Ipotesi!$B$51 -> 1.3234375 | I40: =IF(A40<=12,Ipotesi!$B$42,Ipotesi!$B$43) -> 10.041841 | J40: =MIN(H40,I40) -> 1.3234375 | K40: =H40-J40 -> 0 | L40: =J40*Ipotesi!$B$37 -> 2693.1953 | M40: =(G40-J40)*Ipotesi!$B$19 -> 108.28125 | N40: =IF(A40>=Ipotesi!$B$26,Ipotesi!$B$52*Ipotesi!$B$25/12,0) -> 0 | O40: =IF(A40>=Ipotesi!$B$27,Ipotesi!$B$53,0) -> 0 | P40: =SUM(L40:O40) -> 2801.4766 | Q40: =IF(A40=1,Ipotesi!$B$10+Ipotesi!$B$11,0)+Ipotesi!$B$8*Ipotesi!$B$9+Ipotesi!$B$12+Ipotesi!$B$13+Ipotesi!$B$16*52/12*Ipotesi!$B$17 -> 620 | R40: =Ipotesi!$B$14*52/12*Ipotesi!$B$15 -> 1040 | S40: =J40*IF(A40<=12,Ipotesi!$B$38,Ipotesi!$B$39)*Ipotesi!$B$22 -> 711.67852 | T40: =P40-Q40-R40-S40 -> 429.79805 | U40: =U39+T40 -> -14597.239 | V40: =L40*Ipotesi!$B$20+IF(A40>Ipotesi!$B$21,INDEX($L$5:$L$40,A40-Ipotesi!$B$21)*(1-Ipotesi!$B$20),0)+M40+N40+O40 -> 2768.8064 | W40: =V40-Q40-S40 -> 1437.1279 | X40: =X39+W40 -> 15827.508 | Y40: =IF(U40>=0,A40,999) -> 999 | Z40: =F40*SUMPRODUCT((Social!$C$6:$C$11<=A40)*Social!$B$6:$B$11*Social!$I$6:$I$11) -> 2.0625 | AA40: =Z40*Ipotesi!$B$50 -> 0.721875 | AB40: =AA40*Ipotesi!$B$51 -> 0.39703125 | AC40: =MIN(AB40,MAX(0,I40-J40)) -> 0.39703125 | AD40: =AC40*Ipotesi!$B$37+(AA40-AC40)*Ipotesi!$B$19 -> 840.44297 | AE40: =SUMPRODUCT((Social!$C$6:$C$11<=A40)*Social!$J$6:$J$11) -> 920 | AF40: =SUMPRODUCT((Social!$C$6:$C$11<=A40)*Social!$K$6:$K$11) -> 433.33333 | AG40: =AC40*IF(A40<=12,Ipotesi!$B$38,Ipotesi!$B$39)*Ipotesi!$B$22 -> 213.50355 | AH40: =AD40-AE40-AF40-AG40 -> -726.39392 | AI40: =AI39+AH40 -> -32841.055 | AJ40: =U40+AI40 -> -47438.294 | AK40: =AC40*Ipotesi!$B$37*Ipotesi!$B$20+IF(A40>Ipotesi!$B$21,INDEX($AC$5:$AC$40,A40-Ipotesi!$B$21)*Ipotesi!$B$37*(1-Ipotesi!$B$20),0)+(AA40-AC40)*Ipotesi!$B$19 -> 830.64193 | AL40: =X40+SUM($AK$5:AK40)-SUM($AE$5:AE40)-SUM($AG$5:AG40) -> -4558.1227 | AM40: =IF(AJ40>=0,A40,999) -> 999
A41: Totale 36 mesi | E41: =SUM(E5:E40) -> 78654.874 | F41: =SUM(F5:F40) -> 157.30975 | G41: =SUM(G5:G40) -> 55.058412 | H41: =SUM(H5:H40) -> 30.282127 | J41: =SUM(J5:J40) -> 30.282127 | K41: =SUM(K5:K40) -> 0 | L41: =SUM(L5:L40) -> 61624.128 | M41: =SUM(M5:M40) -> 2477.6285 | N41: =SUM(N5:N40) -> 0 | O41: =SUM(O5:O40) -> 0 | P41: =SUM(P5:P40) -> 64101.756 | Q41: =SUM(Q5:Q40) -> 24520 | ... T41: =SUM(T5:T40) -> -14597.239 | V41: =SUM(V5:V40) -> 57086.503 | W41: =SUM(W5:W40) -> 15827.508 | Z41: =SUM(Z5:Z40) -> 47.124591 | AA41: =SUM(AA5:AA40) -> 16.493607 | AB41: =SUM(AB5:AB40) -> 9.0714838 | AC41: =SUM(AC5:AC40) -> 9.0714838 | AD41: =SUM(AD5:AD40) -> 19202.682 | AE41: =SUM(AE5:AE40) -> 32470 | AF41: =SUM(AF5:AF40) -> 14560 | AG41: =SUM(AG5:AG40) -> 5013.7369 | AH41: =SUM(AH5:AH40) -> -32841.055 | AK41: =SUM(AK5:AK40) -> 17098.106

Sheet Scenario Medio
A1: Scenario Medio — modello mensile su 36 mesi
A2: Calcolato dalle ipotesi: non modificare. Valori in euro, al netto di IVA, Cassa Forense e imposte.
A4: Mese n. | B4: Anno | C4: Mese calendario | D4: Stagionalità | E4: Visualizzazioni | F4: Contatti | G4: Consulenze a pagamento | H4: Incarichi richiesti | I4: Capacità (incarichi) | J4: Incarichi acquisiti | K4: Incarichi persi per capacità | L4: Ricavi incarichi (€) | M4: Ricavi consulenze (€) | N4: Ricavi convenzioni (€) | O4: Ricavi formazione (€) | P4: Ricavi totali (€) | Q4: Costi canale cassa (€) | R4: Tempo avvocato canale (€) | S4: Costo erogazione incarichi (€) | T4: Margine economico (€) | U4: Margine cumulato (€) | V4: Incassi (€) | W4: Flusso di cassa (€) | X4: Cassa cumulata (€) | Y4: Aiuto: mese di pareggio | Z4: Contatti da altri social | AA4: Consulenze da altri social | AB4: Incarichi social richiesti | AC4: Incarichi social acquisiti | AD4: Ricavi da altri social (€) | AE4: Costi social cassa (€) | AF4: Tempo avvocato social (€) | AG4: Costo erogazione social (€) | AH4: Margine altri social (€) | AI4: Margine social cumulato (€) | AJ4: Margine totale cumulato (€) | AK4: Incassi da altri social (€) | AL4: Cassa cumulata totale (€) | AM4: Aiuto: pareggio totale
A5: 1 | B5: =INT((A5-1)/12)+1 -> 1 | C5: =MOD(Ipotesi!$B$7-1+A5-1,12)+1 -> 11 | D5: =INDEX(Ipotesi!$B$58:$B$69,C5) -> 1 | E5: =Ipotesi!$C$47*MIN(1,(A5/Ipotesi!$B$18)^2)*(1+Ipotesi!$C$48)^(MAX(0,A5-12)/12)*D5 -> 166.66667 | F5: =E5*Ipotesi!$C$49 -> 0.5 | G5: =F5*Ipotesi!$C$50 -> 0.2 | H5: =G5*Ipotesi!$C$51 -> 0.12 | I5: =IF(A5<=12,Ipotesi!$B$42,Ipotesi!$B$43) -> 8.9219331 | J5: =MIN(H5,I5) -> 0.12 | K5: =H5-J5 -> 0 | L5: =J5*Ipotesi!$B$37 -> 244.2 | M5: =(G5-J5)*Ipotesi!$B$19 -> 8 | N5: =IF(A5>=Ipotesi!$B$26,Ipotesi!$C$52*Ipotesi!$B$25/12,0) -> 0 | O5: =IF(A5>=Ipotesi!$B$27,Ipotesi!$C$53,0) -> 0 | P5: =SUM(L5:O5) -> 252.2 | Q5: =IF(A5=1,Ipotesi!$B$10+Ipotesi!$B$11,0)+Ipotesi!$B$8*Ipotesi!$B$9+Ipotesi!$B$12+Ipotesi!$B$13+Ipotesi!$B$16*52/12*Ipotesi!$B$17 -> 2820 | R5: =Ipotesi!$B$14*52/12*Ipotesi!$B$15 -> 1040 | S5: =J5*IF(A5<=12,Ipotesi!$B$38,Ipotesi!$B$39)*Ipotesi!$B$22 -> 72.63 | T5: =P5-Q5-R5-S5 -> -3680.43 | U5: =T5 -> -3680.43 | V5: =L5*Ipotesi!$B$20+IF(A5>Ipotesi!$B$21,INDEX($L$5:$L$40,A5-Ipotesi!$B$21)*(1-Ipotesi!$B$20),0)+M5+N5+O5 -> 130.1 | W5: =V5-Q5-S5 -> -2762.53 | X5: =W5 -> -2762.53 | Y5: =IF(U5>=0,A5,999) -> 999 | Z5: =F5*SUMPRODUCT((Social!$C$6:$C$11<=A5)*Social!$B$6:$B$11*Social!$I$6:$I$11) -> 0.125 | AA5: =Z5*Ipotesi!$C$50 -> 0.05 | AB5: =AA5*Ipotesi!$C$51 -> 0.03 | AC5: =MIN(AB5,MAX(0,I5-J5)) -> 0.03 | AD5: =AC5*Ipotesi!$B$37+(AA5-AC5)*Ipotesi!$B$19 -> 63.05 | AE5: =SUMPRODUCT((Social!$C$6:$C$11<=A5)*Social!$J$6:$J$11) -> 703.33333 | AF5: =SUMPRODUCT((Social!$C$6:$C$11<=A5)*Social!$K$6:$K$11) -> 86.666667 | AG5: =AC5*IF(A5<=12,Ipotesi!$B$38,Ipotesi!$B$39)*Ipotesi!$B$22 -> 18.1575 | AH5: =AD5-AE5-AF5-AG5 -> -745.1075 | AI5: =AH5 -> -745.1075 | AJ5: =U5+AI5 -> -4425.5375 | AK5: =AC5*Ipotesi!$B$37*Ipotesi!$B$20+IF(A5>Ipotesi!$B$21,INDEX($AC$5:$AC$40,A5-Ipotesi!$B$21)*Ipotesi!$B$37*(1-Ipotesi!$B$20),0)+(AA5-AC5)*Ipotesi!$B$19 -> 32.525 | AL5: =X5+SUM($AK$5:AK5)-SUM($AE$5:AE5)-SUM($AG$5:AG5) -> -3451.4958 | AM5: =IF(AJ5>=0,A5,999) -> 999
A6: 2 | B6: =INT((A6-1)/12)+1 -> 1 | C6: =MOD(Ipotesi!$B$7-1+A6-1,12)+1 -> 12 | D6: =INDEX(Ipotesi!$B$58:$B$69,C6) -> 0.8 | E6: =Ipotesi!$C$47*MIN(1,(A6/Ipotesi!$B$18)^2)*(1+Ipotesi!$C$48)^(MAX(0,A6-12)/12)*D6 -> 533.33333 | F6: =E6*Ipotesi!$C$49 -> 1.6 | G6: =F6*Ipotesi!$C$50 -> 0.64 | H6: =G6*Ipotesi!$C$51 -> 0.384 | I6: =IF(A6<=12,Ipotesi!$B$42,Ipotesi!$B$43) -> 8.9219331 | J6: =MIN(H6,I6) -> 0.384 | K6: =H6-J6 -> 0 | L6: =J6*Ipotesi!$B$37 -> 781.44 | M6: =(G6-J6)*Ipotesi!$B$19 -> 25.6 | N6: =IF(A6>=Ipotesi!$B$26,Ipotesi!$C$52*Ipotesi!$B$25/12,0) -> 0 | O6: =IF(A6>=Ipotesi!$B$27,Ipotesi!$C$53,0) -> 0 | P6: =SUM(L6:O6) -> 807.04 | Q6: =IF(A6=1,Ipotesi!$B$10+Ipotesi!$B$11,0)+Ipotesi!$B$8*Ipotesi!$B$9+Ipotesi!$B$12+Ipotesi!$B$13+Ipotesi!$B$16*52/12*Ipotesi!$B$17 -> 620 | R6: =Ipotesi!$B$14*52/12*Ipotesi!$B$15 -> 1040 | S6: =J6*IF(A6<=12,Ipotesi!$B$38,Ipotesi!$B$39)*Ipotesi!$B$22 -> 232.416 | T6: =P6-Q6-R6-S6 -> -1085.376 | U6: =U5+T6 -> -4765.806 | V6: =L6*Ipotesi!$B$20+IF(A6>Ipotesi!$B$21,INDEX($L$5:$L$40,A6-Ipotesi!$B$21)*(1-Ipotesi!$B$20),0)+M6+N6+O6 -> 416.32 | W6: =V6-Q6-S6 -> -436.096 | X6: =X5+W6 -> -3198.626 | Y6: =IF(U6>=0,A6,999) -> 999 | Z6: =F6*SUMPRODUCT((Social!$C$6:$C$11<=A6)*Social!$B$6:$B$11*Social!$I$6:$I$11) -> 0.4 | AA6: =Z6*Ipotesi!$C$50 -> 0.16 | AB6: =AA6*Ipotesi!$C$51 -> 0.096 | AC6: =MIN(AB6,MAX(0,I6-J6)) -> 0.096 | AD6: =AC6*Ipotesi!$B$37+(AA6-AC6)*Ipotesi!$B$19 -> 201.76 | AE6: =SUMPRODUCT((Social!$C$6:$C$11<=A6)*Social!$J$6:$J$11) -> 703.33333 | AF6: =SUMPRODUCT((Social!$C$6:$C$11<=A6)*Social!$K$6:$K$11) -> 86.666667 | AG6: =AC6*IF(A6<=12,Ipotesi!$B$38,Ipotesi!$B$39)*Ipotesi!$B$22 -> 58.104 | AH6: =AD6-AE6-AF6-AG6 -> -646.344 | AI6: =AI5+AH6 -> -1391.4515 | AJ6: =U6+AI6 -> -6157.2575 | AK6: =AC6*Ipotesi!$B$37*Ipotesi!$B$20+IF(A6>Ipotesi!$B$21,INDEX($AC$5:$AC$40,A6-Ipotesi!$B$21)*Ipotesi!$B$37*(1-Ipotesi!$B$20),0)+(AA6-AC6)*Ipotesi!$B$19 -> 104.08 | AL6: =X6+SUM($AK$5:AK6)-SUM($AE$5:AE6)-SUM($AG$5:AG6) -> -4544.9492 | AM6: =IF(AJ6>=0,A6,999) -> 999
A7: 3 | B7: =INT((A7-1)/12)+1 -> 1 | C7: =MOD(Ipotesi!$B$7-1+A7-1,12)+1 -> 1 | D7: =INDEX(Ipotesi!$B$58:$B$69,C7) -> 0.9 | E7: =Ipotesi!$C$47*MIN(1,(A7/Ipotesi!$B$18)^2)*(1+Ipotesi!$C$48)^(MAX(0,A7-12)/12)*D7 -> 1350 | F7: =E7*Ipotesi!$C$49 -> 4.05 | G7: =F7*Ipotesi!$C$50 -> 1.62 | H7: =G7*Ipotesi!$C$51 -> 0.972 | I7: =IF(A7<=12,Ipotesi!$B$42,Ipotesi!$B$43) -> 8.9219331 | J7: =MIN(H7,I7) -> 0.972 | K7: =H7-J7 -> 0 | L7: =J7*Ipotesi!$B$37 -> 1978.02 | M7: =(G7-J7)*Ipotesi!$B$19 -> 64.8 | N7: =IF(A7>=Ipotesi!$B$26,Ipotesi!$C$52*Ipotesi!$B$25/12,0) -> 0 | O7: =IF(A7>=Ipotesi!$B$27,Ipotesi!$C$53,0) -> 0 | P7: =SUM(L7:O7) -> 2042.82 | Q7: =IF(A7=1,Ipotesi!$B$10+Ipotesi!$B$11,0)+Ipotesi!$B$8*Ipotesi!$B$9+Ipotesi!$B$12+Ipotesi!$B$13+Ipotesi!$B$16*52/12*Ipotesi!$B$17 -> 620 | R7: =Ipotesi!$B$14*52/12*Ipotesi!$B$15 -> 1040 | S7: =J7*IF(A7<=12,Ipotesi!$B$38,Ipotesi!$B$39)*Ipotesi!$B$22 -> 588.303 | T7: =P7-Q7-R7-S7 -> -205.483 | U7: =U6+T7 -> -4971.289 | V7: =L7*Ipotesi!$B$20+IF(A7>Ipotesi!$B$21,INDEX($L$5:$L$40,A7-Ipotesi!$B$21)*(1-Ipotesi!$B$20),0)+M7+N7+O7 -> 1053.81 | W7: =V7-Q7-S7 -> -154.493 | X7: =X6+W7 -> -3353.119 | Y7: =IF(U7>=0,A7,999) -> 999 | Z7: =F7*SUMPRODUCT((Social!$C$6:$C$11<=A7)*Social!$B$6:$B$11*Social!$I$6:$I$11) -> 1.0125 | AA7: =Z7*Ipotesi!$C$50 -> 0.405 | AB7: =AA7*Ipotesi!$C$51 -> 0.243 | AC7: =MIN(AB7,MAX(0,I7-J7)) -> 0.243 | AD7: =AC7*Ipotesi!$B$37+(AA7-AC7)*Ipotesi!$B$19 -> 510.705 | AE7: =SUMPRODUCT((Social!$C$6:$C$11<=A7)*Social!$J$6:$J$11) -> 703.33333 | AF7: =SUMPRODUCT((Social!$C$6:$C$11<=A7)*Social!$K$6:$K$11) -> 86.666667 | AG7: =AC7*IF(A7<=12,Ipotesi!$B$38,Ipotesi!$B$39)*Ipotesi!$B$22 -> 147.07575 | AH7: =AD7-AE7-AF7-AG7 -> -426.37075 | AI7: =AI6+AH7 -> -1817.8222 | AJ7: =U7+AI7 -> -6789.1112 | AK7: =AC7*Ipotesi!$B$37*Ipotesi!$B$20+IF(A7>Ipotesi!$B$21,INDEX($AC$5:$AC$40,A7-Ipotesi!$B$21)*Ipotesi!$B$37*(1-Ipotesi!$B$20),0)+(AA7-AC7)*Ipotesi!$B$19 -> 263.4525 | AL7: =X7+SUM($AK$5:AK7)-SUM($AE$5:AE7)-SUM($AG$5:AG7) -> -5286.3988 | AM7: =IF(AJ7>=0,A7,999) -> 999
A8: 4 | B8: =INT((A8-1)/12)+1 -> 1 | C8: =MOD(Ipotesi!$B$7-1+A8-1,12)+1 -> 2 | D8: =INDEX(Ipotesi!$B$58:$B$69,C8) -> 1 | E8: =Ipotesi!$C$47*MIN(1,(A8/Ipotesi!$B$18)^2)*(1+Ipotesi!$C$48)^(MAX(0,A8-12)/12)*D8 -> 2666.6667 | F8: =E8*Ipotesi!$C$49 -> 8 | G8: =F8*Ipotesi!$C$50 -> 3.2 | H8: =G8*Ipotesi!$C$51 -> 1.92 | I8: =IF(A8<=12,Ipotesi!$B$42,Ipotesi!$B$43) -> 8.9219331 | J8: =MIN(H8,I8) -> 1.92 | K8: =H8-J8 -> 0 | L8: =J8*Ipotesi!$B$37 -> 3907.2 | M8: =(G8-J8)*Ipotesi!$B$19 -> 128 | N8: =IF(A8>=Ipotesi!$B$26,Ipotesi!$C$52*Ipotesi!$B$25/12,0) -> 0 | O8: =IF(A8>=Ipotesi!$B$27,Ipotesi!$C$53,0) -> 0 | P8: =SUM(L8:O8) -> 4035.2 | Q8: =IF(A8=1,Ipotesi!$B$10+Ipotesi!$B$11,0)+Ipotesi!$B$8*Ipotesi!$B$9+Ipotesi!$B$12+Ipotesi!$B$13+Ipotesi!$B$16*52/12*Ipotesi!$B$17 -> 620 | R8: =Ipotesi!$B$14*52/12*Ipotesi!$B$15 -> 1040 | S8: =J8*IF(A8<=12,Ipotesi!$B$38,Ipotesi!$B$39)*Ipotesi!$B$22 -> 1162.08 | T8: =P8-Q8-R8-S8 -> 1213.12 | U8: =U7+T8 -> -3758.169 | V8: =L8*Ipotesi!$B$20+IF(A8>Ipotesi!$B$21,INDEX($L$5:$L$40,A8-Ipotesi!$B$21)*(1-Ipotesi!$B$20),0)+M8+N8+O8 -> 2081.6 | W8: =V8-Q8-S8 -> 299.52 | X8: =X7+W8 -> -3053.599 | Y8: =IF(U8>=0,A8,999) -> 999 | Z8: =F8*SUMPRODUCT((Social!$C$6:$C$11<=A8)*Social!$B$6:$B$11*Social!$I$6:$I$11) -> 2.4 | AA8: =Z8*Ipotesi!$C$50 -> 0.96 | AB8: =AA8*Ipotesi!$C$51 -> 0.576 | AC8: =MIN(AB8,MAX(0,I8-J8)) -> 0.576 | AD8: =AC8*Ipotesi!$B$37+(AA8-AC8)*Ipotesi!$B$19 -> 1210.56 | AE8: =SUMPRODUCT((Social!$C$6:$C$11<=A8)*Social!$J$6:$J$11) -> 920 | AF8: =SUMPRODUCT((Social!$C$6:$C$11<=A8)*Social!$K$6:$K$11) -> 433.33333 | AG8: =AC8*IF(A8<=12,Ipotesi!$B$38,Ipotesi!$B$39)*Ipotesi!$B$22 -> 348.624 | AH8: =AD8-AE8-AF8-AG8 -> -491.39733 | AI8: =AI7+AH8 -> -2309.2196 | AJ8: =U8+AI8 -> -6067.3886 | AK8: =AC8*Ipotesi!$B$37*Ipotesi!$B$20+IF(A8>Ipotesi!$B$21,INDEX($AC$5:$AC$40,A8-Ipotesi!$B$21)*Ipotesi!$B$37*(1-Ipotesi!$B$20),0)+(AA8-AC8)*Ipotesi!$B$19 -> 624.48 | AL8: =X8+SUM($AK$5:AK8)-SUM($AE$5:AE8)-SUM($AG$5:AG8) -> -5631.0228 | AM8: =IF(AJ8>=0,A8,999) -> 999
A9: 5 | B9: =INT((A9-1)/12)+1 -> 1 | C9: =MOD(Ipotesi!$B$7-1+A9-1,12)+1 -> 3 | D9: =INDEX(Ipotesi!$B$58:$B$69,C9) -> 1.1 | E9: =Ipotesi!$C$47*MIN(1,(A9/Ipotesi!$B$18)^2)*(1+Ipotesi!$C$48)^(MAX(0,A9-12)/12)*D9 -> 4583.3333 | F9: =E9*Ipotesi!$C$49 -> 13.75 | G9: =F9*Ipotesi!$C$50 -> 5.5 | H9: =G9*Ipotesi!$C$51 -> 3.3 | I9: =IF(A9<=12,Ipotesi!$B$42,Ipotesi!$B$43) -> 8.9219331 | J9: =MIN(H9,I9) -> 3.3 | K9: =H9-J9 -> 0 | L9: =J9*Ipotesi!$B$37 -> 6715.5 | M9: =(G9-J9)*Ipotesi!$B$19 -> 220 | N9: =IF(A9>=Ipotesi!$B$26,Ipotesi!$C$52*Ipotesi!$B$25/12,0) -> 0 | O9: =IF(A9>=Ipotesi!$B$27,Ipotesi!$C$53,0) -> 0 | P9: =SUM(L9:O9) -> 6935.5 | Q9: =IF(A9=1,Ipotesi!$B$10+Ipotesi!$B$11,0)+Ipotesi!$B$8*Ipotesi!$B$9+Ipotesi!$B$12+Ipotesi!$B$13+Ipotesi!$B$16*52/12*Ipotesi!$B$17 -> 620 | R9: =Ipotesi!$B$14*52/12*Ipotesi!$B$15 -> 1040 | S9: =J9*IF(A9<=12,Ipotesi!$B$38,Ipotesi!$B$39)*Ipotesi!$B$22 -> 1997.325 | T9: =P9-Q9-R9-S9 -> 3278.175 | U9: =U8+T9 -> -479.994 | V9: =L9*Ipotesi!$B$20+IF(A9>Ipotesi!$B$21,INDEX($L$5:$L$40,A9-Ipotesi!$B$21)*(1-Ipotesi!$B$20),0)+M9+N9+O9 -> 3577.75 | W9: =V9-Q9-S9 -> 960.425 | X9: =X8+W9 -> -2093.174 | Y9: =IF(U9>=0,A9,999) -> 999 | Z9: =F9*SUMPRODUCT((Social!$C$6:$C$11<=A9)*Social!$B$6:$B$11*Social!$I$6:$I$11) -> 4.125 | AA9: =Z9*Ipotesi!$C$50 -> 1.65 | AB9: =AA9*Ipotesi!$C$51 -> 0.99 | AC9: =MIN(AB9,MAX(0,I9-J9)) -> 0.99 | AD9: =AC9*Ipotesi!$B$37+(AA9-AC9)*Ipotesi!$B$19 -> 2080.65 | AE9: =SUMPRODUCT((Social!$C$6:$C$11<=A9)*Social!$J$6:$J$11) -> 920 | AF9: =SUMPRODUCT((Social!$C$6:$C$11<=A9)*Social!$K$6:$K$11) -> 433.33333 | AG9: =AC9*IF(A9<=12,Ipotesi!$B$38,Ipotesi!$B$39)*Ipotesi!$B$22 -> 599.1975 | AH9: =AD9-AE9-AF9-AG9 -> 128.11917 | AI9: =AI8+AH9 -> -2181.1004 | AJ9: =U9+AI9 -> -2661.0944 | AK9: =AC9*Ipotesi!$B$37*Ipotesi!$B$20+IF(A9>Ipotesi!$B$21,INDEX($AC$5:$AC$40,A9-Ipotesi!$B$21)*Ipotesi!$B$37*(1-Ipotesi!$B$20),0)+(AA9-AC9)*Ipotesi!$B$19 -> 1073.325 | AL9: =X9+SUM($AK$5:AK9)-SUM($AE$5:AE9)-SUM($AG$5:AG9) -> -5116.4703 | AM9: =IF(AJ9>=0,A9,999) -> 999
A10: 6 | B10: =INT((A10-1)/12)+1 -> 1 | C10: =MOD(Ipotesi!$B$7-1+A10-1,12)+1 -> 4 | D10: =INDEX(Ipotesi!$B$58:$B$69,C10) -> 1.2 | E10: =Ipotesi!$C$47*MIN(1,(A10/Ipotesi!$B$18)^2)*(1+Ipotesi!$C$48)^(MAX(0,A10-12)/12)*D10 -> 7200 | F10: =E10*Ipotesi!$C$49 -> 21.6 | G10: =F10*Ipotesi!$C$50 -> 8.64 | H10: =G10*Ipotesi!$C$51 -> 5.184 | I10: =IF(A10<=12,Ipotesi!$B$42,Ipotesi!$B$43) -> 8.9219331 | J10: =MIN(H10,I10) -> 5.184 | K10: =H10-J10 -> 0 | L10: =J10*Ipotesi!$B$37 -> 10549.44 | M10: =(G10-J10)*Ipotesi!$B$19 -> 345.6 | N10: =IF(A10>=Ipotesi!$B$26,Ipotesi!$C$52*Ipotesi!$B$25/12,0) -> 0 | O10: =IF(A10>=Ipotesi!$B$27,Ipotesi!$C$53,0) -> 0 | P10: =SUM(L10:O10) -> 10895.04 | Q10: =IF(A10=1,Ipotesi!$B$10+Ipotesi!$B$11,0)+Ipotesi!$B$8*Ipotesi!$B$9+Ipotesi!$B$12+Ipotesi!$B$13+Ipotesi!$B$16*52/12*Ipotesi!$B$17 -> 620 | R10: =Ipotesi!$B$14*52/12*Ipotesi!$B$15 -> 1040 | S10: =J10*IF(A10<=12,Ipotesi!$B$38,Ipotesi!$B$39)*Ipotesi!$B$22 -> 3137.616 | T10: =P10-Q10-R10-S10 -> 6097.424 | U10: =U9+T10 -> 5617.43 | V10: =L10*Ipotesi!$B$20+IF(A10>Ipotesi!$B$21,INDEX($L$5:$L$40,A10-Ipotesi!$B$21)*(1-Ipotesi!$B$20),0)+M10+N10+O10 -> 5620.32 | W10: =V10-Q10-S10 -> 1862.704 | X10: =X9+W10 -> -230.47 | Y10: =IF(U10>=0,A10,999) -> 6 | Z10: =F10*SUMPRODUCT((Social!$C$6:$C$11<=A10)*Social!$B$6:$B$11*Social!$I$6:$I$11) -> 6.48 | AA10: =Z10*Ipotesi!$C$50 -> 2.592 | AB10: =AA10*Ipotesi!$C$51 -> 1.5552 | AC10: =MIN(AB10,MAX(0,I10-J10)) -> 1.5552 | AD10: =AC10*Ipotesi!$B$37+(AA10-AC10)*Ipotesi!$B$19 -> 3268.512 | AE10: =SUMPRODUCT((Social!$C$6:$C$11<=A10)*Social!$J$6:$J$11) -> 920 | AF10: =SUMPRODUCT((Social!$C$6:$C$11<=A10)*Social!$K$6:$K$11) -> 433.33333 | AG10: =AC10*IF(A10<=12,Ipotesi!$B$38,Ipotesi!$B$39)*Ipotesi!$B$22 -> 941.2848 | AH10: =AD10-AE10-AF10-AG10 -> 973.89387 | AI10: =AI9+AH10 -> -1207.2066 | AJ10: =U10+AI10 -> 4410.2235 | AK10: =AC10*Ipotesi!$B$37*Ipotesi!$B$20+IF(A10>Ipotesi!$B$21,INDEX($AC$5:$AC$40,A10-Ipotesi!$B$21)*Ipotesi!$B$37*(1-Ipotesi!$B$20),0)+(AA10-AC10)*Ipotesi!$B$19 -> 1686.096 | AL10: =X10+SUM($AK$5:AK10)-SUM($AE$5:AE10)-SUM($AG$5:AG10) -> -3428.9551 | AM10: =IF(AJ10>=0,A10,999) -> 6
A11: 7 | B11: =INT((A11-1)/12)+1 -> 1 | C11: =MOD(Ipotesi!$B$7-1+A11-1,12)+1 -> 5 | D11: =INDEX(Ipotesi!$B$58:$B$69,C11) -> 1.1 | E11: =Ipotesi!$C$47*MIN(1,(A11/Ipotesi!$B$18)^2)*(1+Ipotesi!$C$48)^(MAX(0,A11-12)/12)*D11 -> 6600 | F11: =E11*Ipotesi!$C$49 -> 19.8 | G11: =F11*Ipotesi!$C$50 -> 7.92 | H11: =G11*Ipotesi!$C$51 -> 4.752 | I11: =IF(A11<=12,Ipotesi!$B$42,Ipotesi!$B$43) -> 8.9219331 | J11: =MIN(H11,I11) -> 4.752 | K11: =H11-J11 -> 0 | L11: =J11*Ipotesi!$B$37 -> 9670.32 | M11: =(G11-J11)*Ipotesi!$B$19 -> 316.8 | N11: =IF(A11>=Ipotesi!$B$26,Ipotesi!$C$52*Ipotesi!$B$25/12,0) -> 0 | O11: =IF(A11>=Ipotesi!$B$27,Ipotesi!$C$53,0) -> 0 | P11: =SUM(L11:O11) -> 9987.12 | Q11: =IF(A11=1,Ipotesi!$B$10+Ipotesi!$B$11,0)+Ipotesi!$B$8*Ipotesi!$B$9+Ipotesi!$B$12+Ipotesi!$B$13+Ipotesi!$B$16*52/12*Ipotesi!$B$17 -> 620 | R11: =Ipotesi!$B$14*52/12*Ipotesi!$B$15 -> 1040 | S11: =J11*IF(A11<=12,Ipotesi!$B$38,Ipotesi!$B$39)*Ipotesi!$B$22 -> 2876.148 | T11: =P11-Q11-R11-S11 -> 5450.972 | U11: =U10+T11 -> 11068.402 | V11: =L11*Ipotesi!$B$20+IF(A11>Ipotesi!$B$21,INDEX($L$5:$L$40,A11-Ipotesi!$B$21)*(1-Ipotesi!$B$20),0)+M11+N11+O11 -> 5274.06 | W11: =V11-Q11-S11 -> 1777.912 | X11: =X10+W11 -> 1547.442 | Y11: =IF(U11>=0,A11,999) -> 7 | Z11: =F11*SUMPRODUCT((Social!$C$6:$C$11<=A11)*Social!$B$6:$B$11*Social!$I$6:$I$11) -> 5.94 | AA11: =Z11*Ipotesi!$C$50 -> 2.376 | AB11: =AA11*Ipotesi!$C$51 -> 1.4256 | AC11: =MIN(AB11,MAX(0,I11-J11)) -> 1.4256 | AD11: =AC11*Ipotesi!$B$37+(AA11-AC11)*Ipotesi!$B$19 -> 2996.136 | AE11: =SUMPRODUCT((Social!$C$6:$C$11<=A11)*Social!$J$6:$J$11) -> 920 | AF11: =SUMPRODUCT((Social!$C$6:$C$11<=A11)*Social!$K$6:$K$11) -> 433.33333 | AG11: =AC11*IF(A11<=12,Ipotesi!$B$38,Ipotesi!$B$39)*Ipotesi!$B$22 -> 862.8444 | AH11: =AD11-AE11-AF11-AG11 -> 779.95827 | AI11: =AI10+AH11 -> -427.24828 | AJ11: =U11+AI11 -> 10641.154 | AK11: =AC11*Ipotesi!$B$37*Ipotesi!$B$20+IF(A11>Ipotesi!$B$21,INDEX($AC$5:$AC$40,A11-Ipotesi!$B$21)*Ipotesi!$B$37*(1-Ipotesi!$B$20),0)+(AA11-AC11)*Ipotesi!$B$19 -> 1576.113 | AL11: =X11+SUM($AK$5:AK11)-SUM($AE$5:AE11)-SUM($AG$5:AG11) -> -1857.7744 | AM11: =IF(AJ11>=0,A11,999) -> 7
A12: 8 | B12: =INT((A12-1)/12)+1 -> 1 | C12: =MOD(Ipotesi!$B$7-1+A12-1,12)+1 -> 6 | D12: =INDEX(Ipotesi!$B$58:$B$69,C12) -> 1 | E12: =Ipotesi!$C$47*MIN(1,(A12/Ipotesi!$B$18)^2)*(1+Ipotesi!$C$48)^(MAX(0,A12-12)/12)*D12 -> 6000 | F12: =E12*Ipotesi!$C$49 -> 18 | G12: =F12*Ipotesi!$C$50 -> 7.2 | H12: =G12*Ipotesi!$C$51 -> 4.32 | I12: =IF(A12<=12,Ipotesi!$B$42,Ipotesi!$B$43) -> 8.9219331 | J12: =MIN(H12,I12) -> 4.32 | K12: =H12-J12 -> 0 | L12: =J12*Ipotesi!$B$37 -> 8791.2 | M12: =(G12-J12)*Ipotesi!$B$19 -> 288 | N12: =IF(A12>=Ipotesi!$B$26,Ipotesi!$C$52*Ipotesi!$B$25/12,0) -> 0 | O12: =IF(A12>=Ipotesi!$B$27,Ipotesi!$C$53,0) -> 0 | P12: =SUM(L12:O12) -> 9079.2 | Q12: =IF(A12=1,Ipotesi!$B$10+Ipotesi!$B$11,0)+Ipotesi!$B$8*Ipotesi!$B$9+Ipotesi!$B$12+Ipotesi!$B$13+Ipotesi!$B$16*52/12*Ipotesi!$B$17 -> 620 | R12: =Ipotesi!$B$14*52/12*Ipotesi!$B$15 -> 1040 | S12: =J12*IF(A12<=12,Ipotesi!$B$38,Ipotesi!$B$39)*Ipotesi!$B$22 -> 2614.68 | T12: =P12-Q12-R12-S12 -> 4804.52 | U12: =U11+T12 -> 15872.922 | V12: =L12*Ipotesi!$B$20+IF(A12>Ipotesi!$B$21,INDEX($L$5:$L$40,A12-Ipotesi!$B$21)*(1-Ipotesi!$B$20),0)+M12+N12+O12 -> 5074.32 | W12: =V12-Q12-S12 -> 1839.64 | X12: =X11+W12 -> 3387.082 | Y12: =IF(U12>=0,A12,999) -> 8 | Z12: =F12*SUMPRODUCT((Social!$C$6:$C$11<=A12)*Social!$B$6:$B$11*Social!$I$6:$I$11) -> 5.4 | AA12: =Z12*Ipotesi!$C$50 -> 2.16 | AB12: =AA12*Ipotesi!$C$51 -> 1.296 | AC12: =MIN(AB12,MAX(0,I12-J12)) -> 1.296 | AD12: =AC12*Ipotesi!$B$37+(AA12-AC12)*Ipotesi!$B$19 -> 2723.76 | AE12: =SUMPRODUCT((Social!$C$6:$C$11<=A12)*Social!$J$6:$J$11) -> 920 | AF12: =SUMPRODUCT((Social!$C$6:$C$11<=A12)*Social!$K$6:$K$11) -> 433.33333 | AG12: =AC12*IF(A12<=12,Ipotesi!$B$38,Ipotesi!$B$39)*Ipotesi!$B$22 -> 784.404 | AH12: =AD12-AE12-AF12-AG12 -> 586.02267 | AI12: =AI11+AH12 -> 158.77438 | AJ12: =U12+AI12 -> 16031.696 | AK12: =AC12*Ipotesi!$B$37*Ipotesi!$B$20+IF(A12>Ipotesi!$B$21,INDEX($AC$5:$AC$40,A12-Ipotesi!$B$21)*Ipotesi!$B$37*(1-Ipotesi!$B$20),0)+(AA12-AC12)*Ipotesi!$B$19 -> 1502.76 | AL12: =X12+SUM($AK$5:AK12)-SUM($AE$5:AE12)-SUM($AG$5:AG12) -> -219.77845 | AM12: =IF(AJ12>=0,A12,999) -> 8
A13: 9 | B13: =INT((A13-1)/12)+1 -> 1 | C13: =MOD(Ipotesi!$B$7-1+A13-1,12)+1 -> 7 | D13: =INDEX(Ipotesi!$B$58:$B$69,C13) -> 1 | E13: =Ipotesi!$C$47*MIN(1,(A13/Ipotesi!$B$18)^2)*(1+Ipotesi!$C$48)^(MAX(0,A13-12)/12)*D13 -> 6000 | F13: =E13*Ipotesi!$C$49 -> 18 | G13: =F13*Ipotesi!$C$50 -> 7.2 | H13: =G13*Ipotesi!$C$51 -> 4.32 | I13: =IF(A13<=12,Ipotesi!$B$42,Ipotesi!$B$43) -> 8.9219331 | J13: =MIN(H13,I13) -> 4.32 | K13: =H13-J13 -> 0 | L13: =J13*Ipotesi!$B$37 -> 8791.2 | M13: =(G13-J13)*Ipotesi!$B$19 -> 288 | N13: =IF(A13>=Ipotesi!$B$26,Ipotesi!$C$52*Ipotesi!$B$25/12,0) -> 0 | O13: =IF(A13>=Ipotesi!$B$27,Ipotesi!$C$53,0) -> 0 | P13: =SUM(L13:O13) -> 9079.2 | Q13: =IF(A13=1,Ipotesi!$B$10+Ipotesi!$B$11,0)+Ipotesi!$B$8*Ipotesi!$B$9+Ipotesi!$B$12+Ipotesi!$B$13+Ipotesi!$B$16*52/12*Ipotesi!$B$17 -> 620 | R13: =Ipotesi!$B$14*52/12*Ipotesi!$B$15 -> 1040 | S13: =J13*IF(A13<=12,Ipotesi!$B$38,Ipotesi!$B$39)*Ipotesi!$B$22 -> 2614.68 | T13: =P13-Q13-R13-S13 -> 4804.52 | U13: =U12+T13 -> 20677.442 | V13: =L13*Ipotesi!$B$20+IF(A13>Ipotesi!$B$21,INDEX($L$5:$L$40,A13-Ipotesi!$B$21)*(1-Ipotesi!$B$20),0)+M13+N13+O13 -> 5672.61 | W13: =V13-Q13-S13 -> 2437.93 | X13: =X12+W13 -> 5825.012 | Y13: =IF(U13>=0,A13,999) -> 9 | Z13: =F13*SUMPRODUCT((Social!$C$6:$C$11<=A13)*Social!$B$6:$B$11*Social!$I$6:$I$11) -> 5.4 | AA13: =Z13*Ipotesi!$C$50 -> 2.16 | AB13: =AA13*Ipotesi!$C$51 -> 1.296 | AC13: =MIN(AB13,MAX(0,I13-J13)) -> 1.296 | AD13: =AC13*Ipotesi!$B$37+(AA13-AC13)*Ipotesi!$B$19 -> 2723.76 | AE13: =SUMPRODUCT((Social!$C$6:$C$11<=A13)*Social!$J$6:$J$11) -> 920 | AF13: =SUMPRODUCT((Social!$C$6:$C$11<=A13)*Social!$K$6:$K$11) -> 433.33333 | AG13: =AC13*IF(A13<=12,Ipotesi!$B$38,Ipotesi!$B$39)*Ipotesi!$B$22 -> 784.404 | AH13: =AD13-AE13-AF13-AG13 -> 586.02267 | AI13: =AI12+AH13 -> 744.79705 | AJ13: =U13+AI13 -> 21422.239 | AK13: =AC13*Ipotesi!$B$37*Ipotesi!$B$20+IF(A13>Ipotesi!$B$21,INDEX($AC$5:$AC$40,A13-Ipotesi!$B$21)*Ipotesi!$B$37*(1-Ipotesi!$B$20),0)+(AA13-AC13)*Ipotesi!$B$19 -> 1652.3325 | AL13: =X13+SUM($AK$5:AK13)-SUM($AE$5:AE13)-SUM($AG$5:AG13) -> 2166.0801 | AM13: =IF(AJ13>=0,A13,999) -> 9
A14: 10 | B14: =INT((A14-1)/12)+1 -> 1 | C14: =MOD(Ipotesi!$B$7-1+A14-1,12)+1 -> 8 | D14: =INDEX(Ipotesi!$B$58:$B$69,C14) -> 0.7 | E14: =Ipotesi!$C$47*MIN(1,(A14/Ipotesi!$B$18)^2)*(1+Ipotesi!$C$48)^(MAX(0,A14-12)/12)*D14 -> 4200 | F14: =E14*Ipotesi!$C$49 -> 12.6 | G14: =F14*Ipotesi!$C$50 -> 5.04 | H14: =G14*Ipotesi!$C$51 -> 3.024 | I14: =IF(A14<=12,Ipotesi!$B$42,Ipotesi!$B$43) -> 8.9219331 | J14: =MIN(H14,I14) -> 3.024 | K14: =H14-J14 -> 0 | L14: =J14*Ipotesi!$B$37 -> 6153.84 | M14: =(G14-J14)*Ipotesi!$B$19 -> 201.6 | N14: =IF(A14>=Ipotesi!$B$26,Ipotesi!$C$52*Ipotesi!$B$25/12,0) -> 0 | O14: =IF(A14>=Ipotesi!$B$27,Ipotesi!$C$53,0) -> 0 | P14: =SUM(L14:O14) -> 6355.44 | Q14: =IF(A14=1,Ipotesi!$B$10+Ipotesi!$B$11,0)+Ipotesi!$B$8*Ipotesi!$B$9+Ipotesi!$B$12+Ipotesi!$B$13+Ipotesi!$B$16*52/12*Ipotesi!$B$17 -> 620 | R14: =Ipotesi!$B$14*52/12*Ipotesi!$B$15 -> 1040 | S14: =J14*IF(A14<=12,Ipotesi!$B$38,Ipotesi!$B$39)*Ipotesi!$B$22 -> 1830.276 | T14: =P14-Q14-R14-S14 -> 2865.164 | U14: =U13+T14 -> 23542.606 | V14: =L14*Ipotesi!$B$20+IF(A14>Ipotesi!$B$21,INDEX($L$5:$L$40,A14-Ipotesi!$B$21)*(1-Ipotesi!$B$20),0)+M14+N14+O14 -> 5232.12 | W14: =V14-Q14-S14 -> 2781.844 | X14: =X13+W14 -> 8606.856 | Y14: =IF(U14>=0,A14,999) -> 10 | Z14: =F14*SUMPRODUCT((Social!$C$6:$C$11<=A14)*Social!$B$6:$B$11*Social!$I$6:$I$11) -> 3.78 | AA14: =Z14*Ipotesi!$C$50 -> 1.512 | AB14: =AA14*Ipotesi!$C$51 -> 0.9072 | AC14: =MIN(AB14,MAX(0,I14-J14)) -> 0.9072 | AD14: =AC14*Ipotesi!$B$37+(AA14-AC14)*Ipotesi!$B$19 -> 1906.632 | AE14: =SUMPRODUCT((Social!$C$6:$C$11<=A14)*Social!$J$6:$J$11) -> 920 | AF14: =SUMPRODUCT((Social!$C$6:$C$11<=A14)*Social!$K$6:$K$11) -> 433.33333 | AG14: =AC14*IF(A14<=12,Ipotesi!$B$38,Ipotesi!$B$39)*Ipotesi!$B$22 -> 549.0828 | AH14: =AD14-AE14-AF14-AG14 -> 4.2158667 | AI14: =AI13+AH14 -> 749.01292 | AJ14: =U14+AI14 -> 24291.619 | AK14: =AC14*Ipotesi!$B$37*Ipotesi!$B$20+IF(A14>Ipotesi!$B$21,INDEX($AC$5:$AC$40,A14-Ipotesi!$B$21)*Ipotesi!$B$37*(1-Ipotesi!$B$20),0)+(AA14-AC14)*Ipotesi!$B$19 -> 1569.636 | AL14: =X14+SUM($AK$5:AK14)-SUM($AE$5:AE14)-SUM($AG$5:AG14) -> 5048.4773 | AM14: =IF(AJ14>=0,A14,999) -> 10
A15: 11 | B15: =INT((A15-1)/12)+1 -> 1 | C15: =MOD(Ipotesi!$B$7-1+A15-1,12)+1 -> 9 | D15: =INDEX(Ipotesi!$B$58:$B$69,C15) -> 1.1 | E15: =Ipotesi!$C$47*MIN(1,(A15/Ipotesi!$B$18)^2)*(1+Ipotesi!$C$48)^(MAX(0,A15-12)/12)*D15 -> 6600 | F15: =E15*Ipotesi!$C$49 -> 19.8 | G15: =F15*Ipotesi!$C$50 -> 7.92 | H15: =G15*Ipotesi!$C$51 -> 4.752 | I15: =IF(A15<=12,Ipotesi!$B$42,Ipotesi!$B$43) -> 8.9219331 | J15: =MIN(H15,I15) -> 4.752 | K15: =H15-J15 -> 0 | L15: =J15*Ipotesi!$B$37 -> 9670.32 | M15: =(G15-J15)*Ipotesi!$B$19 -> 316.8 | N15: =IF(A15>=Ipotesi!$B$26,Ipotesi!$C$52*Ipotesi!$B$25/12,0) -> 0 | O15: =IF(A15>=Ipotesi!$B$27,Ipotesi!$C$53,0) -> 0 | P15: =SUM(L15:O15) -> 9987.12 | Q15: =IF(A15=1,Ipotesi!$B$10+Ipotesi!$B$11,0)+Ipotesi!$B$8*Ipotesi!$B$9+Ipotesi!$B$12+Ipotesi!$B$13+Ipotesi!$B$16*52/12*Ipotesi!$B$17 -> 620 | R15: =Ipotesi!$B$14*52/12*Ipotesi!$B$15 -> 1040 | S15: =J15*IF(A15<=12,Ipotesi!$B$38,Ipotesi!$B$39)*Ipotesi!$B$22 -> 2876.148 | T15: =P15-Q15-R15-S15 -> 5450.972 | U15: =U14+T15 -> 28993.578 | V15: =L15*Ipotesi!$B$20+IF(A15>Ipotesi!$B$21,INDEX($L$5:$L$40,A15-Ipotesi!$B$21)*(1-Ipotesi!$B$20),0)+M15+N15+O15 -> 8509.71 | W15: =V15-Q15-S15 -> 5013.562 | X15: =X14+W15 -> 13620.418 | Y15: =IF(U15>=0,A15,999) -> 11 | Z15: =F15*SUMPRODUCT((Social!$C$6:$C$11<=A15)*Social!$B$6:$B$11*Social!$I$6:$I$11) -> 5.94 | AA15: =Z15*Ipotesi!$C$50 -> 2.376 | AB15: =AA15*Ipotesi!$C$51 -> 1.4256 | AC15: =MIN(AB15,MAX(0,I15-J15)) -> 1.4256 | AD15: =AC15*Ipotesi!$B$37+(AA15-AC15)*Ipotesi!$B$19 -> 2996.136 | AE15: =SUMPRODUCT((Social!$C$6:$C$11<=A15)*Social!$J$6:$J$11) -> 920 | AF15: =SUMPRODUCT((Social!$C$6:$C$11<=A15)*Social!$K$6:$K$11) -> 433.33333 | AG15: =AC15*IF(A15<=12,Ipotesi!$B$38,Ipotesi!$B$39)*Ipotesi!$B$22 -> 862.8444 | AH15: =AD15-AE15-AF15-AG15 -> 779.95827 | AI15: =AI14+AH15 -> 1528.9712 | AJ15: =U15+AI15 -> 30522.549 | AK15: =AC15*Ipotesi!$B$37*Ipotesi!$B$20+IF(A15>Ipotesi!$B$21,INDEX($AC$5:$AC$40,A15-Ipotesi!$B$21)*Ipotesi!$B$37*(1-Ipotesi!$B$20),0)+(AA15-AC15)*Ipotesi!$B$19 -> 2552.913 | AL15: =X15+SUM($AK$5:AK15)-SUM($AE$5:AE15)-SUM($AG$5:AG15) -> 10832.108 | AM15: =IF(AJ15>=0,A15,999) -> 11
A16: 12 | B16: =INT((A16-1)/12)+1 -> 1 | C16: =MOD(Ipotesi!$B$7-1+A16-1,12)+1 -> 10 | D16: =INDEX(Ipotesi!$B$58:$B$69,C16) -> 1.1 | E16: =Ipotesi!$C$47*MIN(1,(A16/Ipotesi!$B$18)^2)*(1+Ipotesi!$C$48)^(MAX(0,A16-12)/12)*D16 -> 6600 | F16: =E16*Ipotesi!$C$49 -> 19.8 | G16: =F16*Ipotesi!$C$50 -> 7.92 | H16: =G16*Ipotesi!$C$51 -> 4.752 | I16: =IF(A16<=12,Ipotesi!$B$42,Ipotesi!$B$43) -> 8.9219331 | J16: =MIN(H16,I16) -> 4.752 | K16: =H16-J16 -> 0 | L16: =J16*Ipotesi!$B$37 -> 9670.32 | M16: =(G16-J16)*Ipotesi!$B$19 -> 316.8 | N16: =IF(A16>=Ipotesi!$B$26,Ipotesi!$C$52*Ipotesi!$B$25/12,0) -> 0 | O16: =IF(A16>=Ipotesi!$B$27,Ipotesi!$C$53,0) -> 0 | P16: =SUM(L16:O16) -> 9987.12 | Q16: =IF(A16=1,Ipotesi!$B$10+Ipotesi!$B$11,0)+Ipotesi!$B$8*Ipotesi!$B$9+Ipotesi!$B$12+Ipotesi!$B$13+Ipotesi!$B$16*52/12*Ipotesi!$B$17 -> 620 | R16: =Ipotesi!$B$14*52/12*Ipotesi!$B$15 -> 1040 | S16: =J16*IF(A16<=12,Ipotesi!$B$38,Ipotesi!$B$39)*Ipotesi!$B$22 -> 2876.148 | T16: =P16-Q16-R16-S16 -> 5450.972 | U16: =U15+T16 -> 34444.55 | V16: =L16*Ipotesi!$B$20+IF(A16>Ipotesi!$B$21,INDEX($L$5:$L$40,A16-Ipotesi!$B$21)*(1-Ipotesi!$B$20),0)+M16+N16+O16 -> 10426.68 | W16: =V16-Q16-S16 -> 6930.532 | X16: =X15+W16 -> 20550.95 | Y16: =IF(U16>=0,A16,999) -> 12 | Z16: =F16*SUMPRODUCT((Social!$C$6:$C$11<=A16)*Social!$B$6:$B$11*Social!$I$6:$I$11) -> 5.94 | AA16: =Z16*Ipotesi!$C$50 -> 2.376 | AB16: =AA16*Ipotesi!$C$51 -> 1.4256 | AC16: =MIN(AB16,MAX(0,I16-J16)) -> 1.4256 | AD16: =AC16*Ipotesi!$B$37+(AA16-AC16)*Ipotesi!$B$19 -> 2996.136 | AE16: =SUMPRODUCT((Social!$C$6:$C$11<=A16)*Social!$J$6:$J$11) -> 920 | AF16: =SUMPRODUCT((Social!$C$6:$C$11<=A16)*Social!$K$6:$K$11) -> 433.33333 | AG16: =AC16*IF(A16<=12,Ipotesi!$B$38,Ipotesi!$B$39)*Ipotesi!$B$22 -> 862.8444 | AH16: =AD16-AE16-AF16-AG16 -> 779.95827 | AI16: =AI15+AH16 -> 2308.9295 | AJ16: =U16+AI16 -> 36753.479 | AK16: =AC16*Ipotesi!$B$37*Ipotesi!$B$20+IF(A16>Ipotesi!$B$21,INDEX($AC$5:$AC$40,A16-Ipotesi!$B$21)*Ipotesi!$B$37*(1-Ipotesi!$B$20),0)+(AA16-AC16)*Ipotesi!$B$19 -> 3128.004 | AL16: =X16+SUM($AK$5:AK16)-SUM($AE$5:AE16)-SUM($AG$5:AG16) -> 19107.799 | AM16: =IF(AJ16>=0,A16,999) -> 12
A17: 13 | B17: =INT((A17-1)/12)+1 -> 2 | C17: =MOD(Ipotesi!$B$7-1+A17-1,12)+1 -> 11 | D17: =INDEX(Ipotesi!$B$58:$B$69,C17) -> 1 | E17: =Ipotesi!$C$47*MIN(1,(A17/Ipotesi!$B$18)^2)*(1+Ipotesi!$C$48)^(MAX(0,A17-12)/12)*D17 -> 6170.6169 | F17: =E17*Ipotesi!$C$49 -> 18.511851 | G17: =F17*Ipotesi!$C$50 -> 7.4047403 | H17: =G17*Ipotesi!$C$51 -> 4.4428442 | I17: =IF(A17<=12,Ipotesi!$B$42,Ipotesi!$B$43) -> 10.041841 | J17: =MIN(H17,I17) -> 4.4428442 | K17: =H17-J17 -> 0 | L17: =J17*Ipotesi!$B$37 -> 9041.1879 | M17: =(G17-J17)*Ipotesi!$B$19 -> 296.18961 | N17: =IF(A17>=Ipotesi!$B$26,Ipotesi!$C$52*Ipotesi!$B$25/12,0) -> 500 | O17: =IF(A17>=Ipotesi!$B$27,Ipotesi!$C$53,0) -> 0 | P17: =SUM(L17:O17) -> 9837.3775 | Q17: =IF(A17=1,Ipotesi!$B$10+Ipotesi!$B$11,0)+Ipotesi!$B$8*Ipotesi!$B$9+Ipotesi!$B$12+Ipotesi!$B$13+Ipotesi!$B$16*52/12*Ipotesi!$B$17 -> 620 | R17: =Ipotesi!$B$14*52/12*Ipotesi!$B$15 -> 1040 | S17: =J17*IF(A17<=12,Ipotesi!$B$38,Ipotesi!$B$39)*Ipotesi!$B$22 -> 2389.1395 | T17: =P17-Q17-R17-S17 -> 5788.2381 | U17: =U16+T17 -> 40232.788 | V17: =L17*Ipotesi!$B$20+IF(A17>Ipotesi!$B$21,INDEX($L$5:$L$40,A17-Ipotesi!$B$21)*(1-Ipotesi!$B$20),0)+M17+N17+O17 -> 10151.944 | W17: =V17-Q17-S17 -> 7142.8041 | X17: =X16+W17 -> 27693.754 | Y17: =IF(U17>=0,A17,999) -> 13 | Z17: =F17*SUMPRODUCT((Social!$C$6:$C$11<=A17)*Social!$B$6:$B$11*Social!$I$6:$I$11) -> 5.5535552 | AA17: =Z17*Ipotesi!$C$50 -> 2.2214221 | AB17: =AA17*Ipotesi!$C$51 -> 1.3328533 | AC17: =MIN(AB17,MAX(0,I17-J17)) -> 1.3328533 | AD17: =AC17*Ipotesi!$B$37+(AA17-AC17)*Ipotesi!$B$19 -> 2801.2133 | AE17: =SUMPRODUCT((Social!$C$6:$C$11<=A17)*Social!$J$6:$J$11) -> 920 | AF17: =SUMPRODUCT((Social!$C$6:$C$11<=A17)*Social!$K$6:$K$11) -> 433.33333 | AG17: =AC17*IF(A17<=12,Ipotesi!$B$38,Ipotesi!$B$39)*Ipotesi!$B$22 -> 716.74184 | AH17: =AD17-AE17-AF17-AG17 -> 731.13809 | AI17: =AI16+AH17 -> 3040.0675 | AJ17: =U17+AI17 -> 43272.856 | AK17: =AC17*Ipotesi!$B$37*Ipotesi!$B$20+IF(A17>Ipotesi!$B$21,INDEX($AC$5:$AC$40,A17-Ipotesi!$B$21)*Ipotesi!$B$37*(1-Ipotesi!$B$20),0)+(AA17-AC17)*Ipotesi!$B$19 -> 2895.5831 | AL17: =X17+SUM($AK$5:AK17)-SUM($AE$5:AE17)-SUM($AG$5:AG17) -> 27509.445 | AM17: =IF(AJ17>=0,A17,999) -> 13
... A40: 36 | B40: =INT((A40-1)/12)+1 -> 3 | C40: =MOD(Ipotesi!$B$7-1+A40-1,12)+1 -> 10 | D40: =INDEX(Ipotesi!$B$58:$B$69,C40) -> 1.1 | E40: =Ipotesi!$C$47*MIN(1,(A40/Ipotesi!$B$18)^2)*(1+Ipotesi!$C$48)^(MAX(0,A40-12)/12)*D40 -> 12936 | F40: =E40*Ipotesi!$C$49 -> 38.808 | G40: =F40*Ipotesi!$C$50 -> 15.5232 | H40: =G40*Ipotesi!$C$51 -> 9.31392 | I40: =IF(A40<=12,Ipotesi!$B$42,Ipotesi!$B$43) -> 10.041841 | J40: =MIN(H40,I40) -> 9.31392 | K40: =H40-J40 -> 0 | L40: =J40*Ipotesi!$B$37 -> 18953.827 | M40: =(G40-J40)*Ipotesi!$B$19 -> 620.928 | N40: =IF(A40>=Ipotesi!$B$26,Ipotesi!$C$52*Ipotesi!$B$25/12,0) -> 500 | O40: =IF(A40>=Ipotesi!$B$27,Ipotesi!$C$53,0) -> 500 | P40: =SUM(L40:O40) -> 20574.755 | Q40: =IF(A40=1,Ipotesi!$B$10+Ipotesi!$B$11,0)+Ipotesi!$B$8*Ipotesi!$B$9+Ipotesi!$B$12+Ipotesi!$B$13+Ipotesi!$B$16*52/12*Ipotesi!$B$17 -> 620 | R40: =Ipotesi!$B$14*52/12*Ipotesi!$B$15 -> 1040 | S40: =J40*IF(A40<=12,Ipotesi!$B$38,Ipotesi!$B$39)*Ipotesi!$B$22 -> 5008.5605 | T40: =P40-Q40-R40-S40 -> 13906.195 | U40: =U39+T40 -> 247696.45 | V40: =L40*Ipotesi!$B$20+IF(A40>Ipotesi!$B$21,INDEX($L$5:$L$40,A40-Ipotesi!$B$21)*(1-Ipotesi!$B$20),0)+M40+N40+O40 -> 19835.428 | W40: =V40-Q40-S40 -> 14206.867 | X40: =X39+W40 -> 236883.95 | Y40: =IF(U40>=0,A40,999) -> 36 | Z40: =F40*SUMPRODUCT((Social!$C$6:$C$11<=A40)*Social!$B$6:$B$11*Social!$I$6:$I$11) -> 11.6424 | AA40: =Z40*Ipotesi!$C$50 -> 4.65696 | AB40: =AA40*Ipotesi!$C$51 -> 2.794176 | AC40: =MIN(AB40,MAX(0,I40-J40)) -> 0.727921 | AD40: =AC40*Ipotesi!$B$37+(AA40-AC40)*Ipotesi!$B$19 -> 1874.2231 | AE40: =SUMPRODUCT((Social!$C$6:$C$11<=A40)*Social!$J$6:$J$11) -> 920 | AF40: =SUMPRODUCT((Social!$C$6:$C$11<=A40)*Social!$K$6:$K$11) -> 433.33333 | AG40: =AC40*IF(A40<=12,Ipotesi!$B$38,Ipotesi!$B$39)*Ipotesi!$B$22 -> 391.43952 | AH40: =AD40-AE40-AF40-AG40 -> 129.45029 | AI40: =AI39+AH40 -> 32700.663 | AJ40: =U40+AI40 -> 280397.12 | AK40: =AC40*Ipotesi!$B$37*Ipotesi!$B$20+IF(A40>Ipotesi!$B$21,INDEX($AC$5:$AC$40,A40-Ipotesi!$B$21)*Ipotesi!$B$37*(1-Ipotesi!$B$20),0)+(AA40-AC40)*Ipotesi!$B$19 -> 2613.5507 | AL40: =X40+SUM($AK$5:AK40)-SUM($AE$5:AE40)-SUM($AG$5:AG40) -> 274102.68 | AM40: =IF(AJ40>=0,A40,999) -> 36
A41: Totale 36 mesi | E41: =SUM(E5:E40) -> 261281.28 | F41: =SUM(F5:F40) -> 783.84385 | G41: =SUM(G5:G40) -> 313.53754 | H41: =SUM(H5:H40) -> 188.12253 | J41: =SUM(J5:J40) -> 188.12253 | K41: =SUM(K5:K40) -> 0 | L41: =SUM(L5:L40) -> 382829.34 | M41: =SUM(M5:M40) -> 12541.502 | N41: =SUM(N5:N40) -> 12000 | O41: =SUM(O5:O40) -> 6000 | P41: =SUM(P5:P40) -> 413370.84 | Q41: =SUM(Q5:Q40) -> 24520 | ... T41: =SUM(T5:T40) -> 247696.45 | V41: =SUM(V5:V40) -> 365118.34 | W41: =SUM(W5:W40) -> 236883.95 | Z41: =SUM(Z5:Z40) -> 234.84566 | AA41: =SUM(AA5:AA40) -> 93.938263 | AB41: =SUM(AB5:AB40) -> 56.362958 | AC41: =SUM(AC5:AC40) -> 50.88374 | AD41: =SUM(AD5:AD40) -> 107853.86 | AE41: =SUM(AE5:AE40) -> 32470 | AF41: =SUM(AF5:AF40) -> 14560 | AG41: =SUM(AG5:AG40) -> 28123.199 | AH41: =SUM(AH5:AH40) -> 32700.663 | AK41: =SUM(AK5:AK40) -> 97811.927

Sheet Scenario Buono
A1: Scenario Buono — modello mensile su 36 mesi
A2: Calcolato dalle ipotesi: non modificare. Valori in euro, al netto di IVA, Cassa Forense e imposte.
A4: Mese n. | B4: Anno | C4: Mese calendario | D4: Stagionalità | E4: Visualizzazioni | F4: Contatti | G4: Consulenze a pagamento | H4: Incarichi richiesti | I4: Capacità (incarichi) | J4: Incarichi acquisiti | K4: Incarichi persi per capacità | L4: Ricavi incarichi (€) | M4: Ricavi consulenze (€) | N4: Ricavi convenzioni (€) | O4: Ricavi formazione (€) | P4: Ricavi totali (€) | Q4: Costi canale cassa (€) | R4: Tempo avvocato canale (€) | S4: Costo erogazione incarichi (€) | T4: Margine economico (€) | U4: Margine cumulato (€) | V4: Incassi (€) | W4: Flusso di cassa (€) | X4: Cassa cumulata (€) | Y4: Aiuto: mese di pareggio | Z4: Contatti da altri social | AA4: Consulenze da altri social | AB4: Incarichi social richiesti | AC4: Incarichi social acquisiti | AD4: Ricavi da altri social (€) | AE4: Costi social cassa (€) | AF4: Tempo avvocato social (€) | AG4: Costo erogazione social (€) | AH4: Margine altri social (€) | AI4: Margine social cumulato (€) | AJ4: Margine totale cumulato (€) | AK4: Incassi da altri social (€) | AL4: Cassa cumulata totale (€) | AM4: Aiuto: pareggio totale
A5: 1 | B5: =INT((A5-1)/12)+1 -> 1 | C5: =MOD(Ipotesi!$B$7-1+A5-1,12)+1 -> 11 | D5: =INDEX(Ipotesi!$B$58:$B$69,C5) -> 1 | E5: =Ipotesi!$D$47*MIN(1,(A5/Ipotesi!$B$18)^2)*(1+Ipotesi!$D$48)^(MAX(0,A5-12)/12)*D5 -> 416.66667 | F5: =E5*Ipotesi!$D$49 -> 1.4583333 | G5: =F5*Ipotesi!$D$50 -> 0.65625 | H5: =G5*Ipotesi!$D$51 -> 0.39375 | I5: =IF(A5<=12,Ipotesi!$B$42,Ipotesi!$B$43) -> 8.9219331 | J5: =MIN(H5,I5) -> 0.39375 | K5: =H5-J5 -> 0 | L5: =J5*Ipotesi!$B$37 -> 801.28125 | M5: =(G5-J5)*Ipotesi!$B$19 -> 26.25 | N5: =IF(A5>=Ipotesi!$B$26,Ipotesi!$D$52*Ipotesi!$B$25/12,0) -> 0 | O5: =IF(A5>=Ipotesi!$B$27,Ipotesi!$D$53,0) -> 0 | P5: =SUM(L5:O5) -> 827.53125 | Q5: =IF(A5=1,Ipotesi!$B$10+Ipotesi!$B$11,0)+Ipotesi!$B$8*Ipotesi!$B$9+Ipotesi!$B$12+Ipotesi!$B$13+Ipotesi!$B$16*52/12*Ipotesi!$B$17 -> 2820 | R5: =Ipotesi!$B$14*52/12*Ipotesi!$B$15 -> 1040 | S5: =J5*IF(A5<=12,Ipotesi!$B$38,Ipotesi!$B$39)*Ipotesi!$B$22 -> 238.31719 | T5: =P5-Q5-R5-S5 -> -3270.7859 | U5: =T5 -> -3270.7859 | V5: =L5*Ipotesi!$B$20+IF(A5>Ipotesi!$B$21,INDEX($L$5:$L$40,A5-Ipotesi!$B$21)*(1-Ipotesi!$B$20),0)+M5+N5+O5 -> 426.89062 | W5: =V5-Q5-S5 -> -2631.4266 | X5: =W5 -> -2631.4266 | Y5: =IF(U5>=0,A5,999) -> 999 | Z5: =F5*SUMPRODUCT((Social!$C$6:$C$11<=A5)*Social!$B$6:$B$11*Social!$I$6:$I$11) -> 0.36458333 | AA5: =Z5*Ipotesi!$D$50 -> 0.1640625 | AB5: =AA5*Ipotesi!$D$51 -> 0.0984375 | AC5: =MIN(AB5,MAX(0,I5-J5)) -> 0.0984375 | AD5: =AC5*Ipotesi!$B$37+(AA5-AC5)*Ipotesi!$B$19 -> 206.88281 | AE5: =SUMPRODUCT((Social!$C$6:$C$11<=A5)*Social!$J$6:$J$11) -> 703.33333 | AF5: =SUMPRODUCT((Social!$C$6:$C$11<=A5)*Social!$K$6:$K$11) -> 86.666667 | AG5: =AC5*IF(A5<=12,Ipotesi!$B$38,Ipotesi!$B$39)*Ipotesi!$B$22 -> 59.579297 | AH5: =AD5-AE5-AF5-AG5 -> -642.69648 | AI5: =AH5 -> -642.69648 | AJ5: =U5+AI5 -> -3913.4824 | AK5: =AC5*Ipotesi!$B$37*Ipotesi!$B$20+IF(A5>Ipotesi!$B$21,INDEX($AC$5:$AC$40,A5-Ipotesi!$B$21)*Ipotesi!$B$37*(1-Ipotesi!$B$20),0)+(AA5-AC5)*Ipotesi!$B$19 -> 106.72266 | AL5: =X5+SUM($AK$5:AK5)-SUM($AE$5:AE5)-SUM($AG$5:AG5) -> -3287.6165 | AM5: =IF(AJ5>=0,A5,999) -> 999
A6: 2 | B6: =INT((A6-1)/12)+1 -> 1 | C6: =MOD(Ipotesi!$B$7-1+A6-1,12)+1 -> 12 | D6: =INDEX(Ipotesi!$B$58:$B$69,C6) -> 0.8 | E6: =Ipotesi!$D$47*MIN(1,(A6/Ipotesi!$B$18)^2)*(1+Ipotesi!$D$48)^(MAX(0,A6-12)/12)*D6 -> 1333.3333 | F6: =E6*Ipotesi!$D$49 -> 4.6666667 | G6: =F6*Ipotesi!$D$50 -> 2.1 | H6: =G6*Ipotesi!$D$51 -> 1.26 | I6: =IF(A6<=12,Ipotesi!$B$42,Ipotesi!$B$43) -> 8.9219331 | J6: =MIN(H6,I6) -> 1.26 | K6: =H6-J6 -> 0 | L6: =J6*Ipotesi!$B$37 -> 2564.1 | M6: =(G6-J6)*Ipotesi!$B$19 -> 84 | N6: =IF(A6>=Ipotesi!$B$26,Ipotesi!$D$52*Ipotesi!$B$25/12,0) -> 0 | O6: =IF(A6>=Ipotesi!$B$27,Ipotesi!$D$53,0) -> 0 | P6: =SUM(L6:O6) -> 2648.1 | Q6: =IF(A6=1,Ipotesi!$B$10+Ipotesi!$B$11,0)+Ipotesi!$B$8*Ipotesi!$B$9+Ipotesi!$B$12+Ipotesi!$B$13+Ipotesi!$B$16*52/12*Ipotesi!$B$17 -> 620 | R6: =Ipotesi!$B$14*52/12*Ipotesi!$B$15 -> 1040 | S6: =J6*IF(A6<=12,Ipotesi!$B$38,Ipotesi!$B$39)*Ipotesi!$B$22 -> 762.615 | T6: =P6-Q6-R6-S6 -> 225.485 | U6: =U5+T6 -> -3045.3009 | V6: =L6*Ipotesi!$B$20+IF(A6>Ipotesi!$B$21,INDEX($L$5:$L$40,A6-Ipotesi!$B$21)*(1-Ipotesi!$B$20),0)+M6+N6+O6 -> 1366.05 | W6: =V6-Q6-S6 -> -16.565 | X6: =X5+W6 -> -2647.9916 | Y6: =IF(U6>=0,A6,999) -> 999 | Z6: =F6*SUMPRODUCT((Social!$C$6:$C$11<=A6)*Social!$B$6:$B$11*Social!$I$6:$I$11) -> 1.1666667 | AA6: =Z6*Ipotesi!$D$50 -> 0.525 | AB6: =AA6*Ipotesi!$D$51 -> 0.315 | AC6: =MIN(AB6,MAX(0,I6-J6)) -> 0.315 | AD6: =AC6*Ipotesi!$B$37+(AA6-AC6)*Ipotesi!$B$19 -> 662.025 | AE6: =SUMPRODUCT((Social!$C$6:$C$11<=A6)*Social!$J$6:$J$11) -> 703.33333 | AF6: =SUMPRODUCT((Social!$C$6:$C$11<=A6)*Social!$K$6:$K$11) -> 86.666667 | AG6: =AC6*IF(A6<=12,Ipotesi!$B$38,Ipotesi!$B$39)*Ipotesi!$B$22 -> 190.65375 | AH6: =AD6-AE6-AF6-AG6 -> -318.62875 | AI6: =AI5+AH6 -> -961.32523 | AJ6: =U6+AI6 -> -4006.6262 | AK6: =AC6*Ipotesi!$B$37*Ipotesi!$B$20+IF(A6>Ipotesi!$B$21,INDEX($AC$5:$AC$40,A6-Ipotesi!$B$21)*Ipotesi!$B$37*(1-Ipotesi!$B$20),0)+(AA6-AC6)*Ipotesi!$B$19 -> 341.5125 | AL6: =X6+SUM($AK$5:AK6)-SUM($AE$5:AE6)-SUM($AG$5:AG6) -> -3856.6561 | AM6: =IF(AJ6>=0,A6,999) -> 999
A7: 3 | B7: =INT((A7-1)/12)+1 -> 1 | C7: =MOD(Ipotesi!$B$7-1+A7-1,12)+1 -> 1 | D7: =INDEX(Ipotesi!$B$58:$B$69,C7) -> 0.9 | E7: =Ipotesi!$D$47*MIN(1,(A7/Ipotesi!$B$18)^2)*(1+Ipotesi!$D$48)^(MAX(0,A7-12)/12)*D7 -> 3375 | F7: =E7*Ipotesi!$D$49 -> 11.8125 | G7: =F7*Ipotesi!$D$50 -> 5.315625 | H7: =G7*Ipotesi!$D$51 -> 3.189375 | I7: =IF(A7<=12,Ipotesi!$B$42,Ipotesi!$B$43) -> 8.9219331 | J7: =MIN(H7,I7) -> 3.189375 | K7: =H7-J7 -> 0 | L7: =J7*Ipotesi!$B$37 -> 6490.3781 | M7: =(G7-J7)*Ipotesi!$B$19 -> 212.625 | N7: =IF(A7>=Ipotesi!$B$26,Ipotesi!$D$52*Ipotesi!$B$25/12,0) -> 0 | O7: =IF(A7>=Ipotesi!$B$27,Ipotesi!$D$53,0) -> 0 | P7: =SUM(L7:O7) -> 6703.0031 | Q7: =IF(A7=1,Ipotesi!$B$10+Ipotesi!$B$11,0)+Ipotesi!$B$8*Ipotesi!$B$9+Ipotesi!$B$12+Ipotesi!$B$13+Ipotesi!$B$16*52/12*Ipotesi!$B$17 -> 620 | R7: =Ipotesi!$B$14*52/12*Ipotesi!$B$15 -> 1040 | S7: =J7*IF(A7<=12,Ipotesi!$B$38,Ipotesi!$B$39)*Ipotesi!$B$22 -> 1930.3692 | T7: =P7-Q7-R7-S7 -> 3112.6339 | U7: =U6+T7 -> 67.332969 | V7: =L7*Ipotesi!$B$20+IF(A7>Ipotesi!$B$21,INDEX($L$5:$L$40,A7-Ipotesi!$B$21)*(1-Ipotesi!$B$20),0)+M7+N7+O7 -> 3457.8141 | W7: =V7-Q7-S7 -> 907.44484 | X7: =X6+W7 -> -1740.5467 | Y7: =IF(U7>=0,A7,999) -> 3 | Z7: =F7*SUMPRODUCT((Social!$C$6:$C$11<=A7)*Social!$B$6:$B$11*Social!$I$6:$I$11) -> 2.953125 | AA7: =Z7*Ipotesi!$D$50 -> 1.3289062 | AB7: =AA7*Ipotesi!$D$51 -> 0.79734375 | AC7: =MIN(AB7,MAX(0,I7-J7)) -> 0.79734375 | AD7: =AC7*Ipotesi!$B$37+(AA7-AC7)*Ipotesi!$B$19 -> 1675.7508 | AE7: =SUMPRODUCT((Social!$C$6:$C$11<=A7)*Social!$J$6:$J$11) -> 703.33333 | AF7: =SUMPRODUCT((Social!$C$6:$C$11<=A7)*Social!$K$6:$K$11) -> 86.666667 | AG7: =AC7*IF(A7<=12,Ipotesi!$B$38,Ipotesi!$B$39)*Ipotesi!$B$22 -> 482.5923 | AH7: =AD7-AE7-AF7-AG7 -> 403.15848 | AI7: =AI6+AH7 -> -558.16676 | AJ7: =U7+AI7 -> -490.83379 | AK7: =AC7*Ipotesi!$B$37*Ipotesi!$B$20+IF(A7>Ipotesi!$B$21,INDEX($AC$5:$AC$40,A7-Ipotesi!$B$21)*Ipotesi!$B$37*(1-Ipotesi!$B$20),0)+(AA7-AC7)*Ipotesi!$B$19 -> 864.45352 | AL7: =X7+SUM($AK$5:AK7)-SUM($AE$5:AE7)-SUM($AG$5:AG7) -> -3270.6834 | AM7: =IF(AJ7>=0,A7,999) -> 999
A8: 4 | B8: =INT((A8-1)/12)+1 -> 1 | C8: =MOD(Ipotesi!$B$7-1+A8-1,12)+1 -> 2 | D8: =INDEX(Ipotesi!$B$58:$B$69,C8) -> 1 | E8: =Ipotesi!$D$47*MIN(1,(A8/Ipotesi!$B$18)^2)*(1+Ipotesi!$D$48)^(MAX(0,A8-12)/12)*D8 -> 6666.6667 | F8: =E8*Ipotesi!$D$49 -> 23.333333 | G8: =F8*Ipotesi!$D$50 -> 10.5 | H8: =G8*Ipotesi!$D$51 -> 6.3 | I8: =IF(A8<=12,Ipotesi!$B$42,Ipotesi!$B$43) -> 8.9219331 | J8: =MIN(H8,I8) -> 6.3 | K8: =H8-J8 -> 0 | L8: =J8*Ipotesi!$B$37 -> 12820.5 | M8: =(G8-J8)*Ipotesi!$B$19 -> 420 | N8: =IF(A8>=Ipotesi!$B$26,Ipotesi!$D$52*Ipotesi!$B$25/12,0) -> 0 | O8: =IF(A8>=Ipotesi!$B$27,Ipotesi!$D$53,0) -> 0 | P8: =SUM(L8:O8) -> 13240.5 | Q8: =IF(A8=1,Ipotesi!$B$10+Ipotesi!$B$11,0)+Ipotesi!$B$8*Ipotesi!$B$9+Ipotesi!$B$12+Ipotesi!$B$13+Ipotesi!$B$16*52/12*Ipotesi!$B$17 -> 620 | R8: =Ipotesi!$B$14*52/12*Ipotesi!$B$15 -> 1040 | S8: =J8*IF(A8<=12,Ipotesi!$B$38,Ipotesi!$B$39)*Ipotesi!$B$22 -> 3813.075 | T8: =P8-Q8-R8-S8 -> 7767.425 | U8: =U7+T8 -> 7834.758 | V8: =L8*Ipotesi!$B$20+IF(A8>Ipotesi!$B$21,INDEX($L$5:$L$40,A8-Ipotesi!$B$21)*(1-Ipotesi!$B$20),0)+M8+N8+O8 -> 6830.25 | W8: =V8-Q8-S8 -> 2397.175 | X8: =X7+W8 -> 656.62828 | Y8: =IF(U8>=0,A8,999) -> 4 | Z8: =F8*SUMPRODUCT((Social!$C$6:$C$11<=A8)*Social!$B$6:$B$11*Social!$I$6:$I$11) -> 7 | AA8: =Z8*Ipotesi!$D$50 -> 3.15 | AB8: =AA8*Ipotesi!$D$51 -> 1.89 | AC8: =MIN(AB8,MAX(0,I8-J8)) -> 1.89 | AD8: =AC8*Ipotesi!$B$37+(AA8-AC8)*Ipotesi!$B$19 -> 3972.15 | AE8: =SUMPRODUCT((Social!$C$6:$C$11<=A8)*Social!$J$6:$J$11) -> 920 | AF8: =SUMPRODUCT((Social!$C$6:$C$11<=A8)*Social!$K$6:$K$11) -> 433.33333 | AG8: =AC8*IF(A8<=12,Ipotesi!$B$38,Ipotesi!$B$39)*Ipotesi!$B$22 -> 1143.9225 | AH8: =AD8-AE8-AF8-AG8 -> 1474.8942 | AI8: =AI7+AH8 -> 916.72741 | AJ8: =U8+AI8 -> 8751.4854 | AK8: =AC8*Ipotesi!$B$37*Ipotesi!$B$20+IF(A8>Ipotesi!$B$21,INDEX($AC$5:$AC$40,A8-Ipotesi!$B$21)*Ipotesi!$B$37*(1-Ipotesi!$B$20),0)+(AA8-AC8)*Ipotesi!$B$19 -> 2049.075 | AL8: =X8+SUM($AK$5:AK8)-SUM($AE$5:AE8)-SUM($AG$5:AG8) -> -888.3559 | AM8: =IF(AJ8>=0,A8,999) -> 4
A9: 5 | B9: =INT((A9-1)/12)+1 -> 1 | C9: =MOD(Ipotesi!$B$7-1+A9-1,12)+1 -> 3 | D9: =INDEX(Ipotesi!$B$58:$B$69,C9) -> 1.1 | E9: =Ipotesi!$D$47*MIN(1,(A9/Ipotesi!$B$18)^2)*(1+Ipotesi!$D$48)^(MAX(0,A9-12)/12)*D9 -> 11458.333 | F9: =E9*Ipotesi!$D$49 -> 40.104167 | G9: =F9*Ipotesi!$D$50 -> 18.046875 | H9: =G9*Ipotesi!$D$51 -> 10.828125 | I9: =IF(A9<=12,Ipotesi!$B$42,Ipotesi!$B$43) -> 8.9219331 | J9: =MIN(H9,I9) -> 8.9219331 | K9: =H9-J9 -> 1.9061919 | L9: =J9*Ipotesi!$B$37 -> 18156.134 | M9: =(G9-J9)*Ipotesi!$B$19 -> 912.49419 | N9: =IF(A9>=Ipotesi!$B$26,Ipotesi!$D$52*Ipotesi!$B$25/12,0) -> 0 | O9: =IF(A9>=Ipotesi!$B$27,Ipotesi!$D$53,0) -> 0 | P9: =SUM(L9:O9) -> 19068.628 | Q9: =IF(A9=1,Ipotesi!$B$10+Ipotesi!$B$11,0)+Ipotesi!$B$8*Ipotesi!$B$9+Ipotesi!$B$12+Ipotesi!$B$13+Ipotesi!$B$16*52/12*Ipotesi!$B$17 -> 620 | R9: =Ipotesi!$B$14*52/12*Ipotesi!$B$15 -> 1040 | S9: =J9*IF(A9<=12,Ipotesi!$B$38,Ipotesi!$B$39)*Ipotesi!$B$22 -> 5400 | T9: =P9-Q9-R9-S9 -> 12008.628 | U9: =U8+T9 -> 19843.386 | V9: =L9*Ipotesi!$B$20+IF(A9>Ipotesi!$B$21,INDEX($L$5:$L$40,A9-Ipotesi!$B$21)*(1-Ipotesi!$B$20),0)+M9+N9+O9 -> 9990.5611 | W9: =V9-Q9-S9 -> 3970.5611 | X9: =X8+W9 -> 4627.1894 | Y9: =IF(U9>=0,A9,999) -> 5 | Z9: =F9*SUMPRODUCT((Social!$C$6:$C$11<=A9)*Social!$B$6:$B$11*Social!$I$6:$I$11) -> 12.03125 | AA9: =Z9*Ipotesi!$D$50 -> 5.4140625 | AB9: =AA9*Ipotesi!$D$51 -> 3.2484375 | AC9: =MIN(AB9,MAX(0,I9-J9)) -> 0 | AD9: =AC9*Ipotesi!$B$37+(AA9-AC9)*Ipotesi!$B$19 -> 541.40625 | AE9: =SUMPRODUCT((Social!$C$6:$C$11<=A9)*Social!$J$6:$J$11) -> 920 | AF9: =SUMPRODUCT((Social!$C$6:$C$11<=A9)*Social!$K$6:$K$11) -> 433.33333 | AG9: =AC9*IF(A9<=12,Ipotesi!$B$38,Ipotesi!$B$39)*Ipotesi!$B$22 -> 0 | AH9: =AD9-AE9-AF9-AG9 -> -811.92708 | AI9: =AI8+AH9 -> 104.80033 | AJ9: =U9+AI9 -> 19948.186 | AK9: =AC9*Ipotesi!$B$37*Ipotesi!$B$20+IF(A9>Ipotesi!$B$21,INDEX($AC$5:$AC$40,A9-Ipotesi!$B$21)*Ipotesi!$B$37*(1-Ipotesi!$B$20),0)+(AA9-AC9)*Ipotesi!$B$19 -> 541.40625 | AL9: =X9+SUM($AK$5:AK9)-SUM($AE$5:AE9)-SUM($AG$5:AG9) -> 2703.6115 | AM9: =IF(AJ9>=0,A9,999) -> 5
A10: 6 | B10: =INT((A10-1)/12)+1 -> 1 | C10: =MOD(Ipotesi!$B$7-1+A10-1,12)+1 -> 4 | D10: =INDEX(Ipotesi!$B$58:$B$69,C10) -> 1.2 | E10: =Ipotesi!$D$47*MIN(1,(A10/Ipotesi!$B$18)^2)*(1+Ipotesi!$D$48)^(MAX(0,A10-12)/12)*D10 -> 18000 | F10: =E10*Ipotesi!$D$49 -> 63 | G10: =F10*Ipotesi!$D$50 -> 28.35 | H10: =G10*Ipotesi!$D$51 -> 17.01 | I10: =IF(A10<=12,Ipotesi!$B$42,Ipotesi!$B$43) -> 8.9219331 | J10: =MIN(H10,I10) -> 8.9219331 | K10: =H10-J10 -> 8.0880669 | L10: =J10*Ipotesi!$B$37 -> 18156.134 | M10: =(G10-J10)*Ipotesi!$B$19 -> 1942.8067 | N10: =IF(A10>=Ipotesi!$B$26,Ipotesi!$D$52*Ipotesi!$B$25/12,0) -> 0 | O10: =IF(A10>=Ipotesi!$B$27,Ipotesi!$D$53,0) -> 0 | P10: =SUM(L10:O10) -> 20098.941 | Q10: =IF(A10=1,Ipotesi!$B$10+Ipotesi!$B$11,0)+Ipotesi!$B$8*Ipotesi!$B$9+Ipotesi!$B$12+Ipotesi!$B$13+Ipotesi!$B$16*52/12*Ipotesi!$B$17 -> 620 | R10: =Ipotesi!$B$14*52/12*Ipotesi!$B$15 -> 1040 | S10: =J10*IF(A10<=12,Ipotesi!$B$38,Ipotesi!$B$39)*Ipotesi!$B$22 -> 5400 | T10: =P10-Q10-R10-S10 -> 13038.941 | U10: =U9+T10 -> 32882.327 | V10: =L10*Ipotesi!$B$20+IF(A10>Ipotesi!$B$21,INDEX($L$5:$L$40,A10-Ipotesi!$B$21)*(1-Ipotesi!$B$20),0)+M10+N10+O10 -> 11020.874 | W10: =V10-Q10-S10 -> 5000.8736 | X10: =X9+W10 -> 9628.063 | Y10: =IF(U10>=0,A10,999) -> 6 | Z10: =F10*SUMPRODUCT((Social!$C$6:$C$11<=A10)*Social!$B$6:$B$11*Social!$I$6:$I$11) -> 18.9 | AA10: =Z10*Ipotesi!$D$50 -> 8.505 | AB10: =AA10*Ipotesi!$D$51 -> 5.103 | AC10: =MIN(AB10,MAX(0,I10-J10)) -> 0 | AD10: =AC10*Ipotesi!$B$37+(AA10-AC10)*Ipotesi!$B$19 -> 850.5 | AE10: =SUMPRODUCT((Social!$C$6:$C$11<=A10)*Social!$J$6:$J$11) -> 920 | AF10: =SUMPRODUCT((Social!$C$6:$C$11<=A10)*Social!$K$6:$K$11) -> 433.33333 | AG10: =AC10*IF(A10<=12,Ipotesi!$B$38,Ipotesi!$B$39)*Ipotesi!$B$22 -> 0 | AH10: =AD10-AE10-AF10-AG10 -> -502.83333 | AI10: =AI9+AH10 -> -398.03301 | AJ10: =U10+AI10 -> 32484.294 | AK10: =AC10*Ipotesi!$B$37*Ipotesi!$B$20+IF(A10>Ipotesi!$B$21,INDEX($AC$5:$AC$40,A10-Ipotesi!$B$21)*Ipotesi!$B$37*(1-Ipotesi!$B$20),0)+(AA10-AC10)*Ipotesi!$B$19 -> 850.5 | AL10: =X10+SUM($AK$5:AK10)-SUM($AE$5:AE10)-SUM($AG$5:AG10) -> 7634.9851 | AM10: =IF(AJ10>=0,A10,999) -> 6
A11: 7 | B11: =INT((A11-1)/12)+1 -> 1 | C11: =MOD(Ipotesi!$B$7-1+A11-1,12)+1 -> 5 | D11: =INDEX(Ipotesi!$B$58:$B$69,C11) -> 1.1 | E11: =Ipotesi!$D$47*MIN(1,(A11/Ipotesi!$B$18)^2)*(1+Ipotesi!$D$48)^(MAX(0,A11-12)/12)*D11 -> 16500 | F11: =E11*Ipotesi!$D$49 -> 57.75 | G11: =F11*Ipotesi!$D$50 -> 25.9875 | H11: =G11*Ipotesi!$D$51 -> 15.5925 | I11: =IF(A11<=12,Ipotesi!$B$42,Ipotesi!$B$43) -> 8.9219331 | J11: =MIN(H11,I11) -> 8.9219331 | K11: =H11-J11 -> 6.6705669 | L11: =J11*Ipotesi!$B$37 -> 18156.134 | M11: =(G11-J11)*Ipotesi!$B$19 -> 1706.5567 | N11: =IF(A11>=Ipotesi!$B$26,Ipotesi!$D$52*Ipotesi!$B$25/12,0) -> 0 | O11: =IF(A11>=Ipotesi!$B$27,Ipotesi!$D$53,0) -> 0 | P11: =SUM(L11:O11) -> 19862.691 | Q11: =IF(A11=1,Ipotesi!$B$10+Ipotesi!$B$11,0)+Ipotesi!$B$8*Ipotesi!$B$9+Ipotesi!$B$12+Ipotesi!$B$13+Ipotesi!$B$16*52/12*Ipotesi!$B$17 -> 620 | R11: =Ipotesi!$B$14*52/12*Ipotesi!$B$15 -> 1040 | S11: =J11*IF(A11<=12,Ipotesi!$B$38,Ipotesi!$B$39)*Ipotesi!$B$22 -> 5400 | T11: =P11-Q11-R11-S11 -> 12802.691 | U11: =U10+T11 -> 45685.017 | V11: =L11*Ipotesi!$B$20+IF(A11>Ipotesi!$B$21,INDEX($L$5:$L$40,A11-Ipotesi!$B$21)*(1-Ipotesi!$B$20),0)+M11+N11+O11 -> 11185.264 | W11: =V11-Q11-S11 -> 5165.2642 | X11: =X10+W11 -> 14793.327 | Y11: =IF(U11>=0,A11,999) -> 7 | Z11: =F11*SUMPRODUCT((Social!$C$6:$C$11<=A11)*Social!$B$6:$B$11*Social!$I$6:$I$11) -> 17.325 | AA11: =Z11*Ipotesi!$D$50 -> 7.79625 | AB11: =AA11*Ipotesi!$D$51 -> 4.67775 | AC11: =MIN(AB11,MAX(0,I11-J11)) -> 0 | AD11: =AC11*Ipotesi!$B$37+(AA11-AC11)*Ipotesi!$B$19 -> 779.625 | AE11: =SUMPRODUCT((Social!$C$6:$C$11<=A11)*Social!$J$6:$J$11) -> 920 | AF11: =SUMPRODUCT((Social!$C$6:$C$11<=A11)*Social!$K$6:$K$11) -> 433.33333 | AG11: =AC11*IF(A11<=12,Ipotesi!$B$38,Ipotesi!$B$39)*Ipotesi!$B$22 -> 0 | AH11: =AD11-AE11-AF11-AG11 -> -573.70833 | AI11: =AI10+AH11 -> -971.74134 | AJ11: =U11+AI11 -> 44713.276 | AK11: =AC11*Ipotesi!$B$37*Ipotesi!$B$20+IF(A11>Ipotesi!$B$21,INDEX($AC$5:$AC$40,A11-Ipotesi!$B$21)*Ipotesi!$B$37*(1-Ipotesi!$B$20),0)+(AA11-AC11)*Ipotesi!$B$19 -> 879.78516 | AL11: =X11+SUM($AK$5:AK11)-SUM($AE$5:AE11)-SUM($AG$5:AG11) -> 12760.034 | AM11: =IF(AJ11>=0,A11,999) -> 7
A12: 8 | B12: =INT((A12-1)/12)+1 -> 1 | C12: =MOD(Ipotesi!$B$7-1+A12-1,12)+1 -> 6 | D12: =INDEX(Ipotesi!$B$58:$B$69,C12) -> 1 | E12: =Ipotesi!$D$47*MIN(1,(A12/Ipotesi!$B$18)^2)*(1+Ipotesi!$D$48)^(MAX(0,A12-12)/12)*D12 -> 15000 | F12: =E12*Ipotesi!$D$49 -> 52.5 | G12: =F12*Ipotesi!$D$50 -> 23.625 | H12: =G12*Ipotesi!$D$51 -> 14.175 | I12: =IF(A12<=12,Ipotesi!$B$42,Ipotesi!$B$43) -> 8.9219331 | J12: =MIN(H12,I12) -> 8.9219331 | K12: =H12-J12 -> 5.2530669 | L12: =J12*Ipotesi!$B$37 -> 18156.134 | M12: =(G12-J12)*Ipotesi!$B$19 -> 1470.3067 | N12: =IF(A12>=Ipotesi!$B$26,Ipotesi!$D$52*Ipotesi!$B$25/12,0) -> 0 | O12: =IF(A12>=Ipotesi!$B$27,Ipotesi!$D$53,0) -> 0 | P12: =SUM(L12:O12) -> 19626.441 | Q12: =IF(A12=1,Ipotesi!$B$10+Ipotesi!$B$11,0)+Ipotesi!$B$8*Ipotesi!$B$9+Ipotesi!$B$12+Ipotesi!$B$13+Ipotesi!$B$16*52/12*Ipotesi!$B$17 -> 620 | R12: =Ipotesi!$B$14*52/12*Ipotesi!$B$15 -> 1040 | S12: =J12*IF(A12<=12,Ipotesi!$B$38,Ipotesi!$B$39)*Ipotesi!$B$22 -> 5400 | T12: =P12-Q12-R12-S12 -> 12566.441 | U12: =U11+T12 -> 58251.458 | V12: =L12*Ipotesi!$B$20+IF(A12>Ipotesi!$B$21,INDEX($L$5:$L$40,A12-Ipotesi!$B$21)*(1-Ipotesi!$B$20),0)+M12+N12+O12 -> 11830.424 | W12: =V12-Q12-S12 -> 5810.4236 | X12: =X11+W12 -> 20603.751 | Y12: =IF(U12>=0,A12,999) -> 8 | Z12: =F12*SUMPRODUCT((Social!$C$6:$C$11<=A12)*Social!$B$6:$B$11*Social!$I$6:$I$11) -> 15.75 | AA12: =Z12*Ipotesi!$D$50 -> 7.0875 | AB12: =AA12*Ipotesi!$D$51 -> 4.2525 | AC12: =MIN(AB12,MAX(0,I12-J12)) -> 0 | AD12: =AC12*Ipotesi!$B$37+(AA12-AC12)*Ipotesi!$B$19 -> 708.75 | AE12: =SUMPRODUCT((Social!$C$6:$C$11<=A12)*Social!$J$6:$J$11) -> 920 | AF12: =SUMPRODUCT((Social!$C$6:$C$11<=A12)*Social!$K$6:$K$11) -> 433.33333 | AG12: =AC12*IF(A12<=12,Ipotesi!$B$38,Ipotesi!$B$39)*Ipotesi!$B$22 -> 0 | AH12: =AD12-AE12-AF12-AG12 -> -644.58333 | AI12: =AI11+AH12 -> -1616.3247 | AJ12: =U12+AI12 -> 56635.133 | AK12: =AC12*Ipotesi!$B$37*Ipotesi!$B$20+IF(A12>Ipotesi!$B$21,INDEX($AC$5:$AC$40,A12-Ipotesi!$B$21)*Ipotesi!$B$37*(1-Ipotesi!$B$20),0)+(AA12-AC12)*Ipotesi!$B$19 -> 1029.2625 | AL12: =X12+SUM($AK$5:AK12)-SUM($AE$5:AE12)-SUM($AG$5:AG12) -> 18679.721 | AM12: =IF(AJ12>=0,A12,999) -> 8
A13: 9 | B13: =INT((A13-1)/12)+1 -> 1 | C13: =MOD(Ipotesi!$B$7-1+A13-1,12)+1 -> 7 | D13: =INDEX(Ipotesi!$B$58:$B$69,C13) -> 1 | E13: =Ipotesi!$D$47*MIN(1,(A13/Ipotesi!$B$18)^2)*(1+Ipotesi!$D$48)^(MAX(0,A13-12)/12)*D13 -> 15000 | F13: =E13*Ipotesi!$D$49 -> 52.5 | G13: =F13*Ipotesi!$D$50 -> 23.625 | H13: =G13*Ipotesi!$D$51 -> 14.175 | I13: =IF(A13<=12,Ipotesi!$B$42,Ipotesi!$B$43) -> 8.9219331 | J13: =MIN(H13,I13) -> 8.9219331 | K13: =H13-J13 -> 5.2530669 | L13: =J13*Ipotesi!$B$37 -> 18156.134 | M13: =(G13-J13)*Ipotesi!$B$19 -> 1470.3067 | N13: =IF(A13>=Ipotesi!$B$26,Ipotesi!$D$52*Ipotesi!$B$25/12,0) -> 0 | O13: =IF(A13>=Ipotesi!$B$27,Ipotesi!$D$53,0) -> 0 | P13: =SUM(L13:O13) -> 19626.441 | Q13: =IF(A13=1,Ipotesi!$B$10+Ipotesi!$B$11,0)+Ipotesi!$B$8*Ipotesi!$B$9+Ipotesi!$B$12+Ipotesi!$B$13+Ipotesi!$B$16*52/12*Ipotesi!$B$17 -> 620 | R13: =Ipotesi!$B$14*52/12*Ipotesi!$B$15 -> 1040 | S13: =J13*IF(A13<=12,Ipotesi!$B$38,Ipotesi!$B$39)*Ipotesi!$B$22 -> 5400 | T13: =P13-Q13-R13-S13 -> 12566.441 | U13: =U12+T13 -> 70817.898 | V13: =L13*Ipotesi!$B$20+IF(A13>Ipotesi!$B$21,INDEX($L$5:$L$40,A13-Ipotesi!$B$21)*(1-Ipotesi!$B$20),0)+M13+N13+O13 -> 13793.563 | W13: =V13-Q13-S13 -> 7773.5627 | X13: =X12+W13 -> 28377.313 | Y13: =IF(U13>=0,A13,999) -> 9 | Z13: =F13*SUMPRODUCT((Social!$C$6:$C$11<=A13)*Social!$B$6:$B$11*Social!$I$6:$I$11) -> 15.75 | AA13: =Z13*Ipotesi!$D$50 -> 7.0875 | AB13: =AA13*Ipotesi!$D$51 -> 4.2525 | AC13: =MIN(AB13,MAX(0,I13-J13)) -> 0 | AD13: =AC13*Ipotesi!$B$37+(AA13-AC13)*Ipotesi!$B$19 -> 708.75 | AE13: =SUMPRODUCT((Social!$C$6:$C$11<=A13)*Social!$J$6:$J$11) -> 920 | AF13: =SUMPRODUCT((Social!$C$6:$C$11<=A13)*Social!$K$6:$K$11) -> 433.33333 | AG13: =AC13*IF(A13<=12,Ipotesi!$B$38,Ipotesi!$B$39)*Ipotesi!$B$22 -> 0 | AH13: =AD13-AE13-AF13-AG13 -> -644.58333 | AI13: =AI12+AH13 -> -2260.908 | AJ13: =U13+AI13 -> 68556.99 | AK13: =AC13*Ipotesi!$B$37*Ipotesi!$B$20+IF(A13>Ipotesi!$B$21,INDEX($AC$5:$AC$40,A13-Ipotesi!$B$21)*Ipotesi!$B$37*(1-Ipotesi!$B$20),0)+(AA13-AC13)*Ipotesi!$B$19 -> 1520.0473 | AL13: =X13+SUM($AK$5:AK13)-SUM($AE$5:AE13)-SUM($AG$5:AG13) -> 27053.33 | AM13: =IF(AJ13>=0,A13,999) -> 9
A14: 10 | B14: =INT((A14-1)/12)+1 -> 1 | C14: =MOD(Ipotesi!$B$7-1+A14-1,12)+1 -> 8 | D14: =INDEX(Ipotesi!$B$58:$B$69,C14) -> 0.7 | E14: =Ipotesi!$D$47*MIN(1,(A14/Ipotesi!$B$18)^2)*(1+Ipotesi!$D$48)^(MAX(0,A14-12)/12)*D14 -> 10500 | F14: =E14*Ipotesi!$D$49 -> 36.75 | G14: =F14*Ipotesi!$D$50 -> 16.5375 | H14: =G14*Ipotesi!$D$51 -> 9.9225 | I14: =IF(A14<=12,Ipotesi!$B$42,Ipotesi!$B$43) -> 8.9219331 | J14: =MIN(H14,I14) -> 8.9219331 | K14: =H14-J14 -> 1.0005669 | L14: =J14*Ipotesi!$B$37 -> 18156.134 | M14: =(G14-J14)*Ipotesi!$B$19 -> 761.55669 | N14: =IF(A14>=Ipotesi!$B$26,Ipotesi!$D$52*Ipotesi!$B$25/12,0) -> 0 | O14: =IF(A14>=Ipotesi!$B$27,Ipotesi!$D$53,0) -> 0 | P14: =SUM(L14:O14) -> 18917.691 | Q14: =IF(A14=1,Ipotesi!$B$10+Ipotesi!$B$11,0)+Ipotesi!$B$8*Ipotesi!$B$9+Ipotesi!$B$12+Ipotesi!$B$13+Ipotesi!$B$16*52/12*Ipotesi!$B$17 -> 620 | R14: =Ipotesi!$B$14*52/12*Ipotesi!$B$15 -> 1040 | S14: =J14*IF(A14<=12,Ipotesi!$B$38,Ipotesi!$B$39)*Ipotesi!$B$22 -> 5400 | T14: =P14-Q14-R14-S14 -> 11857.691 | U14: =U13+T14 -> 82675.589 | V14: =L14*Ipotesi!$B$20+IF(A14>Ipotesi!$B$21,INDEX($L$5:$L$40,A14-Ipotesi!$B$21)*(1-Ipotesi!$B$20),0)+M14+N14+O14 -> 16249.874 | W14: =V14-Q14-S14 -> 10229.874 | X14: =X13+W14 -> 38607.187 | Y14: =IF(U14>=0,A14,999) -> 10 | Z14: =F14*SUMPRODUCT((Social!$C$6:$C$11<=A14)*Social!$B$6:$B$11*Social!$I$6:$I$11) -> 11.025 | AA14: =Z14*Ipotesi!$D$50 -> 4.96125 | AB14: =AA14*Ipotesi!$D$51 -> 2.97675 | AC14: =MIN(AB14,MAX(0,I14-J14)) -> 0 | AD14: =AC14*Ipotesi!$B$37+(AA14-AC14)*Ipotesi!$B$19 -> 496.125 | AE14: =SUMPRODUCT((Social!$C$6:$C$11<=A14)*Social!$J$6:$J$11) -> 920 | AF14: =SUMPRODUCT((Social!$C$6:$C$11<=A14)*Social!$K$6:$K$11) -> 433.33333 | AG14: =AC14*IF(A14<=12,Ipotesi!$B$38,Ipotesi!$B$39)*Ipotesi!$B$22 -> 0 | AH14: =AD14-AE14-AF14-AG14 -> -857.20833 | AI14: =AI13+AH14 -> -3118.1163 | AJ14: =U14+AI14 -> 79557.472 | AK14: =AC14*Ipotesi!$B$37*Ipotesi!$B$20+IF(A14>Ipotesi!$B$21,INDEX($AC$5:$AC$40,A14-Ipotesi!$B$21)*Ipotesi!$B$37*(1-Ipotesi!$B$20),0)+(AA14-AC14)*Ipotesi!$B$19 -> 2419.2 | AL14: =X14+SUM($AK$5:AK14)-SUM($AE$5:AE14)-SUM($AG$5:AG14) -> 38782.404 | AM14: =IF(AJ14>=0,A14,999) -> 10
A15: 11 | B15: =INT((A15-1)/12)+1 -> 1 | C15: =MOD(Ipotesi!$B$7-1+A15-1,12)+1 -> 9 | D15: =INDEX(Ipotesi!$B$58:$B$69,C15) -> 1.1 | E15: =Ipotesi!$D$47*MIN(1,(A15/Ipotesi!$B$18)^2)*(1+Ipotesi!$D$48)^(MAX(0,A15-12)/12)*D15 -> 16500 | F15: =E15*Ipotesi!$D$49 -> 57.75 | G15: =F15*Ipotesi!$D$50 -> 25.9875 | H15: =G15*Ipotesi!$D$51 -> 15.5925 | I15: =IF(A15<=12,Ipotesi!$B$42,Ipotesi!$B$43) -> 8.9219331 | J15: =MIN(H15,I15) -> 8.9219331 | K15: =H15-J15 -> 6.6705669 | L15: =J15*Ipotesi!$B$37 -> 18156.134 | M15: =(G15-J15)*Ipotesi!$B$19 -> 1706.5567 | N15: =IF(A15>=Ipotesi!$B$26,Ipotesi!$D$52*Ipotesi!$B$25/12,0) -> 0 | O15: =IF(A15>=Ipotesi!$B$27,Ipotesi!$D$53,0) -> 0 | P15: =SUM(L15:O15) -> 19862.691 | Q15: =IF(A15=1,Ipotesi!$B$10+Ipotesi!$B$11,0)+Ipotesi!$B$8*Ipotesi!$B$9+Ipotesi!$B$12+Ipotesi!$B$13+Ipotesi!$B$16*52/12*Ipotesi!$B$17 -> 620 | R15: =Ipotesi!$B$14*52/12*Ipotesi!$B$15 -> 1040 | S15: =J15*IF(A15<=12,Ipotesi!$B$38,Ipotesi!$B$39)*Ipotesi!$B$22 -> 5400 | T15: =P15-Q15-R15-S15 -> 12802.691 | U15: =U14+T15 -> 95478.279 | V15: =L15*Ipotesi!$B$20+IF(A15>Ipotesi!$B$21,INDEX($L$5:$L$40,A15-Ipotesi!$B$21)*(1-Ipotesi!$B$20),0)+M15+N15+O15 -> 19862.691 | W15: =V15-Q15-S15 -> 13842.691 | X15: =X14+W15 -> 52449.878 | Y15: =IF(U15>=0,A15,999) -> 11 | Z15: =F15*SUMPRODUCT((Social!$C$6:$C$11<=A15)*Social!$B$6:$B$11*Social!$I$6:$I$11) -> 17.325 | AA15: =Z15*Ipotesi!$D$50 -> 7.79625 | AB15: =AA15*Ipotesi!$D$51 -> 4.67775 | AC15: =MIN(AB15,MAX(0,I15-J15)) -> 0 | AD15: =AC15*Ipotesi!$B$37+(AA15-AC15)*Ipotesi!$B$19 -> 779.625 | AE15: =SUMPRODUCT((Social!$C$6:$C$11<=A15)*Social!$J$6:$J$11) -> 920 | AF15: =SUMPRODUCT((Social!$C$6:$C$11<=A15)*Social!$K$6:$K$11) -> 433.33333 | AG15: =AC15*IF(A15<=12,Ipotesi!$B$38,Ipotesi!$B$39)*Ipotesi!$B$22 -> 0 | AH15: =AD15-AE15-AF15-AG15 -> -573.70833 | AI15: =AI14+AH15 -> -3691.8247 | AJ15: =U15+AI15 -> 91786.454 | AK15: =AC15*Ipotesi!$B$37*Ipotesi!$B$20+IF(A15>Ipotesi!$B$21,INDEX($AC$5:$AC$40,A15-Ipotesi!$B$21)*Ipotesi!$B$37*(1-Ipotesi!$B$20),0)+(AA15-AC15)*Ipotesi!$B$19 -> 779.625 | AL15: =X15+SUM($AK$5:AK15)-SUM($AE$5:AE15)-SUM($AG$5:AG15) -> 52484.72 | AM15: =IF(AJ15>=0,A15,999) -> 11
A16: 12 | B16: =INT((A16-1)/12)+1 -> 1 | C16: =MOD(Ipotesi!$B$7-1+A16-1,12)+1 -> 10 | D16: =INDEX(Ipotesi!$B$58:$B$69,C16) -> 1.1 | E16: =Ipotesi!$D$47*MIN(1,(A16/Ipotesi!$B$18)^2)*(1+Ipotesi!$D$48)^(MAX(0,A16-12)/12)*D16 -> 16500 | F16: =E16*Ipotesi!$D$49 -> 57.75 | G16: =F16*Ipotesi!$D$50 -> 25.9875 | H16: =G16*Ipotesi!$D$51 -> 15.5925 | I16: =IF(A16<=12,Ipotesi!$B$42,Ipotesi!$B$43) -> 8.9219331 | J16: =MIN(H16,I16) -> 8.9219331 | K16: =H16-J16 -> 6.6705669 | L16: =J16*Ipotesi!$B$37 -> 18156.134 | M16: =(G16-J16)*Ipotesi!$B$19 -> 1706.5567 | N16: =IF(A16>=Ipotesi!$B$26,Ipotesi!$D$52*Ipotesi!$B$25/12,0) -> 0 | O16: =IF(A16>=Ipotesi!$B$27,Ipotesi!$D$53,0) -> 0 | P16: =SUM(L16:O16) -> 19862.691 | Q16: =IF(A16=1,Ipotesi!$B$10+Ipotesi!$B$11,0)+Ipotesi!$B$8*Ipotesi!$B$9+Ipotesi!$B$12+Ipotesi!$B$13+Ipotesi!$B$16*52/12*Ipotesi!$B$17 -> 620 | R16: =Ipotesi!$B$14*52/12*Ipotesi!$B$15 -> 1040 | S16: =J16*IF(A16<=12,Ipotesi!$B$38,Ipotesi!$B$39)*Ipotesi!$B$22 -> 5400 | T16: =P16-Q16-R16-S16 -> 12802.691 | U16: =U15+T16 -> 108280.97 | V16: =L16*Ipotesi!$B$20+IF(A16>Ipotesi!$B$21,INDEX($L$5:$L$40,A16-Ipotesi!$B$21)*(1-Ipotesi!$B$20),0)+M16+N16+O16 -> 19862.691 | W16: =V16-Q16-S16 -> 13842.691 | X16: =X15+W16 -> 66292.568 | Y16: =IF(U16>=0,A16,999) -> 12 | Z16: =F16*SUMPRODUCT((Social!$C$6:$C$11<=A16)*Social!$B$6:$B$11*Social!$I$6:$I$11) -> 17.325 | AA16: =Z16*Ipotesi!$D$50 -> 7.79625 | AB16: =AA16*Ipotesi!$D$51 -> 4.67775 | AC16: =MIN(AB16,MAX(0,I16-J16)) -> 0 | AD16: =AC16*Ipotesi!$B$37+(AA16-AC16)*Ipotesi!$B$19 -> 779.625 | AE16: =SUMPRODUCT((Social!$C$6:$C$11<=A16)*Social!$J$6:$J$11) -> 920 | AF16: =SUMPRODUCT((Social!$C$6:$C$11<=A16)*Social!$K$6:$K$11) -> 433.33333 | AG16: =AC16*IF(A16<=12,Ipotesi!$B$38,Ipotesi!$B$39)*Ipotesi!$B$22 -> 0 | AH16: =AD16-AE16-AF16-AG16 -> -573.70833 | AI16: =AI15+AH16 -> -4265.533 | AJ16: =U16+AI16 -> 104015.44 | AK16: =AC16*Ipotesi!$B$37*Ipotesi!$B$20+IF(A16>Ipotesi!$B$21,INDEX($AC$5:$AC$40,A16-Ipotesi!$B$21)*Ipotesi!$B$37*(1-Ipotesi!$B$20),0)+(AA16-AC16)*Ipotesi!$B$19 -> 779.625 | AL16: =X16+SUM($AK$5:AK16)-SUM($AE$5:AE16)-SUM($AG$5:AG16) -> 66187.035 | AM16: =IF(AJ16>=0,A16,999) -> 12
A17: 13 | B17: =INT((A17-1)/12)+1 -> 2 | C17: =MOD(Ipotesi!$B$7-1+A17-1,12)+1 -> 11 | D17: =INDEX(Ipotesi!$B$58:$B$69,C17) -> 1 | E17: =Ipotesi!$D$47*MIN(1,(A17/Ipotesi!$B$18)^2)*(1+Ipotesi!$D$48)^(MAX(0,A17-12)/12)*D17 -> 15515.491 | F17: =E17*Ipotesi!$D$49 -> 54.304219 | G17: =F17*Ipotesi!$D$50 -> 24.436899 | H17: =G17*Ipotesi!$D$51 -> 14.662139 | I17: =IF(A17<=12,Ipotesi!$B$42,Ipotesi!$B$43) -> 10.041841 | J17: =MIN(H17,I17) -> 10.041841 | K17: =H17-J17 -> 4.6202982 | L17: =J17*Ipotesi!$B$37 -> 20435.146 | M17: =(G17-J17)*Ipotesi!$B$19 -> 1439.5058 | N17: =IF(A17>=Ipotesi!$B$26,Ipotesi!$D$52*Ipotesi!$B$25/12,0) -> 1000 | O17: =IF(A17>=Ipotesi!$B$27,Ipotesi!$D$53,0) -> 0 | P17: =SUM(L17:O17) -> 22874.652 | Q17: =IF(A17=1,Ipotesi!$B$10+Ipotesi!$B$11,0)+Ipotesi!$B$8*Ipotesi!$B$9+Ipotesi!$B$12+Ipotesi!$B$13+Ipotesi!$B$16*52/12*Ipotesi!$B$17 -> 620 | R17: =Ipotesi!$B$14*52/12*Ipotesi!$B$15 -> 1040 | S17: =J17*IF(A17<=12,Ipotesi!$B$38,Ipotesi!$B$39)*Ipotesi!$B$22 -> 5400 | T17: =P17-Q17-R17-S17 -> 15814.652 | U17: =U16+T17 -> 124095.62 | V17: =L17*Ipotesi!$B$20+IF(A17>Ipotesi!$B$21,INDEX($L$5:$L$40,A17-Ipotesi!$B$21)*(1-Ipotesi!$B$20),0)+M17+N17+O17 -> 21735.146 | W17: =V17-Q17-S17 -> 15715.146 | X17: =X16+W17 -> 82007.714 | Y17: =IF(U17>=0,A17,999) -> 13 | Z17: =F17*SUMPRODUCT((Social!$C$6:$C$11<=A17)*Social!$B$6:$B$11*Social!$I$6:$I$11) -> 16.291266 | AA17: =Z17*Ipotesi!$D$50 -> 7.3310696 | AB17: =AA17*Ipotesi!$D$51 -> 4.3986418 | AC17: =MIN(AB17,MAX(0,I17-J17)) -> 0 | AD17: =AC17*Ipotesi!$B$37+(AA17-AC17)*Ipotesi!$B$19 -> 733.10696 | AE17: =SUMPRODUCT((Social!$C$6:$C$11<=A17)*Social!$J$6:$J$11) -> 920 | AF17: =SUMPRODUCT((Social!$C$6:$C$11<=A17)*Social!$K$6:$K$11) -> 433.33333 | AG17: =AC17*IF(A17<=12,Ipotesi!$B$38,Ipotesi!$B$39)*Ipotesi!$B$22 -> 0 | AH17: =AD17-AE17-AF17-AG17 -> -620.22637 | AI17: =AI16+AH17 -> -4885.7594 | AJ17: =U17+AI17 -> 119209.86 | AK17: =AC17*Ipotesi!$B$37*Ipotesi!$B$20+IF(A17>Ipotesi!$B$21,INDEX($AC$5:$AC$40,A17-Ipotesi!$B$21)*Ipotesi!$B$37*(1-Ipotesi!$B$20),0)+(AA17-AC17)*Ipotesi!$B$19 -> 733.10696 | AL17: =X17+SUM($AK$5:AK17)-SUM($AE$5:AE17)-SUM($AG$5:AG17) -> 81715.288 | AM17: =IF(AJ17>=0,A17,999) -> 13
... A40: 36 | B40: =INT((A40-1)/12)+1 -> 3 | C40: =MOD(Ipotesi!$B$7-1+A40-1,12)+1 -> 10 | D40: =INDEX(Ipotesi!$B$58:$B$69,C40) -> 1.1 | E40: =Ipotesi!$D$47*MIN(1,(A40/Ipotesi!$B$18)^2)*(1+Ipotesi!$D$48)^(MAX(0,A40-12)/12)*D40 -> 37125 | F40: =E40*Ipotesi!$D$49 -> 129.9375 | G40: =F40*Ipotesi!$D$50 -> 58.471875 | H40: =G40*Ipotesi!$D$51 -> 35.083125 | I40: =IF(A40<=12,Ipotesi!$B$42,Ipotesi!$B$43) -> 10.041841 | J40: =MIN(H40,I40) -> 10.041841 | K40: =H40-J40 -> 25.041284 | L40: =J40*Ipotesi!$B$37 -> 20435.146 | M40: =(G40-J40)*Ipotesi!$B$19 -> 4843.0034 | N40: =IF(A40>=Ipotesi!$B$26,Ipotesi!$D$52*Ipotesi!$B$25/12,0) -> 1000 | O40: =IF(A40>=Ipotesi!$B$27,Ipotesi!$D$53,0) -> 1500 | P40: =SUM(L40:O40) -> 27778.15 | Q40: =IF(A40=1,Ipotesi!$B$10+Ipotesi!$B$11,0)+Ipotesi!$B$8*Ipotesi!$B$9+Ipotesi!$B$12+Ipotesi!$B$13+Ipotesi!$B$16*52/12*Ipotesi!$B$17 -> 620 | R40: =Ipotesi!$B$14*52/12*Ipotesi!$B$15 -> 1040 | S40: =J40*IF(A40<=12,Ipotesi!$B$38,Ipotesi!$B$39)*Ipotesi!$B$22 -> 5400 | T40: =P40-Q40-R40-S40 -> 20718.15 | U40: =U39+T40 -> 536303.69 | V40: =L40*Ipotesi!$B$20+IF(A40>Ipotesi!$B$21,INDEX($L$5:$L$40,A40-Ipotesi!$B$21)*(1-Ipotesi!$B$20),0)+M40+N40+O40 -> 27778.15 | W40: =V40-Q40-S40 -> 21758.15 | X40: =X39+W40 -> 512438.25 | Y40: =IF(U40>=0,A40,999) -> 36 | Z40: =F40*SUMPRODUCT((Social!$C$6:$C$11<=A40)*Social!$B$6:$B$11*Social!$I$6:$I$11) -> 38.98125 | AA40: =Z40*Ipotesi!$D$50 -> 17.541563 | AB40: =AA40*Ipotesi!$D$51 -> 10.524938 | AC40: =MIN(AB40,MAX(0,I40-J40)) -> 0 | AD40: =AC40*Ipotesi!$B$37+(AA40-AC40)*Ipotesi!$B$19 -> 1754.1562 | AE40: =SUMPRODUCT((Social!$C$6:$C$11<=A40)*Social!$J$6:$J$11) -> 920 | AF40: =SUMPRODUCT((Social!$C$6:$C$11<=A40)*Social!$K$6:$K$11) -> 433.33333 | AG40: =AC40*IF(A40<=12,Ipotesi!$B$38,Ipotesi!$B$39)*Ipotesi!$B$22 -> 0 | AH40: =AD40-AE40-AF40-AG40 -> 400.82292 | AI40: =AI39+AH40 -> -10009.645 | AJ40: =U40+AI40 -> 526294.05 | AK40: =AC40*Ipotesi!$B$37*Ipotesi!$B$20+IF(A40>Ipotesi!$B$21,INDEX($AC$5:$AC$40,A40-Ipotesi!$B$21)*Ipotesi!$B$37*(1-Ipotesi!$B$20),0)+(AA40-AC40)*Ipotesi!$B$19 -> 1754.1562 | AL40: =X40+SUM($AK$5:AK40)-SUM($AE$5:AE40)-SUM($AG$5:AG40) -> 516988.61 | AM40: =IF(AJ40>=0,A40,999) -> 36
A41: Totale 36 mesi | E41: =SUM(E5:E40) -> 697088.89 | F41: =SUM(F5:F40) -> 2439.8111 | G41: =SUM(G5:G40) -> 1097.915 | H41: =SUM(H5:H40) -> 658.749 | J41: =SUM(J5:J40) -> 323.52277 | K41: =SUM(K5:K40) -> 335.22623 | L41: =SUM(L5:L40) -> 658368.84 | M41: =SUM(M5:M40) -> 77439.223 | N41: =SUM(N5:N40) -> 24000 | O41: =SUM(O5:O40) -> 18000 | P41: =SUM(P5:P40) -> 777808.07 | Q41: =SUM(Q5:Q40) -> 24520 | ... T41: =SUM(T5:T40) -> 536303.69 | V41: =SUM(V5:V40) -> 716502.63 | W41: =SUM(W5:W40) -> 512438.25 | Z41: =SUM(Z5:Z40) -> 731.04646 | AA41: =SUM(AA5:AA40) -> 328.97091 | AB41: =SUM(AB5:AB40) -> 197.38254 | AC41: =SUM(AC5:AC40) -> 3.1007812 | AD41: =SUM(AD5:AD40) -> 38897.102 | AE41: =SUM(AE5:AE40) -> 32470 | AF41: =SUM(AF5:AF40) -> 14560 | AG41: =SUM(AG5:AG40) -> 1876.7479 | AH41: =SUM(AH5:AH40) -> -10009.645 | AK41: =SUM(AK5:AK40) -> 38897.102
